Workbook

Sheet 目录
A1: 深圳市博创兴供应链有限公司 Your Global Chance, We Deliver
A4: 国家 | B4: 渠道类型 | C4: 渠道名称 | D4: 价格表 | E4: 渠道特点 | F4: 最新动态
A5: 美国 | B5: 海派专线 | C5: 美森正班 | D5: 进入报价表 | E5: 美森正班船，船期准点，时效快且稳！
C6: 以星合德 | E6: 以星合德带车架服务，时效稳定有保障
C7: OA快船 | E7: OA，价优时效快捷 （纯正OA）
B8: 经济线 | C8: 直送~经济线 | D8: 进入报价表 | E8: 普船统配，航期16~20天，75%保柜率
B9: 美中专线 | C9: 休斯顿专线 | D9: 进入报价表 | E9: 休斯顿直航，覆盖7邮编的卡派
C10: 芝加哥专线 | D10: 进入报价表 | E10: 芝加哥专线，覆盖美中4~6邮编的卡派
B11: 美东专线 | C11: 纽约专线 | D11: 进入报价表 | E11: 纽约直航，覆盖美东区域0~3邮编的卡派
C12: 纽约快速达 | E12: 以星（COSCO）铁路快线快船转纽约，美东性价比首选
B13: 萨瓦纳专线 | C13: 萨瓦纳专线 | D13: 进入报价表 | E13: 美东南18仓普船价格性价比高
B14: 美西快线 | C14: 美森正班 | D14: 进入报价表 | E14: 美森正班船，船期准点，时效快且稳！
C15: 以星合德 | E15: 以星合德带车架服务，时效稳定有保障
C16: OA快船 | E16: OA，价优时效快捷 （纯正OA）
A17: 加拿大 | B17: 加拿大直航 | C17: 多伦多专线 | D17: 进入报价表 | E17: 加拿大直航，时效优，航线优，价格优，服务优
C18: 温哥华专线
C19: 卡尔加里专线
B20: 美转加 | C20: 美森正班 | D20: 进入报价表 | E20: 头程至美国，二程转派加拿大
C21: 以星合德
C22: OA快船
B23: 美转加海派 | C23: 美森正班 | D23: 进入报价表 | E23: 加拿大直航，时效优，航线优，价格优，服务优
C24: 以星合德 | E24: 头程至美国，二程转派加拿大
C25: OA快船
A26: 其它 | B26: 发货必读 | D26: 点击进入 | E26: 附加费、开查、赔偿等说明
B27: 船期表 | D27: 点击进入 | E27: 每周更新
B28: 反倾销列表 | D28: 点击进入 | E28: 附加费、开查、赔偿等说明

Sheet 发货必读
A1: 发货必读
A2: 附加费 | B2: 费用类型 | C2: 海卡专线 | D2: 海卡专线CBM | E2: 海派 | G2: 国内仓增值服务
B3: 末端派送类型 | C3: 卡派 | E3: UPS*FEDEX | G3: 收费项目 | H3: 单价*RMB | I3: 单位 | J3: 最低消费 | K3: 备注
A4: 报关费 | B4: 代理报关 | C4: 0 | G4: 更改包装费 | H4: 10 | I4: 箱 | J4: 20 | K4: 不含纸箱费用
B5: 一般贸易报关费 | C5: 350*份(超过5个品名，需加收续页费¥50*页) | G5: 产品贴标签 | H5: 0.5 | I5: 个标签 | J5: 20 | K5: 含标签纸
B6: 手册报关 | C6: 盐田出口500*份，其他口岸无服务 | G6: 换外箱标签 | H6: 1 | I6: 个标签 | J6: 20 | K6: 含标签纸
A7: 产品附加费 | B7: 纺织品 | C7: 1*KG | D7: 0 | E7: 1*KG | G7: 割包装袋*带 | H7: 1 | I7: 箱 | J7: 20
B8: 床上用品-美线 | C8: 0.5*KG | D8: 0 | E8: 0.5*KG | G8: 开木箱查货 | H8: 30 | I8: 箱 | J8: 30 | K8: 含封箱
B9: 床上用品-加线 | C9: 1*KG | D9: 0 | E9: 1*KG | G9: 开箱拍照 | H9: 10 | I9: 票 | J9: 10 | K9: 含操作耗材
B10: 钢制品*铝制品 | C10: 1*KG | D10: 0 | E10: 1*KG | G10: 拆单合票 | H10: 1 | I10: 箱 | J10: 20 | K10: 含二次分货
B11: 汽车配件 | C11: 0.5*KG | D11: 0 | E11: 0.5*KG | G11: 国内退货 | H11: 2 | I11: 箱 | J11: 10 | K11: 含装卸费
B12: 木制品（报关件单询） | C12: 1*KG | D12: 500*票 | E12: 1*KG | G12: 仓租 | H12: 3.5*天 | I12: CBM | J12: 50RMB,，不足一个方按一个方计算 | K12: 自入仓日起免租期7天
B13: 二类医疗 | C13: 无服务 | G13: 仓租 | H13: 5*天 | I13: CBM | K13: 超过1个月出货
B14: EPA\DOT产品 | C14: 180*票（需提供符合目的地海关要求的认证 ） | G14: 仓租 | H14: 7*天 | I14: CBM | K14: 超过2个月出货
B15: 涉FDA产品 | C15: 180RMB*品名
B16: 厨房刀具\太阳能产品\笔 | C16: 1*KG | D16: 150*CBM | E16: 1*KG
B17: 移动电源\纯电池\暖手宝 | C17: 1*KG | D17: 150*CBM | E17: 1*KG
A18: 超尺寸货物附加费 | B18: 120cm≤最长边＜140cm | C18: 0 | E18: 100*件
B19: 140cm≤最长边＜175cm | C19: 1*KG | D19: 190*CBM | E19: 100*件
B20: 单边≥175cm的单询 | C20: 单询 | E20: 无服务
B21: 第二边长≥76cm | C21: 0 | E21: 100*件
B22: 22.5KG≤实重≤40KG | C22: 0 | E22: 120*件
B23: 实重＞40KG | C23: 单询 | E23: 无服务
B24: 260cm≤长+2x(宽+高)≤320cm | C24: 0 | E24: 100*件
B25: 320cm≤长+2x(宽+高)≤390cm | C25: 单询 | E25: 无服务
B26: 长+2x(宽+高)＞390cm | C26: 无服务
B27: 玩具附加费 | C27: 1*KG
B28: 超箱附加费 | C28: 单箱尺寸小于0.05CBM的货物，收取超箱数附加RMB2/箱
A29: 其他附加费 | B29: 清关超品名费（5个以上起收) | C29: 30RMB*品名
B30: 美国 CPC/GCC eFiling 新规申报费 | C30: 1.我司拒接涉CPC儿童产品（客户使用自有进口商以外，且须提供指定机构的有效CPC等认证及申报）。 2.GCC成人消费品，需在发货前提供完整GCC证书，若因无法提供且产品不达质量要求，导致的没收与店铺损失需客户自行承担。 3.代申报服务费：180元/品名(按认证）
B31: 目的港扣货 | C31: 拆柜前 | D31: USD100*票 同柜扣多票+USD50*票 封顶USD200*柜 (加拿大扣货费150USD*票，同柜扣多票+USD100*票） 不保证扣货一定成功，不承担失败产生的费用
C32: 拆柜后 | D32: 扣货费USD200*票+重新分货费USD2*件(低消50USD*票) 同柜扣多票+USD50*票+重新分货费USD2*件（低消50USD*票） (加拿大扣货费150USD*票，同柜扣多票+USD100*票） 不保证扣货一定成功，不承担失败产生的费用
B33: 申请POD | C33: 免费 | E33: 35*RMB主单号
B34: 退运附加费 | C34: 包税渠道需要我司包含5H和9H退运，表价单价自行+1RMB/KG , 不含税+ 200RMB/CBM, 如不需要我司包5H和9H退运，遇到美国海关5H/9H查验，相关仓租、柜租、查验费、退运指定启运港的来回运费 ,产生相关所有费用由客户自行承担，我司实报实销。 但不包含贴标换标费、暂存仓租费，不含改派送地址的派送费(实际派送地址-原先派送地址，差价多退少补)
B35: 卡派私人仓*自提 | C35: 提柜起免租7天，30天内USD1*CBM*天,第31~60天收取USD1.5*CBM*天,第61~90天收取USD2*CBM*天,第91~180天收取USD3*CBM*天,超出180天单询（低消1CBM） 非FBA地址打托只接受混合打板（不分客户，不分唛头，没有任何区分要求)， 如需一一对应，单独打托（（举例：如单个SKU等。是指要求按唛头打板，不接受任何形式的混打）），请单询价格；
A36: 方数换算重货 | C36: * | D36: 每363KG=1CBM | E36: *
A37: 方式计算算重结 | C37: * | D37: CBM结算重保留两位小数 | E37: *
A38: 拒收产品 | B38: 1、带有以下标识：LASER，ACT等授权认证的产品（无论是否有认证）
B39: 2、手机、笔记本电脑、各国国旗，婴儿用品（包括衣服），激光产品，蝴蝶刀、液体、粉末、U盘、光驱、内存条、家具、指尖陀螺、电弧打火机，手机，带压缩机产品，活性植物，太阳眼镜、化妆品、铅笔等
B40: 3、仿牌产品，液体、粉末、食品、药品、易燃易爆、古董、货币等国家禁止出口产品，如发现罚款2000*票，情节严重上报公安局处理
B41: 4、有疗效功能的按摩器
B42: 5、功能眼镜，例如太阳眼镜，防UV功能的滑雪眼镜，有度数的眼镜，包括但不限于老花镜，近视眼镜，有度数的泳镜
B43: 6、反倾销产品（点我看清单）
A44: 目的港拦截仓租 | B44: 提柜起免租7天，第8~60天收取USD2*CBM*天,第61天起收取USD3*CBM*天，（每票最低消费收费5USD*天，提供指令后仓租需+2个工作日用于操作货物） 超过3个月未出货物默认销毁，已产生的仓租正常收取
A45: 开查 | B45: 货物派送后，请客户在签收后7~10个工作日内查询FBA后台是否上架，如递送后15个工作日内提供货物未上架，请提供后台截图至我司客服。
A46: 索赔 | B46: 开启索赔程序(需带有电脑屏幕右下角当下真实时间)；如递送后超过20工作日未开启索赔程序的，不予受理
A47: 其他 | B47: 2025年8月12日如遇加收关税，将会按每10%关税增加0.5元*kg的比例加收附加费，具体需结合美国最新关税政策收取；
A48: 赔偿标准 | B48: ①丢失赔偿：含税渠道在货物运输过程中丢失(包含整票UPS*FEDEX未提取)，按申报货值赔偿最高不超人民币40*KG赔偿，不退运费；自税渠道在货物运输过程中丢失(包含整票UPS*FEDEX未提取)，按申报货值赔偿最高不超人民币2000*CBM赔偿，不退运费；
B49: ②提取后赔偿：已交UPS*FEDEX后(部分子单号未扫描货件，此为常见漏扫现象，我司不负责)丢失的不退运费，按UPS*FEDEX标准赔偿，即按申报价值赔偿但最高不超USD100*票。
B50: ③派送后赔偿：已提供签收完整的POD的货（无论卡派还是UPS派），不接受索赔。 如送错仓，客户提供亚马逊平台的收费明细，我司赔偿入库配置费和缺陷费，不免运费。
B51: ④漏报关赔偿：3倍报关费，请慎接报关件，不接受赔偿标准的不要发！
B52: ⑤延误赔偿：以报价表为准，但如因发件人低申报、品名申报不符、产品涉及反倾销、认证、侵权等不符合当地法规的，由此产生的责任和损失，由发件人承担，我司保留追究法律责任的权利且不予任何赔偿
B53: ⑥扣关赔偿：含税渠道非货物本身的问题产生的扣关按申报货值赔偿最高不超人民币40*KG赔偿，不退运费；自税渠道非货物本身的问题产生的扣关按申报货值赔偿最高不超人民币2000*CBM赔偿，不退运费；但如因发件人低申报、品名申报不符、产品涉及反倾销、认证、侵权等不符合当地法规的，由此产生的责任和损失，由发件人承担，我司保留追究法律责任的权利且不予任何赔偿
B54: ⑦存仓渠道因无法购买保险，即日起问题件只赔偿40*KG，不退头程运费
A55: 一经发货，默认接受我司报价表上所有条款！

Sheet 船期表
A1: 深圳市博创兴供应链有限公司 Your Global Chance, We Deliver
A4: 渠道名称 | C4: 仓库 | D4: 船司 | E4: 截收货 | F4: 船名*航次 | G4: ETD | H4: ETA
A5: 美西快线 美西海派 | B5: 美森正班CLX | C5: 深圳 | D5: MAT | E5: 46207 | F5: DANIEL K. INOUYE 099E | G5: 46211 | H5: 46222
C6: 义乌 | D6: MAT | E6: 46207 | F6: DANIEL K. INOUYE 099E | G6: 46211 | H6: 46222
B7: ZIM*合德带托快提 | C7: 深圳 | D7: ZIM/HEDE | E7: 46207 | F7: MISSISSIPPI 18E（带车架拥有快卸快提服务） HANSA DUBURG 2606E（ETD7.8 ETA7.22） | G7: 46211 | H7: 46224
C8: 义乌 | D8: HEDE | E8: 46207 | F8: PONTRESINA 2606E（ETD7.9 ETA7.22） | G8: 46212 | H8: 46225
B9: EMC快速达 | C9: 深圳 | D9: EMC/ZIM/HEDE | E9: 46207 | F9: EVER MEMO 1461-012E（ETD7.7 ETA 7.21）MISSISSIPPI 18E（ETD7.8 ETA7.21） HANSA DUBURG 2606E（ETD7.8 ETA7.22） | G9: 46211 | H9: 46225
C10: 义乌 | D10: COSCO/HEDE | E10: 46207 | F10: CSCL BOHAI SEA 077E（ETD7.9 ETA7.22） PONTRESINA 2606E（ETD7.9 ETA7.22） | G10: 46212 | H10: 46227
B11: OA快船 | C11: 深圳 | D11: EMC/COSCO | E11: 46207 | F11: COSCO SHIPPING DENALI 054E | G11: 46212 | H11: 46227
E12: 46212 | F12: EVER LOYAL 0022-076E（ETD7.14 ETA 7.28） OOCL LONDON 124E（ETD7.14 ETA7.28） | G12: 46217 | H12: 46227
C13: 义乌 | D13: EMC/COSCO | E13: 46207 | F13: EVER LIVELY 1228-078E（ETD7.7 ETA 7.22） CSCL BOHAI SEA 077E（ETD7.9 ETA7.22） CSCL YELLOW SEA 071E（ETD7.9 ETA7.23） COSCO PORTUGAL 083E（ETD7.7 ETA7.20） | G13: 46212 | H13: 46227
A14: 美中专线 | B14: 芝加哥普船卡派 | C14: 深圳 | D14: EMC/COSCO | E14: 46207 | F14: EVER MEMO 1461-012E（ETD7.7 ETA 7.21） COSCO SHIPPING DENALI 054E（ETD7.9 ETA7.24） | G14: 46212 | H14: 46238
C15: 义乌 | D15: COSCO | E15: 46207 | F15: CSCL BOHAI SEA 077E（ETD7.9 ETA7.22） COSCO PORTUGAL 083E（ETD7.7 ETA7.20） | G15: 46212 | H15: 46238
B16: 芝加哥快速达卡派包税 | C16: 深圳 | D16: ZIM | E16: 46207 | F16: MISSISSIPPI 18E | G16: 46211 | H16: 46231
C17: 义乌 | D17: ZIM | E17: 46206 | F17: MISSISSIPPI 18E | G17: 46211 | H17: 46233
B18: 休斯顿专线卡派 | C18: 深圳 | D18: EMC | E18: 46209 | F18: XIN YA ZHOU 176E | G18: 46215 | H18: 46243
C19: 义乌 | D19: COSCO | E19: 46206 | F19: XIN YA ZHOU 176E（ETD7.8 ETA8.7） CMA CGM RHONE 0PGO5E1MA | G19: 46215 | H19: 46248
A20: 萨凡纳专线 | B20: 萨凡纳专线 | C20: 深圳 | D20: EMC | E20: 46209 | F20: EVER MERCY 1366-007E | G20: 46213 | H20: 46245
C21: 义乌 | D21: COSCO | E21: 46206 | F21: OOCL KOREA 058E（ETD7.10 ETA8.6） OOCL KAPOK 004E（ETD7.9 ETA8.9） EVER FULL 1274E（ETD7.13 ETA8.14） | G21: 46216 | H21: 46246
A22: 美东专线 | B22: 纽约普船 | C22: 深圳 | D22: EMC | E22: 46209 | F22: OOCL LAVENDER 003E | G22: 46215 | H22: 46247
C23: 义乌 | D23: COSCO | E23: 46206 | F23: OOCL KOREA 058E（ETD7.10 ETA8.6） OOCL KAPOK 004E（ETD7.9 ETA8.4） | G23: 46213 | H23: 46239
B24: 纽约快船 | C24: 深圳 | D24: COSCO | E24: 46207 | F24: COSCO SHIPPING DENALI 054E | G24: 46212 | H24: 46232
C25: 义乌 | D25: COSCO | E25: 46205 | F25: COSCO SHIPPING DENALI 054E | G25: 46212 | H25: 46232
B26: 纽约特快 | C26: 深圳 | D26: ZIM | E26: 46207 | F26: MISSISSIPPI 18E | G26: 46211 | H26: 46231
C27: 义乌 | D27: ZIM | E27: 46206 | F27: MISSISSIPPI 18E | G27: 46211 | H27: 46231
A28: 加拿大直航 | B28: 温哥华 | C28: 深圳 | D28: COSCO | E28: 46209 | F28: OOCL SAN FRANCISCO 197E | G28: 46213 | H28: 46233
C29: 义乌 | D29: COSCO | E29: 46208 | F29: OOCL SAN FRANCISCO 197E | G29: 46213 | H29: 46233
B30: 多伦多 | C30: 深圳 | D30: COSCO | E30: 46209 | F30: XIN RI ZHAO 393N | G30: 46211 | H30: 46239
B31: 多伦多 | C31: 义乌 | D31: COSCO | E31: 46208 | F31: COSCO JEDDAH 096N（ETD7.7 ETA7.22） XIN RI ZHAO 393N | G31: 46211 | H31: 46239
B32: 卡尔加里 | C32: 深圳 | D32: COSCO | E32: 46209 | F32: OOCL SAN FRANCISCO 197E | G32: 46213 | H32: 46241
C33: 义乌 | D33: COSCO | E33: 46208 | F33: OOCL SAN FRANCISCO 197E | G33: 46213 | H33: 46241

Sheet 快捷查询
A1: 深圳市博创兴供应链有限公司 Your Global Chance, We Deliver | D1: 快捷查价
D2: 国内站点 | E2: 目的仓 | F2: 清关方式
D3: 深圳 | E3: MDW2 | F3: 包税
A4: 国家 | B4: 渠道类型 | C4: 渠道名称 | D4: 下单渠道 | E4: 单价（KG*CBM） | G4: 参考时效(天）
A5: 美国 | B5: 经济线 | C5: 直送~经济线 | D5: 美西经济线-卡派包税 * 不包税 | E5: {=IFERROR(INDEX(经济线!C6:F34,MATCH(E3,经济线!A6:A34,0),IF(D3="深圳",IF(F3="包税",1,2),IF(D3="义乌/宁波",IF(F3="包税",3,4)))),"*")} -> 8.9 | G5: =IFERROR(VLOOKUP(E3,经济线!A:H,7,0),"*") -> 30~38
B6: 美中专线 | C6: 休斯顿专线 | D6: 休斯顿专线-卡派包税 *不包税 | E6: {=IFERROR(INDEX(美中专线!O7:R31,MATCH(E3,美中专线!N7:N31,0),IF(D3="深圳",IF(F3="包税",1,2),IF(D3="义乌/宁波",IF(F3="包税",3,4)))),"*")} -> * | G6: =IFERROR(VLOOKUP(E3,美中专线!N:T,7,0),"*") -> *
C7: 芝加哥专线 | D7: 芝加哥专线-卡派包税 * 不包税 | E7: {=IFERROR(INDEX(美中专线!B7:E26,MATCH(E3,美中专线!A7:A26,0),IF(D3="深圳",IF(F3="包税",1,2),IF(D3="义乌/宁波",IF(F3="包税",3,4)))),"*")} -> 9.4 | G7: =IFERROR(VLOOKUP(E3,美中专线!A:G,7,0),"*") -> 39~46
B8: 美东专线 | C8: 纽约普船 | D8: 纽约普船-卡派包税 * 不包税 | E8: {=IFERROR(INDEX(美东专线!B7:E63,MATCH(E3,美东专线!A7:A63,0),IF(D3="深圳",IF(F3="包税",1,2),IF(D3="义乌/宁波",IF(F3="包税",3,4)))),"*")} -> * | G8: =IFERROR(VLOOKUP(E3,美东专线!A:G,7,0),"*") -> *
C9: 纽约快船 | D9: 纽约快船-卡派包税 *不包税 | E9: {=IFERROR(INDEX(美东专线!H7:K63,MATCH(E3,美东专线!A7:A63,0),IF(D3="深圳",IF(F3="包税",1,2),IF(D3="义乌/宁波",IF(F3="包税",3,4)))),"*")} -> * | G9: =IFERROR(VLOOKUP(E3,美东专线!A:M,13,0),"*") -> *
C10: 纽约特快 | D10: 纽约特快-卡派包税 *不包税 | E10: {=IFERROR(INDEX(美东专线!N7:Q63,MATCH(E3,美东专线!A7:A63,0),IF(D3="深圳",IF(F3="包税",1,2),IF(D3="义乌/宁波",IF(F3="包税",3,4)))),"*")} -> * | G10: =IFERROR(VLOOKUP(E3,美东专线!A:S,19,0),"*") -> *
B11: 萨瓦纳专线 | C11: 萨瓦纳专线 | D11: 萨瓦纳专线-卡派包税 *不包税 | E11: {=IFERROR(INDEX(萨瓦纳专线!B7:E28,MATCH(E3,萨瓦纳专线!A7:A28,0),IF(D3="深圳",IF(F3="包税",1,2),IF(D3="义乌/宁波",IF(F3="包税",3,4)))),"*")} -> * | G11: =IFERROR(VLOOKUP(E3,萨瓦纳专线!A:G,7,0),"*") -> *
B12: 美西快线 | C12: 美森正班 | D12: 美森-卡派包税 *不包税 | E12: {=IFERROR(INDEX(王牌渠道!B6:E63,MATCH(E3,王牌渠道!A6:A63,0),IF(D3="深圳",IF(F3="包税",1,2),IF(D3="义乌/宁波",IF(F3="包税",3,4)))),"*")} -> 14.5 | G12: =IFERROR(VLOOKUP(E3,王牌渠道!A:F,6,0),"*") -> 19~24
C13: 以星合德 | D13: 限时达-卡派包税 *不包税 | E13: {=IFERROR(INDEX(王牌渠道!G6:K63,MATCH(E3,王牌渠道!A6:A63,0),IF(D3="深圳",IF(F3="包税",1,2),IF(D3="义乌/宁波",IF(F3="包税",3,4)))),"*")} -> 32.02 | G13: =IFERROR(VLOOKUP(E3,王牌渠道!A:L,12,0),"*") -> 20~25
C14: EMC快速达 | D14: EMC快速达卡派包税*不包税 | E14: {=IFERROR(INDEX(王牌渠道!N6:Q63,MATCH(E3,王牌渠道!A6:A63,0),IF(D3="深圳",IF(F3="包税",1,2),IF(D3="义乌/宁波",IF(F3="包税",3,4)))),"*")} -> 10.6 | G14: =IFERROR(VLOOKUP(E3,王牌渠道!A:R,18,0),"*") -> 20~25
C15: OA快船 | D15: OA快船-卡派包税 * 不包税 | E15: {=IFERROR(INDEX(美西专线!B7:E72,MATCH(E3,美西专线!A7:A72,0),IF(D3="深圳",IF(F3="包税",1,2),IF(D3="义乌/宁波",IF(F3="包税",3,4)))),"*")} -> 10.2 | G15: =IFERROR(VLOOKUP(E3,美西专线!A:G,7,0),"*") -> 23~29
A16: 加拿大 | B16: 加拿大直航 | C16: 多伦多 * 温哥华 * 卡尔加里 专线 | D16: 加拿大直航-卡派包税 | E16: =IFERROR(IF(F3="包税",IF(D3="深圳",_xlfn.XLOOKUP(E3,加拿大直航!A6:A30,加拿大直航!B6:B30,"*"),IF(D3="义乌/宁波",_xlfn.XLOOKUP(E3,加拿大直航!A6:A30,加拿大直航!C6:C30,"*"),"*")),"*"),"*") -> * | G16: =IFERROR(VLOOKUP(E3,加拿大直航!A:D,4,0),"*") -> *
B17: 美转加 | C17: 美森正班 | D17: 美转加特快包税 | E17: =IFERROR(IF(F3="包税",IF(D3="深圳",_xlfn.XLOOKUP(E3,#REF!,#REF!,"*"),IF(D3="义乌/宁波",_xlfn.XLOOKUP(E3,#REF!,#REF!,"*"),"*")),"*"),"*") -> * | G17: =IFERROR(VLOOKUP(E3,#REF!,8,0),"*") -> *
C18: 以星合德 | D18: 美转加快船包税 | E18: =IFERROR(IF(F3="包税",IF(D3="深圳",_xlfn.XLOOKUP(E3,#REF!,#REF!,"*"),IF(D3="义乌/宁波",_xlfn.XLOOKUP(E3,#REF!,#REF!,"*"),"*")),"*"),"*") -> * | G18: =IFERROR(VLOOKUP(E3,#REF!,4,0),"*") -> *
B19: 美转加海派 | C19: 美森正班 | D19: 美森海派 | E19: =IFERROR(IF(F3="包税",IF(D3="深圳",_xlfn.XLOOKUP(E3,#REF!,#REF!,"*"),IF(D3="义乌/宁波",_xlfn.XLOOKUP(E3,#REF!,#REF!,"*"),IF(D3="山东/青岛",_xlfn.XLOOKUP(E3,#REF!,#REF!,"*"),"*"))),"*"),"*") -> * | G19: /
C20: 以星合德 | D20: 以星合德海派 | E20: =IFERROR(IF(F3="包税",IF(D3="深圳",_xlfn.XLOOKUP(E3,#REF!,#REF!,"*"),IF(D3="义乌/宁波",_xlfn.XLOOKUP(E3,#REF!,#REF!,"*"),IF(D3="山东/青岛",_xlfn.XLOOKUP(E3,#REF!,#REF!,"*"),"*"))),"*"),"*") -> * | G20: /
C21: OA快船 | D21: OA快船海派 | E21: =IFERROR(IF(F3="包税",IF(D3="深圳",_xlfn.XLOOKUP(E3,#REF!,#REF!,"*"),IF(D3="义乌/宁波",_xlfn.XLOOKUP(E3,#REF!,#REF!,"*"),IF(D3="山东/青岛",_xlfn.XLOOKUP(E3,#REF!,#REF!,"*"),"*"))),"*"),"*") -> * | G21: /

Sheet 海派专线
A1: 深圳市博创兴供应链有限公司 SHENZHEN BOCHANCE SHIPPING INTERNATIONAL SUPPLY CHAIN CO.LTD
A3: 海派专线
A4: 邮编分区 | B4: 美森海派 | D4: 以星合德（统配）海派 | F4: EMC快速达海派 | H4: OA快船海派
B5: 深圳 | C5: 义乌\宁波 | D5: 深圳 | E5: 义乌\宁波 | F5: 深圳 | G5: 义乌\宁波 | H5: 深圳 | I5: 义乌\宁波
B6: 50KG+ | C6: 50KG+ | D6: 50KG+ | E6: 50KG+ | F6: 50KG+ | G6: 50KG+ | H6: 50KG+ | I6: 50KG+
A7: 美国西岸（邮编8.9开头） | B7: 15.6 | C7: 15.1 | D7: 13 | E7: 12.7 | F7: 12 | G7: 12.2 | H7: 11.2 | I7: 11.2
A8: 美国西岸北（邮编97.98.99开头） | B8: 16.6 | C8: 16.1 | D8: 14 | E8: 13.7 | F8: 13 | G8: 13.2 | H8: 12.2 | I8: 12.2
A9: 美国中部(邮编5.6.7开头) | B9: 17.6 | C9: 17.1 | D9: 15.5 | E9: 15.2 | F9: 14.5 | G9: 14.7 | H9: 13.7 | I9: 13.7
A10: 美国东岸(邮编0.1.2.3.4开头) | B10: 19.1 | C10: 18.6 | D10: 17 | E10: 16.7 | F10: 16 | G10: 16.2 | H10: 15.2 | I10: 15.2
A11: 预配船司 | B11: Matson | D11: ZIM.HEDE | F11: EMC定提 | H11: OA普船
A12: 时效参考（非赔付时效） | B12: 开船后11个工作日提取 | D12: 开船后13个工作日提取 | F12: 开船后14个工作日提取 | H12: 开船后16个工作日提取
A13: 说明 | B13: 1、含关税和查验费；尾程UPS*FEDEX派送，不接受指定打单 ； 2、材积重=长cm*宽cm*高cm*6000，不分泡； 3、单件低消12KG，单票12-99KG，单价+4元*KG； 4、私人地址 25*件； 5、偏远附加费 +40*件； 6、单边＞120cm、实重＞22.5KG，长+2宽+2高＞260CM参考《发货必读》 7、表价不含5H,9H退运费,及罚没。
A14: 赔付渠道 | B14: 赔付标准
A15: 美森海派 | B15: 从上海离港后第二天算起，超过11个工作日未提取的，赔偿RMB1*KG*工作日，最高3RMB*KG。 船期延误、进出口查验、亚马逊问题不赔(例如删约*不放约*拒收等不可控因素)
A16: 以星合德海派 | B16: 从离港后第二天算起，超过17个工作日未提取的，赔偿RMB0.5*KG*工作日，最高1.5RMB*KG。 船期延误、进出口查验、亚马逊问题不赔(例如删约*不放约*拒收等不可控因素)

Sheet 王牌渠道
A1: 深圳市博创兴供应链有限公司
A2: SHENZHEN BOCHANCE SHIPPING INTERNATIONAL SUPPLY CHAIN CO.LTD
A3: 美森正班卡派 | H3: 以星*合德*带托（统配）卡派 | N3: EMC快速达卡派
A4: 仓库代码 | B4: 深圳 | D4: 义乌\宁波 | F4: 参考时效 (开船后第二天起)*天 | G4: 理赔时效(开船后第二天起)*天 | H4: 深圳 | J4: 义乌\宁波 | L4: 参考时效 (开船后第二天起)*天 | M4: 理赔时效(开船后第二天起)*天 | N4: 深圳 | P4: 义乌\宁波 | R4: 参考时效 (开船后第二天起)*天 | S4: 理赔时效(开船后第二天起)*天
B5: 21KG+ | C5: 0.5CBM+ | D5: 21KG+ | E5: 0.5CBM+ | H5: 21KG+ | I5: 0.5CBM+ | J5: 21KG+ | K5: 0.5CBM+ | N5: 21KG+ | O5: 0.5CBM+ | P5: 21KG+ | Q5: 0.5CBM+
A6: ONT8 | B6: 11.6 | C6: 1940 | D6: 11.1 | E6: 1845 | F6: 13~16 | G6: 19.02 | H6: 9 | I6: 1430 | J6: 8.5 | K6: 1330 | L6: 15~20 | M6: 22.02 | N6: 7.8 | O6: 1250 | P6: 8 | Q6: 1290 | R6: 16~20 | S6: 24.02
A7: LGB8 | B7: 11.6 | C7: 1940 | D7: 11.1 | E7: 1845 | F7: 13~16 | G7: 19.02 | H7: 9 | I7: 1430 | J7: 8.5 | K7: 1330 | L7: 15~20 | M7: 22.02 | N7: 7.8 | O7: 1250 | P7: 8 | Q7: 1290 | R7: 16~20 | S7: 24.02
A8: LAX9 | B8: 11.6 | C8: 1940 | D8: 11.1 | E8: 1845 | F8: 13~16 | G8: 19.02 | H8: 9 | I8: 1430 | J8: 8.5 | K8: 1330 | L8: 15~20 | M8: 22.02 | N8: 7.8 | O8: 1250 | P8: 8 | Q8: 1290 | R8: 16~20 | S8: 24.02
A9: SBD1 | B9: 11.6 | C9: 1940 | D9: 11.1 | E9: 1845 | F9: 13~16 | G9: 19.02 | H9: 9 | I9: 1430 | J9: 8.5 | K9: 1330 | L9: 15~20 | M9: 22.02 | N9: 7.8 | O9: 1250 | P9: 8 | Q9: 1290 | R9: 16~20 | S9: 24.02
A10: POC1 | B10: 11.9 | C10: 1950 | D10: 11.4 | E10: 1855 | F10: 14~18 | G10: * | H10: 9 | I10: 1440 | J10: 8.5 | K10: 1340 | L10: 16~22 | M10: 24.02 | N10: 7.8 | O10: 1280 | P10: 8 | Q10: 1320 | R10: 17~22 | S10: *
A11: POC2 | B11: 11.9 | C11: 1950 | D11: 11.4 | E11: 1855 | F11: 14~18 | G11: * | H11: 9 | I11: 1440 | J11: 8.5 | K11: 1340 | L11: 16~22 | M11: 24.02 | N11: 7.8 | O11: 1280 | P11: 8 | Q11: 1320 | R11: 17~22 | S11: *
A12: POC3 | B12: 11.9 | C12: 1950 | D12: 11.4 | E12: 1855 | F12: 14~18 | G12: * | H12: 9 | I12: 1440 | J12: 8.5 | K12: 1340 | L12: 16~22 | M12: 24.02 | N12: 7.8 | O12: 1280 | P12: 8 | Q12: 1320 | R12: 17~22 | S12: *
A13: IUSP | B13: 12.1 | C13: 1970 | D13: 11.6 | E13: 1875 | F13: 15~20 | G13: * | H13: 9.1 | I13: 1490 | J13: 8.6 | K13: 1390 | L13: 16~23 | M13: 26.02 | N13: 7.9 | O13: 1290 | P13: 7.9 | Q13: 1290 | R13: 18~23 | S13: 28.02
A14: LGB4 | B14: / | C14: / | D14: / | E14: / | F14: / | G14: / | H14: 9.1 | I14: 1450 | J14: 8.6 | K14: 1350 | L14: 16~22 | M14: * | N14: 8.1 | O14: 1330 | P14: 8.3 | Q14: 1370 | R14: 17~22 | S14: *
A15: LGB6 | B15: / | C15: / | D15: / | E15: / | F15: / | G15: / | H15: 9.4 | I15: 1530 | J15: 8.9 | K15: 1430 | L15: 16~22 | M15: * | N15: 8.2 | O15: 1350 | P15: 8.4 | Q15: 1390 | R15: 17~22 | S15: *
A16: FAT2 | B16: / | C16: / | D16: / | E16: / | F16: / | G16: / | H16: 9.8 | I16: 1570 | J16: 9.3 | K16: 1470 | L16: 16~22 | M16: 24.02 | N16: 8.3 | O16: 1380 | P16: 8.5 | Q16: 1420 | R16: 17~22 | S16: *
A17: SNA4 | B17: / | C17: / | D17: / | E17: / | F17: / | G17: / | H17: 9.4 | I17: 1530 | J17: 8.9 | K17: 1430 | L17: 16~22 | M17: 24.02 | N17: 8.3 | O17: 1350 | P17: 8.5 | Q17: 1390 | R17: 17~22 | S17: *
A18: SBD2 | B18: / | C18: / | D18: / | E18: / | F18: / | G18: / | H18: 9.4 | I18: 1530 | J18: 8.9 | K18: 1430 | L18: 16~22 | M18: 24.02 | N18: 8.3 | O18: 1350 | P18: 8.5 | Q18: 1390 | R18: 17~22 | S18: *
A19: PSP3 | B19: / | C19: / | D19: / | E19: / | F19: / | G19: / | H19: 9 | I19: 1490 | J19: 8.5 | K19: 1390 | L19: 17~22 | M19: * | N19: 7.9 | O19: 1290 | P19: 8.1 | Q19: 1330 | R19: 18~23 | S19: *
A20: LAS6 | B20: / | C20: / | D20: / | E20: / | F20: / | G20: / | H20: 10 | I20: 1650 | J20: 9.5 | K20: 1550 | L20: 17~22 | M20: 24.02 | N20: 8.9 | O20: 1450 | P20: 9.1 | Q20: 1490 | R20: 17~22 | S20: 26.02
A21: MCE1 | B21: / | C21: / | D21: / | E21: / | F21: / | G21: / | H21: 10.2 | I21: 1650 | J21: 9.7 | K21: 1550 | L21: 17~22 | M21: 24.02 | N21: 9 | O21: 1480 | P21: 9.2 | Q21: 1520 | R21: 17~22 | S21: 26.02
A22: PHX5 | B22: / | C22: / | D22: / | E22: / | F22: / | G22: / | H22: 10.2 | I22: 1650 | J22: 9.7 | K22: 1550 | L22: 16~21 | M22: 24.02 | N22: 9 | O22: 1480 | P22: 9.2 | Q22: 1520 | R22: 16~21 | S22: 26.02
A23: PHX7 | B23: / | C23: / | D23: / | E23: / | F23: / | G23: / | H23: 9.6 | I23: 1550 | J23: 9.1 | K23: 1450 | L23: 16~21 | M23: 24.02 | N23: 8.7 | O23: 1450 | P23: 8.9 | Q23: 1490 | R23: 16~21 | S23: 26.02
A24: LAS1 | B24: 12.6 | C24: 2070 | D24: 12.1 | E24: 1975 | F24: 13~17 | G24: 23.02 | H24: 9.7 | I24: 1570 | J24: 9.2 | K24: 1470 | L24: 16~21 | M24: 24.02 | N24: 8.6 | O24: 1380 | P24: 8.8 | Q24: 1420 | R24: 16~21 | S24: 26.02
A25: GYR2 | B25: 12.6 | C25: 2070 | D25: 12.1 | E25: 1975 | F25: 13~17 | G25: 23.02 | H25: 9.7 | I25: 1570 | J25: 9.2 | K25: 1470 | L25: 16~21 | M25: 24.02 | N25: 8.6 | O25: 1380 | P25: 8.8 | Q25: 1420 | R25: 16~21 | S25: 26.02
A26: GYR3 | B26: 12.6 | C26: 2070 | D26: 12.1 | E26: 1975 | F26: 13~17 | G26: 23.02 | H26: 9.7 | I26: 1570 | J26: 9.2 | K26: 1470 | L26: 16~21 | M26: 24.02 | N26: 8.6 | O26: 1380 | P26: 8.8 | Q26: 1420 | R26: 16~21 | S26: 26.02
A27: VGT2 | B27: 12.6 | C27: 2070 | D27: 12.1 | E27: 1975 | F27: 13~17 | G27: 23.02 | H27: 9.7 | I27: 1570 | J27: 9.2 | K27: 1470 | L27: 16~21 | M27: 24.02 | N27: 8.6 | O27: 1380 | P27: 8.8 | Q27: 1420 | R27: 16~21 | S27: 26.02
A28: GEU3 | B28: 12.6 | C28: 2070 | D28: 12.1 | E28: 1975 | F28: 13~17 | G28: 23.02 | H28: 9.7 | I28: 1580 | J28: 9.2 | K28: 1480 | L28: 16~21 | M28: 24.02 | N28: 8.6 | O28: 1380 | P28: 8.8 | Q28: 1420 | R28: 16~21 | S28: 26.02
A29: HLI2 | B29: 12.7 | C29: 2090 | D29: 12.2 | E29: 1995 | F29: 13~17 | G29: * | H29: 9.8 | I29: 1610 | J29: 9.3 | K29: 1510 | L29: 16~21 | M29: 24.02 | N29: 8.6 | O29: 1400 | P29: 8.8 | Q29: 1440 | R29: 16~21 | S29: *
A30: MIT2 | B30: 12.6 | C30: 2070 | D30: 12.1 | E30: 1975 | F30: 13~17 | G30: 23.02 | H30: 9.7 | I30: 1579 | J30: 9.2 | K30: 1479 | L30: 16~21 | M30: 24.02 | N30: 8.6 | O30: 1380 | P30: 8.8 | Q30: 1420 | R30: 16~21 | S30: 26.02
A31: GEU2 | B31: 12.6 | C31: 2070 | D31: 12.1 | E31: 1975 | F31: 13~17 | G31: 23.02 | H31: 9.7 | I31: 1590 | J31: 9.2 | K31: 1490 | L31: 16~21 | M31: 24.02 | N31: 8.6 | O31: 1380 | P31: 8.8 | Q31: 1420 | R31: 16~21 | S31: 26.02
A32: SMF3 | B32: 12.6 | C32: 2070 | D32: 12.1 | E32: 1975 | F32: 13~17 | G32: 25.02 | H32: 9.7 | I32: 1590 | J32: 9.2 | K32: 1490 | L32: 16~21 | M32: 25.02 | N32: 8.6 | O32: 1380 | P32: 8.8 | Q32: 1420 | R32: 16~21 | S32: 28.02
A33: SMF6 | B33: / | C33: / | D33: / | E33: / | F33: / | G33: / | H33: 9.9 | I33: 1600 | J33: 9.4 | K33: 1500 | L33: 17~22 | M33: 25.02 | N33: 8.6 | O33: 1410 | P33: 8.8 | Q33: 1450 | R33: 17~22 | S33: 28.02
A34: SCK1 | B34: / | C34: / | D34: / | E34: / | F34: / | G34: / | H34: 9.9 | I34: 1600 | J34: 9.4 | K34: 1500 | L34: 17~22 | M34: 25.02 | N34: 8.6 | O34: 1410 | P34: 8.8 | Q34: 1450 | R34: 17~22 | S34: 28.02
A35: SCK8 | B35: 12.6 | C35: 2070 | D35: 12.1 | E35: 1975 | F35: 14~18 | G35: * | H35: 9.7 | I35: 1560 | J35: 9.2 | K35: 1460 | L35: 17~22 | M35: * | N35: 8.4 | O35: 1380 | P35: 8.6 | Q35: 1420 | R35: 17~22 | S35: *
A36: SCK4 | B36: 12.6 | C36: 2070 | D36: 12.1 | E36: 1975 | F36: 13~17 | G36: 25.02 | H36: 9.7 | I36: 1600 | J36: 9.2 | K36: 1500 | L36: 16~21 | M36: 26.02 | N36: 8.5 | O36: 1380 | P36: 8.7 | Q36: 1420 | R36: 16~21 | S36: 28.02
A37: TCY1 | B37: 12.6 | C37: 2070 | D37: 12.1 | E37: 1975 | F37: 14~18 | G37: * | H37: 9.7 | I37: 1600 | J37: 9.2 | K37: 1500 | L37: 17~22 | M37: 26.02 | N37: 8.4 | O37: 1380 | P37: 8.6 | Q37: 1420 | R37: 17~22 | S37: *
A38: TCY2 | B38: 12.6 | C38: 2070 | D38: 12.1 | E38: 1975 | F38: 14~18 | G38: * | H38: 9.7 | I38: 1600 | J38: 9.2 | K38: 1500 | L38: 17~22 | M38: 26.02 | N38: 8.4 | O38: 1380 | P38: 8.6 | Q38: 1420 | R38: 17~22 | S38: *
A39: QXY8 | B39: 13.2 | C39: 2170 | D39: 12.7 | E39: 2075 | F39: 16~21 | G39: * | H39: 10.3 | I39: 1690 | J39: 9.8 | K39: 1590 | L39: 16~22 | M39: * | N39: 9 | O39: 1470 | P39: 9.2 | Q39: 1510 | R39: 19~24 | S39: *
A40: QZZ7 | B40: 13.2 | C40: 2150 | D40: 13.2 | E40: 2150 | F40: 16~21 | G40: * | H40: 10.2 | I40: 1670 | J40: 10.2 | K40: 1670 | L40: 16~21 | M40: 24.02 | N40: 9.3 | O40: 1490 | P40: 9.3 | Q40: 1490 | R40: 16~21 | S40: 26.02
A41: ABQ2 | B41: 13.1 | C41: 2180 | D41: 12.6 | E41: 2085 | F41: 14~18 | G41: 26.02 | H41: 10 | I41: 1660 | J41: 9.5 | K41: 1560 | L41: 16~22 | M41: 27.02 | N41: 9.2 | O41: 1490 | P41: 9.4 | Q41: 1530 | R41: 18~23 | S41: 29.02
A42: PSC2 | B42: 14 | C42: 2360 | D42: 13.5 | E42: 2265 | F42: 15~20 | G42: 29.02 | H42: 11.3 | I42: 1870 | J42: 10.8 | K42: 1770 | L42: 16~22 | M42: 30.02 | N42: 10.5 | O42: 1750 | P42: 10.7 | Q42: 1790 | R42: 18~23 | S42: 32.02
A43: MCC1 | B43: / | C43: / | D43: / | E43: / | F43: / | G43: / | H43: 9.9 | I43: 1700 | J43: 9.4 | K43: 1600 | L43: 16~22 | M43: * | N43: 8.9 | O43: 1520 | P43: 9.1 | Q43: 1560 | R43: 18~23 | S43: *
A44: SLC2 | B44: / | C44: / | D44: / | E44: / | F44: / | G44: / | H44: 10.8 | I44: 1770 | J44: 10.3 | K44: 1670 | L44: 20~25 | M44: 30.02 | N44: 10 | O44: 1650 | P44: 10.2 | Q44: 1690 | R44: 19~24 | S44: *
A45: FTW1 | B45: 13.6 | C45: 2280 | D45: 13.1 | E45: 2185 | F45: 16~21 | G45: 29.02 | H45: 10.9 | I45: 1790 | J45: 10.4 | K45: 1690 | L45: 18~23 | M45: 30.02 | N45: 9.7 | O45: 1590 | P45: 9.9 | Q45: 1630 | R45: 19~24 | S45: 32.02
A46: IAH3 | B46: 13.7 | C46: 2290 | D46: 13.2 | E46: 2195 | F46: 16~21 | G46: * | H46: 10.9 | I46: 1790 | J46: 10.4 | K46: 1690 | L46: 18~23 | M46: * | N46: 9.7 | O46: 1590 | P46: 9.9 | Q46: 1630 | R46: 19~24 | S46: *
A47: BJC1 | B47: / | C47: / | D47: / | E47: / | F47: / | G47: / | H47: 11.6 | I47: 1970 | J47: 11.1 | K47: 1870 | L47: 18~23 | M47: * | N47: 11 | O47: 1830 | P47: 11.2 | Q47: 1870 | R47: 19~24 | S47: *
A48: DEN8 | B48: / | C48: / | D48: / | E48: / | F48: / | G48: / | H48: 11.6 | I48: 1970 | J48: 11.1 | K48: 1870 | L48: 18~23 | M48: * | N48: 11 | O48: 1860 | P48: 11.2 | Q48: 1900 | R48: 19~24 | S48: *
A49: MDW2 | B49: 14.5 | C49: 2430 | D49: 14 | E49: 2335 | F49: 19~24 | G49: 32.02 | H49: 11.1 | I49: 1880 | J49: 10.6 | K49: 1780 | L49: 20~25 | M49: 33.02 | N49: 10.6 | O49: 1750 | P49: 10.8 | Q49: 1790 | R49: 20~25 | S49: 35.02
A50: IND9 | B50: 15.3 | C50: 2590 | D50: 14.8 | E50: 2495 | F50: 19~24 | G50: 32.02 | H50: 12.2 | I50: 2100 | J50: 11.7 | K50: 2000 | L50: 20~25 | M50: 33.02 | N50: 11.4 | O50: 1910 | P50: 11.6 | Q50: 1950 | R50: 20~25 | S50: 35.02
A51: FWA4 | B51: 14.3 | C51: 2390 | D51: 13.8 | E51: 2295 | F51: 19~24 | G51: 32.02 | H51: 11.3 | I51: 1890 | J51: 10.8 | K51: 1790 | L51: 20~25 | M51: 33.02 | N51: 10.4 | O51: 1710 | P51: 10.6 | Q51: 1750 | R51: 20~25 | S51: 35.02
A52: MQJ1 | B52: 15.1 | C52: 2550 | D52: 14.6 | E52: 2455 | F52: 19~24 | G52: 32.02 | H52: 12.4 | I52: 2110 | J52: 11.9 | K52: 2010 | L52: 20~25 | M52: 33.02 | N52: 11.2 | O52: 1870 | P52: 11.4 | Q52: 1910 | R52: 20~25 | S52: 35.02
A53: MEM1 | B53: 14.9 | C53: 2510 | D53: 14.4 | E53: 2415 | F53: 19~24 | G53: 32.02 | H53: 12.2 | I53: 2070 | J53: 11.7 | K53: 1970 | L53: 20~25 | M53: 33.02 | N53: 11 | O53: 1830 | P53: 11.2 | Q53: 1870 | R53: 20~25 | S53: 35.02
A54: RFD2 | B54: / | C54: / | D54: / | E54: / | F54: / | G54: / | H54: 10.9 | I54: 1810 | J54: 10.4 | K54: 1710 | L54: 19~23 | M54: * | N54: 10.3 | O54: 1710 | P54: 10.5 | Q54: 1750 | R54: 20~25 | S54: *
A55: PDX7 | B55: / | C55: / | D55: / | E55: / | F55: / | G55: / | H55: 12 | I55: 1980 | J55: 11.5 | K55: 1880 | L55: 21~27 | M55: 34.02 | N55: 11.1 | O55: 1850 | P55: 11.3 | Q55: 1890 | R55: 22~29 | S55: 36.02
A56: GEG2 | B56: / | C56: / | D56: / | E56: / | F56: / | G56: / | H56: 14.9 | I56: 2540 | J56: 14.4 | K56: 2440 | L56: 21~27 | M56: 34.02 | N56: 13.7 | O56: 2360 | P56: 13.9 | Q56: 2400 | R56: 22~29 | S56: 36.02
A57: ABE8 | B57: 15.6 | C57: 2600 | D57: 15.1 | E57: 2505 | F57: 21~26 | G57: 33.02 | H57: 12.8 | I57: 2130 | J57: 12.3 | K57: 2030 | L57: 21~27 | M57: 33.02 | N57: 12.2 | O57: 2070 | P57: 12.4 | Q57: 2110 | R57: 22~29 | S57: 36.02
A58: AVP1 | B58: 15.6 | C58: 2600 | D58: 15.1 | E58: 2505 | F58: 21~26 | G58: 33.02 | H58: 12.8 | I58: 2130 | J58: 12.3 | K58: 2030 | L58: 21~27 | M58: 33.02 | N58: 12.2 | O58: 2070 | P58: 12.4 | Q58: 2110 | R58: 22~29 | S58: 36.02
A59: CLT2 | B59: 15.4 | C59: 2560 | D59: 14.9 | E59: 2465 | F59: 21~26 | G59: 33.02 | H59: 12.6 | I59: 2090 | J59: 12.1 | K59: 1990 | L59: 21~27 | M59: * | N59: 11.7 | O59: 1970 | P59: 11.9 | Q59: 2010 | R59: 22~29 | S59: 36.02
A60: RMN3 | B60: 15.6 | C60: 2600 | D60: 15.1 | E60: 2505 | F60: 21~26 | G60: 33.02 | H60: 12.8 | I60: 2130 | J60: 12.3 | K60: 2030 | L60: 21~27 | M60: 33.02 | N60: 12.2 | O60: 2070 | P60: 12.4 | Q60: 2110 | R60: 22~29 | S60: 36.02
A61: ORF2 | B61: 15.6 | C61: 2600 | D61: 15.1 | E61: 2505 | F61: 21~26 | G61: 33.02 | H61: 12.8 | I61: 2130 | J61: 12.3 | K61: 2030 | L61: 21~27 | M61: 33.02 | N61: 12.2 | O61: 2070 | P61: 12.4 | Q61: 2110 | R61: 22~29 | S61: 36.02
A62: RDU2 | B62: 15.6 | C62: 2600 | D62: 15.1 | E62: 2505 | F62: 21~26 | G62: 33.02 | H62: 12.8 | I62: 2130 | J62: 12.3 | K62: 2030 | L62: 21~27 | M62: * | N62: 12.2 | O62: 2070 | P62: 12.4 | Q62: 2110 | R62: 22~29 | S62: 36.02
A63: TEB9 | B63: 15.9 | C63: 2650 | D63: 15.4 | E63: 2555 | F63: 21~26 | G63: * | H63: 12.9 | I63: 2150 | J63: 12.4 | K63: 2050 | L63: 21~27 | M63: * | N63: 12.1 | O63: 2030 | P63: 12.3 | Q63: 2070 | R63: 22~29 | S63: *
A64: SWF2 | B64: 15.6 | C64: 2600 | D64: 15.1 | E64: 2505 | F64: 21~26 | G64: * | H64: 12.8 | I64: 2130 | J64: 12.3 | K64: 2030 | L64: 21~27 | M64: * | N64: 12.2 | O64: 2070 | P64: 12.4 | Q64: 2110 | R64: 22~29 | S64: *
A65: 理赔时效 (从上海离港后第二天算起) | B65: Matson | H65: ZIM带托架 | N65: EMC快提\COSCO快速达
B66: 从上海离港后第二天算起，超过承诺时效，含税渠道:赔偿RMB1*KG*工作日，最高3RMB*KG； 不含税渠道:赔偿RMB100*CBM*工作日，最高赔偿300RMB*CBM。 船期延误、进出口查验、亚马逊问题不赔(删约*不放约*拒收*关仓等) | H66: 从盐田*南沙开船后第二天起算，超过承诺时效，含税渠道:赔偿0.5RMB*KG*工作日，最高1.5RMB*KG； 不含税渠道:赔偿50*CBM*工作日，最高150RMB*CBM。 船期延误、进出口查验、亚马逊问题不赔(删约*不放约*拒收*关仓等) | N66: 从盐田*上海开船后第二天起算，超过承诺时效，含税渠道:赔偿0.5RMB*KG*天，最高1.5RMB*KG；不含税渠道:赔偿50*CBM*天，最高150RMB*CBM。 船期延误、进出口查验、亚马逊问题不赔(删约*不放约*拒收*关仓等)
A68: 备注 | B68: Matson正班CLX线 1、含关税和查验费； 2、体积*6000； 3、不分泡，单件最低消费5KG 4、50-99KG +1*KG 5、21-49KG +2*KG 6、不足21KG按21KG计算 单边超120CM以上，单件超50KG以上的货物，请参考《发货必读》 ————————— 1、不含关税、如遇查验费实销； 2、计费重=长cm*宽cm*高cm*1000000，不分泡； 3、单边超120CM以上，请参考《发货必读》 4、如因客户资料\产品问题，需承担因此产生的所有仓租、柜租、罚金、销毁费等，恶意瞒报的还需承担进口商损失费2000美金； 5、表价不含5H,9H退运费,及罚没。 | H68: 以星*合德*OA定提 1、含关税和查验费； 2、体积*6000； 3、不分泡，单件最低消费5KG 4、50-99KG +1*KG 5、21-49KG +2*KG 6、不足21KG按21KG计算 单边超120CM以上，单件超50KG以上的货物，请参考《发货必读》 ————————— 1、不含关税、如遇查验费实销； 2、计费重=长cm*宽cm*高cm*1000000，不分泡； 3、单边超120CM以上，请参考《发货必读》 4、如因客户资料\产品问题，需承担因此产生的所有仓租、柜租、罚金、销毁费等，恶意瞒报的还需承担进口商损失费2000美金； 5、表价不含5H,9H退运费,及罚没。 | N68: EMC快提*COSCO 1、含关税和查验费； 2、体积*6000； 3、不分泡，单件最低消费5KG 4、50-99KG +1*KG 5、21-49KG +2*KG 6、不足21KG按21KG计算 单边超120CM以上，单件超50KG以上的货物，请参考《发货必读》 ————————— 1、不含关税、如遇查验费实销； 2、计费重=长cm*宽cm*高cm*1000000，不分泡； 3、单边超120CM以上，请参考《发货必读》 4、如因客户资料\产品问题，需承担因此产生的所有仓租、柜租、罚金、销毁费等，恶意瞒报的还需承担进口商损失费2000美金； 5、表价不含5H,9H退运费,及罚没。

Sheet 美西专线
A1: 深圳市博创兴供应链有限公司
A2: SHENZHEN BOCHANCE SHIPPING INTERNATIONAL SUPPLY CHAIN CO.LTD
A4: 美西OA快船专线
A5: 仓库代码 | B5: 深圳 | D5: 义乌\宁波 | F5: 预计航期*天 | G5: 参考时效 (开船后第二天起)*天
B6: 21KG+ | C6: 0.5CBM+ | D6: 21KG+ | E6: 0.5CBM+
A7: ONT8 | B7: 7.2 | C7: 1300 | D7: 7.2 | E7: 1300 | F7: 16 | G7: 19~24
A8: LGB8 | B8: 7.2 | C8: 1300 | D8: 7.2 | E8: 1300 | F8: 16 | G8: 19~24
A9: LAX9 | B9: 7.2 | C9: 1300 | D9: 7.2 | E9: 1300 | F9: 16 | G9: 19~24
A10: SBD1 | B10: 7.2 | C10: 1300 | D10: 7.2 | E10: 1300 | F10: 16 | G10: 19~24
A11: POC1 | B11: 7.3 | C11: 1310 | D11: 7.3 | E11: 1310 | F11: 16 | G11: 20~25
A12: POC2 | B12: 7.3 | C12: 1310 | D12: 7.3 | E12: 1310 | F12: 16 | G12: 22~28
A13: POC3 | B13: 7.3 | C13: 1310 | D13: 7.3 | E13: 1310 | F13: 16 | G13: 20~25
A14: SNA4 | B14: 7.7 | C14: 1370 | D14: 7.7 | E14: 1370 | F14: 16 | G14: 22~28
A15: XLX7 | B15: 7.9 | C15: 1290 | D15: 7.9 | E15: 1290 | F15: 16 | G15: 22~28
A16: SBD2 | B16: 7.7 | C16: 1370 | D16: 7.7 | E16: 1370 | F16: 16 | G16: 22~28
A17: LGB4 | B17: 7.7 | C17: 1270 | D17: 7.7 | E17: 1270 | F17: 16 | G17: 22~28
A18: LGB6 | B18: 7.7 | C18: 1370 | D18: 7.7 | E18: 1370 | F18: 16 | G18: 22~28
... A72: SWF2 | B72: 11.7 | C72: 1950 | D72: 11.7 | E72: 1950 | F72: 16 | G72: 24~30
A73: 备注 | B73: 1、含关税和查验费； 2、单票低消10KG，单票不足50KG加1*KG，另沃尔玛仓10~99KG加1*KG； 3、计费重：体积重和实重取大者，体积重=长cm*宽cm*高cm*6000； 4、单边超120CM以上，单件超50KG以上的货物，请参考《发货必读》 5、如因客户资料\产品问题，需承担因此产生的所有仓租、柜租、罚金、销毁费等，恶意瞒报的还需承担进口商损失费2000美金； 1、不含关税、如遇查验费实销； 2、计费重=长cm*宽cm*高cm*1000000，不分泡； 3、单边超120CM以上，请参考《发货必读》 4、如因客户资料\产品问题，需承担因此产生的所有仓租、柜租、罚金、销毁费等，恶意瞒报的还需承担进口商损失费2000美金； 5、沃尔玛仓点100+起收价格 6、表价不含5H,9H退运费,及罚没。

Sheet 经济线
A1: 深圳市博创兴供应链有限公司
A2: SHENZHEN BOCHANCE SHIPPING INTERNATIONAL SUPPLY CHAIN CO.LTD
A3: 经济线
A4: 仓库代码 | B4: 卸货港 | C4: 深圳 | E4: 义乌\宁波 | G4: 预计航期*天 | H4: 参考时效 (开船后第二天起)*天 | I4: 理赔时效(开船后第二天起)*天
C5: 21KG+ | D5: 1CBM+ | E5: 21KG+ | F5: 1CBM+
A6: ONT8 | B6: LA | C6: 6.9 | D6: 1220 | E6: 6.9 | F6: 1260 | G6: 16 | H6: 19~24 | I6: *
A7: LGB8 | B7: LA | C7: 6.9 | D7: 1220 | E7: 6.9 | F7: 1260 | G7: 16 | H7: 19~24 | I7: *
A8: SBD1 | B8: LA | C8: 6.9 | D8: 1220 | E8: 6.9 | F8: 1260 | G8: 16 | H8: 19~24 | I8: *
A9: LAX9 | B9: LA | C9: 6.9 | D9: 1220 | E9: 6.9 | F9: 1260 | G9: 16 | H9: 19~24 | I9: *
A10: POC1 | B10: LA | C10: 7 | D10: 1220 | E10: 7 | F10: 1260 | G10: 16 | H10: 19~24 | I10: *
A11: POC2 | B11: LA | C11: 7 | D11: 1220 | E11: 7 | F11: 1260 | G11: 16 | H11: 19~24 | I11: *
A12: POC3 | B12: LA | C12: 7 | D12: 1230 | E12: 7 | F12: 1270 | G12: 16 | H12: 19~24 | I12: *
A13: SMF3 | B13: LA | C13: 7.6 | D13: 1340 | E13: 7.6 | F13: 1380 | G13: 20 | H13: 23~29 | I13: *
A14: SCK4 | B14: LA | C14: 7.6 | D14: 1340 | E14: 7.6 | F14: 1380 | G14: 20 | H14: 23~29 | I14: *
A15: SCK8 | B15: LA | C15: 7.7 | D15: 1340 | E15: 7.7 | F15: 1380 | G15: 20 | H15: 23~29 | I15: *
A16: PSC2 | B16: LA | C16: 9.7 | D16: 1650 | E16: 9.7 | F16: 1690 | G16: 20 | H16: 24~27 | I16: *
A17: LAS1 | B17: LA | C17: 7.6 | D17: 1310 | E17: 7.6 | F17: 1350 | G17: 16 | H17: 19~25 | I17: *
... A25: ABQ2 | B25: LA | C25: 8.7 | D25: 1500 | E25: 8.7 | F25: 1540 | G25: 16 | H25: 20~26 | I25: *
A26: IAH3 | B26: HOU | C26: 7.8 | D26: 1290 | E26: 7.8 | F26: 1330 | G26: 28~35 | H26: 31~44 | I26: *
A27: FTW1 | B27: HOU | C27: 8.4 | D27: 1430 | E27: 8.4 | F27: 1470 | G27: 28~35 | H27: 31~44 | I27: *
A28: MDW2 | B28: CHI | C28: 8.9 | D28: 1510 | E28: 8.9 | F28: 1550 | G28: 30~38 | H28: 39~46 | I28: *
A29: IND9 | B29: CHI | C29: 9 | D29: 1510 | E29: 9 | F29: 1550 | G29: 30~38 | H29: 39~46 | I29: *
A30: ABE8 | B30: NY | C30: 7.9 | D30: 1310 | E30: 7.9 | F30: 1350 | G30: 32 | H30: 36~41 | I30: *
A31: TEB9 | B31: NY | C31: 7.9 | D31: 1310 | E31: 7.9 | F31: 1350 | G31: 32 | H31: 36~41 | I31: *
A32: SWF2 | B32: NY | C32: 8.1 | D32: 1390 | E32: 8.1 | F32: 1430 | G32: 32 | H32: 36~41
A33: AVP1 | B33: NY | C33: 8.2 | D33: 1400 | E33: 8.2 | F33: 1440 | G33: 32 | H33: 36~41 | I33: *
A34: CLT2 | B34: SAV | C34: 8 | D34: 1350 | E34: 8 | F34: 1390 | G34: 34 | H34: 40~45 | I34: *
A35: 备注 | C35: 1、含关税和查验费； 2、体积*6000； 3、不分泡，单件最低消费5KG 4、50-99KG +1*KG 5、21-49KG +2*KG 6、不足21KG按21KG计算 单边超120CM以上，单件超50KG以上的货物，请参考《发货必读》 —————————— 1、不含关税、如遇查验费实销； 2、计费重=长cm*宽cm*高cm*1000000，不分泡； 3、单边超120CM以上，请参考《发货必读》 4、如因客户资料\产品问题，需承担因此产生的所有仓租、柜租、罚金、销毁费等，恶意瞒报的还需承担进口商损失费2000美金； 5、表价不含5H,9H退运费,及罚没。

Sheet 美中专线
A1: 深圳市博创兴供应链有限公司 SHENZHEN BOCHANCE SHIPPING INTERNATIONAL SUPPLY CHAIN CO.LTD
A4: 芝加哥普船卡派 | H4: 芝加哥快速达卡派包税 | N4: 休斯顿专线卡派
A5: 仓库代码 | B5: 深圳 | D5: 义乌\宁波 | F5: 预计航期*天 | G5: 参考时效 (开船后第二天起)*天 | H5: 深圳 | J5: 义乌\宁波 | L5: 预计航期*天 | M5: 参考时效 (开船后第二天起)*天 | N5: 仓库代码 | O5: 深圳 | Q5: 义乌\宁波 | S5: 预计航期*天 | T5: 参考时效 (开船后第二天起)*天
B6: 21KG+ | C6: 0.5CBM+ | D6: 21KG+ | E6: 0.5CBM+ | H6: 21KG+ | I6: 0.5CBM+ | J6: 21KG+ | K6: 0.5CBM+ | O6: 21KG+ | P6: 0.5CBM+ | Q6: 21KG+ | R6: 0.5CBM+
A7: MDW2 | B7: 9.4 | C7: 1610 | D7: 9.4 | E7: 1610 | F7: 30-38 | G7: 39~46 | H7: 10.7 | I7: 1820 | J7: 10.7 | K7: 1820 | L7: 20.32 | M7: 24~29 | N7: HOU1 | O7: 8.4 | P7: 1410 | Q7: 8.7 | R7: 1470 | S7: 28~35 | T7: 32~46
A8: MDW6 | B8: 9.2 | C8: 1570 | D8: 9.2 | E8: 1570 | F8: 30-38 | G8: 39~46 | H8: 10.7 | I8: 1820 | J8: 10.7 | K8: 1820 | L8: 20.32 | M8: 24~29 | N8: HOU2 | O8: 8.4 | P8: 1410 | Q8: 8.7 | R8: 1470 | S8: 28~35 | T8: 32~46
A9: ORD2 | B9: 9.2 | C9: 1570 | D9: 9.2 | E9: 1570 | F9: 30-38 | G9: 39~46 | H9: 10.7 | I9: 1820 | J9: 10.7 | K9: 1820 | L9: 20.32 | M9: 24~29 | N9: HOU3 | O9: 8.4 | P9: 1410 | Q9: 8.7 | R9: 1470 | S9: 28~35 | T9: 32~46
A10: IGQ2 | B10: 9.2 | C10: 1570 | D10: 9.2 | E10: 1570 | F10: 30-38 | G10: 39~46 | H10: 10.7 | I10: 1820 | J10: 10.7 | K10: 1820 | L10: 20.32 | M10: 25~30 | N10: HOU7 | O10: 8.4 | P10: 1410 | Q10: 8.7 | R10: 1470 | S10: 28~35 | T10: 32~46
A11: RFD4 | B11: 9.3 | C11: 1590 | D11: 9.3 | E11: 1590 | F11: 30-38 | G11: 39~46 | H11: 11 | I11: 1840 | J11: 11 | K11: 1840 | L11: 20.32 | M11: 25~30 | N11: HOU8 | O11: 8.4 | P11: 1410 | Q11: 8.7 | R11: 1470 | S11: 28~35 | T11: 31~44
A12: RFD2 | B12: 9.3 | C12: 1590 | D12: 9.3 | E12: 1590 | F12: 30-38 | G12: 39~46 | H12: 11 | I12: 1840 | J12: 11 | K12: 1840 | L12: 20.32 | M12: 25~30 | N12: IAH3 | O12: 8.5 | P12: 1410 | Q12: 8.8 | R12: 1470 | S12: 28~35 | T12: 31~44
A13: STL3 | B13: 9.9 | C13: 1640 | D13: 9.9 | E13: 1640 | F13: 30-38 | G13: 42~48 | H13: 11.6 | I13: 1960 | J13: 11.6 | K13: 1960 | L13: 20.32 | M13: 25~30 | N13: FTW1 | O13: 8.9 | P13: 1520 | Q13: 9.2 | R13: 1580 | S13: 28~35 | T13: 31~44
A14: STL4 | B14: 9.9 | C14: 1640 | D14: 9.9 | E14: 1640 | F14: 30-38 | G14: 42~48 | H14: 11.6 | I14: 1960 | J14: 11.6 | K14: 1960 | L14: 20.32 | M14: 25~30 | N14: SAT6 | O14: 9 | P14: 1520 | Q14: 9.3 | R14: 1580 | S14: 28~35 | T14: 32~46
A15: IND5 | B15: 9.9 | C15: 1640 | D15: 9.9 | E15: 1640 | F15: 30-38 | G15: 42~48 | H15: 11.6 | I15: 1960 | J15: 11.6 | K15: 1960 | L15: 20.32 | M15: 25~30 | N15: SAT1 | O15: 9 | P15: 1520 | Q15: 9.3 | R15: 1580 | S15: 28~35 | T15: 31~44
A16: IND9 | B16: 9.9 | C16: 1640 | D16: 9.9 | E16: 1640 | F16: 30-38 | G16: 42~48 | H16: 11.6 | I16: 1960 | J16: 11.6 | K16: 1960 | L16: 20.32 | M16: 25~30 | N16: DFW6 | O16: 9 | P16: 1520 | Q16: 9.3 | R16: 1580 | S16: 28~35 | T16: 31~44
A17: MQJ1 | B17: 9.9 | C17: 1640 | D17: 9.9 | E17: 1640 | F17: 30-38 | G17: 42~48 | H17: 11.6 | I17: 1960 | J17: 11.6 | K17: 1960 | L17: 20.32 | M17: 25~30 | N17: FTW2 | O17: 9.1 | P17: 1520 | Q17: 9.4 | R17: 1580 | S17: 28~35 | T17: 32~46
A18: FWA4 | B18: 9.9 | C18: 1640 | D18: 9.9 | E18: 1640 | F18: 30-38 | G18: 42~48 | H18: 11.6 | I18: 1960 | J18: 11.6 | K18: 1960 | L18: 20.32 | M18: 25~30 | N18: FTW3 | O18: 9.1 | P18: 1520 | Q18: 9.4 | R18: 1580 | S18: 28~35 | T18: 32~46
... A26: MKC4 | B26: 10.5 | C26: 1790 | D26: 10.5 | E26: 1790 | F26: 30-38 | G26: 42~48 | H26: 12.7 | I26: 2200 | J26: 12.7 | K26: 2200 | L26: 20.32 | M26: 25~30 | N26: MEM8 | O26: 9.6 | P26: 1610 | Q26: 9.9 | R26: 1670 | S26: 28~35 | T26: 32~46
A27: MCI4 | B27: 11.98 | C27: 2090 | D27: 11.98 | E27: 2090 | F27: 30-38 | G27: 42~48 | H27: / | I27: / | J27: / | K27: / | L27: / | M27: / | N27: LFT1 | O27: 9.7 | P27: 1610 | Q27: 10 | R27: 1670 | S27: 28~35 | T27: 31~44
A28: * | B28: * | C28: * | D28: * | E28: * | F28: * | G28: * | H28: * | I28: * | J28: * | K28: * | L28: * | M28: * | N28: OKC2 | O28: 9.7 | P28: 1610 | Q28: 10 | R28: 1670 | S28: 28~35 | T28: 31~44
A29: * | B29: * | C29: * | D29: * | E29: * | F29: * | G29: * | H29: * | I29: * | J29: * | K29: * | L29: * | M29: * | N29: ICT2 | O29: 9.7 | P29: 1610 | Q29: 10 | R29: 1670 | S29: 28~35 | T29: 31~44
A30: * | B30: * | C30: * | D30: * | E30: * | F30: * | G30: * | H30: * | I30: * | J30: * | K30: * | L30: * | M30: * | N30: LIT2 | O30: 9.7 | P30: 1610 | Q30: 10 | R30: 1670 | S30: 28~35 | T30: 34~48
A31: * | B31: * | C31: * | D31: * | E31: * | F31: * | G31: * | H31: * | I31: * | J31: * | K31: * | L31: * | M31: * | N31: FOE1 | O31: 10.1 | P31: 1650 | Q31: 10.4 | R31: 1710 | S31: 28~35 | T31: 34~48
A32: 备注 | B32: 1、含关税和查验费； 2、单票低消10KG，单票不足50KG加1/KG； 3、计费重：体积重和实重取大者，体积重=长cm*宽cm*高cm/6000； 4、单边超120CM以上，单件超50KG以上的货物，请参考《发货必读》； 5、如因客户资料\产品问题，需承担因此产生的所有仓租、柜租、罚金、销毁费等，恶意瞒报的还需承担进口商损失费2000美金； 6、表价不含5H,9H退运费,及罚没。

Sheet 美东专线
A1: 深圳市博创兴供应链有限公司 SHENZHEN BOCHANCE SHIPPING INTERNATIONAL SUPPLY CHAIN CO.LTD
A4: 纽约普船 | H4: 纽约快船 | N4: 纽约特快
A5: 仓库代码 | B5: 深圳 | D5: 义乌\宁波 | F5: 预计航期*天 | G5: 参考时效 (开船后第二天起)*天 | H5: 深圳 | J5: 义乌\宁波 | L5: 预计航期*天 | M5: 参考时效 (开船后第二天起)*天 | N5: 深圳 | P5: 义乌\宁波 | R5: 预计航期*天 | S5: 参考时效 (开船后第二天起)*天 | T5: 理赔时效
B6: 21KG+ | C6: 0.5CBM+ | D6: 21KG+ | E6: 0.5CBM+ | H6: 21KG+ | I6: 0.5CBM+ | J6: 21KG+ | K6: 0.5CBM+ | N6: 21KG+ | O6: 0.5CBM+ | P6: 21KG+ | Q6: 0.5CBM+
A7: TEB3 | B7: 8.4 | C7: 1430 | D7: 8.4 | E7: 1430 | F7: 32 | G7: 37~43 | H7: 11.6 | I7: 1970 | J7: 11.6 | K7: 1970 | L7: 25 | M7: 29~33 | N7: 13.9 | O7: 2410 | P7: 13.9 | Q7: 2410 | R7: 21 | S7: 25~29 | T7: *
A8: TEB4 | B8: 8.4 | C8: 1430 | D8: 8.4 | E8: 1430 | F8: 32 | G8: 37~43 | H8: 11.6 | I8: 1970 | J8: 11.6 | K8: 1970 | L8: 25 | M8: 30~34 | N8: 13.9 | O8: 2410 | P8: 13.9 | Q8: 2410 | R8: 21 | S8: 26~30 | T8: *
A9: TEB6 | B9: 8.4 | C9: 1430 | D9: 8.4 | E9: 1430 | F9: 32 | G9: 36~41 | H9: 11.6 | I9: 1970 | J9: 11.6 | K9: 1970 | L9: 25 | M9: 29~33 | N9: 13.9 | O9: 2410 | P9: 13.9 | Q9: 2410 | R9: 21 | S9: 25~29 | T9: *
A10: TEB9 | B10: 8.4 | C10: 1430 | D10: 8.4 | E10: 1430 | F10: 32 | G10: 36~41 | H10: 11.6 | I10: 1970 | J10: 11.6 | K10: 1970 | L10: 25 | M10: 29~33 | N10: 13.9 | O10: 2410 | P10: 13.9 | Q10: 2410 | R10: 21 | S10: 25~29 | T10: 35
A11: ABE3 | B11: 8.5 | C11: 1470 | D11: 8.5 | E11: 1470 | F11: 32 | G11: 37~43 | H11: 11.7 | I11: 2020 | J11: 11.7 | K11: 2020 | L11: 25 | M11: 29~33 | N11: 14 | O11: 2450 | P11: 14 | Q11: 2450 | R11: 21 | S11: 25~29 | T11: *
A12: ABE4 | B12: 8.5 | C12: 1470 | D12: 8.5 | E12: 1470 | F12: 32 | G12: 37~43 | H12: 11.7 | I12: 2020 | J12: 11.7 | K12: 2020 | L12: 25 | M12: 29~33 | N12: 14 | O12: 2450 | P12: 14 | Q12: 2450 | R12: 21 | S12: 25~29 | T12: *
A13: ABE8 | B13: 8.4 | C13: 1430 | D13: 8.4 | E13: 1430 | F13: 32 | G13: 36~41 | H13: 11.6 | I13: 1970 | J13: 11.6 | K13: 1970 | L13: 25 | M13: 29~33 | N13: 14 | O13: 2410 | P13: 14 | Q13: 2410 | R13: 21 | S13: 25~29 | T13: 35
A14: ACY2 | B14: 8.4 | C14: 1430 | D14: 8.4 | E14: 1430 | F14: 32 | G14: 36~41 | H14: 11.6 | I14: 1970 | J14: 11.6 | K14: 1970 | L14: 25 | M14: 29~33 | N14: 14 | O14: 2410 | P14: 14 | Q14: 2410 | R14: 21 | S14: 25~29 | T14: 35
A15: ILG1 | B15: 8.9 | C15: 1540 | D15: 8.9 | E15: 1540 | F15: 32 | G15: 37~43 | H15: 12.1 | I15: 2090 | J15: 12.1 | K15: 2090 | L15: 25 | M15: 34~40 | N15: 14.4 | O15: 2520 | P15: 14.4 | Q15: 2520 | R15: 21 | S15: 30~36 | T15: *
A16: HEA2 | B16: 8.8 | C16: 1540 | D16: 8.8 | E16: 1540 | F16: 32 | G16: 37~43 | H16: 11.7 | I16: 2020 | J16: 11.7 | K16: 2020 | L16: 25 | M16: 32~38 | N16: 14.2 | O16: 2440 | P16: 14.2 | Q16: 2440 | R16: 21 | S16: 25~29 | T16: *
A17: AVP1 | B17: 8.8 | C17: 1460 | D17: 8.8 | E17: 1460 | F17: 32 | G17: 36~41 | H17: 11.7 | I17: 2020 | J17: 11.7 | K17: 2020 | L17: 25 | M17: 29~33 | N17: 14.2 | O17: 2440 | P17: 14.2 | Q17: 2440 | R17: 21 | S17: 25~29 | T17: 35
A18: AVP9 | B18: 8.8 | C18: 1460 | D18: 8.8 | E18: 1460 | F18: 32 | G18: 37~43 | H18: 11.7 | I18: 2020 | J18: 11.7 | K18: 2020 | L18: 25 | M18: 32~38 | N18: 14.2 | O18: 2440 | P18: 14.2 | Q18: 2440 | R18: 21 | S18: 28~34 | T18: *
A19: XEW5 | B19: 8.8 | C19: 1460 | D19: 8.8 | E19: 1460 | F19: 32 | G19: 36~41 | H19: 11.7 | I19: 2060 | J19: 11.7 | K19: 2060 | L19: 25 | M19: 29~33 | N19: 14.2 | O19: 2440 | P19: 14.2 | Q19: 2440 | R19: 21 | S19: 25~29 | T19: *
A20: PHL4 | B20: 9 | C20: 1520 | D20: 9 | E20: 1520 | F20: 32 | G20: 37~43 | H20: 12.2 | I20: 2070 | J20: 12.2 | K20: 2070 | L20: 25 | M20: 30~34 | N20: 14.4 | O20: 2510 | P20: 14.4 | Q20: 2510 | R20: 21 | S20: 26~30 | T20: *
A21: PHL5 | B21: 8.8 | C21: 1480 | D21: 8.8 | E21: 1480 | F21: 32 | G21: 37~43 | H21: 12 | I21: 2030 | J21: 12 | K21: 2030 | L21: 25 | M21: 30~34 | N21: 14.2 | O21: 2470 | P21: 14.2 | Q21: 2470 | R21: 21 | S21: 26~30 | T21: *
A22: PHL6 | B22: 8.8 | C22: 1480 | D22: 8.8 | E22: 1480 | F22: 32 | G22: 38~44 | H22: 12 | I22: 2030 | J22: 12 | K22: 2030 | L22: 25 | M22: 29~33 | N22: 14.2 | O22: 2470 | P22: 14.2 | Q22: 2470 | R22: 21 | S22: 25~29 | T22: 36
A23: SWF1 | B23: 8.8 | C23: 1480 | D23: 8.8 | E23: 1480 | F23: 32 | G23: 37~43 | H23: 12 | I23: 2030 | J23: 12 | K23: 2030 | L23: 25 | M23: 30~35 | N23: 14.2 | O23: 2470 | P23: 14.2 | Q23: 2470 | R23: 21 | S23: 26~31 | T23: 36
A24: SWF2 | B24: 8.8 | C24: 1480 | D24: 8.8 | E24: 1480 | F24: 32 | G24: 37~43 | H24: 12 | I24: 2030 | J24: 12 | K24: 2030 | L24: 25 | M24: 30~34 | N24: 14.2 | O24: 2470 | P24: 14.2 | Q24: 2470 | R24: 21 | S24: 26~30 | T24: 37
A25: MDT1 | B25: 8.8 | C25: 1480 | D25: 8.8 | E25: 1480 | F25: 32 | G25: 37~43 | H25: 12 | I25: 2030 | J25: 12 | K25: 2030 | L25: 25 | M25: 29~33 | N25: 14.2 | O25: 2470 | P25: 14.2 | Q25: 2470 | R25: 21 | S25: 25~29 | T25: *
A26: MDT4 | B26: 8.8 | C26: 1480 | D26: 8.8 | E26: 1480 | F26: 32 | G26: 37~43 | H26: 12 | I26: 2020 | J26: 12 | K26: 2020 | L26: 25 | M26: 30~35 | N26: 14.2 | O26: 2470 | P26: 14.2 | Q26: 2470 | R26: 21 | S26: 26~31 | T26: *
A27: DCA6 | B27: 8.8 | C27: 1510 | D27: 8.8 | E27: 1510 | F27: 32 | G27: 37~43 | H27: 12.1 | I27: 2050 | J27: 12.1 | K27: 2050 | L27: 25 | M27: 33~39 | N27: 14.4 | O27: 2510 | P27: 14.4 | Q27: 2510 | R27: 21 | S27: 29~35 | T27: 36
A28: TTN2 | B28: 8.9 | C28: 1480 | D28: 8.9 | E28: 1480 | F28: 32 | G28: 37~43 | H28: 11.8 | I28: 2000 | J28: 11.8 | K28: 2000 | L28: 25 | M28: 30~34 | N28: 14.3 | O28: 2460 | P28: 14.3 | Q28: 2460 | R28: 21 | S28: 26~30 | T28: 37
A29: HIA1 | B29: 9.2 | C29: 1480 | D29: 9.2 | E29: 1480 | F29: 32 | G29: 37~43 | H29: 12.2 | I29: 2060 | J29: 12.2 | K29: 2060 | L29: 25 | M29: 34~40 | N29: 14.6 | O29: 2470 | P29: 14.6 | Q29: 2470 | R29: 21 | S29: 30~36 | T29: 40
A30: LBE1 | B30: 9.2 | C30: 1480 | D30: 9.2 | E30: 1480 | F30: 32 | G30: 37~43 | H30: 12.2 | I30: 2040 | J30: 12.2 | K30: 2040 | L30: 25 | M30: 32~38 | N30: 14.6 | O30: 2470 | P30: 14.6 | Q30: 2470 | R30: 21 | S30: 28~34 | T30: 40
A31: ALB1 | B31: 9.3 | C31: 1530 | D31: 9.3 | E31: 1530 | F31: 32 | G31: 37~43 | H31: 12.2 | I31: 2090 | J31: 12.2 | K31: 2090 | L31: 25 | M31: 30~34 | N31: 14.7 | O31: 2510 | P31: 14.7 | Q31: 2510 | R31: 21 | S31: 26~30 | T31: 36
A32: PIT2 | B32: 9.3 | C32: 1530 | D32: 9.3 | E32: 1530 | F32: 32 | G32: 37~43 | H32: 12.2 | I32: 2090 | J32: 12.2 | K32: 2090 | L32: 25 | M32: 31~37 | N32: 14.7 | O32: 2510 | P32: 14.7 | Q32: 2510 | R32: 21 | S32: 27~33 | T32: *
A33: XLX1 | B33: 9.3 | C33: 1530 | D33: 9.3 | E33: 1530 | F33: 32 | G33: 37~43 | H33: 12.2 | I33: 2090 | J33: 12.2 | K33: 2090 | L33: 25 | M33: 32~38 | N33: 14.7 | O33: 2510 | P33: 14.7 | Q33: 2510 | R33: 21 | S33: 28~34 | T33: 36
A34: HGR6 | B34: 9.3 | C34: 1530 | D34: 9.3 | E34: 1530 | F34: 32 | G34: 37~43 | H34: 12.5 | I34: 2110 | J34: 12.5 | K34: 2110 | L34: 25 | M34: 32~38 | N34: 14.7 | O34: 2510 | P34: 14.7 | Q34: 2510 | R34: 21 | S34: 28~34 | T34: 40
A35: BOS7 | B35: 9.3 | C35: 1570 | D35: 9.3 | E35: 1570 | F35: 32 | G35: 37~43 | H35: 12.5 | I35: 2110 | J35: 12.5 | K35: 2110 | L35: 25 | M35: 31~37 | N35: 14.7 | O35: 2550 | P35: 14.7 | Q35: 2550 | R35: 21 | S35: 27~33 | T35: 36
A36: BWI4 | B36: 9.3 | C36: 1570 | D36: 9.3 | E36: 1570 | F36: 32 | G36: 37~43 | H36: 12.5 | I36: 2110 | J36: 12.5 | K36: 2110 | L36: 25 | M36: 30~35 | N36: 14.7 | O36: 2550 | P36: 14.7 | Q36: 2550 | R36: 21 | S36: 26~31 | T36: *
A37: BDL6 | B37: 9.3 | C37: 1570 | D37: 9.3 | E37: 1570 | F37: 32 | G37: 38~44 | H37: 12.5 | I37: 2110 | J37: 12.5 | K37: 2110 | L37: 25 | M37: 33~39 | N37: 14.7 | O37: 2550 | P37: 14.7 | Q37: 2550 | R37: 21 | S37: 29~35 | T37: *
A38: CHO1 | B38: 9.3 | C38: 1570 | D38: 9.3 | E38: 1570 | F38: 32 | G38: 37~43 | H38: 12.5 | I38: 2110 | J38: 12.5 | K38: 2110 | L38: 25 | M38: 34~36 | N38: 14.7 | O38: 2550 | P38: 14.7 | Q38: 2550 | R38: 21 | S38: 30~32 | T38: 38
A39: XRI3 | B39: 9.3 | C39: 1570 | D39: 9.3 | E39: 1570 | F39: 32 | G39: 37~43 | H39: 12.5 | I39: 2110 | J39: 12.5 | K39: 2110 | L39: 25 | M39: 29~33 | N39: 14.7 | O39: 2550 | P39: 14.7 | Q39: 2550 | R39: 21 | S39: 25~29 | T39: *
A40: ORF2 | B40: 9.3 | C40: 1570 | D40: 9.3 | E40: 1570 | F40: 32 | G40: 37~43 | H40: 12.5 | I40: 2110 | J40: 12.5 | K40: 2110 | L40: 25 | M40: 34~36 | N40: 14.7 | O40: 2550 | P40: 14.7 | Q40: 2550 | R40: 21 | S40: 30~32 | T40: 38
A41: RMN3 | B41: 9.3 | C41: 1570 | D41: 9.3 | E41: 1570 | F41: 32 | G41: 37~43 | H41: 12.5 | I41: 2110 | J41: 12.5 | K41: 2110 | L41: 25 | M41: 32~38 | N41: 14.7 | O41: 2550 | P41: 14.7 | Q41: 2550 | R41: 21 | S41: 28~34 | T41: 38
A42: CLT2 | B42: 9.4 | C42: 1630 | D42: 9.4 | E42: 1630 | F42: 32 | G42: 37~43 | H42: 12.7 | I42: 2190 | J42: 12.7 | K42: 2190 | L42: 25 | M42: 32~38 | N42: 14.9 | O42: 2610 | P42: 14.9 | Q42: 2610 | R42: 21 | S42: 28~34 | T42: 37
A43: GSO1 | B43: 9.4 | C43: 1630 | D43: 9.4 | E43: 1630 | F43: 32 | G43: 38~44 | H43: 12.7 | I43: 2190 | J43: 12.7 | K43: 2190 | L43: 25 | M43: 33~39 | N43: 14.9 | O43: 2610 | P43: 14.9 | Q43: 2610 | R43: 21 | S43: 29~35 | T43: *
A44: AKR1 | B44: 9.4 | C44: 1630 | D44: 9.4 | E44: 1630 | F44: 32 | G44: 37~43 | H44: 12.7 | I44: 2190 | J44: 12.7 | K44: 2190 | L44: 25 | M44: 32~38 | N44: 14.9 | O44: 2610 | P44: 14.9 | Q44: 2610 | R44: 21 | S44: 28~34 | T44: *
A45: XLX6 | B45: 9.4 | C45: 1630 | D45: 9.4 | E45: 1630 | F45: 32 | G45: 37~43 | H45: 12.7 | I45: 2190 | J45: 12.7 | K45: 2190 | L45: 25 | M45: 34~40 | N45: 14.9 | O45: 2610 | P45: 14.9 | Q45: 2610 | R45: 21 | S45: 30~36 | T45: 40
A46: RDU2 | B46: 9.4 | C46: 1630 | D46: 9.4 | E46: 1630 | F46: 32 | G46: 37~43 | H46: 12.7 | I46: 2190 | J46: 12.7 | K46: 2190 | L46: 25 | M46: 32~38 | N46: 14.9 | O46: 2610 | P46: 14.9 | Q46: 2610 | R46: 21 | S46: 28~34 | T46: 38
A47: IUSL | B47: 9.6 | C47: 1650 | D47: 9.6 | E47: 1650 | F47: 32 | G47: 40~47 | H47: 12.7 | I47: 2140 | J47: 12.7 | K47: 2140 | L47: 25 | M47: 32~38 | N47: 14.7 | O47: 2550 | P47: 14.7 | Q47: 2550 | R47: 21 | S47: 28~34 | T47: 38
A48: HGR2 | B48: 9.6 | C48: 1650 | D48: 9.6 | E48: 1650 | F48: 32 | G48: 37~43 | H48: 12.7 | I48: 2140 | J48: 12.7 | K48: 2140 | L48: 25 | M48: 34~40 | N48: 14.7 | O48: 2550 | P48: 14.7 | Q48: 2550 | R48: 21 | S48: 30~36 | T48: *
A49: IUST | B49: 9.8 | C49: 1640 | D49: 9.8 | E49: 1640 | F49: 32 | G49: 40~47 | H49: 12.7 | I49: 2140 | J49: 12.7 | K49: 2140 | L49: 25 | M49: 32~38 | N49: 15 | O49: 2620 | P49: 15 | Q49: 2620 | R49: 21 | S49: 28~34 | T49: *
A50: IUSR | B50: 9.9 | C50: 1760 | D50: 9.9 | E50: 1760 | F50: 32 | G50: 38~44 | H50: 13.1 | I50: 2270 | J50: 13.1 | K50: 2270 | L50: 25 | M50: 33~39 | N50: 15.5 | O50: 2740 | P50: 15.5 | Q50: 2740 | R50: 21 | S50: 29~35 | T50: *
A51: BNA2 | B51: 10.4 | C51: 1760 | D51: 10.4 | E51: 1760 | F51: 32 | G51: 37~43 | H51: 13.6 | I51: 2340 | J51: 13.6 | K51: 2340 | L51: 25 | M51: 32~38 | N51: 15.8 | O51: 2740 | P51: 15.8 | Q51: 2740 | R51: 21 | S51: 28~34 | T51: *
A52: CHA2 | B52: 10.4 | C52: 1760 | D52: 10.4 | E52: 1760 | F52: 32 | G52: 38~44 | H52: 13.6 | I52: 2340 | J52: 13.6 | K52: 2340 | L52: 25 | M52: 34~40 | N52: 16.1 | O52: 2810 | P52: 16.1 | Q52: 2810 | R52: 21 | S52: 30~36 | T52: 38
A53: BNA6 | B53: 10.4 | C53: 1760 | D53: 10.4 | E53: 1760 | F53: 32 | G53: 37~43 | H53: 13.6 | I53: 2340 | J53: 13.6 | K53: 2340 | L53: 25 | M53: 32~38 | N53: 15.8 | O53: 2740 | P53: 15.8 | Q53: 2740 | R53: 21 | S53: 28~34 | T53: *
A54: MGE1 | B54: 10.4 | C54: 1760 | D54: 10.4 | E54: 1760 | F54: 32 | G54: 37~43 | H54: 13.6 | I54: 2340 | J54: 13.6 | K54: 2340 | L54: 25 | M54: 34~40 | N54: 15.8 | O54: 2740 | P54: 15.8 | Q54: 2740 | R54: 21 | S54: 30~36 | T54: *
A55: HSV1 | B55: 10.4 | C55: 1760 | D55: 10.4 | E55: 1760 | F55: 32 | G55: 37~43 | H55: 13.6 | I55: 2340 | J55: 13.6 | K55: 2340 | L55: 25 | M55: 34~40 | N55: 15.8 | O55: 2740 | P55: 15.8 | Q55: 2740 | R55: 21 | S55: 30~36 | T55: *
A56: CMH3 | B56: 10.1 | C56: 1760 | D56: 10.1 | E56: 1760 | F56: 32 | G56: 37~43 | H56: 12.9 | I56: 2210 | J56: 12.9 | K56: 2210 | L56: 25 | M56: 32~38 | N56: 15.1 | O56: 2660 | P56: 15.1 | Q56: 2660 | R56: 21 | S56: 28~34 | T56: *
A57: CMH2 | B57: 10.1 | C57: 1780 | D57: 10.1 | E57: 1780 | F57: 32 | G57: 37~43 | H57: 12.9 | I57: 2210 | J57: 12.9 | K57: 2210 | L57: 25 | M57: 31~37 | N57: 15.1 | O57: 2680 | P57: 15.1 | Q57: 2680 | R57: 21 | S57: 27~33 | T57: 37
A58: CLT6 | B58: 10.1 | C58: 1790 | D58: 10.1 | E58: 1790 | F58: 32 | G58: 37~43 | H58: 12.9 | I58: 2210 | J58: 12.9 | K58: 2210 | L58: 25 | M58: 34~40 | N58: 15.1 | O58: 2690 | P58: 15.1 | Q58: 2690 | R58: 21 | S58: 30~36 | T58: *
A59: RYY2 | B59: 10.8 | C59: 1810 | D59: 10.8 | E59: 1810 | F59: 32 | G59: 37~43 | H59: 13.6 | I59: 2340 | J59: 13.6 | K59: 2340 | L59: 25 | M59: 34~40 | N59: 16.1 | O59: 2810 | P59: 16.1 | Q59: 2810 | R59: 21 | S59: 30~36 | T59: *
A60: MGE3 | B60: / | C60: / | D60: / | E60: / | F60: 32 | G60: 37~43 | H60: / | I60: / | J60: / | K60: / | L60: 25 | M60: 32~38 | N60: 16.1 | O60: 2810 | P60: 16.1 | Q60: 2810 | R60: 21 | S60: 28~34 | T60: *
A61: MCO2 | B61: 11.8 | C61: 1980 | D61: 11.8 | E61: 1980 | F61: 32 | G61: 37~43 | H61: 14.6 | I61: 2490 | J61: 14.6 | K61: 2490 | L61: 25 | M61: 32~38 | N61: 16.8 | O61: 2880 | P61: 16.8 | Q61: 2880 | R61: 21 | S61: 28~34 | T61: *
A62: TPA2 | B62: 11.8 | C62: 1980 | D62: 11.8 | E62: 1980 | F62: 32 | G62: 37~43 | H62: 14.6 | I62: 2490 | J62: 14.6 | K62: 2490 | L62: 25 | M62: 32~38 | N62: 16.8 | O62: 2880 | P62: 16.8 | Q62: 2880 | R62: 21 | S62: 28~34 | T62: *
A63: TPA3 | B63: 11.8 | C63: 1980 | D63: 11.8 | E63: 1980 | F63: 32 | G63: 37~43 | H63: 14.6 | I63: 2490 | J63: 14.6 | K63: 2490 | L63: 25 | M63: 32~38 | N63: 16.8 | O63: 2880 | P63: 16.8 | Q63: 2880 | R63: 21 | S63: 28~34 | T63: *
A64: 备注 | B64: COSCO\EMC\WHL： 1、含关税和查验费； 2、体积*6000； 3、不分泡，单件最低消费5KG 4、50-99KG +1*KG 5、21-49KG +2*KG 6、不足21KG按21KG计算 单边超120CM以上，单件超50KG以上的货物，请参考《发货必读》 —————————— 1、不含关税、如遇查验费实销； 2、计费重=长cm*宽cm*高cm*1000000，不分泡； 3、单边超120CM以上，请参考《发货必读》 4、如因客户资料\产品问题，需承担因此产生的所有仓租、柜租、罚金、销毁费等，恶意瞒报的还需承担进口商损失费2000美金； 5、表价不含5H,9H退运费,及罚没。 | H64: COSCO\ZIM： 1、含关税和查验费； 2、体积*6000； 3、不分泡，单件最低消费5KG 4、50-99KG +1*KG 5、21-49KG +2*KG 6、不足21KG按21KG计算 单边超120CM以上，单件超50KG以上的货物，请参考《发货必读》 —————————— 1、不含关税、如遇查验费实销； 2、计费重=长cm*宽cm*高cm*1000000，不分泡； 3、单边超120CM以上，请参考《发货必读》 4、如因客户资料\产品问题，需承担因此产生的所有仓租、柜租、罚金、销毁费等，恶意瞒报的还需承担进口商损失费2000美金； 5、表价不含5H,9H退运费,及罚没。 | N64: ZIM： 1、含关税和查验费； 2、体积*6000； 3、不分泡，单件最低消费5KG 4、50-99KG +1*KG 5、21-49KG +2*KG 6、不足21KG按21KG计算 单边超120CM以上，单件超50KG以上的货物，请参考《发货必读》 —————————— 1、不含关税、如遇查验费实销； 2、计费重=长cm*宽cm*高cm*1000000，不分泡； 3、单边超120CM以上，请参考《发货必读》 4、如因客户资料\产品问题，需承担因此产生的所有仓租、柜租、罚金、销毁费等，恶意瞒报的还需承担进口商损失费2000美金； 5、表价不含5H,9H退运费,及罚没。

Sheet 萨瓦纳专线
A1: 深圳市博创兴供应链有限公司 SHENZHEN BOCHANCE SHIPPING INTERNATIONAL SUPPLY CHAIN CO.LTD
A4: 萨瓦纳专线
A5: 仓库代码 | B5: 深圳 | D5: 义乌\宁波 | F5: 预计航期*天 | G5: 参考时效 (开船后第二天起)*天 | H5: 理赔时效(开船后第二天起)*天
B6: 21KG+ | C6: 0.5CBM+ | D6: 21KG+ | E6: 0.5CBM+
A7: JAX3 | B7: 8.7 | C7: 1470 | D7: 9 | E7: 1530 | F7: 34 | G7: 39~44 | H7: *
A8: XLX6 | B8: 8.7 | C8: 1470 | D8: 9 | E8: 1530 | F8: 34 | G8: 40~45 | H8: *
A9: GSO1 | B9: 8.7 | C9: 1470 | D9: 9 | E9: 1530 | F9: 34 | G9: 39~44 | H9: *
A10: RYY2 | B10: 8.7 | C10: 1470 | D10: 9 | E10: 1530 | F10: 34 | G10: 39~44 | H10: *
A11: CLT3 | B11: 8.7 | C11: 1470 | D11: 9 | E11: 1530 | F11: 34 | G11: 41~46 | H11: *
A12: CLT6 | B12: 8.7 | C12: 1470 | D12: 9 | E12: 1530 | F12: 34 | G12: 41~46 | H12: *
A13: RDU2 | B13: 8.7 | C13: 1470 | D13: 9 | E13: 1530 | F13: 34 | G13: 40~45 | H13: *
A14: IUSR | B14: 8.9 | C14: 1490 | D14: 9.2 | E14: 1550 | F14: 34 | G14: 40~45 | H14: *
A15: MGE3 | B15: 8.9 | C15: 1490 | D15: 9.2 | E15: 1550 | F15: 34 | G15: 39~44 | H15: *
A16: CLT2 | B16: 8.9 | C16: 1490 | D16: 9.2 | E16: 1550 | F16: 34 | G16: 40~45 | H16: *
A17: MCO2 | B17: 8.9 | C17: 1510 | D17: 9.2 | E17: 1570 | F17: 34 | G17: 39~44 | H17: *
A18: TPA2 | B18: 8.9 | C18: 1510 | D18: 9.2 | E18: 1570 | F18: 34 | G18: 40~45 | H18: *
... A28: MEM1 | B28: 9.3 | C28: 1530 | D28: 9.6 | E28: 1590 | F28: 34 | G28: 40~45 | H28: *
A29: 备注 | B29: 优先OA联盟： 1、含关税和查验费； 2、体积*6000； 3、不分泡，单件最低消费5KG 4、50-99KG +1*KG 5、21-49KG +2*KG 6、不足21KG按21KG计算 单边超120CM以上，单件超50KG以上的货物，请参考《发货必读》 —————————— 1、不含关税、如遇查验费实销； 2、计费重=长cm*宽cm*高cm*1000000，不分泡； 3、单边超120CM以上，请参考《发货必读》 4、如因客户资料\产品问题，需承担因此产生的所有仓租、柜租、罚金、销毁费等，恶意瞒报的还需承担进口商损失费2000美金； 5、表价不含5H,9H退运费,及罚没。

Sheet 海运整柜
A1: 深圳市凯琦供应链管理有限公司
A2: 地址：深圳市龙岗区坂田高新技术工业园2栋B座501-514
A3: 财务ATTN:洪小姐 电话：0755-28314752 网址：www.catchfba.com
A4: 海运整柜
A5: 渠道代码 仓库地址 | B5: F01-盐田普船 | E5: F01-盐田以星 | G5: F01-上海美森
B6: 运费 | C6: 卸货港 | D6: 备注 | E6: 运费 | F6: 备注 | G6: 运费 | H6: 备注
A7: 91邮编海外仓 | B7: 单询 | C7: 洛杉矶 | D7: 1、4截1开/5截3开，EMC，正常航期14天（塞港除外）； 2、其他船公司单询； | E7: - | F7: 1、7截3开，ZIM，正常航期12天 | G7: - | H7: 1、6截3开，MASTON，正常航期11天;
A8: ONT8、LGB8、LAX9 | B8: 单询 | C8: 洛杉矶 | E8: - | G8: -
A9: SMF3/SJC7/OAK3 | B9: 单询 | C9: 奥克兰 | E9: LA拆柜送 | G9: LA拆柜送
A10: LAS1、GYR3 | B10: 单询 | C10: 洛杉矶 | E10: LA拆柜送 | G10: LA拆柜送
A11: FTW1/FTW2/DFW6 | B11: - | C11: 达拉斯 | E11: LA拆柜送 | G11: LA拆柜送
A12: STA1 | B12: - | C12: 达拉斯 | E12: LA拆柜送 | G12: LA拆柜送
A13: MDW2 | B13: - | C13: 芝加哥 | E13: LA拆柜送 | G13: LA拆柜送
A14: IND9 | B14: - | C14: 芝加哥 | E14: LA拆柜送 | G14: LA拆柜送
A15: MEM1 | B15: - | C15: 孟菲斯 | E15: LA拆柜送 | G15: LA拆柜送
A16: ABE8 | B16: - | C16: 纽约 | E16: LA拆柜送 | G16: LA拆柜送
A17: 产品说明
A18: 以上为直送价格，亚马逊仓库请务必按亚马逊要求装柜，否则亚马逊有可能会拒收，我司不承担因仓库拒收产生的费用和责任
A19: 以上价格包含：基本运费，起运港杂费，目的港清关费（5个HSCODE），派送费，3天托架费，1-2个小时等候费（美西2小时，美中、美东1小时)
A20: 以上价格不包含：国内拖车费，码头提进费&落箱费（华东地区会产生），报关费，商检费，熏蒸费，政府部门申报费（如FDA,LACEY,EPA等），查验及查验引起的一切费用，关税，亚马逊预约及爆仓引起的仓租/柜租/预提/拒收等非可控因素导致的额外费用
A21: 实报实销费用明细：
A22: 1、HS CODE费用:RMB30/个
A23: 2、FDA/TSCA/LACEY/DOT/EPA等申报费：USD30/票
A24: 3、拖架费：USD35/天/柜,以星USD125/柜/天
A25: 4、预提费：USD150/柜；货柜存储费：USD35/天/柜（预提出来的柜子放海外仓仓库）
A26: 5、超时等候费：USD75/小时（美西） USD85/小时（美中&美东）
A27: 6、底盘分离: USD150-200/柜（等同于甩柜，商业海外仓才会产生，亚马逊仓不产生）
A28: 7、Layover fee：USD350/柜
... A37: 疫情期间因亚马逊不提供POD，所以暂不接受丢失索赔，建议自行购买保险

Sheet 美东海卡
A1: 深圳市凯琦供应链管理有限公司
A2: 地址：深圳市龙岗区坂田高新技术工业园2栋B座501-514
A3: 财务ATTN:洪小姐 电话：0755-28314752 网址：www.catchfba.com
A4: 美东海运+卡车派送
A5: 仓库地址 | B5: K15-纽约海卡（不包税） | F5: K15-纽约海卡B（含税） | H5: 时效参考
B6: 2CBM | C6: 10CBM | D6: 20CBM | E6: 备注 | F6: 150KG+ | G6: 关税附加费
A7: 美东海外仓 | B7: - | C7: 1440 | D7: 1440 | E7: 1、非报关件5CBM以内的+350/票， 2、关税、查验费实报实销(查验费按65CBM均摊) 3、重货按每300KG=1CBM | F7: 10(800KG+) | G7: 1、体积/6000,单件最低消费8KG，不分泡！ 2、含关税和查验费； 3、附加费见下 | H7: 提柜后3-7天
A8: ABE4、ABE8，TEB3、TEB6 | B8: 1750 | C8: 1700 | D8: 1700 | F8: 10.5 | H8: 提柜后3-7天
A9: EWR4、AVP3、AVP1 | B9: 1900 | C9: 1850 | D9: 1850 | F9: 11.5 | H9: 提柜后3-7天
A10: PHL5、PHL6 | B10: 1900 | C10: 1850 | D10: 1850 | F10: 11.5 | H10: 提柜后3-7天
A11: MDT1、MDT2 | B11: 1900 | C11: 1850 | D11: 1850 | F11: 11.5 | H11: 提柜后3-7天
A12: BWI4、RIC1、BOS7 | B12: 2100 | C12: 2050 | D12: 2050 | F12: 12.5 | H12: 提柜后4-8天
A13: CLT2、CLT3、GSP1 | B13: 2180 | C13: 2130 | D13: 2130 | F13: 13 | H13: 提柜后5-9天
A14: MGE3、ATL8、JAX3 | B14: - | C14: 2190 | D14: 2190 | F14: 13.5 | H14: 提柜后5-9天
A15: PIT5、TPA2、TPA1、BNA2 | B15: - | C15: 2190 | D15: 2190 | F15: 13.5 | H15: 提柜后5-9天
A16: CHA2、MCO5、LAL1 | B16: - | C16: 2190 | D16: 2190 | F16: 13.5 | H16: 提柜后5-9天
A17: 船期说明 | B17: 5截3开，航期29天到纽约（因美国塞港，最终船期和航期船公司以为准，预计38天+）
A18: 产品说明
A19: 1、单边超120cm的货物需按1.2倍体积计费，超过1.7cm的货物需双板派送，按2倍体积计费
A20: 2、因海关查验，船公司船期/航线变更/延迟到港，不可抗力如罢工、疫情原因导致亚马逊仓库关闭不在此时效范围内
A21: 一、附加费
A22: 1、报关件+350RMB/份单，备案大鹏海关！一达通报关件+500/票！漏报关仅赔偿3倍报关费，不接受可不出！
A23: 2、申报品名超5个以上的部分需加收30元/个
A24: 3、自税渠道：涉FDA、EPA产品+300RMB/品名；商检产品+500/票，移动电源+300/方，纯电池+400/方，需提供MSDS和运输报告
A25: 4、含税渠道：纺织品、木制品、FDA\EPA产品+1；厨房刀具、太阳能产品+2、移动电源、纯电池单询
A26: 5、涉认证产品需提供认证审核，确认OK后方可以出；我司不保证所有认证均可被目的国海关认可，不接受可以不出！
A27: 6、目的港扣货：操作费USD200/票；免柜租7天，超过7天收取USD5/CBM/天，最低收费15USD/天；超过3个月货物自动销毁；
A28: 二、注意事项：
A29: 1、自税渠道不足2CBM按2CBM计费，只保留小数点后1位（进位）
... A46: 3、如派送中收件方或寄件方要求或者错误地址无法投递导致退件,我司只接受货件退回我司美国仓库并免费保存货物7天,超出7天的按人民币5RMB/件/天计费,最低消费10RMB/票;退件过程产生的费用,我司将向发件方收取；如有退回货物要求重发的快件我们将按照12/KG的运费结算并加收50RMB/件操作费。

Sheet 美中海卡
A1: 深圳市凯琦供应链管理有限公司
A2: 地址：深圳市龙岗区坂田高新技术工业园2栋B座501-514
A3: 财务ATTN:洪小姐 电话：0755-28314752 网址：www.catchfba.com
A4: 美中海运+卡车派送
A5: 仓库地址 | B5: K13-美中海卡（不包税） | F5: K13-美中海卡B（含税） | H5: 时效参考
B6: 2CBM | C6: 10CBM | D6: 20CBM | E6: 备注 | F6: 150KG+ | G6: 关税附加费
A7: MDW6、MDW7、MDW9 | B7: 1180 | C7: 1180 | D7: 1180 | E7: 1、非报关件5CBM以内的+350/票， 2、关税、查验费实报实销(查验费按65CBM均摊) 3、重货按每300KG=1CBM | F7: 8.5 | G7: 1、体积/6000，单件最低消费8KG，不分泡！ 2、含关税和查验费； 3、附加费见下 | H7: 到芝加哥后5-7天递送
A8: MDW8 | B8: 1180 | C8: 1180 | D8: 1180 | F8: 8.5 | H8: 到芝加哥后5-7天递送
A9: JVL1 | B9: 1230 | C9: 1230 | D9: =D8+50 -> 1230 | F9: 8.8 | H9: 到芝加哥后5-7天递送
A10: IND2、IND5、IND9 | B10: 1230 | C10: 1230 | D10: 1230 | F10: 8.8 | H10: 到芝加哥后5-7天递送
A11: SDF8、CMH2、CMH3 | B11: 1230 | C11: 1230 | D11: 1230 | F11: 8.8 | H11: 到芝加哥后5-7天递送
A12: STL4 | B12: 1230 | C12: 1230 | D12: 1230 | F12: 8.8 | H12: 到芝加哥后5-7天递送
A13: DET1/DET2 | B13: 1260 | C13: 1260 | D13: =D8+80 -> 1260 | F13: 9 | H13: 到芝加哥后5-7天递送
A14: BNA2 | B14: 1340 | C14: 1340 | D14: 1340 | F14: 9.5 | H14: 到芝加哥后5-7天递送
A15: SDF其他、LEX1、LEX2 | B15: 1340 | C15: 1340 | D15: 1340 | F15: 9.5 | H15: 到芝加哥后6-10天递送 | J15: 暂停
A16: TUL1、MCI5、MCI7、ORD6 | B16: 1340 | C16: 1340 | D16: 1340 | F16: 9.5 | H16: 到芝加哥后6-10天递送
A17: MSP1、MKE1、MKE5 | B17: 1340 | C17: 1340 | D17: 1340 | F17: 9.5 | H17: 到芝加哥后6-10天递送
A18: MQJ1 | B18: 1420 | C18: 1420 | D18: 1420 | F18: 10 | H18: 到芝加哥后6-10天递送
A19: 船期说明 | B19: 4截1开，航期22天到芝加哥（因美国塞港，最终船期和航期船公司以为准，预计40天+）
A20: 产品说明
A21: 1、单边超120cm的货物需按1.2倍体积计费，超过1.7cm的货物需双板派送，按2倍体积计费
A22: 2、因海关查验，船公司船期/航线变更/延迟到港，不可抗力如罢工、疫情原因导致亚马逊仓库关闭不在此时效范围内
A23: 一、附加费
A24: 1、报关件+350RMB/份单，备案大鹏海关！一达通报关件+500/票！漏报关仅赔偿3倍报关费，不接受可不出！
A25: 2、申报品名超5个以上的部分需加收30元/个
A26: 3、自税渠道：涉FDA、EPA产品+300RMB/品名；商检产品+500/票，移动电源+300/方，纯电池+400/方，需提供MSDS和运输报告
A27: 4、含税渠道：纺织品、木制品、FDA\EPA产品+1；厨房刀具、太阳能产品+2、移动电源、纯电池单询
A28: 5、涉认证产品需提供认证审核，确认OK后方可以出；我司不保证所有认证均可被目的国海关认可，不接受可以不出！
A29: 6、目的港扣货：操作费USD200/票；免柜租7天，超过7天收取USD5/CBM/天，最低收费15USD/天；超过3个月货物自动销毁；
A30: 二、注意事项：
A31: 1、自税渠道不足2CBM按2CBM计费，只保留小数点后1位（进位）
... A48: 3、如派送中收件方或寄件方要求或者错误地址无法投递导致退件,我司只接受货件退回我司美国仓库并免费保存货物7天,超出7天的按人民币5RMB/件/天计费,最低消费10RMB/票;退件过程产生的费用,我司将向发件方收取；如有退回货物要求重发的快件我们将按照12/KG的运费结算并加收50RMB/件操作费。

Sheet 加拿大直航
A1: 深圳市博创兴供应链有限公司
A2: SHENZHEN BOCHANCE SHIPPING INTERNATIONAL SUPPLY CHAIN CO.LTD
A3: 加拿大直航卡派
A4: 仓库代码 | B4: 深圳 | C4: 义乌\宁波 | D4: 参考时效 (开船后第二天起)*天 | E4: 对应区域
A5: 多伦多-FBA仓 仓库代码 | B5: 101KG+ | C5: 101KG+
A6: YYZ3 | B6: 8.6 | C6: 8.6 | D6: 30~35天 | E6: 多伦多-FBA仓仓库代码
A7: YYZ4 | B7: 8.6 | C7: 8.6 | D7: 30~35天 | E7: 多伦多-FBA仓仓库代码
A8: YYZ1 | B8: 8.6 | C8: 8.6 | D8: 30~40天 | E8: 多伦多-FBA仓仓库代码
A9: YYZ2 | B9: 8.6 | C9: 8.6 | D9: 30~40天 | E9: 多伦多-FBA仓仓库代码
A10: YYZ6 | B10: 8.6 | C10: 8.6 | D10: 30~40天 | E10: 多伦多-FBA仓仓库代码
A11: YYZ7 | B11: 8.6 | C11: 8.6 | D11: 30~40天 | E11: 多伦多-FBA仓仓库代码
A12: YYZ9 | B12: 8.6 | C12: 8.6 | D12: 30~40天 | E12: 多伦多-FBA仓仓库代码
A13: YOO1 | B13: 9 | C13: 9 | D13: 30~40天 | E13: 多伦多-FBA仓仓库代码
A14: YHM1 | B14: 9 | C14: 9 | D14: 30~40天 | E14: 多伦多-FBA仓仓库代码
A15: YXU1 | B15: 9 | C15: 9 | D15: 30~40天 | E15: 多伦多-FBA仓仓库代码
A16: XYY1 | B16: 9 | C16: 9 | D16: 30~40天 | E16: 多伦多-FBA仓仓库代码
A17: YOW1 | B17: 9.2 | C17: 9.2 | D17: 30~40天 | E17: 多伦多-FBA仓仓库代码
... A30: YEG2 | B30: 8.4 | C30: 8.4 | D30: 35~45天 | E30: 卡尔加里-FBA仓仓库代码
B31: YGK1最小收货尺寸为:不低于50LBS，尺寸 不小于33*33*59 INCH
A32: 附加费 | B32: 1、含关税和查验费； 2、单票低消21KG，低于100KG的按照21-49KG单价+2RMB*KG 50-99KG单价+1RMB*KG，低消最低1CBM起收，单件最低5KG起，不足5KG按5KG计费，财务默认出账单； 3、计费重：体积重和实重取大者，体积重=长cm*宽cm*高cm*6000； 4、超长*超重附加：120cm＜外箱单边长度≤150cm，包税+RMB1.2*KG,不包税+228*CBM；150cm＜外箱单边长度≤200cm、包税+RMB1.8*KG,不包税+285*CBM；外箱单边长度＞2m单询； 30KG＜单件实重＜70KG，包税+RMB10*件。（适用于商业*私人*亚马逊可接收地址，另亚马逊收货尺寸*重量限制请客户出货前自行确认*咨询我司客服同事）
A33: 拒收产品 | B33: 1、手机、智能手环、假发、汽车诊断仪、望远镜、硒鼓、化妆品（面膜等），3岁以下儿童产品、婴儿玩具、母婴用品，二类医疗产品（牙刷、牙线、冲牙器、吸奶器等）、禁塑令产品（一次性纸杯等）、成人用品； 2、液体、纯电池、食品、粉末、移动电源、电子烟、制毒用品、医疗用品、仿牌商品、化工产品、美国*加拿大反倾销产品等。如发现冲货罚款RMB2000*票。 3、纯太阳能板、筋膜枪等按摩类产品
A34: 备注 | B34: OA为主： 1、含关税和查验费； 2、体积*6000； 3、不分泡，单件最低消费5KG 4、50-99KG +1*KG 5、21-49KG +2*KG 6、不足21KG按21KG计算 单边超120CM以上，单件超50KG以上的货物，请参考《发货必读》 —————————— 1、不含关税、如遇查验费实销； 2、计费重=长cm*宽cm*高cm*1000000，不分泡； 3、单边超120CM以上，请参考《发货必读》 4、如因客户资料\产品问题，需承担因此产生的所有仓租、柜租、罚金、销毁费等，恶意瞒报的还需承担进口商损失费2000美金； 5、表价不含5H,9H退运费,及罚没。

Sheet 沃尔玛专线
A1: 深圳市博创兴供应链有限公司 SHENZHEN BOCHANCE SHIPPING INTERNATIONAL SUPPLY CHAIN CO.LTD
A4: 沃尔玛专线
A5: 仓库代码 | B5: 深圳 | D5: 义乌 | F5: 预计航期*天 | G5: 参考时效 (开船后第二天起)*天 | H5: 目的港 | I5: 对应渠道
B6: 21KG+ | C6: 0.5CBM+ | D6: 21KG+ | E6: 0.5CBM+
A7: WMT-LAX2 | B7: 12.3 | C7: 1990 | D7: 11.8 | E7: 1895 | F7: 11 | G7: 15~20 | H7: LA | I7: 美森正班卡派
A8: WMT-LAX2T | B8: 12.3 | C8: 1990 | D8: 11.8 | E8: 1895 | F8: 11 | G8: 15~20
A9: WMT-LAX2 | B9: 9.6 | C9: 1590 | D9: 9.1 | E9: 1490 | F9: 13 | G9: 17~22 | H9: LA | I9: 以星*合德*带托（统配）卡派
A10: WMT-LAX2T | B10: 9.6 | C10: 1590 | D10: 9.1 | E10: 1490 | F10: 13 | G10: 17~22
A11: WMT-LAX2 | B11: 8.7 | C11: 1440 | D11: 8.9 | E11: 1480 | F11: 14 | G11: 17~22 | H11: LA | I11: EMC快速达卡派
A12: WMT-LAX2T | B12: 8.7 | C12: 1440 | D12: 8.9 | E12: 1480 | F12: 14 | G12: 17~22
A13: WMT-LAX2 | B13: 8 | C13: 1360 | D13: 8 | E13: 1360 | F13: 16 | G13: 22~28 | H13: LA | I13: 美西OA快船专线
A14: WMT-LAX2T | B14: 8 | C14: 1360 | D14: 8 | E14: 1360 | F14: 16 | G14: 22~28
A15: WMT-LAX2 | B15: 7.3 | C15: 1240 | D15: 7.3 | E15: 1280 | F15: 16 | G15: 19~25 | H15: LA | I15: 经济线
A16: WMT-LAX2T | B16: 7.3 | C16: 1240 | D16: 7.3 | E16: 1280 | F16: 16 | G16: 19~25
A17: WMT-DFW5s | B17: 9.2 | C17: 1500 | D17: 9.7 | E17: 1600 | F17: 28~35 | G17: 31~46 | H17: HOU | I17: K13美中专线
A18: WMT-DFW6s | B18: 9.2 | C18: 1500 | D18: 9.7 | E18: 1600 | F18: 28~35 | G18: 31~46
A19: WMT-DFW2n | B19: 9.2 | C19: 1500 | D19: 9.7 | E19: 1600 | F19: 28~35 | G19: 31~46
A20: WMT-IND3 | B20: 9.5 | C20: 1540 | D20: 9.5 | E20: 1540 | F20: 30~38 | G20: 40~48 | H20: CHI | I20: 芝加哥普船卡派
A21: WMT-CVG1n | B21: 10 | C21: 1620 | D21: 10 | E21: 1620 | F21: 30~38 | G21: 40~48
A22: WMT-KS1 | B22: 10.3 | C22: 1680 | D22: 10.3 | E22: 1680 | F22: 30~38 | G22: 40~48
A23: WMT-KY1 | B23: 10.3 | C23: 1680 | D23: 10.3 | E23: 1680 | F23: 30~38 | G23: 40~48
A24: WMT-IND2n | B24: 9.5 | C24: 1540 | D24: 9.5 | E24: 1540 | F24: 30~38 | G24: 40~48
A25: WMT-ORD1s | B25: 9.2 | C25: 1480 | D25: 9.2 | E25: 1480 | F25: 30~38 | G25: 40~48
A26: WMT-MCI1n | B26: 10.3 | C26: 1680 | D26: 10.3 | E26: 1680 | F26: 30~38 | G26: 40~48
A27: WMT-IND1 | B27: 10.7 | C27: 1810 | D27: 10.7 | E27: 1810 | F27: 30~38 | G27: 40~48
A28: WMT-IND2t | B28: 9.5 | C28: 1540 | D28: 9.5 | E28: 1540 | F28: 30~38 | G28: 40~48
A29: WMT-IND2 | B29: 9.5 | C29: 1540 | D29: 9.5 | E29: 1540 | F29: 30~38 | G29: 40~48
A30: WMT-IND3 | B30: 11.1 | C30: 1820 | D30: 11.1 | E30: 1820 | F30: 20 | G30: 37~39 | H30: CHI | I30: 芝加哥快线
A31: WMT-CVG1n | B31: 11.5 | C31: 1880 | D31: 11.5 | E31: 1880 | F31: 20 | G31: 37~39
A32: WMT-KS1 | B32: 11.9 | C32: 1950 | D32: 11.9 | E32: 1950 | F32: 20 | G32: 37~39
A33: WMT-KY1 | B33: 11.9 | C33: 1950 | D33: 11.9 | E33: 1950 | F33: 20 | G33: 37~39
A34: WMT-IND2n | B34: 11.1 | C34: 1820 | D34: 11.1 | E34: 1820 | F34: 20 | G34: 37~39
A35: WMT-ORD1s | B35: 10.8 | C35: 1760 | D35: 10.8 | E35: 1760 | F35: 20 | G35: 37~39
A36: WMT-MCI1n | B36: 11.9 | C36: 1950 | D36: 11.9 | E36: 1950 | F36: 20 | G36: 37~39
A37: WMT-IND1 | B37: 12.3 | C37: 2090 | D37: 12.3 | E37: 2090 | F37: 20 | G37: 37~39
A38: WMT-IND2t | B38: 11.1 | C38: 1820 | D38: 11.1 | E38: 1820 | F38: 20 | G38: 37~39
A39: WMT-IND2 | B39: 11.1 | C39: 1820 | D39: 11.1 | E39: 1820 | F39: 20 | G39: 37~39
A40: WMT-NJ1 | B40: 9.8 | C40: 1640 | D40: 9.8 | E40: 1640 | F40: 32 | G40: 40~47 | H40: NY | I40: 纽约普船
A41: WMT-NJ3 | B41: 10 | C41: 1680 | D41: 10 | E41: 1680 | F41: 32 | G41: 40~47
A42: WMT-NJ3T | B42: 10 | C42: 1680 | D42: 10 | E42: 1680 | F42: 32 | G42: 40~47
A43: WMT-PHL2n | B43: 10 | C43: 1690 | D43: 10 | E43: 1690 | F43: 32 | G43: 40~47
A44: WMT-PHL1S | B44: 10 | C44: 1690 | D44: 10 | E44: 1690 | F44: 32 | G44: 40~47
A45: WMT-PHL4n | B45: 9.8 | C45: 1690 | D45: 9.8 | E45: 1690 | F45: 32 | G45: 40~47
A46: WMT-PHL5s | B46: 10 | C46: 1730 | D46: 10 | E46: 1730 | F46: 32 | G46: 40~47
A47: WMT-MEM1s | B47: 12 | C47: 2080 | D47: 12 | E47: 2080 | F47: 32 | G47: 40~47
A48: WMT-BNA1s | B48: 11.6 | C48: 2000 | D48: 11.6 | E48: 2000 | F48: 32 | G48: 40~47
A49: WMT-NJ1 | B49: 14.8 | C49: 2540 | D49: 14.8 | E49: 2540 | F49: 21 | G49: 28~34 | H49: NY | I49: 纽约特快
A50: WMT-NJ3 | B50: 15.4 | C50: 2660 | D50: 15.4 | E50: 2660 | F50: 21 | G50: 28~34
A51: WMT-NJ3T | B51: 15.4 | C51: 2660 | D51: 15.4 | E51: 2660 | F51: 21 | G51: 28~34
A52: WMT-PHL2n | B52: 15 | C52: 2590 | D52: 15 | E52: 2590 | F52: 21 | G52: 28~34
A53: WMT-PHL1S | B53: 15 | C53: 2590 | D53: 15 | E53: 2590 | F53: 21 | G53: 28~34
A54: WMT-PHL4n | B54: 15 | C54: 2590 | D54: 15 | E54: 2590 | F54: 21 | G54: 28~34
A55: WMT-PHL5s | B55: 15.4 | C55: 2670 | D55: 15.4 | E55: 2670 | F55: 21 | G55: 28~34
A56: WMT-MEM1s | B56: 17 | C56: 2980 | D56: 17 | E56: 2980 | F56: 21 | G56: 28~34
A57: WMT-BNA1s | B57: 16.6 | C57: 2910 | D57: 16.6 | E57: 2910 | F57: 21 | G57: 28~34
A58: WMT-NJ1 | B58: 12.9 | C58: 2180 | D58: 12.9 | E58: 2180 | F58: 25 | G58: 32~38 | H58: NY | I58: 纽约快船
A59: WMT-NJ3 | B59: 13 | C59: 2200 | D59: 13 | E59: 2200 | F59: 25 | G59: 32~38
A60: WMT-NJ3T | B60: 13 | C60: 2200 | D60: 13 | E60: 2200 | F60: 25 | G60: 32~38
A61: WMT-PHL2n | B61: 13.1 | C61: 2230 | D61: 13.1 | E61: 2230 | F61: 25 | G61: 32~38
A62: WMT-PHL1S | B62: 13.1 | C62: 2230 | D62: 13.1 | E62: 2230 | F62: 25 | G62: 32~38
A63: WMT-PHL4n | B63: 13.1 | C63: 2230 | D63: 13.1 | E63: 2230 | F63: 25 | G63: 32~38
A64: WMT-PHL5s | B64: 13.1 | C64: 2230 | D64: 13.1 | E64: 2230 | F64: 25 | G64: 32~38
A65: WMT-MEM1s | B65: 15.1 | C65: 2620 | D65: 15.1 | E65: 2620 | F65: 25 | G65: 32~38
A66: WMT-BNA1s | B66: 14.7 | C66: 2550 | D66: 14.7 | E66: 2550 | F66: 25 | G66: 32~38
A67: WMT-ATL1 | B67: 8.6 | C67: 1450 | D67: 8.9 | E67: 1510 | F67: 34 | G67: 40~45 | H67: SAV | I67: 萨瓦纳专线
A68: WMT-ATL2 | B68: 9.1 | C68: 1470 | D68: 9.1 | E68: 1470 | F68: 34 | G68: 40~45
A69: WMT-ATL3 | B69: 8.6 | C69: 1450 | D69: 8.9 | E69: 1510 | F69: 34 | G69: 40~45
A70: WMT-ATL2n | B70: 11.4 | C70: 1960 | D70: 11.4 | E70: 1960 | F70: 34 | G70: 40~45
A71: WMT-MCO1 | B71: 9.2 | C71: 1490 | D71: 9.2 | E71: 1490 | F71: 34 | G71: 40~45
A72: WMT-BNA1N | B72: 9.4 | C72: 1520 | D72: 9.4 | E72: 1520 | F72: 34 | G72: 40~45
A73: 备注 | B73: 1、含关税和查验费； 2、单票低消100KG， 不足100kg按100kg计费； 3、计费重：体积重和实重取大者，体积重=长cm*宽cm*高cm/6000； 4、单边超120CM以上，单件超50KG以上的货物，请参考《发货必读》 5、如因客户资料\产品问题，需承担因此产生的所有仓租、柜租、罚金、销毁费等，恶意瞒报的还需承担进口商损失费2000美金； 6、表价不含5H,9H退运费,及罚没。
B74: 1、不含关税、如遇查验费实销； 2、低消0.5CBM，不足按0.5CBM结算； 3、计费重=长cm*宽cm*高cm/1000000，不分泡； 4、单边超120CM以上，请参考《发货必读》 5、如因客户资料\产品问题，需承担因此产生的所有仓租、柜租、罚金、销毁费等，恶意瞒报的还需承担进口商损失费2000美金； 6、表价不含5H,9H退运费,及罚没。

Sheet 商业地址
A1: 深圳市博创兴供应链有限公司
A2: SHENZHEN BOCHANCE SHIPPING INTERNATIONAL SUPPLY CHAIN CO.LTD
A3: 美森正班卡派 | I3: 以星*合德*带托（统配）卡派 | O3: EMC快速达卡派 | U3: 美西OA快船专线
A4: 仓库代码 | B4: 邮编 | C4: 深圳 | E4: 义乌\宁波 | G4: 参考时效 (开船后第二天起)*天 | H4: 理赔时效(开船后第二天起)*天 | I4: 深圳 | K4: 义乌\宁波 | M4: 参考时效 (开船后第二天起)*天 | N4: 理赔时效(开船后第二天起)*天 | O4: 深圳 | Q4: 义乌\宁波 | S4: 参考时效 (开船后第二天起)*天 | T4: 理赔时效(开船后第二天起)*天 | U4: 仓库代码 | V4: 邮编 | W4: 深圳 | Y4: 义乌\宁波 | AA4: 预计航期*天 | AB4: 参考时效 (开船后第二天起)*天
C5: 334KG+ | D5: 2CBM+ | E5: 334KG+ | F5: 2CBM+ | I5: 334KG+ | J5: 2CBM+ | K5: 334KG+ | L5: 2CBM+ | O5: 334KG+ | P5: 2CBM+ | Q5: 334KG+ | R5: 2CBM+ | W5: 334KG+ | X5: 2CBM+ | Y5: 334KG+ | Z5: 2CBM+
A6: 洛杉矶FBN头程 | B6: / | C6: 12.4 | D6: 2150 | E6: 11.9 | F6: 2060 | G6: 11 | H6: 12~15天 | I6: 9.8 | J6: 1630 | K6: 9.8 | L6: 1630 | M6: 13 | N6: 18~19天 | O6: 9 | P6: 1470 | Q6: 9.5 | R6: 1570 | S6: 14 | T6: 19~20天 | U6: 洛杉矶FBN头程 | V6: / | W6: 8.3 | X6: 1490 | Y6: 8.3 | Z6: 1490 | AA6: 16 | AB6: 21~25天
A7: 云仓-USCA01 | B7: 91761 | C7: 12.4 | D7: 2150 | E7: 11.9 | F7: 2060 | G7: 11 | H7: 15~20天 | I7: 9.8 | J7: 1630 | K7: 9.8 | L7: 1630 | M7: 13 | N7: 18~24天 | O7: 9 | P7: 1470 | Q7: 9.5 | R7: 1570 | S7: 14 | T7: 19~25天 | U7: 云仓-USCA01 | V7: 91761 | W7: 8.3 | X7: 1490 | Y7: 8.3 | Z7: 1490 | AA7: 16 | AB7: 25~32天
A8: YC美西仓 | B8: 91710 | C8: 12.7 | D8: 2280 | E8: 12.2 | F8: 2190 | G8: 11 | H8: 15~20天 | I8: 10.2 | J8: 1980 | K8: 10.2 | L8: 1980 | M8: 13 | N8: 18~24天 | O8: 9.3 | P8: 1800 | Q8: 9.8 | R8: 1900 | S8: 14 | T8: 19~25天 | U8: YC美西仓 | V8: 91710 | W8: 8.8 | X8: 1590 | Y8: 8.8 | Z8: 1590 | AA8: 16 | AB8: 25~32天
A9: 万邑通91789 | B9: 91789 | C9: 13.2 | D9: 2340 | E9: 12.7 | F9: 2250 | G9: 11 | H9: 15~20天 | I9: 10.7 | J9: 2080 | K9: 10.7 | L9: 2080 | M9: 13 | N9: 18~24天 | O9: 9.8 | P9: 1900 | Q9: 10.3 | R9: 2000 | S9: 14 | T9: 19~25天 | U9: 万邑通91789 | V9: 91789 | W9: 9.3 | X9: 1690 | Y9: 9.3 | Z9: 1690 | AA9: 16 | AB9: 25~32天
A10: 万邑通91748 | B10: 91748 | C10: 13.2 | D10: 2340 | E10: 12.7 | F10: 2250 | G10: 11 | H10: 15~20天 | I10: 10.7 | J10: 2080 | K10: 10.7 | L10: 2080 | M10: 13 | N10: 18~24天 | O10: 9.8 | P10: 1900 | Q10: 10.3 | R10: 2000 | S10: 14 | T10: 19~25天 | U10: 万邑通91748 | V10: 91748 | W10: 9.3 | X10: 1690 | Y10: 9.3 | Z10: 1690 | AA10: 16 | AB10: 25~32天
A11: 4PX91730 | B11: 91730 | C11: 12.9 | D11: 2280 | E11: 12.4 | F11: 2190 | G11: 11 | H11: 15~20天 | I11: 10.4 | J11: 2020 | K11: 10.4 | L11: 2020 | M11: 13 | N11: 18~24天 | O11: 9.5 | P11: 1840 | Q11: 10 | R11: 1940 | S11: 14 | T11: 19~25天 | U11: 4PX91730 | V11: 91730 | W11: 9 | X11: 1630 | Y11: 9 | Z11: 1630 | AA11: 16 | AB11: 25~32天
A12: 4PX90022 | B12: 90022 | C12: 13.5 | D12: 2360 | E12: 13 | F12: 2270 | G12: 11 | H12: 15~20天 | I12: 11 | J12: 2140 | K12: 11 | L12: 2140 | M12: 13 | N12: 18~24天 | O12: 10.1 | P12: 1960 | Q12: 10.6 | R12: 2060 | S12: 14 | T12: 19~25天 | U12: 4PX90022 | V12: 90022 | W12: 9.6 | X12: 1750 | Y12: 9.6 | Z12: 1750 | AA12: 16 | AB12: 25~32天
A13: 风雷仓91789 | B13: 91789 | C13: 13.2 | D13: 2340 | E13: 12.7 | F13: 2250 | G13: 11 | H13: 15~20天 | I13: 10.7 | J13: 2080 | K13: 10.7 | L13: 2080 | M13: 13 | N13: 18~24天 | O13: 9.8 | P13: 1900 | Q13: 10.3 | R13: 2000 | S13: 14 | T13: 19~25天 | U13: 风雷仓91789 | V13: 91789 | W13: 9.3 | X13: 1690 | Y13: 9.3 | Z13: 1690 | AA13: 16 | AB13: 25~32天
A14: 橙联仓91730 | B14: 91730 | C14: 12.9 | D14: 2280 | E14: 12.4 | F14: 2190 | G14: 11 | H14: 15~20天 | I14: 10.4 | J14: 2020 | K14: 10.4 | L14: 2020 | M14: 13 | N14: 18~24天 | O14: 9.5 | P14: 1840 | Q14: 10 | R14: 1940 | S14: 14 | T14: 19~25天 | U14: 橙联仓91730 | V14: 91730 | W14: 9 | X14: 1630 | Y14: 9 | Z14: 1630 | AA14: 16 | AB14: 25~32天
A15: 橙联仓91731 | B15: 91731 | C15: 13.4 | D15: 2330 | E15: 12.9 | F15: 2240 | G15: 11 | H15: 15~20天 | I15: 10.9 | J15: 2110 | K15: 10.9 | L15: 2110 | M15: 13 | N15: 18~24天 | O15: 10 | P15: 1930 | Q15: 10.5 | R15: 2030 | S15: 14 | T15: 19~25天 | U15: 橙联仓91731 | V15: 91731 | W15: 9.5 | X15: 1720 | Y15: 9.5 | Z15: 1720 | AA15: 16 | AB15: 25~32天
A16: 西邮仓 91730 | B16: 91730 | C16: 12.9 | D16: 2280 | E16: 12.4 | F16: 2190 | G16: 11 | H16: 15~20天 | I16: 10.4 | J16: 2020 | K16: 10.4 | L16: 2020 | M16: 13 | N16: 18~24天 | O16: 9.5 | P16: 1840 | Q16: 10 | R16: 1940 | S16: 14 | T16: 19~25天 | U16: 西邮仓 91730 | V16: 91730 | W16: 9 | X16: 1630 | Y16: 9 | Z16: 1630 | AA16: 16 | AB16: 25~32天
A17: 美西3号谷仓 | B17: 91761 | C17: 12.9 | D17: 2280 | E17: 12.4 | F17: 2190 | G17: 11 | H17: 15~20天 | I17: 10.4 | J17: 2020 | K17: 10.4 | L17: 2020 | M17: 13 | N17: 18~24天 | O17: 9.5 | P17: 1840 | Q17: 10 | R17: 1940 | S17: 14 | T17: 19~25天 | U17: 美西3号谷仓 | V17: 91761 | W17: 9 | X17: 1630 | Y17: 9 | Z17: 1630 | AA17: 16 | AB17: 25~32天
A18: 美西5号谷仓 | B18: 91710 | C18: 13.1 | D18: 2310 | E18: 12.6 | F18: 2220 | G18: 11 | H18: 15~20天 | I18: 10.6 | J18: 2050 | K18: 10.6 | L18: 2050 | M18: 13 | N18: 18~24天 | O18: 9.7 | P18: 1870 | Q18: 10.2 | R18: 1970 | S18: 14 | T18: 19~25天 | U18: 美西5号谷仓 | V18: 91710 | W18: 9.2 | X18: 1660 | Y18: 9.2 | Z18: 1660 | AA18: 16 | AB18: 25~32天
... A21: 美西10号谷仓 | B21: 92336 | C21: 13.1 | D21: 2310 | E21: 12.6 | F21: 2220 | G21: 11 | H21: 15~20天 | I21: 10.6 | J21: 2050 | K21: 10.6 | L21: 2050 | M21: 13 | N21: 18~24天 | O21: 9.7 | P21: 1870 | Q21: 10.2 | R21: 1970 | S21: 14 | T21: 19~25天 | U21: 美西10号谷仓 | V21: 92336 | W21: 9.2 | X21: 1660 | Y21: 9.2 | Z21: 1660 | AA21: 16 | AB21: 25~32天
A22: ALHAMNRA | B22: 9180X | C22: 13.4 | D22: 2330 | E22: 12.9 | F22: 2240 | G22: 11 | H22: 15~20天 | I22: 10.9 | J22: 2110 | K22: 10.9 | L22: 2110 | M22: 13 | N22: 18~24天 | O22: 10 | P22: 1930 | Q22: 10.5 | R22: 2030 | S22: 14 | T22: 19~25天 | U22: ALHAMNRA | V22: 9180X | W22: 9.5 | X22: 1720 | Y22: 9.5 | Z22: 1720 | AA22: 16 | AB22: 25~32天
A23: ANAHEIM | B23: 9280X | C23: 13.4 | D23: 2330 | E23: 12.9 | F23: 2240 | G23: 11 | H23: 15~20天 | I23: 10.9 | J23: 2110 | K23: 10.9 | L23: 2110 | M23: 13 | N23: 18~24天 | O23: 10 | P23: 1930 | Q23: 10.5 | R23: 2030 | S23: 14 | T23: 19~25天 | U23: ANAHEIM | V23: 9280X | W23: 9.5 | X23: 1720 | Y23: 9.5 | Z23: 1720 | AA23: 16 | AB23: 25~32天
A24: ARCADIA | B24: 9100X | C24: 13.4 | D24: 2330 | E24: 12.9 | F24: 2240 | G24: 11 | H24: 15~20天 | I24: 10.9 | J24: 2110 | K24: 10.9 | L24: 2110 | M24: 13 | N24: 18~24天 | O24: 10 | P24: 1930 | Q24: 10.5 | R24: 2030 | S24: 14 | T24: 19~25天 | U24: ARCADIA | V24: 9100X | W24: 9.5 | X24: 1720 | Y24: 9.5 | Z24: 1720 | AA24: 16 | AB24: 25~32天
A25: AZUSA | B25: 9170X | C25: 13.2 | D25: 2340 | E25: 12.7 | F25: 2250 | G25: 11 | H25: 15~20天 | I25: 10.7 | J25: 2080 | K25: 10.7 | L25: 2080 | M25: 13 | N25: 18~24天 | O25: 9.8 | P25: 1900 | Q25: 10.3 | R25: 2000 | S25: 14 | T25: 19~25天 | U25: AZUSA | V25: 9170X | W25: 9.3 | X25: 1690 | Y25: 9.3 | Z25: 1690 | AA25: 16 | AB25: 25~32天
A26: BREA | B26: 9282X | C26: 13.2 | D26: 2340 | E26: 12.7 | F26: 2250 | G26: 11 | H26: 15~20天 | I26: 10.7 | J26: 2080 | K26: 10.7 | L26: 2080 | M26: 13 | N26: 18~24天 | O26: 9.8 | P26: 1900 | Q26: 10.3 | R26: 2000 | S26: 14 | T26: 19~25天 | U26: BREA | V26: 9282X | W26: 9.3 | X26: 1690 | Y26: 9.3 | Z26: 1690 | AA26: 16 | AB26: 25~32天
A27: CERRITOS | B27: 9070X | C27: 13.5 | D27: 2360 | E27: 13 | F27: 2270 | G27: 11 | H27: 15~20天 | I27: 11 | J27: 2140 | K27: 11 | L27: 2140 | M27: 13 | N27: 18~24天 | O27: 10.1 | P27: 1960 | Q27: 10.6 | R27: 2060 | S27: 14 | T27: 19~25天 | U27: CERRITOS | V27: 9070X | W27: 9.6 | X27: 1750 | Y27: 9.6 | Z27: 1750 | AA27: 16 | AB27: 25~32天
A28: CHINO | B28: 9171X | C28: 13.2 | D28: 2280 | E28: 12.7 | F28: 2190 | G28: 11 | H28: 15~20天 | I28: 10.7 | J28: 2080 | K28: 10.7 | L28: 2080 | M28: 13 | N28: 18~24天 | O28: 9.8 | P28: 1900 | Q28: 10.3 | R28: 2000 | S28: 14 | T28: 19~25天 | U28: CHINO | V28: 9171X | W28: 9.3 | X28: 1690 | Y28: 9.3 | Z28: 1690 | AA28: 16 | AB28: 25~32天
A29: CITY OF INDUSTRY | B29: 9174X | C29: 13.2 | D29: 2340 | E29: 12.7 | F29: 2250 | G29: 11 | H29: 15~20天 | I29: 10.7 | J29: 2080 | K29: 10.7 | L29: 2080 | M29: 13 | N29: 18~24天 | O29: 9.8 | P29: 1900 | Q29: 10.3 | R29: 2000 | S29: 14 | T29: 19~25天 | U29: CITY OF INDUSTRY | V29: 9174X | W29: 9.3 | X29: 1690 | Y29: 9.3 | Z29: 1690 | AA29: 16 | AB29: 25~32天
A30: COLTON | B30: 9232X | C30: 13.1 | D30: 2310 | E30: 12.6 | F30: 2220 | G30: 11 | H30: 15~20天 | I30: 10.6 | J30: 2050 | K30: 10.6 | L30: 2050 | M30: 13 | N30: 18~24天 | O30: 9.7 | P30: 1870 | Q30: 10.2 | R30: 1970 | S30: 14 | T30: 19~25天 | U30: COLTON | V30: 9232X | W30: 9.2 | X30: 1660 | Y30: 9.2 | Z30: 1660 | AA30: 16 | AB30: 25~32天
A31: CORONA | B31: 9288X | C31: 13.2 | D31: 2340 | E31: 12.7 | F31: 2250 | G31: 11 | H31: 15~20天 | I31: 10.7 | J31: 2080 | K31: 10.7 | L31: 2080 | M31: 13 | N31: 18~24天 | O31: 9.8 | P31: 1900 | Q31: 10.3 | R31: 2000 | S31: 14 | T31: 19~25天 | U31: CORONA | V31: 9288X | W31: 9.3 | X31: 1690 | Y31: 9.3 | Z31: 1690 | AA31: 16 | AB31: 25~32天
A32: DIAMOND BAR | B32: 9176X | C32: 13.1 | D32: 2310 | E32: 12.6 | F32: 2220 | G32: 11 | H32: 15~20天 | I32: 10.6 | J32: 2050 | K32: 10.6 | L32: 2050 | M32: 13 | N32: 18~24天 | O32: 9.7 | P32: 1870 | Q32: 10.2 | R32: 1970 | S32: 14 | T32: 19~25天 | U32: DIAMOND BAR | V32: 9176X | W32: 9.2 | X32: 1660 | Y32: 9.2 | Z32: 1660 | AA32: 16 | AB32: 25~32天
A33: EL MONTE | B33: 9173X | C33: 13.4 | D33: 2330 | E33: 12.9 | F33: 2240 | G33: 11 | H33: 15~20天 | I33: 10.9 | J33: 2110 | K33: 10.9 | L33: 2110 | M33: 13 | N33: 18~24天 | O33: 10 | P33: 1930 | Q33: 10.5 | R33: 2030 | S33: 14 | T33: 19~25天 | U33: EL MONTE | V33: 9173X | W33: 9.5 | X33: 1720 | Y33: 9.5 | Z33: 1720 | AA33: 16 | AB33: 25~32天
... A57: YORBA LINDA | B57: 9288X | C57: 13.4 | D57: 2330 | E57: 12.9 | F57: 2240 | G57: 11 | H57: 15~20天 | I57: 10.9 | J57: 2110 | K57: 10.9 | L57: 2110 | M57: 13 | N57: 18~24天 | O57: 10 | P57: 1930 | Q57: 10.5 | R57: 2030 | S57: 14 | T57: 19~25天 | U57: YORBA LINDA | V57: 9288X | W57: 9.5 | X57: 1720 | Y57: 9.5 | Z57: 1720 | AA57: 16 | AB57: 25~32天
A58: 说明：尾数的X可为0-9的数字
A59: 额外产生的费用 | C59: 金额 | M59: 单位 | U59: 备注
A60: 卸货等候费 | C60: 85 | M60: Per Hour 每小时 | U60: 免费等候一小时
A61: 跑空 | C61: 实报实销 | M61: Per Entry 每次 | U61: 如果产生
A62: 地址更改 | C62: 补差价，多退少补 | M62: Per Entry 每次 | U62: 需在我司可派送范围内，如已发车，费用不退，需额外加上二次派送费。
A63: 更改自提 | C63: 20 | M63: 每板 | U63: 如未派送尾程费退还，收取对应出仓费
A64: 尾板费 | C64: 65 | M64: 每次 | U64: 无卸货平台需收取
A65: 非工作日送仓（商业/私人地址） | C65: 附加费单询 | M65: 每次 | U65: 周六日或节假日送仓，需要加收费用
A66: 含税渠道 | B66: 1、含关税和查验费； 2、低消334kg，不足按334kg结算； 3、计费重：体积重和实重取大者，体积重=长cm*宽cm*高cm/6000； 4、单边超120CM以上，单件超40KG以上的货物，请参考《发货必读》； 5、如因客户资料\产品问题，需承担因此产生的所有仓租、柜租、罚金、销毁费等，恶意瞒报的还需承担进口商损失费2000美金；
A67: 不含税渠道 | B67: 1、不含关税、如遇查验费实销； 2、低消2CBM，不足按2CBM结算； 3、计费重=长cm*宽cm*高cm/1000000，不分泡； 4、单边超120CM以上，请参考《发货必读》 5、如因客户资料\产品问题，需承担因此产生的所有仓租、柜租、罚金、销毁费等，恶意瞒报的还需承担进口商损失费2000美金；
A69: 纽约普船 | I69: 纽约特快 | O69: 纽约快船
A70: 仓库代码 | B70: 邮编 | C70: 深圳 | E70: 义乌\宁波 | G70: 参考时效 (开船后第二天起)*天 | H70: 理赔时效(开船后第二天起)*天 | I70: 深圳 | K70: 义乌\宁波 | M70: 参考时效 (开船后第二天起)*天 | N70: 理赔时效(开船后第二天起)*天 | O70: 深圳 | Q70: 义乌\宁波 | S70: 参考时效 (开船后第二天起)*天 | T70: 理赔时效(开船后第二天起)*天 | U70: 邮编1 | V70: 邮编2 | W70: 邮编3 | X70: 邮编4 | Y70: 邮编5 | Z70: 邮编6 | AA70: 邮编7 | AB70: 邮编8 | AC70: 邮编9 | AD70: 邮编10 | AE70: 邮编11 | AF70: 邮编12 | AG70: 邮编13 | AH70: 邮编14 | AI70: 邮编15 | AJ70: 邮编16 | AK70: 邮编17 | AL70: 邮编18 | AM70: 邮编19 | AN70: 邮编20 | AO70: 邮编21 | AP70: 邮编22 | AQ70: 邮编23 | AR70: 邮编24 | AS70: 邮编25 | AT70: 邮编26 | AU70: 邮编27 | AV70: 邮编28 | AW70: 邮编29 | AX70: 邮编30 | AY70: 邮编31 | AZ70: 邮编32 | BA70: 邮编33 | BB70: 邮编34 | BC70: 邮编35 | BD70: 邮编36 | BE70: 邮编37 | BF70: 邮编38 | BG70: 邮编39 | BH70: 邮编40 | BI70: 邮编41 | BJ70: 邮编42 | BK70: 邮编43 | BL70: 邮编44 | BM70: 邮编45 | BN70: 邮编46 | BO70: 邮编47 | BP70: 邮编48 | BQ70: 邮编49 | BR70: 邮编50 | BS70: 邮编51 | BT70: 邮编52 | BU70: 邮编53 | BV70: 邮编54 | BW70: 邮编55 | BX70: 邮编56 | BY70: 邮编57 | BZ70: 邮编58 | CA70: 邮编59 | CB70: 邮编60 | CC70: 邮编61 | CD70: 邮编62 | CE70: 邮编63 | CF70: 邮编64 | CG70: 邮编65 | CH70: 邮编66 | CI70: 邮编67 | CJ70: 邮编68 | CK70: 邮编69 | CL70: 邮编70 | CM70: 邮编71 | CN70: 邮编72 | CO70: 邮编73 | CP70: 邮编74 | CQ70: 邮编75 | CR70: 邮编76 | CS70: 邮编77 | CT70: 邮编78 | CU70: 邮编79 | CV70: 邮编80 | CW70: 邮编81 | CX70: 邮编82 | CY70: 邮编83 | CZ70: 邮编84 | DA70: 邮编85 | DB70: 邮编86 | DC70: 邮编87 | DD70: 邮编88 | DE70: 邮编89 | DF70: 邮编90 | DG70: 邮编91 | DH70: 邮编92 | DI70: 邮编93 | DJ70: 邮编94 | DK70: 邮编95 | DL70: 邮编96 | DM70: 邮编97 | DN70: 邮编98 | DO70: 邮编99 | DP70: 邮编100 | DQ70: 邮编101 | DR70: 邮编102 | DS70: 邮编103 | DT70: 邮编104 | DU70: 邮编105 | DV70: 邮编106 | DW70: 邮编107 | DX70: 邮编108 | DY70: 邮编109 | DZ70: 邮编110 | EA70: 邮编111 | EB70: 邮编112 | EC70: 邮编113 | ED70: 邮编114 | EE70: 邮编115 | EF70: 邮编116 | EG70: 邮编117 | EH70: 邮编118 | EI70: 邮编119 | EJ70: 邮编120 | EK70: 邮编121 | EL70: 邮编122 | EM70: 邮编123 | EN70: 邮编124 | EO70: 邮编125 | EP70: 邮编126 | EQ70: 邮编127 | ER70: 邮编128 | ES70: 邮编129 | ET70: 邮编130 | EU70: 邮编131 | EV70: 邮编132 | EW70: 邮编133 | EX70: 邮编134 | EY70: 邮编135 | EZ70: 邮编136 | FA70: 邮编137 | FB70: 邮编138 | FC70: 邮编139 | FD70: 邮编140 | FE70: 邮编141 | FF70: 邮编142 | FG70: 邮编143 | FH70: 邮编144 | FI70: 邮编145 | FJ70: 邮编146 | FK70: 邮编147 | FL70: 邮编148 | FM70: 邮编149 | FN70: 邮编150 | FO70: 邮编151 | FP70: 邮编152 | FQ70: 邮编153 | FR70: 邮编154 | FS70: 邮编155 | FT70: 邮编156 | FU70: 邮编157 | FV70: 邮编158 | FW70: 邮编159 | FX70: 邮编160 | FY70: 邮编161 | FZ70: 邮编162 | GA70: 邮编163 | GB70: 邮编164 | GC70: 邮编165 | GD70: 邮编166 | GE70: 邮编167 | GF70: 邮编168 | GG70: 邮编169 | GH70: 邮编170 | GI70: 邮编171 | GJ70: 邮编172 | GK70: 邮编173 | GL70: 邮编174 | GM70: 邮编175 | GN70: 邮编176 | GO70: 邮编177 | GP70: 邮编178 | GQ70: 邮编179 | GR70: 邮编180 | GS70: 邮编181 | GT70: 邮编182 | GU70: 邮编183 | GV70: 邮编184 | GW70: 邮编185 | GX70: 邮编186 | GY70: 邮编187 | GZ70: 邮编188 | HA70: 邮编189 | HB70: 邮编190 | HC70: 邮编191 | HD70: 邮编192 | HE70: 邮编193 | HF70: 邮编194 | HG70: 邮编195 | HH70: 邮编196 | HI70: 邮编197 | HJ70: 邮编198 | HK70: 邮编199 | HL70: 邮编200 | HM70: 邮编201 | HN70: 邮编202 | HO70: 邮编203 | HP70: 邮编204 | HQ70: 邮编205 | HR70: 邮编206 | HS70: 邮编207 | HT70: 邮编208 | HU70: 邮编209 | HV70: 邮编210 | HW70: 邮编211 | HX70: 邮编212 | HY70: 邮编213 | HZ70: 邮编214 | IA70: 邮编215 | IB70: 邮编216 | IC70: 邮编217 | ID70: 邮编218 | IE70: 邮编219 | IF70: 邮编220 | IG70: 邮编221 | IH70: 邮编222 | II70: 邮编223 | IJ70: 邮编224 | IK70: 邮编225 | IL70: 邮编226 | IM70: 邮编227 | IN70: 邮编228 | IO70: 邮编229 | IP70: 邮编230 | IQ70: 邮编231 | IR70: 邮编232 | IS70: 邮编233 | IT70: 邮编234 | IU70: 邮编235 | IV70: 邮编236 | IW70: 邮编237 | IX70: 邮编238 | IY70: 邮编239 | IZ70: 邮编240 | JA70: 邮编241 | JB70: 邮编242 | JC70: 邮编243 | JD70: 邮编244 | JE70: 邮编245 | JF70: 邮编246 | JG70: 邮编247 | JH70: 邮编248 | JI70: 邮编249 | JJ70: 邮编250 | JK70: 邮编251 | JL70: 邮编252 | JM70: 邮编253 | JN70: 邮编254 | JO70: 邮编255 | JP70: 邮编256 | JQ70: 邮编257 | JR70: 邮编258 | JS70: 邮编259 | JT70: 邮编260 | JU70: 邮编261 | JV70: 邮编262 | JW70: 邮编263 | JX70: 邮编264 | JY70: 邮编265 | JZ70: 邮编266 | KA70: 邮编267 | KB70: 邮编268 | KC70: 邮编269 | KD70: 邮编270 | KE70: 邮编271 | KF70: 邮编272 | KG70: 邮编273 | KH70: 邮编274 | KI70: 邮编275
C71: 334KG+ | D71: 2CBM+ | E71: 334KG+ | F71: 2CBM+ | I71: 334KG+ | J71: 2CBM+ | K71: 334KG+ | L71: 2CBM+ | O71: 334KG+ | P71: 2CBM+ | Q71: 334KG+ | R71: 2CBM+
A72: 纽约FBN头程 | B72: / | C72: 8.4 | D72: 1448 | E72: 8.4 | F72: 1448 | G72: 32 | H72: / | I72: 14.6 | J72: 2410 | K72: 14.6 | L72: 2410 | M72: 20~23 | N72: / | O72: 12.6 | P72: 2100 | Q72: 12.6 | R72: 2100 | S72: 23~27 | T72: /
A73: YC美东仓 | B73: 08854 | C73: 8.9 | D73: 1548 | E73: 8.9 | F73: 1548 | G73: 32 | H73: 40~45 | I73: 15.1 | J73: 2510 | K73: 15.1 | L73: 2510 | M73: 20~23 | N73: 25~29 | O73: 13.1 | P73: 2200 | Q73: 13.1 | R73: 2200 | S73: 23~27 | T73: 29~34
A74: 谷仓2号 | B74: 08518 | C74: 10.5 | D74: 1845 | E74: 10.5 | F74: 1845 | G74: 32 | H74: 40~45 | I74: 16.3 | J74: 2860 | K74: 16.3 | L74: 2860 | M74: 20~23 | N74: 25~29 | O74: 14.3 | P74: 2440 | Q74: 14.3 | R74: 2440 | S74: 23~27 | T74: 29~34
A75: 谷仓5号 | B75: 08831 | C75: 10.5 | D75: 1845 | E75: 10.5 | F75: 1845 | G75: 32 | H75: 40~45 | I75: 16.3 | J75: 2860 | K75: 16.3 | L75: 2860 | M75: 20~23 | N75: 25~29 | O75: 14.3 | P75: 2440 | Q75: 14.3 | R75: 2440 | S75: 23~27 | T75: 29~34
A76: 谷仓8号 | B76: 07836 | C76: 10.5 | D76: 1845 | E76: 10.5 | F76: 1845 | G76: 32 | H76: 40~45 | I76: 16.3 | J76: 2860 | K76: 16.3 | L76: 2860 | M76: 20~23 | N76: 25~29 | O76: 14.3 | P76: 2440 | Q76: 14.3 | R76: 2440 | S76: 23~27 | T76: 29~34
A77: 谷仓11号 | B77: 08505 | C77: 10.5 | D77: 1845 | E77: 10.5 | F77: 1845 | G77: 32 | H77: 40~45 | I77: 16.3 | J77: 2860 | K77: 16.3 | L77: 2860 | M77: 20~23 | N77: 25~29 | O77: 14.3 | P77: 2440 | Q77: 14.3 | R77: 2440 | S77: 23~27 | T77: 29~34
A78: 谷仓12号 | B78: 08505 | C78: 10.5 | D78: 1845 | E78: 10.5 | F78: 1845 | G78: 32 | H78: 40~45 | I78: 16.3 | J78: 2860 | K78: 16.3 | L78: 2860 | M78: 20~23 | N78: 25~29 | O78: 14.3 | P78: 2440 | Q78: 14.3 | R78: 2440 | S78: 23~27 | T78: 29~34
A79: 谷仓15号 | B79: 08036 | C79: 10.5 | D79: 1845 | E79: 10.5 | F79: 1845 | G79: 32 | H79: 40~45 | I79: 16.3 | J79: 2860 | K79: 16.3 | L79: 2860 | M79: 20~23 | N79: 25~29 | O79: 14.3 | P79: 2440 | Q79: 14.3 | R79: 2440 | S79: 23~27 | T79: 29~34
A80: 谷仓16号 | B80: 08057 | C80: 10.5 | D80: 1845 | E80: 10.5 | F80: 1845 | G80: 32 | H80: 40~45 | I80: 16.3 | J80: 2860 | K80: 16.3 | L80: 2860 | M80: 20~23 | N80: 25~29 | O80: 14.3 | P80: 2440 | Q80: 14.3 | R80: 2440 | S80: 23~27 | T80: 29~34
A81: 谷仓18号 | B81: 08016 | C81: 10.5 | D81: 1845 | E81: 10.5 | F81: 1845 | G81: 32 | H81: 40~45 | I81: 16.3 | J81: 2860 | K81: 16.3 | L81: 2860 | M81: 20~23 | N81: 25~29 | O81: 14.3 | P81: 2440 | Q81: 14.3 | R81: 2440 | S81: 23~27 | T81: 29~34
A82: 4PX-新泽西1仓 | B82: 08861 | C82: 10.5 | D82: 1845 | E82: 10.5 | F82: 1845 | G82: 32 | H82: 40~45 | I82: 16.3 | J82: 2860 | K82: 16.3 | L82: 2860 | M82: 20~23 | N82: 25~29 | O82: 14.3 | P82: 2440 | Q82: 14.3 | R82: 2440 | S82: 23~27 | T82: 29~34
A83: 凯琦云仓-USNJ03 | B83: 08810 | C83: 9.6 | D83: 1668 | E83: 9.6 | F83: 1668 | G83: 32 | H83: 40~45 | I83: 15.4 | J83: 2680 | K83: 15.4 | L83: 2680 | M83: 20~23 | N83: 25~29 | O83: 13.4 | P83: 2270 | Q83: 13.4 | R83: 2270 | S83: 23~27 | T83: 29~34
A84: Edison,NJ 08837 | B84: 见右端 | C84: 9.3 | D84: 1602 | E84: 9.3 | F84: 1602 | G84: 32 | H84: 40~45 | I84: 15.1 | J84: 2720 | K84: 15.1 | L84: 2720 | M84: 20~23 | N84: 25~29 | O84: 13.1 | P84: 2200 | Q84: 13.1 | R84: 2200 | S84: 23~27 | T84: 29~34 | U84: 8837
A85: 0-15 MILES | B85: 见右端 | C85: 9.4 | D85: 1624 | E85: 9.4 | F85: 1624 | G85: 32 | H85: 40~45 | I85: 15.2 | J85: 2740 | K85: 15.2 | L85: 2740 | M85: 20~23 | N85: 25~29 | O85: 13.2 | P85: 2220 | Q85: 13.2 | R85: 2220 | S85: 23~27 | T85: 29~34 | U85: 8818 | V85: 8817 | W85: 8832 | X85: 8840 | Y85: 7080 | Z85: 8830 | AA85: 8861 | AB85: 8862 | AC85: 8854 | AD85: 8055 | AE85: 8859 | AF85: 8989 | AG85: 8902 | AH85: 8846 | AI85: 8880 | AJ85: 7027 | AK85: 7091 | AL85: 7203 | AM85: 8828 | AN85: 7033 | AO85: 7023 | AP85: 7036 | AQ85: 8872 | AR85: 7016 | AS85: 7204 | AT85: 7059 | AU85: 8805 | AV85: 8875 | AW85: 8857 | AX85: 7747 | AY85: 7206 | AZ85: 8823 | BA85: 7069 | BB85: 8852 | BC85: 7735 | BD85: 8824 | BE85: 7207 | BF85: 7208 | BG85: 7201 | BH85: 8904 | BI85: 7095 | BJ85: 7067 | BK85: 8906 | BL85: 7077 | BM85: 8901 | BN85: 7001 | BO85: 8879 | BP85: 8850 | BQ85: 7064 | BR85: 7061 | BS85: 7065 | BT85: 8882 | BU85: 8855 | BV85: 7076 | BW85: 7063 | BX85: 7060 | BY85: 8816 | BZ85: 7066 | CA85: 8871 | CB85: 8933 | CC85: 7062
A86: 15.01-25 MILES | B86: 见右端 | C86: 9.6 | D86: 1668 | E86: 9.6 | F86: 1668 | G86: 32 | H86: 40~45 | I86: 15.4 | J86: 2680 | K86: 15.4 | L86: 2680 | M86: 20~23 | N86: 25~29 | O86: 13.4 | P86: 2270 | Q86: 13.4 | R86: 2270 | S86: 23~27 | T86: 29~34 | U86: 7083 | V86: 7090 | W86: 8873 | X86: 7730 | Y86: 7202 | Z86: 8810 | AA86: 7205 | AB86: 7111 | AC86: 7980 | AD86: 7112 | AE86: 8812 | AF86: 7019 | AG86: 7902 | AH86: 7921 | AI86: 8544 | AJ86: 7051 | AK86: 7738 | AL86: 7003 | AM86: 7028 | AN86: 7701 | AO86: 8836 | AP86: 7092 | AQ86: 8835 | AR86: 7922 | AS86: 7733 | AT86: 8890 | AU86: 7946 | AV86: 7734 | AW86: 7765 | AX86: 7081 | AY86: 7088 | AZ86: 7933 | BA86: 7974 | BB86: 7939 | BC86: 8528 | BD86: 8512 | BE86: 8831 | BF86: 7751 | BG86: 7746 | BH86: 7758 | BI86: 7040 | BJ86: 7748 | BK86: 7103 | BL86: 8807 | BM86: 8869 | BN86: 8553 | BO86: 7928 | BP86: 8536 | BQ86: 7002 | BR86: 7018 | BS86: 8844 | BT86: 7718 | BU86: 7726 | BV86: 7108 | BW86: 7106 | BX86: 7041 | BY86: 7976 | BZ86: 8542 | CA86: 8540 | CB86: 7101 | CC86: 7192 | CD86: 7193 | CE86: 7175 | CF86: 7184 | CG86: 7188 | CH86: 7191 | CI86: 7198 | CJ86: 7195 | CK86: 7017 | CL86: 7978 | CM86: 7102 | CN86: 7105 | CO86: 7901 | CP86: 8541 | CQ86: 8543 | CR86: 8502 | CS86: 7114 | CT86: 7029 | CU86: 7920 | CV86: 7737 | CW86: 8876 | CX86: 8821 | CY86: 7477 | CZ86: 7107 | DA86: 7050 | DB86: 7039 | DC86: 7752 | DD86: 8520 | DE86: 8504 | DF86: 7395 | DG86: 7032 | DH86: 7189 | DI86: 7763 | DJ86: 7716 | DK86: 7104 | DL86: 7099 | DM86: 7305 | DN86: 8558 | DO86: 7728
A87: 25.01-35 MILES | B87: 见右端 | C87: 9.9 | D87: 1712 | E87: 9.9 | F87: 1712 | G87: 32 | H87: 40~45 | I87: 15.7 | J87: 2730 | K87: 15.7 | L87: 2730 | M87: 20~23 | N87: 25~29 | O87: 13.7 | P87: 2310 | Q87: 13.7 | R87: 2310 | S87: 23~27 | T87: 29~34 | U87: 7702 | V87: 7977 | W87: 7704 | X87: 8619 | Y87: 8648 | Z87: 7934 | AA87: 7979 | AB87: 8638 | AC87: 8691 | AD87: 7930 | AE87: 8628 | AF87: 8801 | AG87: 7109 | AH87: 8550 | AI87: 7303 | AJ87: 7304 | AK87: 7306 | AL87: 8888 | AM87: 7052 | AN87: 7960 | AO87: 7710 | AP87: 7938 | AQ87: 7311 | AR87: 7931 | AS87: 7940 | AT87: 7110 | AU87: 8535 | AV87: 7031 | AW87: 7302 | AX87: 8853 | AY87: 7308 | AZ87: 7739 | BA87: 7042 | BB87: 7087 | BC87: 7945 | BD87: 7310 | BE87: 7935 | BF87: 7932 | BG87: 7307 | BH87: 8887 | BI87: 7760 | BJ87: 8889 | BK87: 7724 | BL87: 7044 | BM87: 7703 | BN87: 7068 | BO87: 8858 | BP87: 7096 | BQ87: 7013 | BR87: 8525 | BS87: 7097 | BT87: 7926 | BU87: 7030 | BV87: 7012 | BW87: 7086 | BX87: 7043 | BY87: 8555 | BZ87: 7094 | CA87: 7055 | CB87: 7009 | CC87: 7073 | CD87: 8561 | CE87: 7732 | CF87: 7764 | CG87: 8690 | CH87: 7047 | CI87: 7021 | CJ87: 7750 | CK87: 8833 | CL87: 7799 | CM87: 8863 | CN87: 7015 | CO87: 7007 | CP87: 7011 | CQ87: 7533 | CR87: 7093 | CS87: 7070 | CT87: 7924 | CU87: 7072 | CV87: 7014 | CW87: 7424 | CX87: 8602 | CY87: 8603 | CZ87: 7927 | DA87: 8625 | DB87: 7755 | DC87: 7753 | DD87: 7936 | DE87: 7006 | DF87: 7071 | DG87: 7057 | DH87: 8695 | DI87: 7740 | DJ87: 8666 | DK87: 7544 | DL87: 7962 | DM87: 7963 | DN87: 8646 | DO87: 8647 | DP87: 7731 | DQ87: 8650 | DR87: 7712 | DS87: 7503 | DT87: 8629 | DU87: 8604 | DV87: 8605 | DW87: 8606 | DX87: 8607 | DY87: 8645 | DZ87: 7999 | EA87: 8609 | EB87: 7961 | EC87: 7522 | ED87: 8551 | EE87: 7512 | EF87: 8610 | EG87: 7022 | EH87: 8601 | EI87: 7513 | EJ87: 8510 | EK87: 7543 | EL87: 7074 | EM87: 7660 | EN87: 7075 | EO87: 8822 | EP87: 7505 | EQ87: 7510 | ER87: 8608 | ES87: 7981 | ET87: 7754 | EU87: 8534 | EV87: 7524 | EW87: 7504 | EX87: 7538 | EY87: 7058 | EZ87: 7514 | FA87: 7010 | FB87: 8530 | FC87: 7650 | FD87: 7657 | FE87: 7407 | FF87: 7699 | FG87: 7509 | FH87: 7723 | FI87: 7950 | FJ87: 7502 | FK87: 7511 | FL87: 7501 | FM87: 7026 | FN87: 8620 | FO87: 7606 | FP87: 7604 | FQ87: 7034 | FR87: 7727 | FS87: 7608 | FT87: 7711 | FU87: 7720 | FV87: 7663
A88: 35.01-50 MILES | B88: 见右端 | C88: 10.1 | D88: 1756 | E88: 10.1 | F88: 1756 | G88: 32 | H88: 40~45 | I88: 15.9 | J88: 2770 | K88: 15.9 | L88: 2770 | M88: 20~23 | N88: 25~29 | O88: 13.9 | P88: 2360 | Q88: 13.9 | R88: 2360 | S88: 23~27 | T88: 29~34 | U88: 8829 | V88: 8501 | W88: 7836 | X88: 7853 | Y88: 7870 | Z88: 8730 | AA88: 8809 | AB88: 8827 | AC88: 8724 | AD88: 7803 | AE88: 8826 | AF88: 8738 | AG88: 7020 | AH88: 7605 | AI88: 7004 | AJ88: 7878 | AK88: 7603 | AL88: 7054 | AM88: 7719 | AN88: 7666 | AO88: 7662 | AP88: 7607 | AQ88: 8527 | AR88: 7035 | AS88: 8720 | AT88: 7602 | AU88: 7024 | AV88: 8560 | AW88: 7507 | AX88: 8701 | AY88: 7715 | AZ88: 7644 | BA88: 7717 | BB88: 7474 | BC88: 7508 | BD88: 7440 | BE88: 7452 | BF88: 8559 | BG88: 7845 | BH88: 7876 | BI88: 7631 | BJ88: 7970 | BK88: 8736 | BL88: 7653 | BM88: 7410 | BN88: 7470 | BO88: 7046 | BP88: 8526 | BQ88: 7506 | BR88: 8557 | BS88: 8514 | BT88: 7444 | BU88: 8803 | BV88: 8868 | BW88: 7670 | BX88: 7661 | BY88: 7762 | BZ88: 7646 | CA88: 7621 | CB88: 7005 | CC88: 7045 | CD88: 7865 | CE88: 7649 | CF88: 8750 | CG88: 7601 | CH88: 8562 | CI88: 7652 | CJ88: 8903 | CK88: 8820 | CL88: 7442 | CM88: 7869 | CN88: 8867 | CO88: 8742 | CP88: 7628 | CQ88: 8505 | CR88: 8515 | CS88: 7834 | CT88: 8511 | CU88: 7626 | CV88: 7630 | CW88: 7457 | CX88: 8022 | CY88: 8755 | CZ88: 7423 | DA88: 7676 | DB88: 7806 | DC88: 8556 | DD88: 7481 | DE88: 7641 | DF88: 7866 | DG88: 7620 | DH88: 8802 | DI88: 8518 | DJ88: 7852 | DK88: 7847 | DL88: 8825 | DM88: 7677 | DN88: 7857 | DO88: 7417 | DP88: 8533 | DQ88: 7831 | DR88: 7885 | DS88: 7420 | DT88: 7850 | DU88: 7627 | DV88: 7432 | DW88: 7828 | DX88: 8041 | DY88: 7840 | DZ88: 7436 | EA88: 7463 | EB88: 7656 | EC88: 7842 | ED88: 8733 | EE88: 7458 | EF88: 7880 | EG88: 8723 | EH88: 7645 | EI88: 8804 | EJ88: 7802 | EK88: 7401 | EL88: 7675 | EM88: 7874 | EN88: 7465 | EO88: 7403 | EP88: 7821 | EQ88: 7446 | ER88: 8739 | ES88: 8834 | ET88: 8016 | EU88: 8848 | EV88: 7820 | EW88: 7640 | EX88: 7624 | EY88: 8641 | EZ88: 8042 | FA88: 8640 | FB88: 7882 | FC88: 7856 | FD88: 7843 | FE88: 7648 | FF88: 8757 | FG88: 8722 | FH88: 8735 | FI88: 8060 | FJ88: 7801 | FK88: 7435 | FL88: 7647 | FM88: 8011 | FN88: 7456 | FO88: 7632 | FP88: 7838 | FQ88: 8808 | FR88: 8073 | FS88: 8886 | FT88: 7495
A89: NYC 1区Code | B89: 见右端 | C89: 10.3 | D89: 1801 | E89: 10.3 | F89: 1801 | G89: 32 | H89: 40~45 | I89: 16.1 | J89: 2820 | K89: 16.1 | L89: 2820 | M89: 20~23 | N89: 25~29 | O89: 14.1 | P89: 2400 | Q89: 14.1 | R89: 2400 | S89: 23~27 | T89: 29~34 | U89: 10307 | V89: 10309 | W89: 10312 | X89: 10308 | Y89: 10313 | Z89: 10314 | AA89: 10306 | AB89: 10311 | AC89: 10303 | AD89: 10302 | AE89: 10304 | AF89: 10310 | AG89: 10301 | AH89: 10305 | AI89: 11252 | AJ89: 11209 | AK89: 11209 | AL89: 11228
A90: NYC 2区Code | B90: 见右端 | C90: 10.5 | D90: 1845 | E90: 10.5 | F90: 1845 | G90: 32 | H90: 40~45 | I90: 16.3 | J90: 2860 | K90: 16.3 | L90: 2860 | M90: 20~23 | N90: 25~29 | O90: 14.3 | P90: 2440 | Q90: 14.3 | R90: 2440 | S90: 23~27 | T90: 29~34 | U90: 11214 | V90: 11204 | W90: 11232 | X90: 11224 | Y90: 11223 | Z90: 11218 | AA90: 10007 | AB90: 11231 | AC90: 11242 | AD90: 11215 | AE90: 11241 | AF90: 11202 | AG90: 10013 | AH90: 10081 | AI90: 10090 | AJ90: 11217 | AK90: 10004 | AL90: 10006 | AM90: 10008 | AN90: 10045 | AO90: 10080 | AP90: 10113 | AQ90: 10114 | AR90: 10002 | AS90: 11235 | AT90: 11226 | AU90: 11225 | AV90: 10014 | AW90: 10159 | AX90: 10003 | AY90: 10005 | AZ90: 10123 | BA90: 10160 | BB90: 10001 | BC90: 10018 | BD90: 10109 | BE90: 10110 | BF90: 10116 | BG90: 10117 | BH90: 10118 | BI90: 10119 | BJ90: 10121 | BK90: 10122 | BL90: 10156 | BM90: 10009 | BN90: 11201 | BO90: 11229 | BP90: 11238 | BQ90: 11245 | BR90: 11230 | BS90: 11243 | BT90: 11213 | BU90: 10041 | BV90: 10043 | BW90: 10150 | BX90: 10152 | BY90: 10154 | BZ90: 10020 | CA90: 10101 | CB90: 10103 | CC90: 10104 | CD90: 10106 | CE90: 10111 | CF90: 10112 | CG90: 10129 | CH90: 10138 | CI90: 10163 | CJ90: 10164 | CK90: 10171 | CL90: 10173 | CM90: 10174 | CN90: 10060 | CO90: 10087 | CP90: 10105 | CQ90: 10107 | CR90: 10108 | CS90: 10120 | CT90: 10133 | CU90: 10151 | CV90: 10153 | CW90: 10157 | CX90: 10168 | CY90: 10169 | CZ90: 10170 | DA90: 10172 | DB90: 10016 | DC90: 10017 | DD90: 10019 | DE90: 10055 | DF90: 10102 | DG90: 11216 | DH90: 11251 | DI90: 11205 | DJ90: 11211 | DK90: 10158 | DL90: 10132 | DM90: 10023 | DN90: 10155 | DO90: 10024 | DP90: 10065 | DQ90: 10022 | DR90: 10131 | DS90: 11233 | DT90: 11210 | DU90: 10162 | DV90: 10021 | DW90: 10075 | DX90: 10028 | DY90: 11206 | DZ90: 11695 | EA90: 11109 | EB90: 11101 | EC90: 11222 | ED90: 11236 | EE90: 11694 | EF90: 10128 | EG90: 10130 | EH90: 11104 | EI90: 11237 | EJ90: 10025 | EK90: 10069 | EL90: 10026 | EM90: 10027 | EN90: 10029 | EO90: 11212 | EP90: 11239 | EQ90: 11234 | ER90: 10115 | ES90: 10030 | ET90: 10044 | EU90: 11378 | EV90: 11207 | EW90: 11377 | EX90: 11373 | EY90: 11256 | EZ90: 11414 | FA90: 11379 | FB90: 11417 | FC90: 11692 | FD90: 11374 | FE90: 11372 | FF90: 11120 | FG90: 10032 | FH90: 10040 | FI90: 11380 | FJ90: 11370 | FK90: 11416 | FL90: 11208 | FM90: 11106 | FN90: 11103 | FO90: 11385 | FP90: 10031 | FQ90: 10039 | FR90: 10453 | FS90: 10034 | FT90: 11421 | FU90: 11105 | FV90: 11371 | FW90: 11375 | FX90: 11418 | FY90: 11102 | FZ90: 11419 | GA90: 11690 | GB90: 11368 | GC90: 11369 | GD90: 10161 | GE90: 10456 | GF90: 10468 | GG90: 10451 | GH90: 10033 | GI90: 11381 | GJ90: 11693 | GK90: 11386 | GL90: 11436 | GM90: 11244 | GN90: 11352 | GO90: 10471 | GP90: 11355 | GQ90: 11434 | GR90: 11430 | GS90: 10463 | GT90: 10472 | GU90: 10459 | GV90: 10454 | GW90: 10460 | GX90: 11367 | GY90: 11499 | GZ90: 11691 | HA90: 11413 | HB90: 11415 | HC90: 10455 | HD90: 10457 | HE90: 10462 | HF90: 10474 | HG90: 11365 | HH90: 11451 | HI90: 11366 | HJ90: 11435 | HK90: 11354 | HL90: 10705 | HM90: 11432 | HN90: 11422 | HO90: 11425 | HP90: 11412 | HQ90: 11433 | HR90: 11439 | HS90: 11255 | HT90: 10702 | HU90: 10035 | HV90: 10473 | HW90: 10470 | HX90: 10467 | HY90: 10467 | HZ90: 10465 | IA90: 10458 | IB90: 11424 | IC90: 11351 | ID90: 11431 | IE90: 11405 | IF90: 11358 | IG90: 11582 | IH90: 10466 | II90: 10704 | IJ90: 11357 | IK90: 11581 | IL90: 11592 | IM90: 11356 | IN90: 11096 | IO90: 11411 | IP90: 10461 | IQ90: 11423 | IR90: 11364 | IS90: 11362 | IT90: 11428 | IU90: 11240 | IV90: 11427 | IW90: 10475 | IX90: 10469 | IY90: 10701 | IZ90: 11429 | JA90: 11594 | JB90: 10703 | JC90: 11595 | JD90: 11598 | JE90: 11426 | JF90: 10964 | JG90: 11020 | JH90: 11003 | JI90: 11363 | JJ90: 11580 | JK90: 11004 | JL90: 10965 | JM90: 10464 | JN90: 11559 | JO90: 10708 | JP90: 11563 | JQ90: 10552 | JR90: 10976 | JS90: 11557 | JT90: 10551 | JU90: 11002 | JV90: 11005 | JW90: 10710 | JX90: 10803 | JY90: 11001 | JZ90: 10553 | KA90: 11509 | KB90: 10550 | KC90: 11027 | KD90: 10968 | KE90: 10954 | KF90: 10977 | KG90: 11042 | KH90: 11254 | KI90: 11597
A91: NYC 3区Code | B91: 见右端 | C91: 10.7 | D91: 1889 | E91: 10.7 | F91: 1889 | G91: 32 | H91: 40~45 | I91: 16.5 | J91: 2900 | K91: 16.5 | L91: 2900 | M91: 20~23 | N91: 25~29 | O91: 14.5 | P91: 2490 | Q91: 14.5 | R91: 2490 | S91: 23~27 | T91: 29~34 | U91: 10982 | V91: 11040 | W91: 11010 | X91: 11010 | Y91: 11565 | Z91: 10707 | AA91: 11026 | AB91: 10801 | AC91: 10706 | AD91: 10522 | AE91: 10962 | AF91: 10983 | AG91: 10805 | AH91: 11507 | AI91: 11024 | AJ91: 11552 | AK91: 10709 | AL91: 11577 | AM91: 10901 | AN91: 10804 | AO91: 10994 | AP91: 11596 | AQ91: 10502 | AR91: 11550 | AS91: 11571 | AT91: 11551 | AU91: 11576 | AV91: 11558 | AW91: 11570 | AX91: 10913 | AY91: 10931 | AZ91: 11530 | BA91: 10960 | BB91: 11549 | BC91: 11501 | BD91: 11531 | BE91: 11572 | BF91: 10503 | BG91: 10538 | BH91: 10530 | BI91: 10974 | BJ91: 11575 | BK91: 11051 | BL91: 11052 | BM91: 11599 | BN91: 10533 | BO91: 11553 | BP91: 10583 | BQ91: 10989 | BR91: 11556 | BS91: 11548 | BT91: 11055 | BU91: 11053 | BV91: 11050 | BW91: 10523 | BX91: 10956 | BY91: 10543 | BZ91: 10528 | CA91: 11514 | CB91: 11054 | CC91: 11547 | CD91: 10606 | CE91: 11510 | CF91: 11555 | CG91: 10920 | CH91: 10601 | CI91: 11853 | CJ91: 11545 | CK91: 10602 | CL91: 10605 | CM91: 11579 | CN91: 10979 | CO91: 11554 | CP91: 10607 | CQ91: 11590 | CR91: 11520 | CS91: 10532 | CT91: 11542 | CU91: 10580 | CV91: 10595 | CW91: 11802 | CX91: 11801 | CY91: 10577 | CZ91: 10573 | DA91: 10927 | DB91: 11710 | DC91: 10925 | DD91: 11815 | DE91: 11793 | DF91: 10970 | DG91: 10923 | DH91: 10984 | DI91: 10591 | DJ91: 10603 | DK91: 11756 | DL91: 10987 | DM91: 10610 | DN91: 10604 | DO91: 11560 | DP91: 11732 | DQ91: 11773 | DR91: 11803 | DS91: 11791 | DT91: 11797 | DU91: 11783 | DV91: 10975 | DW91: 10594 | DX91: 10993 | DY91: 11758 | DZ91: 11762 | EA91: 10910 | EB91: 10570 | EC91: 11771 | ED91: 11747 | EE91: 11714 | EF91: 11775 | EG91: 10510 | EH91: 11735 | EI91: 11804 | EJ91: 11701 | EK91: 11709 | EL91: 11765 | EM91: 10986 | EN91: 10562 | EO91: 11561 | EP91: 11724 | EQ91: 11726 | ER91: 10514 | ES91: 10990 | ET91: 10950 | EU91: 10959 | EV91: 11757 | EW91: 11746 | EX91: 11707 | EY91: 11798 | EZ91: 10917 | FA91: 10560 | FB91: 11703 | FC91: 10545 | FD91: 10520 | FE91: 10912 | FF91: 10911 | FG91: 11743 | FH91: 10969 | FI91: 10926 | FJ91: 10922 | FK91: 11721 | FL91: 11729 | FM91: 11740 | FN91: 11702 | FO91: 10980 | FP91: 11795 | FQ91: 10949 | FR91: 11718 | FS91: 10549 | FT91: 10521 | FU91: 10507 | FV91: 10928 | FW91: 11731 | FX91: 11706 | FY91: 10918 | FZ91: 10598 | GA91: 11725 | GB91: 11717 | GC91: 10988 | GD91: 10548 | GE91: 10566
A92: 额外产生的费用 | C92: 金额 | I92: 单位 | O92: 备注
A93: 卸货等候费 | C93: 85 | I93: Per Hour 每小时 | O93: 免费等候一小时
A94: 跑空 | C94: 实报实销 | I94: Per Entry 每次 | O94: 如果产生
A95: 地址更改 | C95: 补差价，多退少补 | I95: Per Entry 每次 | O95: 需在我司可派送范围内，如已发车，费用不退，需额外加上二次派送费。
A96: 更改自提 | C96: 20 | I96: 每板 | O96: 如未派送尾程费退还，收取对应出仓费
A97: 尾板费 | C97: 75 | I97: 每次 | O97: 无卸货平台需收取
A98: 非工作日送仓（商业/私人地址） | C98: 附加费单询 | I98: 每次 | O98: 周六日或节假日送仓，需要加收费用
A99: 含税渠道 | B99: 1、含关税和查验费； 2、低消334kg，不足按334kg结算；； 3、计费重：体积重和实重取大者，体积重=长cm*宽cm*高cm/6000； 4、单边超120CM以上，单件超40KG以上的货物，请参考《发货必读》； 5、如因客户资料\产品问题，需承担因此产生的所有仓租、柜租、罚金、销毁费等，恶意瞒报的还需承担进口商损失费2000美金；
A100: 不含税渠道 | B100: 1、不含关税、如遇查验费实销； 2、低消2CBM，不足按2CBM结算； 3、计费重=长cm*宽cm*高cm/1000000，不分泡； 4、单边超120CM以上，请参考《发货必读》 5、如因客户资料\产品问题，需承担因此产生的所有仓租、柜租、罚金、销毁费等，恶意瞒报的还需承担进口商损失费2000美金；
A102: 芝加哥普船卡派 | I102: 芝加哥快速达卡派包税
A103: 仓库代码 | B103: 邮编 | C103: 深圳 | E103: 义乌\宁波 | G103: 预计航期*天 | H103: 参考时效 (开船后第二天起)*天 | I103: 深圳 | K103: 义乌\宁波 | M103: 预计航期*天 | N103: 参考时效 (开船后第二天起)*天 | O103: 邮编1 | P103: 邮编2 | Q103: 邮编3 | R103: 邮编4 | S103: 邮编5 | T103: 邮编6 | U103: 邮编7 | V103: 邮编8 | W103: 邮编9 | X103: 邮编10 | Y103: 邮编11 | Z103: 邮编12 | AA103: 邮编13 | AB103: 邮编14 | AC103: 邮编15 | AD103: 邮编16 | AE103: 邮编17 | AF103: 邮编18 | AG103: 邮编19 | AH103: 邮编20 | AI103: 邮编21 | AJ103: 邮编22 | AK103: 邮编23 | AL103: 邮编24 | AM103: 邮编25 | AN103: 邮编26 | AO103: 邮编27 | AP103: 邮编28 | AQ103: 邮编29 | AR103: 邮编30 | AS103: 邮编31 | AT103: 邮编32 | AU103: 邮编33 | AV103: 邮编34 | AW103: 邮编35 | AX103: 邮编36 | AY103: 邮编37 | AZ103: 邮编38 | BA103: 邮编39 | BB103: 邮编40 | BC103: 邮编41 | BD103: 邮编42 | BE103: 邮编43 | BF103: 邮编44 | BG103: 邮编45 | BH103: 邮编46 | BI103: 邮编47 | BJ103: 邮编48 | BK103: 邮编49 | BL103: 邮编50 | BM103: 邮编51 | BN103: 邮编52 | BO103: 邮编53 | BP103: 邮编54 | BQ103: 邮编55 | BR103: 邮编56 | BS103: 邮编57 | BT103: 邮编58 | BU103: 邮编59 | BV103: 邮编60 | BW103: 邮编61 | BX103: 邮编62 | BY103: 邮编63 | BZ103: 邮编64 | CA103: 邮编65 | CB103: 邮编66 | CC103: 邮编67 | CD103: 邮编68 | CE103: 邮编69 | CF103: 邮编70 | CG103: 邮编71 | CH103: 邮编72 | CI103: 邮编73 | CJ103: 邮编74 | CK103: 邮编75
C104: 334KG+ | D104: 2CBM+ | E104: 334KG+ | F104: 2CBM+ | I104: 334KG+ | J104: 2CBM+ | K104: 334KG+ | L104: 2CBM+
A105: 芝加哥FBN头程 | B105: / | C105: 8.9 | D105: 1470 | E105: 8.9 | F105: 1470 | G105: 30~38 | H105: 40~48 | I105: 12.2 | J105: 2130 | K105: 12.2 | L105: 2130 | M105: 20 | N105: 37~39
A106: TikTok_IL | B106: 60188 | C106: 9.6 | D106: 1700 | E106: 9.6 | F106: 1700 | G106: 30~38 | H106: 40~48 | I106: 12.9 | J106: 2360 | K106: 12.9 | L106: 2360 | M106: 20 | N106: 37~39
A107: TikTok-IN | B107: 46241 | C107: 10.3 | D107: 1850 | E107: 10.3 | F107: 1850 | G107: 30~38 | H107: 40~48 | I107: 13.6 | J107: 2510 | K107: 13.6 | L107: 2510 | M107: 20 | N107: 37~39
A108: < 10 Miles | B108: 见右端 | C108: 9.9 | D108: 1760 | E108: 9.9 | F108: 1760 | G108: 30~38 | H108: 40~48 | I108: 13.2 | J108: 2420 | K108: 13.2 | L108: 2420 | M108: 20 | N108: 37~39 | O108: 60490 | P108: 60440 | Q108: 60446 | R108: 60564 | S108: 60403 | T108: 60441 | U108: 60544
A109: 10（含）-20 Miles | B109: 见右端 | C109: 10 | D109: 1780 | E109: 10 | F109: 1780 | G109: 30~38 | H109: 40~48 | I109: 13.3 | J109: 2440 | K109: 13.3 | L109: 2440 | M109: 20 | N109: 37~39 | O109: 60435 | P109: 60439 | Q109: 60432 | R109: 60503 | S109: 60491 | T109: 60434 | U109: 60507 | V109: 60598 | W109: 60543 | X109: 60572 | Y109: 60464 | Z109: 60436 | AA109: 60431 | AB109: 60189 | AC109: 60433 | AD109: 60404 | AE109: 60505 | AF109: 60137 | AG109: 60538 | AH109: 60480 | AI109: 60568 | AJ109: 60138 | AK109: 60502 | AL109: 60465 | AM109: 60525 | AN109: 60458 | AO109: 60451 | AP109: 60190 | AQ109: 60462 | AR109: 60467 | AS109: 60482 | AT109: 60463 | AU109: 60455 | AV109: 60154 | AW109: 60560
A110: 20（含）-30 Miles | B110: 见右端 | C110: 10.1 | D110: 1800 | E110: 10.1 | F110: 1800 | G110: 30~38 | H110: 40~48 | I110: 13.4 | J110: 2460 | K110: 13.4 | L110: 2460 | M110: 20 | N110: 37~39 | O110: 60186 | P110: 60512 | Q110: 60542 | R110: 60506 | S110: 60501 | T110: 60148 | U110: 60448 | V110: 60499 | W110: 60181 | X110: 60454 | Y110: 60415 | Z110: 60539 | AA110: 60421 | AB110: 60459 | AC110: 60447 | AD110: 60513 | AE110: 60126 | AF110: 60185 | AG110: 60546 | AH110: 60487 | AI110: 60162 | AJ110: 60402 | AK110: 60445 | AL110: 60442 | AM110: 60163 | AN110: 60141 | AO110: 60453 | AP110: 60452 | AQ110: 60130 | AR110: 60472 | AS110: 60187 | AT110: 60104 | AU110: 60153 | AV110: 60101 | AW110: 60199 | AX110: 60165 | AY110: 60510 | AZ110: 60164 | BA110: 60174 | BB110: 60423 | BC110: 60128 | BD110: 60132 | BE110: 60197 | BF110: 60106 | BG110: 60536 | BH110: 60105 | BI110: 60116 | BJ110: 60305 | BK110: 60303 | BL110: 60188 | BM110: 60399 | BN110: 60161 | BO110: 60117 | BP110: 60545 | BQ110: 60160 | BR110: 60191 | BS110: 60184 | BT110: 60103 | BU110: 60304 | BV110: 60108 | BW110: 60131 | BX110: 60481 | BY110: 60171 | BZ110: 60554 | CA110: 60477 | CB110: 60172 | CC110: 60406 | CD110: 60511 | CE110: 60157 | CF110: 60541 | CG110: 60469 | CH110: 60007 | CI110: 60537 | CJ110: 60144
A111: 30（含）-40 Miles | B111: 见右端 | C111: 10.2 | D111: 1820 | E111: 10.2 | F111: 1820 | G111: 30~38 | H111: 40~48 | I111: 13.5 | J111: 2480 | K111: 13.5 | L111: 2480 | M111: 20 | N111: 37~39 | O111: 60009 | P111: 60175 | Q111: 60183 | R111: 60119 | S111: 60147 | T111: 60173 | U111: 60176 | V111: 60450 | W111: 60426 | X111: 60428 | Y111: 60193 | Z111: 60177 | AA111: 60443 | AB111: 60018 | AC111: 60120 | AD111: 60019 | AE111: 60548 | AF111: 60520 | AG111: 60068 | AH111: 60017 | AI111: 60429 | AJ111: 60478 | AK111: 60168 | AL111: 60194 | AM111: 60122 | AN111: 60008 | AO111: 60133 | AP111: 60551 | AQ111: 60416 | AR111: 60056 | AS111: 60196 | AT111: 60473 | AU111: 60430 | AV111: 60005 | AW111: 60121 | AX111: 60016 | AY111: 60169 | AZ111: 60095 | BA111: 60407 | BB111: 60107 | BC111: 60422 | BD111: 60449 | BE111: 60471 | BF111: 60078 | BG111: 60006 | BH111: 60067 | BI111: 60476 | BJ111: 60004 | BK111: 60466 | BL111: 60461 | BM111: 60425 | BN111: 60484 | BO111: 60074 | BP111: 60151 | BQ111: 60038 | BR111: 60094 | BS111: 60935 | BT111: 60025 | BU111: 60412 | BV111: 60438 | BW111: 60444 | BX111: 60549 | BY111: 60029 | BZ111: 60070
A112: 40（含）-50 Miles | B112: 见右端 | C112: 10.3 | D112: 1850 | E112: 10.3 | F112: 1850 | G112: 30~38 | H112: 40~48 | I112: 13.6 | J112: 2510 | K112: 13.6 | L112: 2510 | M112: 20 | N112: 37~39 | O112: 60077 | P112: 60195 | Q112: 60192 | R112: 60424 | S112: 60419 | T112: 60062 | U112: 60950 | V112: 60076 | W112: 60531 | X112: 60409 | Y112: 60026 | Z112: 61360 | AA112: 60468 | AB112: 60474 | AC112: 60065 | AD112: 60090 | AE112: 60203 | AF112: 60011 | AG112: 60475 | AH112: 60179 | AI112: 60136 | AJ112: 60082 | AK112: 60010 | AL112: 60969 | AM112: 60557 | AN112: 60204 | AO112: 60112 | AP112: 60089 | AQ112: 60015 | AR112: 60091 | AS112: 60411 | AT112: 60202 | AU112: 60047 | AV112: 60401 | AW112: 60201 | AX112: 60961 | AY112: 60093 | AZ112: 60208 | BA112: 60479 | BB112: 60043 | BC112: 60550 | BD112: 60115 | BE112: 60069 | BF112: 60021 | BG112: 60420 | BH112: 60035 | BI112: 60022 | BJ112: 60110 | BK112: 60118 | BL112: 60140 | BM112: 60013 | BN112: 60102 | BO112: 61353 | BP112: 60917 | BQ112: 60518 | BR112: 60530
A113: 50（含）-60 Miles | B113: 见右端 | C113: 10.4 | D113: 1870 | E113: 10.4 | F113: 1870 | G113: 30~38 | H113: 40~48 | I113: 13.7 | J113: 2530 | K113: 13.7 | L113: 2530 | M113: 20 | N113: 37~39 | O113: 60178 | P113: 60045 | Q113: 60901 | R113: 60040 | S113: 60941 | T113: 60437 | U113: 60084 | V113: 60910 | W113: 60920 | X113: 60037 | Y113: 60156 | Z113: 60109 | AA113: 60553 | AB113: 60039 | AC113: 60048 | AD113: 60014 | AE113: 60044 | AF113: 60111 | AG113: 60150 | AH113: 61318 | AI113: 60088 | AJ113: 60042 | AK113: 60030 | AL113: 60934 | AM113: 60964 | AN113: 60460 | AO113: 60142 | AP113: 60064 | AQ113: 60946 | AR113: 61325 | AS113: 60470 | AT113: 61371 | AU113: 60086 | AV113: 60073 | AW113: 60113 | AX113: 60145 | AY113: 61373 | AZ113: 60135 | BA113: 60031 | BB113: 60012 | BC113: 60051 | BD113: 60922 | BE113: 60929
A114: 60（含）-70 Miles | B114: 见右端 | C114: 10.6 | D114: 1910 | E114: 10.6 | F114: 1910 | G114: 30~38 | H114: 40~48 | I114: 13.9 | J114: 2570 | K114: 13.9 | L114: 2570 | M114: 20 | N114: 37~39 | O114: 61378 | P114: 60085 | Q114: 61372 | R114: 60046 | S114: 60020 | T114: 60954 | U114: 60940 | V114: 61769 | W114: 60041 | X114: 60079 | Y114: 60146 | Z114: 60050 | AA114: 61301 | AB114: 61313 | AC114: 60087 | AD114: 60927 | AE114: 60083 | AF114: 60911 | AG114: 60129 | AH114: 61764 | AI114: 60180 | AJ114: 61068 | AK114: 61350 | AL114: 60098 | AM114: 60959 | AN114: 61331 | AO114: 61367 | AP114: 60099 | AQ114: 61006 | AR114: 61320 | AS114: 60930 | AT114: 61052 | AU114: 60002 | AV114: 60944 | AW114: 61329 | AX114: 60951 | AY114: 61364 | AZ114: 61319 | BA114: 60956 | BB114: 60921 | BC114: 60152 | BD114: 61354 | BE114: 61316 | BF114: 60075 | BG114: 61310 | BH114: 61332 | BI114: 61038
A115: 70（含）-80 Miles | B115: 见右端 | C115: 10.9 | D115: 1960 | E115: 10.9 | F115: 1960 | G115: 30~38 | H115: 40~48 | I115: 14.2 | J115: 2620 | K115: 14.2 | L115: 2620 | M115: 20 | N115: 37~39 | O115: 61317 | P115: 61312 | Q115: 61741 | R115: 60071 | S115: 61016 | T115: 61362 | U115: 61370 | V115: 61311 | W115: 60034 | X115: 60958 | Y115: 60096 | Z115: 61324 | AA115: 60912 | AB115: 61359 | AC115: 60928 | AD115: 61330 | AE115: 61743 | AF115: 60033 | AG115: 60938 | AH115: 61326 | AI115: 61333 | AJ115: 61739 | AK115: 60970 | AL115: 61008 | AM115: 60968 | AN115: 61015 | AO115: 61337 | AP115: 61020 | AQ115: 61334 | AR115: 61323 | AS115: 61322 | AT115: 61374
A116: 80（含）-100Miles | B116: 见右端 | C116: 11 | D116: 1980 | E116: 11 | F116: 1980 | G116: 30~38 | H116: 40~48 | I116: 14.3 | J116: 2640 | K116: 14.3 | L116: 2640 | M116: 20 | N116: 37~39 | O116: 61012 | P116: 61065 | Q116: 61109 | R116: 61740 | S116: 61315 | T116: 61356 | U116: 61011 | V116: 60931 | W116: 61726 | X116: 60955 | Y116: 61321 | Z116: 61377 | AA116: 61091 | AB116: 60974 | AC116: 61108 | AD116: 61327 | AE116: 61061 | AF116: 61358 | AG116: 61773 | AH116: 61731 | AI116: 61126 | AJ116: 61112 | AK116: 61125 | AL116: 61335 | AM116: 61084 | AN116: 60952 | AO116: 61021 | AP116: 61073 | AQ116: 61753 | AR116: 61107 | AS116: 61010 | AT116: 60918 | AU116: 61064 | AV116: 60966 | AW116: 61720 | AX116: 61328 | AY116: 60924 | AZ116: 61114 | BA116: 61102 | BB116: 60936 | BC116: 61111 | BD116: 61369 | BE116: 61110 | BF116: 61336 | BG116: 61054 | BH116: 61376 | BI116: 60926 | BJ116: 61130 | BK116: 61131 | BL116: 61132 | BM116: 61728 | BN116: 61104 | BO116: 60953 | BP116: 60962 | BQ116: 61375 | BR116: 60957 | BS116: 61081 | BT116: 61379 | BU116: 61103 | BV116: 61368 | BW116: 61115 | BX116: 61776 | BY116: 61338 | BZ116: 61516 | CA116: 61541 | CB116: 61088 | CC116: 60973 | CD116: 61730 | CE116: 61758 | CF116: 61080 | CG116: 61845 | CH116: 60949 | CI116: 61037 | CJ116: 61770 | CK116: 61051
A117: 额外产生的费用 | C117: 金额 | E117: 单位 | G117: 备注
A118: 卸货等候费 | C118: 85 | E118: Per Hour 每小时 | G118: 免费等候一小时
A119: 跑空 | C119: 实报实销 | E119: Per Entry 每次 | G119: 如果产生
A120: 地址更改 | C120: 补差价，多退少补 | E120: Per Entry 每次 | G120: 需在我司可派送范围内，如已发车，费用不退，需额外加上二次派送费。
A121: 更改自提 | C121: 20 | E121: 每板 | G121: 如未派送尾程费退还，收取对应出仓费
A122: 尾板费 | C122: 75 | E122: 每次 | G122: 无卸货平台需收取
A123: 非工作日送仓（商业/私人地址） | C123: 附加费单询 | E123: 每次 | G123: 周六日或节假日送仓，需要加收费用
A124: 含税渠道 | B124: 1、含关税和查验费； 2、低消334kg，不足按334kg结算；； 3、计费重：体积重和实重取大者，体积重=长cm*宽cm*高cm/6000； 4、单边超120CM以上，单件超40KG以上的货物，请参考《发货必读》； 5、如因客户资料\产品问题，需承担因此产生的所有仓租、柜租、罚金、销毁费等，恶意瞒报的还需承担进口商损失费2000美金；
A125: 不含税渠道 | B125: 1、不含关税、如遇查验费实销； 2、低消2CBM，不足按2CBM结算； 3、计费重=长cm*宽cm*高cm/1000000，不分泡； 4、单边超120CM以上，请参考《发货必读》 5、如因客户资料\产品问题，需承担因此产生的所有仓租、柜租、罚金、销毁费等，恶意瞒报的还需承担进口商损失费2000美金；
A127: 休斯顿专线卡派
A128: 仓库代码 | B128: 邮编 | C128: 深圳 | E128: 义乌\宁波 | G128: 预计航期*天 | H128: 参考时效 (开船后第二天起)*天 | I128: 邮编1 | J128: 邮编2 | K128: 邮编3 | L128: 邮编4 | M128: 邮编5 | N128: 邮编6 | O128: 邮编7 | P128: 邮编8 | Q128: 邮编9 | R128: 邮编10 | S128: 邮编11 | T128: 邮编12 | U128: 邮编13 | V128: 邮编14 | W128: 邮编15 | X128: 邮编16 | Y128: 邮编17 | Z128: 邮编18 | AA128: 邮编19 | AB128: 邮编20 | AC128: 邮编21 | AD128: 邮编22 | AE128: 邮编23 | AF128: 邮编24 | AG128: 邮编25 | AH128: 邮编26 | AI128: 邮编27 | AJ128: 邮编28 | AK128: 邮编29 | AL128: 邮编30 | AM128: 邮编31 | AN128: 邮编32 | AO128: 邮编33 | AP128: 邮编34 | AQ128: 邮编35 | AR128: 邮编36 | AS128: 邮编37 | AT128: 邮编38 | AU128: 邮编39 | AV128: 邮编40 | AW128: 邮编41 | AX128: 邮编42 | AY128: 邮编43 | AZ128: 邮编44 | BA128: 邮编45 | BB128: 邮编46 | BC128: 邮编47 | BD128: 邮编48 | BE128: 邮编49 | BF128: 邮编50 | BG128: 邮编51 | BH128: 邮编52 | BI128: 邮编53 | BJ128: 邮编54 | BK128: 邮编55 | BL128: 邮编56 | BM128: 邮编57 | BN128: 邮编58 | BO128: 邮编59 | BP128: 邮编60 | BQ128: 邮编61 | BR128: 邮编62 | BS128: 邮编63 | BT128: 邮编64 | BU128: 邮编65 | BV128: 邮编66 | BW128: 邮编67 | BX128: 邮编68 | BY128: 邮编69 | BZ128: 邮编70 | CA128: 邮编71 | CB128: 邮编72 | CC128: 邮编73 | CD128: 邮编74 | CE128: 邮编75 | CF128: 邮编76 | CG128: 邮编77 | CH128: 邮编78 | CI128: 邮编79 | CJ128: 邮编80 | CK128: 邮编81 | CL128: 邮编82 | CM128: 邮编83 | CN128: 邮编84 | CO128: 邮编85 | CP128: 邮编86 | CQ128: 邮编87 | CR128: 邮编88 | CS128: 邮编89 | CT128: 邮编90 | CU128: 邮编91 | CV128: 邮编92 | CW128: 邮编93 | CX128: 邮编94
...

Sheet 反倾销系列
A1: 美国反倾销系列
A2: Case No. | B2: Product | C2: Chinese Name | D2: HTSUS | E2: 解释
A3: A-570-904 | B3: Activated Carbon | C3: 活性炭 | D3: 3802.10.00 | E3: 订单范围涵盖通过蒸汽或二氧化碳活化的所有形式的活性炭，无论原料、等级、混合物、添加剂、进一步洗涤或活化后化学处理（化学或水洗、化学浸渍或其他处理） ) 或产品形式。该订单的范围涵盖某些活性炭的所有物理形式，包括粉末状活性炭 (“PAC”)、颗粒状活性炭 (“GAC”) 和颗粒状活性炭。
A4: A-570-104 | B4: Alloy and Certain Carbon Steel Threaded Rod | C4: 合金和某些碳钢螺纹杆 | D4: 7318.15.5051、7318.15.5056 、 7318.15.5090、7318.15.2095 、 7318.19.0000 | E4: 本订单范围内的商品为合金和某些碳钢螺纹杆。合金和某些碳钢螺纹杆是由碳钢或合金钢制成的某些螺纹杆、棒或螺柱，具有任何直径、任何直线长度的实心圆形横截面。合金和某些碳钢螺纹杆通常经过拉拔、冷轧、螺纹和矫直，也可以进行热轧。此外，受此订单约束的合金和某些碳钢螺纹杆、棒或螺柱是无头的，并且螺纹长度超过其实际总长度的 25%。各种饰面或涂层，例如作为临时防锈剂的普通油饰面、锌涂层（即镀锌，无论是通过电镀还是热浸）、油漆和其他类似的饰面和涂层。 标的商品包括已在第三国完成、组装或包装的符合上述描述的材料，包括通过切割、倒角、涂层或涂漆螺纹杆，将螺纹杆连接到另一产品或将其与另一产品包装在一起, 或任何其他精加工、组装或包装操作，如果在螺纹杆的制造国执行，则不会将商品从订单范围中删除。 合金和某些碳钢螺纹杆也包括在本订单的范围内，无论是否与其他零件和附件（如螺母和垫圈）连接或结合进口。如果进口碳钢和合金钢丝杆附在或与此类非标的商品结合使用，则仅丝杆包含在范围内。
A5: A-570-967 | B5: Aluminum Extrusions | C5: 铝型材 | D5: 604.21.0000、7604.29.1000、7604.29.3010、7604.29.3050、7604.29.5030、7604.29.5060 、7608.20.0030 、7608.20.0090、7610.10、7610.90、7615.19、7615.20 、 7616.99、8418.99.80.50 、 8418.99.80.60 | E5: 该订单涵盖的商品是铝挤压件，其形状和形状是通过挤压工艺生产的，由铝合金制成，其金属元素对应于铝业协会公布的合金系列名称，从数字 1、3 和 6 开始（或专有等效物或其他认证机构等效物）。 铝型材以各种形状和形式生产和进口，包括但不限于空心型材、其他实心型材、管材、管材、棒材和棒材。在挤压之后拉制的铝型材（“拉制铝”）也包括在范围内。 不限于窗框、门框、太阳能电池板、幕墙或家具。其他符合铝型材定义的零件都包括在范围内。该范围包括连接（例如，通过焊接或紧固件）以形成子组件的铝挤压部件，即部分组装的商品，除非作为成品套件的一部分进口，否则将在下文进一步定义。该范围不包括子组件或主题套件的非铝挤压部件。 可以参考其最终用途来识别主题挤压件，例如栅栏柱、电线导管、门门槛、地毯装饰或散热器（不符合以下成品散热器排除语言）。如果此类商品在其他方面符合范围定义，则无论它们在进口时是否准备好使用，都属于标的商品。
A6: A-570-053 | B6: Aluminum Foil | C6: 铝箔 | D6: 7607.11.3000、7607.11.6000、7607.11.9030、7607.11.9060、7607.11.9090 、 7607.19.6000、7606.11.3060、7606.11.6000、7606.12.3045、7606.12.3055、7606.12.3090、7606.12.6000、7606.91.3090 、7606.91.6080、7606.92.3090 、 7606.92.6080 | E6: 此订单涵盖的商品是厚度为 0.2 毫米或更小的铝箔，卷装超过 25 磅，无论宽度如何。铝箔由含有 92% 以上铝的铝合金制成。铝箔可以按照 ASTM 规范 ASTM B479 制造，但也可以按照其他规范制造。然而，无论规格如何，所有符合范围描述的铝箔都包括在范围内，包括已在箔的一侧或两侧施加润滑剂的铝箔。
A7: A-570-095 | B7: Aluminum Wire and Cable | C7: 铝电线电缆 | D7: 8544.49.9000、8544.42.9090 | E7: 该订单的范围包括铝电线和电缆，该组件可以： (1) 包括接地或中性导体；(2) 包覆铝、钢或其他贱金属；
A8: A-570-049 | B8: Ammonium Sulfate | C8: 硫酸铵 | D8: 3102.21.0000 | E8: 范围包括与其他产品组合的硫酸铵，包括例如通过混合（即，将硫酸铵颗粒与一种或多种其他产品的颗粒混合）、复合（即，当硫酸铵与一种或多种高压下的其他产品），或造粒（通过例如浆料工艺将多种产品结合成颗粒）。对于此类组合产品，这些订单范围仅涵盖硫酸铵成分。 与其他产品混合使用的硫酸铵，无论是否发生在中国以外的国家，均包含在该范围内。
A9: A-570-899 | B9: Artist Canvas | C9: 艺术家画布 | D9: 5901.90.20.00 、5901.90.40.00 | E9: 此订单所涵盖的产品是艺术家画布，无论尺寸和*或尺寸，无论是否组装，是否已上底漆*涂层，无论是否由棉制成，无论是否存档，是否漂白或未漂白，以及是否包含吸墨面漆。底漆*涂层包括溶液的应用，旨在促进艺术家材料（如油漆或墨水）对织物的附着力。艺术家画布（即预拉伸画布、画布面板、画布垫、画布卷（包括已涂底漆的散装卷）、可印刷画布、地板布和餐垫）是紧密编织的准备绘画和*或印刷表面。
A10: A-570-880 | B10: Barium Carbonate | C10: 碳酸钡 | D10: 2836.60.0000 | E10: 本订单所涵盖的商品为碳酸钡，不分形式或等级
A11: A-570-007 | B11: Barium Chloride | C11: 氯化钡 | D11: 2827.39.45.00 | E11: 该订单涵盖的商品是氯化钡，一种化学式为 BaCl2 或 BaCl2-2H2O 的化合物，
A12: A-570-018 | B12: Boltless Steel Shelving Units Prepackaged for sale | C12: 预包装出售的无螺栓钢搁架单元 | D12: 9403.20.0018、9403.20.0020、9403.20.0025 、 9403.20.0026 、 9403.10.0040 | E12: 本订单涵盖的商品是预包装出售的无螺栓钢货架单元，带或不带甲板（“无螺栓钢货架”）。 范围包括所有符合上述描述的无螺栓钢货架，无论（1）垂直支撑或立柱类型（包括但不限于开放式立柱、封闭式立柱和管道）；（2）水平支撑或梁*支撑型材（包括但不限于Z型梁、C型梁、L型梁、台阶梁和货架）；(3) 支座数量；（4）表面涂层（包括但不限于油漆、环氧树脂、粉末涂料、锌等金属涂层）；(5) 层数；(6) 承重能力；（7）形状（包括但不限于矩形、正方形、角单元）；(8) 铺面材料（包括但不限于金属丝铺面、刨花板、层压板或根本没有铺面）；(9) 垂直和水平支撑连接的无螺栓方法（包括但不限于锁孔和铆钉、槽和凸片，
A13: A-570-008 | B13: Calcium Hypochlorite | C13: 次氯酸钙 | D13: 2828.10.0000、3808.94.5000 、 3808.99.9500 | E13: 本订单涵盖的产品是次氯酸钙，无论其形式如何（例如，粉末、片剂（压缩）、结晶（颗粒）或液体溶液），无论是否与其他材料混合，均含有至少 10% 的有效氯按实际重量。范围还包括漂白粉和半碱式次氯酸钙。次氯酸钙的一般化学配方为 Ca(OCl)2，但也可以以更稀释的形式作为漂白粉与化学配方
... A19: A-570-079 | B19: Cast Iron Soil Pipe | C19: 铸铁土管 | D19: 7303.00.0030 | E19: 该订单涵盖的商品是铸铁土管，无论是成品还是未成品，无论行业或专有规格如何，也无论壁厚、长度、直径、表面光洁度、端部光洁度或模板。该订单的范围包括但不限于无轮毂和轮毂和插口铸铁土管。铸铁土管是各种设计和尺寸的不可锻铸铁管。铸铁土壤管与其他类型的不可锻铸铁管的区别通常在于它与铸铁土壤管配件的连接方式。 铸铁土管分为无轮毂和轮毂套管两大类。无轮毂铸铁土管是在没有轮毂的情况下制造的，通常符合铸铁土管协会 (CISPI) 规范 301 和*或美国测试与材料协会 (ASTM) 规范 A888，包括对这些规范的任何修订。集线器和插口管具有一个或多个集线器，管件的插口（平端）插入其中。所有符合上述物理描述的管道都包含在本订单的范围内，无论是否根据特定标准生产。
A20: A-570-062 | B20: Cast Iron Soil Pipe Fittings | C20: 铸铁土管配件
A21: A-570-108 | B21: Ceramic Tile | C21: 瓷砖 | D21: 6907.21.1005、6907.21.1011、6907.21.1051、6907.21.2000、6907.21.3000、6907.21.4000、6907.2 .9011，6907.21.9051，6907.22.1005，6907.22.1011，6907.22.1051，6907.22.2000，6907.22.3000，6907.22.4000 , 6907.23.2000, 6907.23.3000, 6907.23.4000, 6907.23.9011, 6907.23.9051, 6907.30.1005, 6907.30.1011, 6907.30.1051, 6907.30.2000, 6907.30.3000, 6907.30.4000, 6907.30.9011, 6907.30 .9051、6907.40.1005、6907.40.1011、6907.40.1051、6907.40.2000、6907.40.3000、6907.40.4000、6907.40.9011 、 6907.40.9051, 6914 、 6905 ,6914.10.8000、6914.90.8000、6905.10.0000 ,690590.0050 | E21: 本次订单涉及的商品有瓷砖地砖、墙砖、铺路砖、炉床砖、瓷砖、马赛克砖、旗帜、饰面砖等（以下简称瓷砖）。瓷砖是含有矿物混合物的物品，包括粘土（通常是氧化铝或镁的水合硅酸盐），经过烧制，原材料被熔化以生产实际厚度小于 3.2 厘米的成品。无论最终用途、表面积和重量如何，无论瓷砖是上釉还是未上釉，无论按重量计算的吸水系数如何，无论玻璃化程度如何，无论是否或不是瓷砖在背衬上。标的商品包括具有可能超过 3 个的装饰特征的瓷砖。
A22: A-570-038 | B22: Certain Amorphous Silica Fabric | C22: 某些无定形二氧化硅织物 | D22: 019.59.4021、7019.59.4096、7019.59.9021 、 7019.59.9096，7019.40.4030、7019.40。 4060、7019.40.9030、7019.40.9060、7019.51.9010、7019.51.9090、7019.52.9010、7019.52.9021、7019.52.9096 、7019.90.1000。 | E22: 此订单涵盖的商品是机织（无论是纱线还是粗纱）工业级无定形二氧化硅织物，按标称重量计，其二氧化硅 (SiO2) 含量至少为 90%，标称宽度超过 8 英寸。该订单涵盖工业级无定形二氧化硅织物，无论织物中包含的其他材料如何，无论是卷状还是定长切割，无论重量、宽度（除上述情况外）或长度如何。该订单涵盖工业级无定形二氧化硅织物，无论产品是否获得标准测试机构的批准（例如工厂互助 (FM) 批准），或者无论其是否符合任何政府规范。 标的商品还包括（1）任何工业级无定形二氧化硅织物，在中国由第三国生产的玻璃纤维布转化为工业级无定形二氧化硅织物；(2) 任何工业级无定形二氧化硅织物在出口到美国之前在第三国进行了进一步加工，包括但不限于处理、涂层、分切、定长切割、定宽切割、边缘整理，如果在范围内工业级无定形二氧化硅织物的制造国进行，则添加索环或任何其他不会将商品从订单范围中删除的处理。
A23: A-570-036 | B23: Certain Biaxial Integral Geogrid Products | C23: 某些双轴整体土工格栅产品 | D23: 3926.90.9996， 3920.20.0050 、 3925.90.0000 | E23: 范围涵盖的产品为某些双轴整体土工格栅产品。双轴整体土工格栅产品是一种聚合物网格或网状材料（无论是否经过加工、开缝、定尺切割、附在机织或非织造织物或片材上，或包装），其中的四边开口形式为正方形、长方形、菱形、菱形或其他四边形图形占主导地位。所覆盖的产品具有整体股线，这些股股线已被拉伸以将分子定向到材料中（这表明股线的宽度在接头之间的中间比在接头本身处更细）构成了开口的侧面和整体接头，其中股线相交。范围包括以四边形为主的产品，无论它们是否还包含与四边形相交的附加股线，以及四边形的内角是否为圆角或非锐角。如本文所用，术语“整体”是指彼此同质的股线和接头。 标的商品包括已在第三国完成、包装或以其他方式进一步加工的与上述描述相匹配的材料，包括通过修整、分切、涂层、切割、打孔、拉伸、附着到织造或非织造织物或片材上，或任何其他精加工、包装或其他进一步处理，如果在双轴整体土工格栅制造国进行，则不会将商品从调查范围中删除。
A24: A-570-047 | B24: Certain Carbon and Alloy Steel Cut-to-Length Plate | C24: 某些碳钢和合金钢定尺切割板 | D24: 7208.40.3030、7208.40.3060、7208.51.0030、7208.51.0045、7208.51.0060、7208.52.0000、7211.13 .0000、7211.14.0030、7211.14.0045、7225.40.1110、7225.40.1180、7225.40.3005、7225.40.3050、7226.20.0000 、 7226.91.5000。7208.40.6060、7208.53.0000、7208.90.0000、7210.70.3000、7210.90.9000、7211.19.1500、7211.19.2000、7211.1.19.4.5 6000，7211.19.7590，7211.90.0000，7212.40.1000，7212.40.5000，7212.50.0000，7214.10.0000，7214.30.0010，7214.30.0080 7214.91.0090，7225.11.0000，7225.19.0000，7225.40.5110，7225.40.5130，7225.40.5160，7225.40.7000，7225.99.0010 9000、7226.91.0500、7226.91.1530、7226.91.1560、7226.91.2530、7226.91.2560、7226.91.7000、7226.91.8000、7226.99.0180。 | E24: 本订单涵盖的产品是某些非成卷的碳钢和合金钢热轧或锻造平板产品，无论是否涂漆、清漆或涂有塑料或其他非金属物质（定尺切割板）。标的商品包括通过从卷材或其他离散长度板材定长切割生产的板材以及轧制或锻造成离散长度的板材。 涵盖的产品包括（1）万能轧板（即四面轧制或封闭箱形道次轧制的平轧产品，宽度超过 150 毫米但不超过 1250 毫米，厚度不小于 4 毫米） ，不是成卷的，没有浮雕图案），和（2）厚度为4的热轧或锻造扁钢产品。75 毫米或以上，宽度超过 150 毫米，尺寸至少是厚度的两倍，并且不成卷，无论是否带有浮雕图案。上述覆盖产品可以是矩形、正方形、圆形或其他形状，并且包括具有矩形或非矩形横截面的产品，其中这种非矩形横截面是在轧制过程之后获得的，即，已经过“轧制后加工”（例如，边缘已斜切或倒圆的产品）。
A25: A-570-135 | B25: Certain Chassis and Subassemblies Thereof | C25: 某些底盘及其子组件 | D25: 8716.39.0090 、 8716.90.5060， 8716.90.5010 | E25: 本订单涵盖的商品包括底盘及其子组件，无论是成品还是未成品，组装或未组装，涂层或未涂层，无论轴数如何，用于运输集装箱或其他有效载荷（包括自支撑有效载荷）用于公路、海上滚装*滚装 (RORO) 和*或铁路运输。底盘通常是但不限于带有悬架和车轴系统、车轮和轮胎、制动器、照明和电气系统、用于牵引卡车牵引车后面的联轴器以及用于固定车辆的锁定系统或系统的矩形框架拖车。使用扭锁、滑动销或类似的连接装置将一个或多个集装箱运输到底盘，以接合集装箱或其他有效载荷上的角配件。 任何这些子组件的进口，无论是组装的还是未组装的，都构成了本订单中未完成的底盘。
A26: A-570-058 | B26: Certain Cold-Drawn Mechanical Tubing of Carbon and Alloy Steel | C26: 某些碳钢和合金钢冷拔机械管 | D26: 7304.31.3000、7304.31.6050、7304.51.1000、7304.51.5005、7304.51.5060、7306.30.5015、7306.30 .5020、7306.50.5030,7306.30.1000 、 7306.50.1000 | E26: 该订单的范围包括圆形截面的碳钢和合金钢冷拉机械管（冷拉机械管），长度为 304.8 毫米或以上，实际外径小于 331 毫米，无论壁厚如何，表面光洁度、最终光洁度或行业规范。主题冷拔机械管是具有圆形横截面形状的管状产品，在初始管形成后以涉及管的直径或壁厚变化的方式冷拉或以其他方式冷精加工， 或两者。主题冷拔机械管可以由焊接（例如，电阻焊接、连续焊接等）或无缝（例如，穿孔、皮尔格或挤压等）碳或合金钢管产品生产。也可以在冷加工后进行热处理。这种热处理可以包括但不限于退火、正火、淬火和回火、应力消除或最终退火。主题商品的典型冷拔方法包括但不限于在芯轴上拉拔、棒拉拔、塞拉拔、下沉拉拔和涉及使用模具或类似装置减小管材外径的类似工艺，无论是否使用内部支撑装置（例如心轴、杆、塞子或类似装置）控制管道的内径。可用于生产主题商品的其他冷精加工操作包括冷轧和冷定型管材。消除应力或完成退火。主题商品的典型冷拔方法包括但不限于在芯轴上拉拔、棒拉拔、塞拉拔、下沉拉拔和涉及使用模具或类似装置减小管材外径的类似工艺，无论是否使用内部支撑装置（例如心轴、杆、塞子或类似装置）控制管道的内径。可用于生产主题商品的其他冷精加工操作包括冷轧和冷定型管材。消除应力或完成退火。主题商品的典型冷拔方法包括但不限于在芯轴上拉拔、棒拉拔、塞拉拔、下沉拉拔和涉及使用模具或类似装置减小管材外径的类似工艺，无论是否使用内部支撑装置（例如心轴、杆、塞子或类似装置）控制管道的内径。可用于生产主题商品的其他冷精加工操作包括冷轧和冷定型管材。无论是否使用内部支撑装置（例如心轴、杆、塞子或类似装置）来控制管道的内径。可用于生产主题商品的其他冷精加工操作包括冷轧和冷定型管材。无论是否使用内部支撑装置（例如心轴、杆、塞子或类似装置）来控制管道的内径。可用于生产主题商品的其他冷精加工操作包括冷轧和冷定型管材。 主题冷拔机械管通常经过认证，符合冷拔管的行业规范，包括但不限于：
A27: A-570-029 | B27: Certain Cold-Rolled Steel Flat Products | C27: 某些冷轧扁钢产品 | D27: 7209.15.0000、7209.16.0030、7209.16.0060、7209.16.0070、7209.16.0091、7209.17.0030、7209.17 .0060，7209.17.0070，7209.17.0091，7209.18.1530，7209.18.1560，7209.18.2510，7209.18.2520，7209.18.2580 , 7209.28.0000, 7209.90.0000, 7210.70.3000, 7211.23.1500, 7211.23.2000, 7211.23.3000, 7211.23.4500, 7211.23.6030, 7211.23.6060, 7211.23.6090, 7211.29.2030, 7211.29.2090, 7211.29 .4500，7211.29.6030，7211.29.6080，7211.90.0000，7212.40.1000，7212.40.5000，7225.50.6000，7225.50.8080，722255.99.0090，7226.0090 ,7210.90。 | E27: 本订单涵盖的产品是某些冷轧（冷轧）平轧钢产品，无论是否经过退火、涂漆、清漆或涂有塑料或其他非金属物质。涵盖的产品不包括包覆、镀覆或涂有金属的产品。涵盖的产品包括宽度或其他横向测量（“宽度”）为 12.7 毫米或更大的线圈，无论线圈的形式如何（例如，在连续叠加的层中，螺旋振荡等）。涵盖的产品还包括厚度小于 4.75 毫米、宽度为 12.7 毫米或更大且尺寸至少为厚度的 10 倍的非线圈产品（例如，直线长度）。涵盖的产品还包括厚度为 4 的非线圈（例如，直线长度）的产品。75 毫米或以上，宽度超过 150 毫米，并测量至少两倍的厚度。上述产品可以是矩形、正方形、圆形或其他形状，包括具有矩形或非矩形横截面的产品，这种横截面是在轧制过程之后获得的，即经过“加工”的产品轧制后''（例如，边缘已斜切或倒圆的产品）。出于上述宽度和厚度要求的目的：“轧制后加工”的产品（例如，边缘已斜切或倒圆的产品）。出于上述宽度和厚度要求的目的：“轧制后加工”的产品（例如，边缘已斜切或倒圆的产品）。
A28: A-570-122 | B28: Certain Corrosion Inhibitors | C28: 某些缓蚀剂 | D28: 2933.99.8220,2933.99.8290, 2933.99.8210,2933.99.8290 | E28: 该订单涵盖的商品为甲苯基三唑和苯并三唑。这包括所有等级和形式的甲苯基三唑和苯并三唑，包括它们的钠盐形式。甲苯基三唑在技术上被称为甲苯基三唑 IUPAC 4,5 甲基苯并三唑。也可识别为4,5甲基苯并三唑、甲苯三唑、TTA、TTZ。 苯并三唑在技术上称为 IUPAC 1,2,3-苯并三唑。它也可以被识别为 1,2,3-苯并三唑、1,2-氨基并亚苯基、1H-苯并三唑和 BTA。 所有形式的甲苯基三唑和苯并三唑，包括但不限于薄片、颗粒、丸剂、小球、针头、粉末或液体，都包括在本订单的范围内。 范围包括与其他产品组合或混合的甲苯基三唑*甲苯基三唑钠和苯并三唑*苯并三唑钠。对于此类组合产品，只有甲苯基三唑*甲苯基三唑钠和苯并三唑*苯并三唑钠组分在本订单范围内。已与其他产品合用的甲苯基三唑和甲苯基三唑钠均包含在范围内，无论是否发生在第三国。与不受此命令约束的来源的甲苯基三唑、甲苯基三唑钠、苯并三唑钠或苯并三唑钠混合时，不排除其他受此命令约束的甲苯基三唑、甲苯基三唑钠、苯并三唑和苯并三唑钠。
A29: A-570-026 | B29: Certain Corrosion-Resistant Steel Products | C29: 某些耐腐蚀钢制品 | D29: 7210.30.0030、7210.30.0060、7210.41.0000、7210.49.0030、7210.49.0091、7210.49.0095 ，7210.61.0000，7210.69.0000，7210.70.6030，7210.70.6060，7210.70.6090，7210.90.6000，7210.90.90.90.9000，7212.20.20.20.20.0000，7212.30.30.30.30.30.30.30.30.30.30.30.30.30.30.30.30. 000，721.10.30.10.10.19.10.19.30.30.30. 000，72330.10.19.30.30. 000，72330.10.g30.330.bhter .1000、7212.40.5000、7212.50.0000 、 7212.60.0000 7210.90.1000、7215.90.1000、7215.90.3000、7215.90.5000、7217.20.1500、7217.30.1530、7217.30.156000、7217.7.90.0.2 5030，7217.90.5060，7217.90.5090，7225.91.0000，7225.92.0000，7225.99.0090，7226.99.0110，7226.99.0130 | E29: 本次调查涵盖的产品是某些平板轧钢产品，无论是否包覆、电镀或涂有耐腐蚀金属
A30: A-570-849 | B30: Certain Cut-To-Length Carbon Steel | C30: 某些定尺切割碳钢 | D30: 7208.40.3030、7208.40.3060、7208.51.0030、7208.51.0045、7208.51.0060、7208.52.0000、7208.53.0000、7208。 0000、7210.70.3000、7210.90.9000、7211.13.0000、7211.14.0030、7211.14.0045、7211.90.0000、7212.40.1000、7212.40.50000、7212.50. | E30: 本订单涉及的商品为中华人民共和国某定长定尺碳钢板
A31: A-570-051 | B31: Certain Hardwood Plywood Products | C31: 某些硬木胶合板产品 | D31: 4412.10.0500;4412.31.0520; 4412.31.0540；4412.31.0560；4412.31.0620；4412.31.0640；4412.31.0660；4412.31.2510；4412.31.2520；4412.31.2610；4412.31.2620；4412.31.4040；4412.31.4050；4412.31.4060；4412.31.4075；4412.31.4080；4412.31.4140；4412.31.4150；4412.31.4160；4412.31.4180；4412.31.5125；4412.31.5135；4412.31.5155；4412.31.5165；4412.31.5175；4412.31.5235；4412.31.5255；4412.31.5265；4412.31.5275；4412.31.6000；4412.31.6100；4412.31.9100；4412.31.9200；4412.32.0520；4412.32.0540；4412.32.0565；4412.32.0570；4412.32.0620；4412.32.0640；4412.32.0670；4412.32.2510；4412.32.2525；4412.32.2530；4412.32.2610；4412.32.2630；4412.32.3125；4412.32.3135；4412.32.3155；4412.32.3165；4412.32.3175；4412.32。3185; 4412.32.3235；4412.32.3255；4412.32.3265；4412.32.3275；4412.32.3285；4412.32.5600；4412.32.3235；4412.32.3255；4412.32.3265；4412.32.3275；4412.32.3285；4412.32.5700；4412.94.1030；4412.94.1050；4412.94.3105；4412.94.3111；4412.94.3121；4412.94.3141；4412.94.3161；4412.94.3175；4412.94.4100；4412.99.0600；4412.99.1020；4412.99.1030；4412.99.1040；4412.99.3110；4412.99.3120；4412.99.3130；4412.99.3140；4412.99.3150；4412.99.3160；4412.99.3170；4412.99.4100；4412.99.5115 、 4412.99.5710; 4412.99.3110；4412.99.3120；4412.99.3130；4412.99.3140；4412.99.3150；4412.99.3160；4412.99.3170；4412.99.4100；4412.99.5115； 、 4412.99.5710,4412.99.3110；4412.99.3120；4412.99.3130；4412.99.3140；4412.99.3150；4412.99.3160；4412.99.3170；4412.99.4100；4412.99.5115； 、 4412.99.5710。 4412.99.7000；4412.99.8000；4412.99.9000；4412.10.9000；4412.94.5100；4412.94.9500 、 4412.99.9500。 | E31: 本次调查的商品是硬木和装饰胶合板，以及如下所述的某些单板。就本程序而言，硬木和装饰胶合板被定义为一般平坦的多层胶合板或其他单板，由两层或多层木单板和一个芯组成，表面和*或背面单板由非-针叶木（硬木）或竹子。单板连同芯可以胶合或以其他方式结合在一起。硬木和装饰胶合板可能包括符合美国硬木和装饰胶合板国家标准 ANSI*HPVA HP-1-2016（包括对该标准的任何修订）的产品。 就本次调查而言，“单板”是指从原木、螺栓或木片上切割、切割或锯开的一片木头，无论其厚度如何。正面和背面单板是芯材任一侧的最外层木材单板，与下文所述的附加表面涂层或覆盖层无关。 硬木和装饰胶合板的芯材由位于正面和背面单板之间的一层或多层材料组成。芯材可由多种材料组成，包括但不限于硬木、软木、刨花板或中密度纤维板 (MDF)。 所有硬木胶合板都包括在本次调查的范围内，无论正面和*或背面单板是否经过表面涂层或覆盖，以及此类表面涂层或覆盖层是否会掩盖木材的纹理、纹理或标记木头。表面涂层和覆盖物的例子包括但不限于： 紫外光固化聚氨酯；油或油改性或水基聚氨酯；蜡; 环氧酯饰面；湿固化聚氨酯；油漆；污渍；纸; 铝; 高压层压板；中密度纤维板；中密度覆盖（MDO）；和酚醛薄膜。此外，硬木胶合板的饰面可以打磨；通过手工刮擦或钢丝刷等方法使外观平滑或呈现“仿旧”外观。所有硬木胶合板都包括在范围内，即使它被修剪过；按尺寸裁剪；缺口; 打孔；钻孔；或经过其他形式的小加工。 所有硬木和装饰胶合板都包括在本次调查范围内，不考虑尺寸（总厚度、正面单板厚度、背单板厚度、芯材厚度、内单板厚度、宽度或长度）。
A32: A-570-865 | B32: Certain Hot-Rolled Carbon Steel Flat Products | C32: 某些热轧碳钢平板产品 | D32: 7208.10.15.00, 7208.10.30.00, 7208.10.60.00, 7208.25.30.00, 7208.25.60.00, 7208.26.00.30, 7208.26.00.60, 7208.27.00.30, 7208.27.00.60, 7208.36.00.30, 7208.36.00.60, 7208.37.00.30, 7208.37.00.60, 7208.38.00.15, 7208.38.00.30, 7208.38.00.90, 7208.39.00.15, 7208.39.00.30, 7208.39.00.90, 7208.40.60.30, 7208.40.60.60, 7208.53. 00.00, 7208.54.00.00, 7208.90.00.00, 7211.14.00.90, 7211.19.15.00, 7211.19.20.00, 7211.19.30.00, 7211.19.45.00, 7211.19.60.00, 7211.19.75.30, 7211.19.75.60, and 7211.19.75.90. 7225.11.00.00、7225.19.00。00，7225.30.30.50，7225.30.70.00，7225.40.70.00，7225.99.00.90，7226.11.11.10.11.11.11.11.11.90.90.30，7226.11.11.90.11.90.60 、 7226.99.00.00。 7210.70.30.00、7210.90.90.00、7211.14.00.30、7212.40.10.00、7212.40.50.00 、 7212.50.00.00 | E32: 订单所涵盖的产品是某些矩形热轧碳钢扁平产品，宽度为 0.5 英寸或更大，既不包覆、镀覆或涂敷金属，也不论是否涂漆、清漆或涂有塑料或其他非金属物质，成卷的（不论是否在连续叠加的层中），无论厚度如何，直线长度小于 4.75 毫米，宽度至少为厚度的 10 倍。通用轧板（即在四个面或封闭箱形道次轧制的平轧产品，宽度超过 150 毫米但不超过 1,250 毫米，厚度不小于 4.0 毫米，非成卷且无厚度不小于 4.0 毫米的浮雕图案）不包括在订单范围内。订单范围内具体包括真空脱气、完全稳定（通常称为无间隙（“IF”））钢、高强度低合金（“HSLA”）钢和电机层压钢的基材。IF 钢被认为是低碳钢，添加了微合金化水平的元素，例如钛或铌（通常也称为钶）或两者，以稳定碳和氮元素。HSLA 钢被公认为具有微合金化水平的元素，例如铬、铜、铌、钒和钼。电机层压钢的基材包含微合金化水平的元素，例如硅和铝。高强度低合金（“HSLA”）钢，以及电机层压钢的基材。IF 钢被认为是低碳钢，添加了微合金化水平的元素，例如钛或铌（通常也称为钶）或两者，以稳定碳和氮元素。HSLA 钢被公认为具有微合金化水平的元素，例如铬、铜、铌、钒和钼。电机层压钢的基材包含微合金化水平的元素，例如硅和铝。高强度低合金（“HSLA”）钢，以及电机层压钢的基材。IF 钢被认为是低碳钢，添加了微合金化水平的元素，例如钛或铌（通常也称为钶）或两者，以稳定碳和氮元素。HSLA 钢被公认为具有微合金化水平的元素，例如铬、铜、铌、钒和钼。电机层压钢的基材包含微合金化水平的元素，例如硅和铝。HSLA 钢被公认为具有微合金化水平的元素，例如铬、铜、铌、钒和钼。电机层压钢的基材包含微合金化水平的元素，例如硅和铝。HSLA 钢被公认为具有微合金化水平的元素，例如铬、铜、铌、钒和钼。电机层压钢的基材包含微合金化水平的元素，例如硅和铝。
... A159: A-570-985 | B159: Xanthan Gum | C159: 黄原胶 | D159: 3913.90.20 | E159: 当所得混合物含有 15% 或更多干重的黄原胶时，已与其他产品混合的黄原胶包含在此范围内。可以与黄原胶混合的其他产品包括但不限于糖、矿物质和盐。黄原胶是一种由油菜黄单胞菌有氧发酵产生的多糖。重复五糖单体单元的化学结构由两个 P-1,4-D-葡萄糖单糖单元的主链组成，第二个具有由 PD-甘露糖-(1,4)-P-D-葡萄糖醛酸组成的三糖侧链-(1,2) - aD-甘露糖单糖单元。末端甘露糖可以被丙酮酸化并且内部甘露糖单元可以被乙酰化。
