Workbook

Sheet 目录
B2: 美 琦 国 际 货 运 代 理（深圳）有 限 公 司 地址：深圳市龙岗区坂田街道坂雪岗大道4088号奥博中心6楼A609-611
B4: 目的地 | C4: 目的港 | D4: 类型 | E4: 渠道名称 | F4: 渠道价格 | G4: 渠道特点分析 | H4: 优势目标区域 | I4: 渠道变动（2026/06/30生效）
D5: 货真价实 Match系列 | E5: Match12-卡派（CLX、MAX-GES服务) | F5: 查看报价 | G5: CLX、MAX-GES服务，时效达标率99%，12天提柜，超15自然日即赔 | H5: 4-9邮编 | I5: 上调0.1/KG或15/CBM
E6: Match15(ZIM带车架、EXX统配） | F6: 查看报价 | G6: EXX+ZIM带车架统配，平均15天签收 | H6: 4-9邮编 | I6: 上调0.5/KG或75/CBM
E7: Match20(长荣定提、合德快提统配） | F7: 查看报价 | G7: 精选快船中的王牌 平均20天签收 | H7: 4-9邮编 | I7: 上调0.8/KG或120/CBM
D8: OA系列 | E8: OA-直送专线（纯正OA） | F8: 查看报价 | G8: 优选COSCO OOCL EMC 最佳船期，永不截单 | H8: 4-9邮编 | I8: 上调0.8/KG或120/CBM
E9: OA-拆送专线（纯正OA） | F9: 查看报价 | G9: 盐田最快的船期，时效王者，稳定时效 | H9: 4-9邮编 | I9: 上调0.8/KG或120/CBM
E10: OA-奥克兰（纯正OA） | F10: 查看报价 | G10: 奥克兰最稳定的海外仓服务 94 95邮编海外仓王牌 | H10: 93-95邮编 | I10: 上调0.8/KG或120/CBM
D11: 海派专线 | E11: 海派渠道 | F11: 查看报价 | G11: 汇总各渠道海派价格 | H11: 0-9邮编 | I11: 对应渠道调整
D12: 海外仓暂存 | E12: 暂存渠道 | F12: 查看报价 | G12: 美西海外仓中转特价 | H12: 0-9邮编 | I12: 上调0.8/KG或120/CBM
C13: 洛杉矶 | D13: 专线渠道 | E13: MT-专线-美西 | F13: 查看报价 | G13: 超实惠，稳定时效 | H13: 9邮编 | I13: 上调0.8/KG或120/CBM
C14: 纽约 | D14: 专线渠道 | E14: MT-专线-纽约 | F14: 查看报价 | G14: 超实惠，稳定时效 | H14: 0-1邮编 | I14: 上调0.8/KG或120/CBM
C15: 萨凡纳 | D15: 专线渠道 | E15: MT-专线-萨凡纳 | F15: 查看报价 | G15: 超实惠，稳定时效 | H15: 3邮编 | I15: 上调0.8/KG或120/CBM
C16: 洛杉矶 | D16: 美东秒送 | E16: 美森美东秒送 | F16: 查看报价 | G16: 美森GES服务，17天到港，21天签收 | H16: 0-3邮编 | I16: 上调0.1/KG或15/CBM
C17: 纽约 | D17: 美东直航 | E17: 美东普快专线 | F17: 查看报价 | G17: 普船到纽约 经济保证 普船价格 | H17: 0-4邮编 | I17: 上调0.8/KG或120/CBM
D18: 美东极速 | E18: 美东极速快车 | F18: 查看报价 | G18: ZIM带车架海铁联运+末端高级卡车 美东26天 | H18: 0-4邮编 | I18: 上调2.3/KG或345/CBM
C19: 芝加哥 | D19: 芝加哥快线 | E19: 芝加哥海铁快车 | F19: 查看报价 | G19: COSCO稳速达，海铁快运到芝加哥 海铁快车 性价比高 时效赔付 | H19: 4-6邮编 | I19: 上调0.6/KG或90/CBM
D20: 芝加哥海铁专线 | E20: 芝加哥海铁联运 | F20: 查看报价 | G20: 芝加哥海铁联运 | H20: 4-6邮编 | I20: 上调0.8/KG或120/CBM
C21: 休斯敦 | D21: 休斯敦专线 | E21: 休斯敦专线 | F21: 查看报价 | G21: 休斯敦直航 质价比高 | H21: 7邮编 | I21: 上调0.8/KG或120/CBM
C22: 萨瓦纳 | D22: 美东南直航 | E22: 萨瓦纳专线 | F22: 查看报价 | G22: 美东南18仓普船价格性价比高 | H22: 28-3邮编 | I22: 上调0.8/KG或120/CBM
B23: 加拿大 | C23: 洛杉矶 | D23: 美转加 | E23: 美转加 | F23: 查看报价 | G23: 北美自由贸易区 时效稳定 急货首选 恢复时效赔付 | H23: 多伦多 卡尔加里 | I23: 不变
C24: 加拿大 | D24: 加拿大直航 | E24: 加拿大直航 | F24: 查看报价 | G24: 加拿大特惠 市场最低价 | H24: 多伦多 卡尔加里 | I24: 上调0.8/KG或120/CBM
B25: 墨西哥 | C25: 洛杉矶 | D25: 美转墨 | E25: 美 墨 快 线 | F25: 查看报价 | G25: 到仓时效稳定 备货有保证 30天左右稳定到仓时间(开船后） | H25: 墨西哥城 | I25: 不变
C26: 墨西哥城 | D26: 墨西哥直航 | E26: 墨西哥直航 | F26: 查看报价 | G26: 清关稳定 查验率不足1.5% | H26: 墨西哥城 | I26: /
B27: 美 琦 国 际 -- 北 美 第 一 站！
B28: 每周船期表 | E28: 美国发货须知 | G28: 合作流程 | I28: 亚马逊仓库地址
B29: 业务联系方式：易强 18320819718 微信同号
B30: 客服联系方式：黄彩琼 18025857142 微信同号
B31: 财务联系方式：汤红旗 13670010730
B32: 东莞1号仓库地址：广东省东莞市东莞市清溪镇银湖工业区科技路70号，导航：科技路70号美琦国际 联系人 陈希平 180 0288 5680
B33: 东莞2号仓库地址：广东省东莞市清溪镇九乡村大为路1号 联系人 邱先生 18318726670
B34: 中山仓库地址：广东省中山市大涌镇青岗村涌横路 35号一楼 电话：杨18928119960
B35: 义乌仓库地址：浙江省金华市金东区菜鸟网络浙江金义2-1期园区地面停车场 13栋1号2号3号4号货台收货 郑先生：195 3765 8019（周一至周日10：00-22:00）
B36: 广州仓库地址：广东省广州市白云区人和镇黄榜岭西二路46号2号仓(收货时间上午10:00-晚上10：00) 联系人：聂显俊13265457191 14737372131
B37: 汕头中转点：澄海区秀水路厂房第一层誉航达仓库 联系人：王：13414061251 胡：13923475593
B38: 厦门仓库地址：厦门市同安区集祥路66-4（2号仓西边） 美琦国际 18179585143 聂 （周一至周日10：00-22:00）
B39: 青岛仓库地址:青岛市城阳区天河路88号普洛斯空港东物流园B3库南区4-5号门 邱先生151 8054 3540
B40: 苏州仓地址：江苏省苏州市姑苏区金筑街588号，传化公路港，金义康物流（8:00-10:30）。叶经理，18862342877

Sheet 快捷查价
B2: 美 琦 国 际 货 运 代 理（深圳）有 限 公 司 地址：深圳市龙岗区坂田街道坂雪岗大道4088号奥博中心6楼A609-611
G4: 快捷查价
G5: 国内站点 | H5: 目的仓 | I5: 清关方式
G6: 深圳/中山/广州/汕头/厦门 | H6: SCK8 | I6: 含税
B7: 区域 | C7: 目的港 | D7: 线路类型 | E7: 渠道名称 | F7: 预配船司 | G7: 单价（KG/CBM） | H7: 截收货时间 | I7: ETD | J7: ETA | K7: 航期 | L7: 提柜时效 | M7: 备注
E8: Match12-卡派（CLX、MAX-GES服务) | F8: MATSON | G8: =IFERROR(_xlfn.IFS(AND(G6="深圳/中山/广州/汕头/厦门",I6="含税"),VLOOKUP("*"&TRIM(SUBSTITUTE(H6,",","|"))&"*",'Match系列 '!C7:I24,2,0),AND(G6="深圳/中山/广州/汕头/厦门",I6="不含税"),VLOOKUP("*"&TRIM(SUBSTITUTE(H6,",","|"))&"*",'Match系列 '!C7:I24,3,0),AND(G6="义乌/苏州",I6="含税"),VLOOKUP("*"&TRIM(SUBSTITUTE(H6,",","|"))&"*",'Match系列 '!C7:I24,4,0),AND(G6="义乌/苏州",I6="不含税"),VLOOKUP("*"&TRIM(SUBSTITUTE(H6,",","|"))&"*",'Match系列 '!C7:I24,5,0),AND(G6="汕头/厦门",I6="含税"),VLOOKUP("*"&TRIM(SUBSTITUTE(H6,",","|"))&"*",'Match系列 '!C7:I24,2,0),AND(G6="汕头/厦门",I6="不含税"),VLOOKUP("*"&TRIM(SUBSTITUTE(H6,",","|"))&"*",'Match系列 '!C7:I24,3,0),AND(G6="青岛",I6="含税"),VLOOKUP("*"&TRIM(SUBSTITUTE(H6,",","|"))&"*",'Match系列 '!C7:I24,6,0),AND(G6="青岛",I6="不含税"),VLOOKUP("*"&TRIM(SUBSTITUTE(H6,",","|"))&"*",'Match系列 '!C7:I24,7,0)),"-") -> 11.8 | H8: =VLOOKUP(E8,[1]Sheet1!$A:$I,4,0) -> 7月2日 22:00 | I8: =VLOOKUP(E8,[1]Sheet1!$A:$I,5,0) -> 46209 | J8: =VLOOKUP(E8,[1]Sheet1!$A:$I,6,0) -> 46222 | K8: =VLOOKUP(E8,[1]Sheet1!$A:$J,7,0) -> 13 | L8: =VLOOKUP(E8,[1]Sheet1!$A:$J,8,0) -> 46223 | M8: =IFERROR(_xlfn.IFS(AND(G6="深圳/中山/广州/汕头/厦门",I6="含税"),VLOOKUP("*"&TRIM(SUBSTITUTE(H6,",","|"))&"*",'[2]Match系列 '!C7:R27,8,0),AND(G6="深圳/中山/广州/汕头/厦门",I6="不含税"),VLOOKUP("*"&TRIM(SUBSTITUTE(H6,",","|"))&"*",'[2]Match系列 '!C7:R27,8,0),AND(G6="义乌/苏州",I6="含税"),VLOOKUP("*"&TRIM(SUBSTITUTE(H6,",","|"))&"*",'[2]Match系列 '!C7:R27,8,0),AND(G6="义乌/苏州",I6="不含税"),VLOOKUP("*"&TRIM(SUBSTITUTE(H6,",","|"))&"*",'[2]Match系列 '!C7:R27,8,0),AND(G6="青岛",I6="含税"),VLOOKUP("*"&TRIM(SUBSTITUTE(H6,",","|"))&"*",'[2]Match系列 '!C7:R27,8,0),AND(G6="青岛",I6="不含税"),VLOOKUP("*"&TRIM(SUBSTITUTE(H6,",","|"))&"*",'[2]Match系列 '!C7:R27,8,0)),"-") -> 15-17
E9: Match15(ZIM带车架、EXX统配） | F9: 以星 EXX | G9: =IFERROR(_xlfn.IFS(AND(G6="深圳/中山/广州/汕头/厦门",I6="含税"),VLOOKUP("*"&TRIM(SUBSTITUTE(H6,",","|"))&"*",'Match系列 '!C7:Z24,10,0),AND(G6="深圳/中山/广州/汕头/厦门",I6="不含税"),VLOOKUP("*"&TRIM(SUBSTITUTE(H6,",","|"))&"*",'Match系列 '!C7:Z24,11,0),AND(G6="义乌/苏州",I6="含税"),VLOOKUP("*"&TRIM(SUBSTITUTE(H6,",","|"))&"*",'Match系列 '!C7:Z24,12,0),AND(G6="义乌/苏州",I6="不含税"),VLOOKUP("*"&TRIM(SUBSTITUTE(H6,",","|"))&"*",'Match系列 '!C7:Z24,13,0),AND(G6="汕头/厦门",I6="含税"),VLOOKUP("*"&TRIM(SUBSTITUTE(H6,",","|"))&"*",'Match系列 '!C31:Q53,2,0),AND(G6="汕头/厦门",I6="不含税"),VLOOKUP("*"&TRIM(SUBSTITUTE(H6,",","|"))&"*",'Match系列 '!C31:Q53,3,0),AND(G6="青岛",I6="含税"),VLOOKUP("*"&TRIM(SUBSTITUTE(H6,",","|"))&"*",'Match系列 '!C7:Z24,14,0),AND(G6="青岛",I6="不含税"),VLOOKUP("*"&TRIM(SUBSTITUTE(H6,",","|"))&"*",'Match系列 '!C7:Z24,15,0)),"-") -> 9.7 | H9: =VLOOKUP(E9,[1]Sheet1!$A:$I,4,0) -> 7月4日 18:00 | I9: =VLOOKUP(E9,[1]Sheet1!$A:$I,5,0) -> 46212 | J9: =VLOOKUP(E9,[1]Sheet1!$A:$I,6,0) -> 46223 | K9: =VLOOKUP(E9,[1]Sheet1!$A:$J,7,0) -> 11 | L9: =VLOOKUP(E9,[1]Sheet1!$A:$J,8,0) -> 46224 | M9: =IFERROR(_xlfn.IFS(AND(G6="深圳/中山/广州/汕头/厦门",I6="含税"),VLOOKUP("*"&TRIM(SUBSTITUTE(H6,",","|"))&"*",'[2]Match系列 '!C7:R27,16,0),AND(G6="深圳/中山/广州/汕头/厦门",I6="不含税"),VLOOKUP("*"&TRIM(SUBSTITUTE(H6,",","|"))&"*",'[2]Match系列 '!C7:R27,16,0),AND(G6="义乌/苏州",I6="含税"),VLOOKUP("*"&TRIM(SUBSTITUTE(H6,",","|"))&"*",'[2]Match系列 '!C7:R27,16,0),AND(G6="义乌/苏州",I6="不含税"),VLOOKUP("*"&TRIM(SUBSTITUTE(H6,",","|"))&"*",'[2]Match系列 '!C7:R27,16,0),AND(G6="青岛",I6="含税"),VLOOKUP("*"&TRIM(SUBSTITUTE(H6,",","|"))&"*",'[2]Match系列 '!C7:R27,16,0),AND(G6="青岛",I6="不含税"),VLOOKUP("*"&TRIM(SUBSTITUTE(H6,",","|"))&"*",'[2]Match系列 '!C7:R27,16,0)),"-") -> 17-19
E10: Match20(长荣定提、合德快提统配） | F10: EMC 合德 | G10: =IFERROR(_xlfn.IFS(AND(G6="深圳/中山/广州/汕头/厦门",I6="含税"),VLOOKUP("*"&TRIM(SUBSTITUTE(H6,",","|"))&"*",'Match系列 '!C7:Z24,18,0),AND(G6="深圳/中山/广州/汕头/厦门",I6="不含税"),VLOOKUP("*"&TRIM(SUBSTITUTE(H6,",","|"))&"*",'Match系列 '!C7:Z24,19,0),AND(G6="义乌/苏州",I6="含税"),VLOOKUP("*"&TRIM(SUBSTITUTE(H6,",","|"))&"*",'Match系列 '!C7:Z24,20,0),AND(G6="义乌/苏州",I6="不含税"),VLOOKUP("*"&TRIM(SUBSTITUTE(H6,",","|"))&"*",'Match系列 '!C7:Z24,21,0),AND(G6="汕头/厦门",I6="含税"),VLOOKUP("*"&TRIM(SUBSTITUTE(H6,",","|"))&"*",'Match系列 '!C31:Q53,10,0),AND(G6="汕头/厦门",I6="不含税"),VLOOKUP("*"&TRIM(SUBSTITUTE(H6,",","|"))&"*",'Match系列 '!C31:Q53,11,0),AND(G6="青岛",I6="含税"),VLOOKUP("*"&TRIM(SUBSTITUTE(H6,",","|"))&"*",'Match系列 '!C7:Z24,22,0),AND(G6="青岛",I6="不含税"),VLOOKUP("*"&TRIM(SUBSTITUTE(H6,",","|"))&"*",'Match系列 '!C7:Z24,23,0)),"-") -> 8.4 | H10: =VLOOKUP(E10,[1]Sheet1!$A:$I,4,0) -> 7月4日 18:00 | I10: =VLOOKUP(E10,[1]Sheet1!$A:$I,5,0) -> 46209 | J10: =VLOOKUP(E10,[1]Sheet1!$A:$I,6,0) -> 46224 | K10: =VLOOKUP(E10,[1]Sheet1!$A:$J,7,0) -> 15 | L10: =VLOOKUP(E10,[1]Sheet1!$A:$J,8,0) -> 46226 | M10: =IFERROR(_xlfn.IFS(AND(G6="深圳/中山/广州/汕头/厦门",I6="含税"),VLOOKUP("*"&TRIM(SUBSTITUTE(H6,",","|"))&"*",'[2]Match系列 '!C7:AA27,24,0),AND(G6="深圳/中山/广州/汕头/厦门",#REF!="不含税"),VLOOKUP("*"&TRIM(SUBSTITUTE(H6,",","|"))&"*",'[2]Match系列 '!C7:AA27,24,0),AND(G6="义乌/苏州",I6="含税"),VLOOKUP("*"&TRIM(SUBSTITUTE(H6,",","|"))&"*",'[2]Match系列 '!C7:AA27,24,0),AND(G6="义乌/苏州",#REF!="不含税"),VLOOKUP("*"&TRIM(SUBSTITUTE(H6,",","|"))&"*",'[2]Match系列 '!C7:AA27,24,0),AND(G6="青岛",I6="含税"),VLOOKUP("*"&TRIM(SUBSTITUTE(H6,",","|"))&"*",'[2]Match系列 '!C7:AA27,24,0),AND(G6="青岛",I6="不含税"),VLOOKUP("*"&TRIM(SUBSTITUTE(H6,",","|"))&"*",'[2]Match系列 '!C7:AA27,24,0)),"-") -> 20-22
D11: 美东秒送 | E11: 美森美东秒送 | F11: MATSON | G11: =IFERROR(_xlfn.IFS(AND(G6="深圳/中山/广州/汕头/厦门",I6="含税"),VLOOKUP("*"&TRIM(SUBSTITUTE(H6,",","|"))&"*",美森美东秒送!C:G,2,0),AND(G6="深圳/中山/广州/汕头/厦门",I6="不含税"),VLOOKUP("*"&TRIM(SUBSTITUTE(H6,",","|"))&"*",美森美东秒送!C:G,3,0),AND(G6="青岛",I6="含税"),VLOOKUP("*"&TRIM(SUBSTITUTE(H6,",","|"))&"*",美森美东秒送!C:G,4,0),AND(G6="青岛",I6="不含税"),VLOOKUP("*"&TRIM(SUBSTITUTE(H6,",","|"))&"*",美森美东秒送!C:G,5,0)),"-") -> - | H11: =VLOOKUP(E11,[1]Sheet1!$A:$I,4,0) -> 7月3日 22:00 | I11: =VLOOKUP(E11,[1]Sheet1!$A:$I,5,0) -> 46212 | J11: =VLOOKUP(E11,[1]Sheet1!$A:$I,6,0) -> 46237 | K11: =VLOOKUP(E11,[1]Sheet1!$A:$J,7,0) -> 25 | L11: =VLOOKUP(E11,[1]Sheet1!$A:$J,8,0) -> 46239 | M11: =IFERROR(_xlfn.IFS(AND(G6="深圳/中山/广州/汕头/厦门",I6="含税"),VLOOKUP("*"&TRIM(SUBSTITUTE(H6,",","|"))&"*",[2]美森美东秒送!C:I,7,0),AND(G6="深圳/中山/广州/汕头/厦门",I6="不含税"),VLOOKUP("*"&TRIM(SUBSTITUTE(H6,",","|"))&"*",[2]美森美东秒送!C:I,7,0),AND(G6="义乌/苏州",I6="含税"),VLOOKUP("*"&TRIM(SUBSTITUTE(H6,",","|"))&"*",[2]美森美东秒送!C:I,7,0),AND(G6="义乌/苏州",I6="不含税"),VLOOKUP("*"&TRIM(SUBSTITUTE(H6,",","|"))&"*",[2]美森美东秒送!C:I,7,0),AND(G6="青岛",I6="含税"),VLOOKUP("*"&TRIM(SUBSTITUTE(H6,",","|"))&"*",[2]美森美东秒送!C:I,7,0),AND(G6="青岛",I6="不含税"),VLOOKUP("*"&TRIM(SUBSTITUTE(H6,",","|"))&"*",[2]美森美东秒送!C:I,7,0)),"-") -> -
D12: OA系列 | E12: OA-拆送专线 | F12: OA | G12: =IFERROR(_xlfn.IFS(AND(G6="深圳/中山/广州/汕头/厦门",I6="含税"),VLOOKUP("*"&TRIM(SUBSTITUTE(H6,",","|"))&"*",'OA-拆送 '!C7:G29,2,0),AND(G6="深圳/中山/广州/汕头/厦门",I6="不含税"),VLOOKUP("*"&TRIM(SUBSTITUTE(H6,",","|"))&"*",'OA-拆送 '!C7:G29,3,0),AND(G6="义乌/苏州",I6="含税"),VLOOKUP("*"&TRIM(SUBSTITUTE(H6,",","|"))&"*",'OA-拆送 '!C7:G29,2,0),AND(G6="义乌/苏州",I6="不含税"),VLOOKUP("*"&TRIM(SUBSTITUTE(H6,",","|"))&"*",'OA-拆送 '!C7:G29,3,0),AND(G6="汕头/厦门",I6="含税"),VLOOKUP("*"&TRIM(SUBSTITUTE(H6,",","|"))&"*",'OA-拆送 '!C7:G29,2,0),AND(G6="汕头/厦门",I6="不含税"),VLOOKUP("*"&TRIM(SUBSTITUTE(H6,",","|"))&"*",'OA-拆送 '!C7:G29,3,0),AND(G6="青岛",I6="含税"),VLOOKUP("*"&TRIM(SUBSTITUTE(H6,",","|"))&"*",'OA-拆送 '!C7:G29,4,0),AND(G6="青岛",I6="不含税"),VLOOKUP("*"&TRIM(SUBSTITUTE(H6,",","|"))&"*",'OA-拆送 '!C7:G29,5,0)),"-") -> 8.1 | H12: =VLOOKUP(E12,[1]Sheet1!$A:$I,4,0) -> 7月4日 18:00 | I12: =VLOOKUP(E12,[1]Sheet1!$A:$I,5,0) -> 46212 | J12: =VLOOKUP(E12,[1]Sheet1!$A:$I,6,0) -> 46228 | K12: =VLOOKUP(E12,[1]Sheet1!$A:$J,7,0) -> 16 | L12: =VLOOKUP(E12,[1]Sheet1!$A:$J,8,0) -> 46232 | M12: =IFERROR(_xlfn.IFS(AND(G6="深圳/中山/广州/汕头/厦门",I6="含税"),VLOOKUP("*"&TRIM(SUBSTITUTE(H6,",","|"))&"*",'[2]OA-拆送 '!C7:I26,7,0),AND(G6="深圳/中山/广州/汕头/厦门",I6="不含税"),VLOOKUP("*"&TRIM(SUBSTITUTE(H6,",","|"))&"*",'[2]OA-拆送 '!C7:I26,7,0),AND(G6="义乌/苏州",I6="含税"),VLOOKUP("*"&TRIM(SUBSTITUTE(H6,",","|"))&"*",'[2]OA-拆送 '!C7:I26,7,0),AND(G6="义乌/苏州",I6="不含税"),VLOOKUP("*"&TRIM(SUBSTITUTE(H6,",","|"))&"*",'[2]OA-拆送 '!C7:I26,7,0),AND(G6="青岛",I6="含税"),VLOOKUP("*"&TRIM(SUBSTITUTE(H6,",","|"))&"*",'[2]OA-拆送 '!C7:I26,7,0),AND(G6="青岛",I6="不含税"),VLOOKUP("*"&TRIM(SUBSTITUTE(H6,",","|"))&"*",'[2]OA-拆送 '!C7:I26,7,0)),"-") -> 26-32
E13: OA-直送专线 | F13: OA | G13: =IFERROR(_xlfn.IFS(AND(G6="深圳/中山/广州/汕头/厦门",I6="含税"),VLOOKUP("*"&TRIM(SUBSTITUTE(H6,",","|"))&"*",'OA-直送'!C7:G16,2,0),AND(G6="深圳/中山/广州/汕头/厦门",I6="不含税"),VLOOKUP("*"&TRIM(SUBSTITUTE(H6,",","|"))&"*",'OA-直送'!C7:G16,3,0),AND(G6="义乌/苏州",I6="含税"),VLOOKUP("*"&TRIM(SUBSTITUTE(H6,",","|"))&"*",'OA-直送'!C7:G16,2,0),AND(G6="义乌/苏州",I6="不含税"),VLOOKUP("*"&TRIM(SUBSTITUTE(H6,",","|"))&"*",'OA-直送'!C7:G16,3,0),AND(G6="汕头/厦门",I6="含税"),VLOOKUP("*"&TRIM(SUBSTITUTE(H6,",","|"))&"*",'OA-直送'!C7:G16,2,0),AND(G6="汕头/厦门",I6="不含税"),VLOOKUP("*"&TRIM(SUBSTITUTE(H6,",","|"))&"*",'OA-直送'!C7:G16,3,0),AND(G6="青岛",I6="含税"),VLOOKUP("*"&TRIM(SUBSTITUTE(H6,",","|"))&"*",'OA-直送'!C7:G16,4,0),AND(G6="青岛",I6="不含税"),VLOOKUP("*"&TRIM(SUBSTITUTE(H6,",","|"))&"*",'OA-直送'!C7:G16,5,0)),"-") -> 7.6 | H13: =VLOOKUP(E13,[1]Sheet1!$A:$I,4,0) -> 7月4日 18:00 | I13: =VLOOKUP(E13,[1]Sheet1!$A:$I,5,0) -> 46209 | J13: =VLOOKUP(E13,[1]Sheet1!$A:$I,6,0) -> 46224 | K13: =VLOOKUP(E13,[1]Sheet1!$A:$J,7,0) -> 15 | L13: =VLOOKUP(E13,[1]Sheet1!$A:$J,8,0) -> 46228 | M13: =IFERROR(_xlfn.IFS(AND(G6="深圳/中山/广州/汕头/厦门",I6="含税"),VLOOKUP("*"&TRIM(SUBSTITUTE(H6,",","|"))&"*",'[2]OA-直送'!C7:I16,7,0),AND(G6="深圳/中山/广州/汕头/厦门",I6="不含税"),VLOOKUP("*"&TRIM(SUBSTITUTE(H6,",","|"))&"*",'[2]OA-直送'!C7:I16,7,0),AND(G6="义乌/苏州",I6="含税"),VLOOKUP("*"&TRIM(SUBSTITUTE(H6,",","|"))&"*",'[2]OA-直送'!C7:I16,7,0),AND(G6="义乌/苏州",I6="不含税"),VLOOKUP("*"&TRIM(SUBSTITUTE(H6,",","|"))&"*",'[2]OA-直送'!C7:I16,7,0),AND(G6="青岛",I6="含税"),VLOOKUP("*"&TRIM(SUBSTITUTE(H6,",","|"))&"*",'[2]OA-直送'!C7:I16,7,0),AND(G6="青岛",I6="不含税"),VLOOKUP("*"&TRIM(SUBSTITUTE(H6,",","|"))&"*",'[2]OA-直送'!C7:I16,7,0)),"-") -> 28-30
E14: OA-美东直送 | F14: OA | G14: =IFERROR(_xlfn.IFS(AND(G6="深圳/中山/广州/汕头/厦门",I6="含税"),VLOOKUP("*"&TRIM(SUBSTITUTE(H6,",","|"))&"*",'OA-直送'!C19:G20,2,0),AND(G6="深圳/中山/广州/汕头/厦门",I6="不含税"),VLOOKUP("*"&TRIM(SUBSTITUTE(H6,",","|"))&"*",'OA-直送'!C19:G20,3,0),AND(G6="义乌/苏州",I6="含税"),VLOOKUP("*"&TRIM(SUBSTITUTE(H6,",","|"))&"*",'OA-直送'!C19:G20,2,0),AND(G6="义乌/苏州",I6="不含税"),VLOOKUP("*"&TRIM(SUBSTITUTE(H6,",","|"))&"*",'OA-直送'!C19:G20,3,0),AND(G6="汕头/厦门",I6="含税"),VLOOKUP("*"&TRIM(SUBSTITUTE(H6,",","|"))&"*",'OA-直送'!C19:G20,2,0),AND(G6="汕头/厦门",I6="不含税"),VLOOKUP("*"&TRIM(SUBSTITUTE(H6,",","|"))&"*",'OA-直送'!C19:G20,3,0),AND(G6="青岛",I6="含税"),VLOOKUP("*"&TRIM(SUBSTITUTE(H6,",","|"))&"*",'OA-直送'!C19:G20,4,0),AND(G6="青岛",I6="不含税"),VLOOKUP("*"&TRIM(SUBSTITUTE(H6,",","|"))&"*",'OA-直送'!C19:G20,5,0)),"-") -> - | H14: =VLOOKUP(E14,[1]Sheet1!$A:$I,4,0) -> 7月4日 18:00 | I14: =VLOOKUP(E14,[1]Sheet1!$A:$I,5,0) -> 46213 | J14: =VLOOKUP(E14,[1]Sheet1!$A:$I,6,0) -> 46250 | K14: =VLOOKUP(E14,[1]Sheet1!$A:$J,7,0) -> 37 | L14: =VLOOKUP(E14,[1]Sheet1!$A:$J,8,0) -> 46254 | M14: =IFERROR(_xlfn.IFS(AND(G6="深圳/中山/广州/汕头/厦门",I6="含税"),VLOOKUP("*"&TRIM(SUBSTITUTE(H6,",","|"))&"*",'[2]OA-直送'!C19:I20,7,0),AND(G6="深圳/中山/广州/汕头/厦门",I6="不含税"),VLOOKUP("*"&TRIM(SUBSTITUTE(H6,",","|"))&"*",'[2]OA-直送'!C19:I20,7,0),AND(G6="义乌/苏州",I6="含税"),VLOOKUP("*"&TRIM(SUBSTITUTE(H6,",","|"))&"*",'[2]OA-直送'!C19:I20,7,0),AND(G6="义乌/苏州",I6="不含税"),VLOOKUP("*"&TRIM(SUBSTITUTE(H6,",","|"))&"*",'[2]OA-直送'!C19:I20,7,0),AND(G6="青岛",I6="含税"),VLOOKUP("*"&TRIM(SUBSTITUTE(H6,",","|"))&"*",'[2]OA-直送'!C19:I20,7,0),AND(G6="青岛",I6="不含税"),VLOOKUP("*"&TRIM(SUBSTITUTE(H6,",","|"))&"*",'[2]OA-直送'!C19:I20,7,0)),"-") -> -
C15: 洛杉矶 | D15: 专线渠道 | E15: MT-专线-美西 | F15: 2M、THE | G15: =IFERROR(_xlfn.IFS(AND(G6="深圳/中山/广州/汕头/厦门",I6="含税"),VLOOKUP("*"&TRIM(SUBSTITUTE(H6,",","|"))&"*",'MT-专线'!C7:G10,2,0),AND(G6="深圳/中山/广州/汕头/厦门",I6="不含税"),VLOOKUP("*"&TRIM(SUBSTITUTE(H6,",","|"))&"*",'MT-专线'!C7:G10,3,0),AND(G6="义乌/苏州",I6="含税"),VLOOKUP("*"&TRIM(SUBSTITUTE(H6,",","|"))&"*",'MT-专线'!C7:G10,2,0),AND(G6="义乌/苏州",I6="不含税"),VLOOKUP("*"&TRIM(SUBSTITUTE(H6,",","|"))&"*",'MT-专线'!C7:G10,3,0),AND(G6="汕头/厦门",I6="含税"),VLOOKUP("*"&TRIM(SUBSTITUTE(H6,",","|"))&"*",'MT-专线'!C7:G10,2,0),AND(G6="汕头/厦门",I6="不含税"),VLOOKUP("*"&TRIM(SUBSTITUTE(H6,",","|"))&"*",'MT-专线'!C7:G10,3,0),AND(G6="青岛",I6="含税"),VLOOKUP("*"&TRIM(SUBSTITUTE(H6,",","|"))&"*",'MT-专线'!C7:G10,4,0),AND(G6="青岛",I6="不含税"),VLOOKUP("*"&TRIM(SUBSTITUTE(H6,",","|"))&"*",'MT-专线'!C7:G10,5,0)),"-") -> 7.4 | H15: =VLOOKUP(E15,[1]Sheet1!$A:$I,4,0) -> 7月4日 18:00 | I15: =VLOOKUP(E15,[1]Sheet1!$A:$I,5,0) -> 46222 | J15: =VLOOKUP(E15,[1]Sheet1!$A:$I,6,0) -> 46237 | K15: =VLOOKUP(E15,[1]Sheet1!$A:$J,7,0) -> 15 | L15: =VLOOKUP(E15,[1]Sheet1!$A:$J,8,0) -> 46241 | M15: =IFERROR(_xlfn.IFS(AND(G6="深圳/中山/广州/汕头/厦门",I6="含税"),VLOOKUP("*"&TRIM(SUBSTITUTE(H6,",","|"))&"*",'MT-专线'!C7:K10,7,0),AND(G6="深圳/中山/广州/汕头/厦门",I6="不含税"),VLOOKUP("*"&TRIM(SUBSTITUTE(H6,",","|"))&"*",'MT-专线'!C7:K10,7,0),AND(G6="义乌/苏州",I6="含税"),VLOOKUP("*"&TRIM(SUBSTITUTE(H6,",","|"))&"*",'MT-专线'!C7:K10,7,0),AND(G6="义乌/苏州",I6="不含税"),VLOOKUP("*"&TRIM(SUBSTITUTE(H6,",","|"))&"*",'MT-专线'!C7:K10,7,0),AND(G6="青岛",I6="含税"),VLOOKUP("*"&TRIM(SUBSTITUTE(H6,",","|"))&"*",'MT-专线'!C7:K10,7,0),AND(G6="青岛",I6="不含税"),VLOOKUP("*"&TRIM(SUBSTITUTE(H6,",","|"))&"*",'MT-专线'!C7:K10,7,0)),"-") -> 32-37
C16: 纽约 | D16: 专线渠道 | E16: MT-专线-纽约 | F16: 2M、THE | G16: =IFERROR(_xlfn.IFS(AND(G6="深圳/中山/广州/汕头/厦门",I6="含税"),VLOOKUP("*"&TRIM(SUBSTITUTE(H6,",","|"))&"*",'MT-专线'!C11:K15,2,0),AND(G6="深圳/中山/广州/汕头/厦门",I6="不含税"),VLOOKUP("*"&TRIM(SUBSTITUTE(H6,",","|"))&"*",'MT-专线'!C11:K15,3,0),AND(G6="义乌/苏州",I6="含税"),VLOOKUP("*"&TRIM(SUBSTITUTE(H6,",","|"))&"*",'MT-专线'!C11:K15,2,0),AND(G6="义乌/苏州",I6="不含税"),VLOOKUP("*"&TRIM(SUBSTITUTE(H6,",","|"))&"*",'MT-专线'!C11:K15,3,0),AND(G6="汕头/厦门",I6="含税"),VLOOKUP("*"&TRIM(SUBSTITUTE(H6,",","|"))&"*",'MT-专线'!C11:K15,2,0),AND(G6="汕头/厦门",I6="不含税"),VLOOKUP("*"&TRIM(SUBSTITUTE(H6,",","|"))&"*",'MT-专线'!C11:K15,3,0),AND(G6="青岛",I6="含税"),VLOOKUP("*"&TRIM(SUBSTITUTE(H6,",","|"))&"*",'MT-专线'!C11:K15,4,0),AND(G6="青岛",I6="不含税"),VLOOKUP("*"&TRIM(SUBSTITUTE(H6,",","|"))&"*",'MT-专线'!C11:K15,5,0)),"-") -> - | H16: =VLOOKUP(E16,[1]Sheet1!$A:$I,4,0) -> 7月4日 18:00 | I16: =VLOOKUP(E16,[1]Sheet1!$A:$I,5,0) -> 46219 | J16: =VLOOKUP(E16,[1]Sheet1!$A:$I,6,0) -> 46258 | K16: =VLOOKUP(E16,[1]Sheet1!$A:$J,7,0) -> 39 | L16: =VLOOKUP(E16,[1]Sheet1!$A:$J,8,0) -> 46262 | M16: =IFERROR(_xlfn.IFS(AND(G6="深圳/中山/广州/汕头/厦门",I6="含税"),VLOOKUP("*"&TRIM(SUBSTITUTE(H6,",","|"))&"*",'MT-专线'!C11:K15,7,0),AND(G6="深圳/中山/广州/汕头/厦门",I6="不含税"),VLOOKUP("*"&TRIM(SUBSTITUTE(H6,",","|"))&"*",'MT-专线'!C11:K15,7,0),AND(G6="义乌/苏州",I6="含税"),VLOOKUP("*"&TRIM(SUBSTITUTE(H6,",","|"))&"*",'MT-专线'!C11:K15,7,0),AND(G6="义乌/苏州",I6="不含税"),VLOOKUP("*"&TRIM(SUBSTITUTE(H6,",","|"))&"*",'MT-专线'!C11:K15,7,0),AND(G6="青岛",I6="含税"),VLOOKUP("*"&TRIM(SUBSTITUTE(H6,",","|"))&"*",'MT-专线'!C11:K15,7,0),AND(G6="青岛",I6="不含税"),VLOOKUP("*"&TRIM(SUBSTITUTE(H6,",","|"))&"*",'MT-专线'!C11:K15,7,0)),"-") -> -
C17: 萨凡纳 | D17: 专线渠道 | E17: MT-专线-萨凡纳 | F17: 2M、THE | G17: =IFERROR(_xlfn.IFS(AND(G6="深圳/中山/广州/汕头/厦门",I6="含税"),VLOOKUP("*"&TRIM(SUBSTITUTE(H6,",","|"))&"*",'MT-专线'!C16:K18,2,0),AND(G6="深圳/中山/广州/汕头/厦门",I6="不含税"),VLOOKUP("*"&TRIM(SUBSTITUTE(H6,",","|"))&"*",'MT-专线'!C16:K18,3,0),AND(G6="义乌/苏州",I6="含税"),VLOOKUP("*"&TRIM(SUBSTITUTE(H6,",","|"))&"*",'MT-专线'!C16:K18,2,0),AND(G6="义乌/苏州",I6="不含税"),VLOOKUP("*"&TRIM(SUBSTITUTE(H6,",","|"))&"*",'MT-专线'!C16:K18,3,0),AND(G6="汕头/厦门",I6="含税"),VLOOKUP("*"&TRIM(SUBSTITUTE(H6,",","|"))&"*",'MT-专线'!C16:K18,2,0),AND(G6="汕头/厦门",I6="不含税"),VLOOKUP("*"&TRIM(SUBSTITUTE(H6,",","|"))&"*",'MT-专线'!C16:K18,3,0),AND(G6="青岛",I6="含税"),VLOOKUP("*"&TRIM(SUBSTITUTE(H6,",","|"))&"*",'MT-专线'!C16:K18,4,0),AND(G6="青岛",I6="不含税"),VLOOKUP("*"&TRIM(SUBSTITUTE(H6,",","|"))&"*",'MT-专线'!C16:K18,5,0)),"-") -> - | H17: =VLOOKUP(E17,[1]Sheet1!$A:$I,4,0) -> 7月4日 18:00 | I17: =VLOOKUP(E17,[1]Sheet1!$A:$I,5,0) -> 46220 | J17: =VLOOKUP(E17,[1]Sheet1!$A:$I,6,0) -> 46251 | K17: =VLOOKUP(E17,[1]Sheet1!$A:$J,7,0) -> 31 | L17: =VLOOKUP(E17,[1]Sheet1!$A:$J,8,0) -> 46255 | M17: =IFERROR(_xlfn.IFS(AND(G6="深圳/中山/广州/汕头/厦门",I6="含税"),VLOOKUP("*"&TRIM(SUBSTITUTE(H6,",","|"))&"*",'MT-专线'!C16:K18,7,0),AND(G6="深圳/中山/广州/汕头/厦门",I6="不含税"),VLOOKUP("*"&TRIM(SUBSTITUTE(H6,",","|"))&"*",'MT-专线'!C16:K18,7,0),AND(G6="义乌/苏州",I6="含税"),VLOOKUP("*"&TRIM(SUBSTITUTE(H6,",","|"))&"*",'MT-专线'!C16:K18,7,0),AND(G6="义乌/苏州",I6="不含税"),VLOOKUP("*"&TRIM(SUBSTITUTE(H6,",","|"))&"*",'MT-专线'!C16:K18,7,0),AND(G6="青岛",I6="含税"),VLOOKUP("*"&TRIM(SUBSTITUTE(H6,",","|"))&"*",'MT-专线'!C16:K18,7,0),AND(G6="青岛",I6="不含税"),VLOOKUP("*"&TRIM(SUBSTITUTE(H6,",","|"))&"*",'MT-专线'!C16:K18,7,0)),"-") -> -
C18: 纽约 | D18: 美东极速 | E18: 美东极速快车 | F18: ZIM带车架 | G18: =IFERROR(_xlfn.IFS(AND(G6="深圳/中山/广州/汕头/厦门",I6="含税"),VLOOKUP("*"&TRIM(SUBSTITUTE(H6,",","|"))&"*",纽约!C:N,2,0),AND(G6="深圳/中山/广州/汕头/厦门",I6="不含税"),VLOOKUP("*"&TRIM(SUBSTITUTE(H6,",","|"))&"*",纽约!C:N,3,0),AND(G6="义乌/苏州",I6="含税"),VLOOKUP("*"&TRIM(SUBSTITUTE(H6,",","|"))&"*",纽约!C:N,2,0),AND(G6="义乌/苏州",I6="不含税"),VLOOKUP("*"&TRIM(SUBSTITUTE(H6,",","|"))&"*",纽约!C:N,3,0),AND(G6="青岛",I6="含税"),VLOOKUP("*"&TRIM(SUBSTITUTE(H6,",","|"))&"*",纽约!C:N,4,0),AND(G6="青岛",I6="不含税"),VLOOKUP("*"&TRIM(SUBSTITUTE(H6,",","|"))&"*",纽约!C:N,5,0)),"-") -> - | H18: =VLOOKUP(E18,[1]Sheet1!$A:$I,4,0) -> 7月4日 22:00 | I18: =VLOOKUP(E18,[1]Sheet1!$A:$I,5,0) -> 46211 | J18: =VLOOKUP(E18,[1]Sheet1!$A:$I,6,0) -> 46228 | K18: =VLOOKUP(E18,[1]Sheet1!$A:$J,7,0) -> 17 | L18: =VLOOKUP(E18,[1]Sheet1!$A:$J,8,0) -> 46229 | M18: =IFERROR(_xlfn.IFS(AND(G6="深圳/中山/广州/汕头/厦门",I6="含税"),VLOOKUP("*"&TRIM(SUBSTITUTE(H6,",","|"))&"*",[2]纽约!C:I,7,0),AND(G6="深圳/中山/广州/汕头/厦门",I6="不含税"),VLOOKUP("*"&TRIM(SUBSTITUTE(H6,",","|"))&"*",[2]纽约!C:I,7,0),AND(G6="义乌/苏州",I6="含税"),VLOOKUP("*"&TRIM(SUBSTITUTE(H6,",","|"))&"*",[2]纽约!C:I,7,0),AND(G6="义乌/苏州",I6="不含税"),VLOOKUP("*"&TRIM(SUBSTITUTE(H6,",","|"))&"*",[2]纽约!C:I,7,0),AND(G6="青岛",I6="含税"),VLOOKUP("*"&TRIM(SUBSTITUTE(H6,",","|"))&"*",[2]纽约!C:I,7,0),AND(G6="青岛",I6="不含税"),VLOOKUP("*"&TRIM(SUBSTITUTE(H6,",","|"))&"*",[2]纽约!C:I,7,0)),"-") -> -
D19: 美东普快 | E19: 美东普快专线 | F19: COSCO | G19: =IFERROR(_xlfn.IFS(AND(G6="深圳/中山/广州/汕头/厦门",I6="含税"),VLOOKUP("*"&TRIM(SUBSTITUTE(H6,",","|"))&"*",纽约!C:N,9,0),AND(G6="深圳/中山/广州/汕头/厦门",I6="不含税"),VLOOKUP("*"&TRIM(SUBSTITUTE(H6,",","|"))&"*",纽约!C:N,10,0),AND(G6="义乌/苏州",I6="含税"),VLOOKUP("*"&TRIM(SUBSTITUTE(H6,",","|"))&"*",纽约!C:N,9,0),AND(G6="义乌/苏州",I6="不含税"),VLOOKUP("*"&TRIM(SUBSTITUTE(H6,",","|"))&"*",纽约!C:N,10,0),AND(G6="青岛",I6="含税"),VLOOKUP("*"&TRIM(SUBSTITUTE(H6,",","|"))&"*",纽约!C:N,11,0),AND(G6="青岛",I6="不含税"),VLOOKUP("*"&TRIM(SUBSTITUTE(H6,",","|"))&"*",纽约!C:N,12,0)),"-") -> - | H19: =VLOOKUP(E19,[1]Sheet1!$A:$I,4,0) -> 7月4日 18:00 | I19: =VLOOKUP(E19,[1]Sheet1!$A:$I,5,0) -> 46215 | J19: =VLOOKUP(E19,[1]Sheet1!$A:$I,6,0) -> 46245 | K19: =VLOOKUP(E19,[1]Sheet1!$A:$J,7,0) -> 30 | L19: =VLOOKUP(E19,[1]Sheet1!$A:$J,8,0) -> 46249 | M19: =IFERROR(_xlfn.IFS(AND(G6="深圳/中山/广州/汕头/厦门",I6="含税"),VLOOKUP("*"&TRIM(SUBSTITUTE(H6,",","|"))&"*",[2]纽约!C:P,14,0),AND(G6="深圳/中山/广州/汕头/厦门",I6="不含税"),VLOOKUP("*"&TRIM(SUBSTITUTE(H6,",","|"))&"*",[2]纽约!C:P,14,0),AND(G6="义乌/苏州",I6="含税"),VLOOKUP("*"&TRIM(SUBSTITUTE(H6,",","|"))&"*",[2]纽约!C:P,14,0),AND(G6="义乌/苏州",I6="不含税"),VLOOKUP("*"&TRIM(SUBSTITUTE(H6,",","|"))&"*",[2]纽约!C:P,14,0),AND(G6="青岛",I6="含税"),VLOOKUP("*"&TRIM(SUBSTITUTE(H6,",","|"))&"*",[2]纽约!C:P,14,0),AND(G6="青岛",I6="不含税"),VLOOKUP("*"&TRIM(SUBSTITUTE(H6,",","|"))&"*",[2]纽约!C:P,14,0)),"-") -> -
C20: 芝加哥 | D20: 芝加哥快线 | E20: 芝加哥海铁快车 | F20: COSCO稳速达 | G20: =IFERROR(_xlfn.IFS(AND(G6="深圳/中山/广州/汕头/厦门",I6="含税"),VLOOKUP("*"&TRIM(SUBSTITUTE(H6,",","|"))&"*",芝加哥!B:M,2,0),AND(G6="深圳/中山/广州/汕头/厦门",I6="不含税"),VLOOKUP("*"&TRIM(SUBSTITUTE(H6,",","|"))&"*",芝加哥!B:M,3,0),AND(G6="义乌/苏州",I6="含税"),VLOOKUP("*"&TRIM(SUBSTITUTE(H6,",","|"))&"*",芝加哥!B:M,2,0),AND(G6="义乌/苏州",I6="不含税"),VLOOKUP("*"&TRIM(SUBSTITUTE(H6,",","|"))&"*",芝加哥!B:M,3,0),AND(G6="青岛",I6="含税"),VLOOKUP("*"&TRIM(SUBSTITUTE(H6,",","|"))&"*",芝加哥!B:M,4,0),AND(G6="青岛",I6="不含税"),VLOOKUP("*"&TRIM(SUBSTITUTE(H6,",","|"))&"*",芝加哥!B:M,5,0)),"-") -> - | H20: =VLOOKUP(E20,[1]Sheet1!$A:$I,4,0) -> 7月4日 18:00 | I20: =VLOOKUP(E20,[1]Sheet1!$A:$I,5,0) -> 46212 | J20: =VLOOKUP(E20,[1]Sheet1!$A:$I,6,0) -> 46236 | K20: =VLOOKUP(E20,[1]Sheet1!$A:$J,7,0) -> 24 | L20: =VLOOKUP(E20,[1]Sheet1!$A:$J,8,0) -> 46238 | M20: =IFERROR(_xlfn.IFS(AND(G6="深圳/中山/广州/汕头/厦门",I6="含税"),VLOOKUP("*"&TRIM(SUBSTITUTE(H6,",","|"))&"*",[2]芝加哥!B:H,7,0),AND(G6="深圳/中山/广州/汕头/厦门",I6="不含税"),VLOOKUP("*"&TRIM(SUBSTITUTE(H6,",","|"))&"*",[2]芝加哥!B:H,7,0),AND(G6="义乌/苏州",I6="含税"),VLOOKUP("*"&TRIM(SUBSTITUTE(H6,",","|"))&"*",[2]芝加哥!B:H,7,0),AND(G6="义乌/苏州",I6="不含税"),VLOOKUP("*"&TRIM(SUBSTITUTE(H6,",","|"))&"*",[2]芝加哥!B:H,7,0),AND(G6="青岛",I6="含税"),VLOOKUP("*"&TRIM(SUBSTITUTE(H6,",","|"))&"*",[2]芝加哥!B:H,7,0),AND(G6="青岛",I6="不含税"),VLOOKUP("*"&TRIM(SUBSTITUTE(H6,",","|"))&"*",[2]芝加哥!B:H,7,0)),"-") -> -
C21: 芝加哥 | D21: 芝加哥海普船 | E21: 芝加哥海铁联运 | F21: COSCO | G21: =IFERROR(_xlfn.IFS(AND(G6="深圳/中山/广州/汕头/厦门",I6="含税"),VLOOKUP("*"&TRIM(SUBSTITUTE(H6,",","|"))&"*",芝加哥!B:M,9,0),AND(G6="深圳/中山/广州/汕头/厦门",I6="不含税"),VLOOKUP("*"&TRIM(SUBSTITUTE(H6,",","|"))&"*",芝加哥!B:M,10,0),AND(G6="义乌/苏州",I6="含税"),VLOOKUP("*"&TRIM(SUBSTITUTE(H6,",","|"))&"*",芝加哥!B:M,9,0),AND(G6="义乌/苏州",I6="不含税"),VLOOKUP("*"&TRIM(SUBSTITUTE(H6,",","|"))&"*",芝加哥!B:M,10,0),AND(G6="青岛",I6="含税"),VLOOKUP("*"&TRIM(SUBSTITUTE(H6,",","|"))&"*",芝加哥!B:M,11,0),AND(G6="青岛",I6="不含税"),VLOOKUP("*"&TRIM(SUBSTITUTE(H6,",","|"))&"*",芝加哥!B:M,12,0)),"-") -> - | H21: =VLOOKUP(E21,[1]Sheet1!$A:$I,4,0) -> 7月4日 18:00 | I21: =VLOOKUP(E21,[1]Sheet1!$A:$I,5,0) -> 46212 | J21: =VLOOKUP(E21,[1]Sheet1!$A:$I,6,0) -> 46243 | K21: =VLOOKUP(E21,[1]Sheet1!$A:$J,7,0) -> 31 | L21: =VLOOKUP(E21,[1]Sheet1!$A:$J,8,0) -> 46245 | M21: =IFERROR(_xlfn.IFS(AND(G6="深圳/中山/广州/汕头/厦门",I6="含税"),VLOOKUP("*"&TRIM(SUBSTITUTE(H6,",","|"))&"*",[2]芝加哥!B:O,14,0),AND(G6="深圳/中山/广州/汕头/厦门",I6="不含税"),VLOOKUP("*"&TRIM(SUBSTITUTE(H6,",","|"))&"*",[2]芝加哥!B:O,14,0),AND(G6="义乌/苏州",I6="含税"),VLOOKUP("*"&TRIM(SUBSTITUTE(H6,",","|"))&"*",[2]芝加哥!B:O,14,0),AND(G6="义乌/苏州",I6="不含税"),VLOOKUP("*"&TRIM(SUBSTITUTE(H6,",","|"))&"*",[2]芝加哥!B:O,14,0),AND(G6="青岛",I6="含税"),VLOOKUP("*"&TRIM(SUBSTITUTE(H6,",","|"))&"*",[2]芝加哥!B:O,14,0),AND(G6="青岛",I6="不含税"),VLOOKUP("*"&TRIM(SUBSTITUTE(H6,",","|"))&"*",[2]芝加哥!B:O,14,0)),"-") -> -
C22: 休斯敦 | D22: 休斯顿专线 | E22: 休斯顿专线 | F22: COSCO/EMC/OOCL | G22: =IFERROR(_xlfn.IFS(AND(G6="深圳/中山/广州/汕头/厦门",I6="含税"),VLOOKUP("*"&TRIM(SUBSTITUTE(H6,",","|"))&"*",休斯敦!B:F,2,0),AND(G6="深圳/中山/广州/汕头/厦门",I6="不含税"),VLOOKUP("*"&TRIM(SUBSTITUTE(H6,",","|"))&"*",休斯敦!B:F,3,0),AND(G6="义乌/苏州",I6="含税"),VLOOKUP("*"&TRIM(SUBSTITUTE(H6,",","|"))&"*",休斯敦!B:F,2,0),AND(G6="义乌/苏州",I6="不含税"),VLOOKUP("*"&TRIM(SUBSTITUTE(H6,",","|"))&"*",休斯敦!B:F,3,0),AND(G6="青岛",I6="含税"),VLOOKUP("*"&TRIM(SUBSTITUTE(H6,",","|"))&"*",休斯敦!B:F,4,0),AND(G6="青岛",I6="不含税"),VLOOKUP("*"&TRIM(SUBSTITUTE(H6,",","|"))&"*",休斯敦!B:F,5,0)),"-") -> - | H22: =VLOOKUP(E22,[1]Sheet1!$A:$I,4,0) -> 7月4日 18:00 | I22: =VLOOKUP(E22,[1]Sheet1!$A:$I,5,0) -> 46215 | J22: =VLOOKUP(E22,[1]Sheet1!$A:$I,6,0) -> 46241 | K22: =VLOOKUP(E22,[1]Sheet1!$A:$J,7,0) -> 26 | L22: =VLOOKUP(E22,[1]Sheet1!$A:$J,8,0) -> 46245 | M22: =IFERROR(_xlfn.IFS(AND(G6="深圳/中山/广州/汕头/厦门",I6="含税"),VLOOKUP("*"&TRIM(SUBSTITUTE(H6,",","|"))&"*",[2]休斯敦!B7:H18,7,0),AND(G6="深圳/中山/广州/汕头/厦门",I6="不含税"),VLOOKUP("*"&TRIM(SUBSTITUTE(H6,",","|"))&"*",[2]休斯敦!B7:H18,7,0),AND(G6="义乌/苏州",I6="含税"),VLOOKUP("*"&TRIM(SUBSTITUTE(H6,",","|"))&"*",[2]休斯敦!B7:H18,7,0),AND(G6="义乌/苏州",I6="不含税"),VLOOKUP("*"&TRIM(SUBSTITUTE(H6,",","|"))&"*",[2]休斯敦!B7:H18,7,0),AND(G7="青岛",I6="含税"),VLOOKUP("*"&TRIM(SUBSTITUTE(H6,",","|"))&"*",[2]休斯敦!B7:H18,7,0),AND(G6="青岛",I6="不含税"),VLOOKUP("*"&TRIM(SUBSTITUTE(H6,",","|"))&"*",[2]休斯敦!B7:H18,7,0)),"-") -> -
C23: 萨瓦纳 | D23: 美东南普船 | E23: 萨瓦纳专线 | F23: EMC | G23: =IFERROR(_xlfn.IFS(AND(G6="深圳/中山/广州/汕头/厦门",I6="含税"),VLOOKUP("*"&TRIM(SUBSTITUTE(H6,",","|"))&"*",萨瓦纳!B:F,2,0),AND(G6="深圳/中山/广州/汕头/厦门",I6="不含税"),VLOOKUP("*"&TRIM(SUBSTITUTE(H6,",","|"))&"*",萨瓦纳!B:F,3,0),AND(G6="义乌/苏州",I6="含税"),VLOOKUP("*"&TRIM(SUBSTITUTE(H6,",","|"))&"*",萨瓦纳!B:F,2,0),AND(G6="义乌/苏州",I6="不含税"),VLOOKUP("*"&TRIM(SUBSTITUTE(H6,",","|"))&"*",萨瓦纳!B:F,3,0),AND(G6="青岛",I6="含税"),VLOOKUP("*"&TRIM(SUBSTITUTE(H6,",","|"))&"*",萨瓦纳!B:F,4,0),AND(G6="青岛",I6="不含税"),VLOOKUP("*"&TRIM(SUBSTITUTE(H6,",","|"))&"*",萨瓦纳!B:F,5,0)),"-") -> - | H23: =VLOOKUP(E23,[1]Sheet1!$A:$I,4,0) -> 7月4日 18:00 | I23: =VLOOKUP(E23,[1]Sheet1!$A:$I,5,0) -> 46213 | J23: =VLOOKUP(E23,[1]Sheet1!$A:$I,6,0) -> 46245 | K23: =VLOOKUP(E23,[1]Sheet1!$A:$J,7,0) -> 32 | L23: =VLOOKUP(E23,[1]Sheet1!$A:$J,8,0) -> 46249 | M23: =IFERROR(_xlfn.IFS(AND(G6="深圳/中山/广州/汕头/厦门",I6="含税"),VLOOKUP("*"&TRIM(SUBSTITUTE(H6,",","|"))&"*",[2]萨瓦纳!B7:H20,7,0),AND(G6="深圳/中山/广州/汕头/厦门",I6="不含税"),VLOOKUP("*"&TRIM(SUBSTITUTE(H6,",","|"))&"*",[2]萨瓦纳!B7:H20,7,0),AND(G6="义乌/苏州",I6="含税"),VLOOKUP("*"&TRIM(SUBSTITUTE(H6,",","|"))&"*",[2]萨瓦纳!B7:H20,7,0),AND(G6="义乌/苏州",I6="不含税"),VLOOKUP("*"&TRIM(SUBSTITUTE(H6,",","|"))&"*",[2]萨瓦纳!B7:H20,7,0),AND(G6="青岛",I6="含税"),VLOOKUP("*"&TRIM(SUBSTITUTE(H6,",","|"))&"*",[2]萨瓦纳!B7:H20,7,0),AND(G6="青岛",I6="不含税"),VLOOKUP("*"&TRIM(SUBSTITUTE(H6,",","|"))&"*",[2]萨瓦纳!B7:H20,7,0)),"-") -> -
C24: 加拿大 | D24: 加拿大直航 | E24: 加拿大直航 | F24: COSCO | G24: =IFERROR(_xlfn.IFS(AND(G6="深圳/中山/广州",I6="含税"),VLOOKUP("*"&TRIM(SUBSTITUTE(H6,",","|"))&"*",加拿大!C:K,2,0),AND(G6="深圳/中山/广州",I6="不含税"),VLOOKUP("*"&TRIM(SUBSTITUTE(H6,",","|"))&"*",加拿大!C:K,3,0),AND(G6="义乌/苏州",I6="含税"),VLOOKUP("*"&TRIM(SUBSTITUTE(H6,",","|"))&"*",加拿大!C:K,4,0),AND(G6="义乌/苏州",I6="不含税"),VLOOKUP("*"&TRIM(SUBSTITUTE(H6,",","|"))&"*",加拿大!C:K,5,0),AND(G6="汕头/厦门",I6="含税"),VLOOKUP("*"&TRIM(SUBSTITUTE(H6,",","|"))&"*",加拿大!C:K,6,0),AND(G6="汕头/厦门",I6="不含税"),VLOOKUP("*"&TRIM(SUBSTITUTE(H6,",","|"))&"*",加拿大!C:K,7,0),AND(G6="青岛",I6="含税"),VLOOKUP("*"&TRIM(SUBSTITUTE(H6,",","|"))&"*",加拿大!C:K,8,0),AND(G6="青岛",I6="不含税"),VLOOKUP("*"&TRIM(SUBSTITUTE(H6,",","|"))&"*",加拿大!C:K,9,0)),"-") -> - | H24: =VLOOKUP(E24,[1]Sheet1!$A:$I,4,0) -> 7月4日 18:00 | I24: =VLOOKUP(E24,[1]Sheet1!$A:$I,5,0) -> 46214 | J24: =VLOOKUP(E24,[1]Sheet1!$A:$I,6,0) -> 46233 | K24: =VLOOKUP(E24,[1]Sheet1!$A:$J,7,0) -> 19 | L24: =VLOOKUP(E24,[1]Sheet1!$A:$J,8,0) -> 46237 | M24: =IFERROR(_xlfn.IFS(AND(G3="深圳/中山/广州/汕头/厦门",I3="含税"),VLOOKUP("*"&TRIM(SUBSTITUTE(H3,",","|"))&"*",[2]加拿大!C4:L9,10,0),AND(G3="深圳/中山/广州/汕头/厦门",I3="不含税"),VLOOKUP("*"&TRIM(SUBSTITUTE(H3,",","|"))&"*",[2]加拿大!C4:L9,10,0),AND(G3="义乌/苏州",I3="含税"),VLOOKUP("*"&TRIM(SUBSTITUTE(H3,",","|"))&"*",[2]加拿大!C4:L9,10,0),AND(G3="义乌/苏州",I3="不含税"),VLOOKUP("*"&TRIM(SUBSTITUTE(H3,",","|"))&"*",[2]加拿大!C4:L9,10,0),AND(G3="青岛",I3="含税"),VLOOKUP("*"&TRIM(SUBSTITUTE(H3,",","|"))&"*",[2]加拿大!C4:L9,10,0),AND(G3="青岛",I3="不含税"),VLOOKUP("*"&TRIM(SUBSTITUTE(H3,",","|"))&"*",[2]加拿大!C4:L9,10,0)),"-") -> -
B25: 墨西哥 | C25: 洛杉矶 | D25: 美转墨 | E25: 美 墨 快 线 | F25: / | G25: / | H25: / | I25: / | J25: / | K25: / | L25: /
C26: 墨西哥城 | D26: 墨西哥直航 | E26: 墨西哥直航 | F26: / | G26: / | H26: / | I26: / | J26: / | K26: / | L26: /
M27: =IFERROR(_xlfn.IFS(AND(G6="深圳/中山/广州/汕头/厦门",I6="含税"),VLOOKUP("*"&TRIM(SUBSTITUTE(H6,",","|"))&"*",[2]加拿大!C7:L12,10,0),AND(G6="深圳/中山/广州/汕头/厦门",I6="不含税"),VLOOKUP("*"&TRIM(SUBSTITUTE(H6,",","|"))&"*",[2]加拿大!C7:L12,10,0),AND(G6="义乌/苏州",I6="含税"),VLOOKUP("*"&TRIM(SUBSTITUTE(H6,",","|"))&"*",[2]加拿大!C7:L12,10,0),AND(G6="义乌/苏州",I6="不含税"),VLOOKUP("*"&TRIM(SUBSTITUTE(H6,",","|"))&"*",[2]加拿大!C7:L12,10,0),AND(G6="青岛",I6="含税"),VLOOKUP("*"&TRIM(SUBSTITUTE(H6,",","|"))&"*",[2]加拿大!C7:L12,10,0),AND(G6="青岛",I6="不含税"),VLOOKUP("*"&TRIM(SUBSTITUTE(H6,",","|"))&"*",[2]加拿大!C7:L12,10,0)),"-") -> -
G28: 12KG+（包税） | H28: 100KG+（包税） | I28: 分区 | J28: 邮编 | M28: 参考提取时效（开船后）
D29: 海派专线 | E29: Match12-海派 | F29: MATSON | G29: =IFERROR(_xlfn.IFS(AND(G6="深圳/中山/广州/汕头/厦门",I6="含税"),VLOOKUP("*"&TRIM(SUBSTITUTE(I29,",","|"))&"*",海派渠道!B5:I10,3,0),AND(G6="义乌/苏州",I6="含税"),VLOOKUP("*"&TRIM(SUBSTITUTE(I29,",","|"))&"*",海派渠道!B5:I10,5,0),AND(G6="青岛",I6="含税"),VLOOKUP("*"&TRIM(SUBSTITUTE(I29,",","|"))&"*",海派渠道!B5:I10,7,0)),"-") -> 16.2 | H29: =IFERROR(_xlfn.IFS(AND(G6="深圳/中山/广州/汕头/厦门",I6="含税"),VLOOKUP("*"&TRIM(SUBSTITUTE(I29,",","|"))&"*",海派渠道!B5:I10,4,0),AND(G6="义乌/苏州",I6="含税"),VLOOKUP("*"&TRIM(SUBSTITUTE(I29,",","|"))&"*",海派渠道!B5:I10,6,0),AND(G6="青岛",I6="含税"),VLOOKUP("*"&TRIM(SUBSTITUTE(I29,",","|"))&"*",海派渠道!B5:I10,8,0)),"-") -> 13.2 | I29: =VLOOKUP(H6,分区!A:D,4,0) -> 美西 | J29: =VLOOKUP(H6,分区!A:E,2,0) -> 94561-2677 | K29: 11 | L29: 查看报价 | M29: 14-15天
E30: Match15-海派 | F30: 以星 EXX | G30: =IFERROR(_xlfn.IFS(AND(G6="深圳/中山/广州/汕头/厦门",I6="含税"),VLOOKUP("*"&TRIM(SUBSTITUTE(I29,",","|"))&"*",海派渠道!B6:R11,12,0),AND(G6="义乌/苏州",I6="含税"),VLOOKUP("*"&TRIM(SUBSTITUTE(I29,",","|"))&"*",海派渠道!B6:R11,14,0),AND(G6="青岛",I6="含税"),VLOOKUP("*"&TRIM(SUBSTITUTE(I29,",","|"))&"*",海派渠道!B6:R11,16,0)),"-") -> 14.6 | H30: =IFERROR(_xlfn.IFS(AND(G6="深圳/中山/广州/汕头/厦门",I6="含税"),VLOOKUP("*"&TRIM(SUBSTITUTE(I29,",","|"))&"*",海派渠道!B6:T11,13,0),AND(G6="义乌/苏州",I6="含税"),VLOOKUP("*"&TRIM(SUBSTITUTE(I29,",","|"))&"*",海派渠道!B6:T11,15,0),AND(G6="青岛",I6="含税"),VLOOKUP("*"&TRIM(SUBSTITUTE(I29,",","|"))&"*",海派渠道!B6:T11,17,0)),"-") -> 11.6 | K30: 11 | L30: 查看报价 | M30: 16-17天
E31: Match20-海派 | F31: EMC 合德 | G31: =IFERROR(_xlfn.IFS(AND(G6="深圳/中山/广州/汕头/厦门",I6="含税"),VLOOKUP("*"&TRIM(SUBSTITUTE(I29,",","|"))&"*",海派渠道!B16:I20,3,0),AND(G6="义乌/苏州",I6="含税"),VLOOKUP("*"&TRIM(SUBSTITUTE(I29,",","|"))&"*",海派渠道!B16:I20,5,0),AND(G6="青岛",I6="含税"),VLOOKUP("*"&TRIM(SUBSTITUTE(I29,",","|"))&"*",海派渠道!B16:I20,7,0)),"-") -> 12.7 | H31: =IFERROR(_xlfn.IFS(AND(G6="深圳/中山/广州/汕头/厦门",I6="含税"),VLOOKUP("*"&TRIM(SUBSTITUTE(I29,",","|"))&"*",海派渠道!B16:I20,4,0),AND(G6="义乌/苏州",I6="含税"),VLOOKUP("*"&TRIM(SUBSTITUTE(I29,",","|"))&"*",海派渠道!B16:I20,6,0),AND(G6="青岛",I6="含税"),VLOOKUP("*"&TRIM(SUBSTITUTE(I29,",","|"))&"*",海派渠道!B16:I20,8,0)),"-") -> 9.7 | K31: 14 | L31: 查看报价 | M31: 21-22天
E32: OA-拆送海派 | F32: OA | G32: =IFERROR(_xlfn.IFS(AND(G6="深圳/中山/广州/汕头/厦门",I6="含税"),VLOOKUP("*"&TRIM(SUBSTITUTE(I29,",","|"))&"*",海派渠道!B16:R21,12,0),AND(G6="义乌/苏州",I6="含税"),VLOOKUP("*"&TRIM(SUBSTITUTE(I29,",","|"))&"*",海派渠道!B16:R21,14,0),AND(G6="青岛",I6="含税"),VLOOKUP("*"&TRIM(SUBSTITUTE(I29,",","|"))&"*",海派渠道!B16:R21,16,0)),"-") -> 12.5 | H32: =IFERROR(_xlfn.IFS(AND(G6="深圳/中山/广州/汕头/厦门",I6="含税"),VLOOKUP("*"&TRIM(SUBSTITUTE(I29,",","|"))&"*",海派渠道!B16:R21,13,0),AND(G6="义乌/苏州",I6="含税"),VLOOKUP("*"&TRIM(SUBSTITUTE(I29,",","|"))&"*",海派渠道!B16:R21,15,0),AND(G6="青岛",I6="含税"),VLOOKUP("*"&TRIM(SUBSTITUTE(I29,",","|"))&"*",海派渠道!B16:R21,17,0)),"-") -> 9.5 | K32: 14 | L32: 查看报价 | M32: 26-28天

Sheet 发货须知
B2: 美 琦 国 际 货 运 代 理（深圳）有 限 公 司 地址：深圳市龙岗区坂田街道坂雪岗大道4088号奥博中心6楼A609-611
B4: 附加费 | C4: 渠道 | D4: 海卡包税 | E4: 海卡不包税 | F4: 海派渠道 | G4: 直通车（包税） | H4: 直通车（不包税）
C5: 末端派送类型 | D5: 卡派 | E5: 卡派 | F5: UPS | G5: 卡派 | H5: 卡派不包税
B6: 报关费 | C6: 买单报关 | D6: 0 | E6: 0 | F6: 0 | G6: 0 | H6: 0
C7: 一般贸易报关费 | D7: 350 | E7: 350 | F7: 350 | G7: 350 | H7: 350 | J7: 国内仓库费用 | K7: 收费项目 | L7: 单价/RMB | M7: 单位 | N7: 备注 | O7: 备注
C8: 手册报关/其他报关（9710/9810，一达通报关） | D8: 350 | E8: 350 | F8: 350 | G8: 350 | H8: 350 | K8: 更改包装费 | L8: 10 | M8: 箱 | N8: 不含纸箱费用
B9: 产品附加费 | C9: 服装类（穿戴类纺织品） | D9: 0.5/KG | E9: 0 | F9: 0.5/KG | G9: 0.5/KG | H9: 0 | K9: 产品贴标签 | L9: 1 | M9: 个标签 | N9: 含标签纸
C10: 木制品（报关件单询） | D10: 0.5/KG | E10: 500 | F10: 0.5/KG | G10: 0.5/KG | H10: 500 | K10: 换外箱标签 | L10: 1 | M10: 个标签 | N10: 含标签纸
C11: 包包 | D11: 0.5/KG | E11: 500 | F11: 0.5/KG | G11: 0.5/KG | H11: 500
C12: FDA\EPA\DOT认证产品 | D12: 单询 | E12: 单询 | F12: 单询 | G12: 单询 | H12: 单询 | K12: 割包装袋/带 | L12: 1 | M12: 箱
C13: 涉FDA产品 | D13: 单询 | E13: 单询 | F13: 单询 | G13: 单询 | H13: 单询 | K13: 开木箱查货 | L13: 30 | M13: 箱 | N13: 含封箱
C14: 厨房刀具 | D14: 单询 | E14: 单询 | F14: 单询 | G14: 单询 | H14: 单询 | K14: 仓租 | L14: 3.5/天 | M14: CBM | N14: 自入仓日起免租期7天，最久存仓1个月 | O14: 免仓期7天
C15: 涉太阳能产品 | D15: 单询 | E15: 单询 | F15: 单询 | G15: 单询 | H15: 单询
C16: 移动电源\纯电池\暖手宝 | D16: 单询 | E16: 单询 | F16: 单询 | G16: 单询 | H16: 单询
C17: 单件计费重低消 | D17: 5KG/件 | E17: 5KG/件 | F17: 12KG/件 | G17: 5KG/件 | H17: 5KG/件
B18: 特殊地址附加费 | C18: 商业地址 | D18: 0 | E18: 0 | F18: 0 | G18: 0 | H18: 0
C19: 私人地址 | D19: 0 | E19: 0 | F19: 25/件 | G19: 0 | H19: 0
C20: 偏远附加费 | D20: 0 | E20: 0 | F20: 40/件 | G20: 0 | H20: 0
B21: 超重超尺寸附加费 | C21: 140cm≤最长边＜169cm | D21: 1/KG | E21: 200/CBM | F21: 无服务 | G21: 无服务 | H21: 无服务
C22: 120cm≤最长边＜140cm | D22: 0 | E22: 0 | F22: 160/件 | G22: 无服务 | H22: 无服务
C23: 第二边长≥76cm | D23: 0 | E23: 0 | F23: 120/件 | G23: 无服务 | H23: 无服务
C24: 三边相乘体积>0.17立方米 | D24: 0 | E24: 0 | F24: 160/件 | G24: 无服务 | H24: 无服务
C25: 22.5KG≤实重≤40KG | D25: 0 | E25: 0 | F25: 160/件 | G25: 无服务 | H25: 无服务
C26: 实重＞40KG | D26: 单询 | E26: 单询 | F26: 500/件 | G26: 单询 | H26: 单询
C27: 266cm≤长+2x(宽+高)≤330cm | D27: 单询 | E27: 单询 | F27: 160/件 | G27: 单询 | H27: 单询
C28: 330cm≤长+2x(宽+高)≤419cm | D28: 单询 | E28: 单询 | F28: 900/件 | G28: 单询 | H28: 单询
C29: 三边相乘体积>0.28立方米 | D29: 单询 | E29: 单询 | F29: 600/件 | G29: 单询 | H29: 单询
C30: 单件重量超过49.8KG | D30: 单询 | E30: 单询 | F30: 600/件 | G30: 单询 | H30: 单询
C31: 长+2x(宽+高)＞419cm | D31: 单询 | E31: 单询 | F31: 无服务 | G31: 单询 | H31: 单询
B32: 其他附加费 | C32: 关税和查验费 | D32: 0 | E32: 实报实销 | F32: 0 | G32: 0 | H32: 实报实销
C33: 清关超品名费 | D33: 30/品名 | E33: 30/品名 | F33: 30/品名 | G33: 30/品名 | H33: 30/品名
C34: 退件费（打单后） | D34: 0 | E34: 0 | F34: 100/票 | G34: 0 | H34: 0
C35: 目的港扣货 | D35: USD200/票 | E35: USD200/票 | F35: USD200/票 | G35: USD1200/票 | H35: USD1200/票
C36: 申请POD | D36: 免费 | E36: 免费 | F36: 35/主单号 | G36: 免费 | H36: 免费
B37: 拒收产品 | C37: 1、带有以下标识：LASER，ACT等授权认证的产品（无论是否有认证）
C38: 2、手机、笔记本电脑等高货值产品、婴儿用品（包括衣服），激光产品，蝴蝶刀、液体、粉末、U盘、光驱、内存条、家具、指尖陀螺、电弧打火机，带压缩机产品，活性植物，太阳眼镜、化妆品等
C39: 3、仿牌产品，液体、粉末、食品、药品、易燃易爆、古董、货币等国家禁止出口产品，如发现罚款2000/票，情节严重上报公安局处理
C40: 4、反倾销产品（点我看清单）
B41: 海外仓仓租 | C41: 提柜起免租7天，第8-60天收取USD2/CBM/天,第61天起收取USD3/CBM/天，（每票最低消费收费5USD/天） 超过3个月未出货物默认销毁，已产生的仓租正常收取
B42: 开 查 | C42: 货物派送后，请客户在签收后7-10个工作日内查询FBA后台是否上架，如递送后15个工作日内提供货物未上架，请提供后台截图至我司客服。
B43: 索赔 | C43: 开启索赔程序(需带有电脑屏幕右下角当下真实时间)；如递送后超过20工作日未开启索赔程序的，不予受理
B44: 赔偿标准 | C44: ①丢失赔偿：含税渠道在货物运输过程中丢失(包含整票UPS/FEDEX未提取)，按申报货值赔偿最高不超人民币40/KG赔偿，不退运费；自税渠道在货物运输过程中丢失(包含整票UPS/FEDEX未提取)，按申报货值赔偿最高不超人民币2000/CBM赔偿，不退运费；
C45: ②提取后赔偿：已交UPS/FEDEX后(部分子单号未扫描货件，此为常见漏扫现象，我司不负责)丢失的不退运费，按UPS/FEDEX标准赔偿，即按申报价值赔偿但最高不超USD100/票。
C46: ③派送后赔偿：已提供签收完整的POD的货（无论卡派还是UPS派），不接受索赔。
C47: ④漏报关、错报导致无法改单或改单失败赔偿：3倍报关费，请慎接报关件，不接受赔偿标准的不要发！
C48: ⑤延误赔偿：以报价表为准，但如因发件人低申报、品名申报不符、产品涉及反倾销、认证、侵权等不符合当地法规的，由此产生的责任和损失，由发件人承担，我司保留追究法律责任的权利且不予任何赔偿
C49: ⑥扣关赔偿：含税渠道非货物本身的问题产生的扣关按申报货值赔偿最高不超人民币40/KG赔偿，不退运费；自税渠道非货物本身的问题产生的扣关按申报货值赔偿最高不超人民币2000/CBM赔偿，不退运费；但如因发件人低申报、品名申报不符、产品涉及反倾销、认证、侵权等不符合当地法规的，由此产生的责任和损失，由发件人承担，我司保留追究法律责任的权利且不予任何赔偿
B50: 特别提示：客户一旦同意接受我公司服务，即默认客户已详细阅读过此价格表备注内容以及我司托运条款，并接受各条款的约束。

Sheet MATCH闪送
A1: 美 琦 国 际 货 运 代 理（深圳）有 限 公 司 地址：深圳市龙岗区坂田街道坂雪岗大道4088号奥博中心6楼A609-611
A3: MATCH 闪送系列
A4: 目的港 | B4: Match美西闪送-海派 | K4: 返回目录
A5: 洛杉矶 | B5: 邮编 | C5: 12KG+(海派包税） | D5: 50KG+(海派包税） | E5: 100KG+(海派包税） | F5: 参考时效（开船后） | G5: 理赔时效（开船后提取） | H5: 备注
B6: 邮编 8 9 | C6: - | D6: - | E6: - | F6: 13Day | G6: 13Day | H6: 重货优惠 1 :200 =-0.3/KG 1:240= -0.6/KG 1:280= -0.9/KG 1:320 =-1.2/KG 1:360= -1.5/KG 1:420 = -1.8/KG 1:480=- 2.1/KG 1:500=-2.5/KG （封顶）
B7: 邮编（97 98 99） | C7: - | D7: - | E7: - | F7: 13Day | G7: 13Day
B8: 邮编 5 6 7 | C8: - | D8: - | E8: - | F8: 13Day | G8: 13Day
B9: 邮编 0 1 2 3 4 | C9: - | D9: - | E9: - | F9: 13Day | G9: 13Day
B10: 下单渠道 | C10: Match美西闪送海派包税 | D10: Y-Match美西闪送海派包税 | E10: Match美西闪送海派包税 | F10: 美西闪送-海派（汕头/厦门中转仓到货的按深圳价格+0.3，青岛仓价格按义乌报价+0.5）
A11: Match美西闪送
A12: 目的港 | C12: 深圳/中山/广州/义乌 | D12: 汕头/厦门 | E12: 青岛
A13: 洛杉矶 | B13: 亚马逊仓库地址 | C13: 21KG+（卡派包税） | D13: 21KG+（卡派包税） | E13: 21KG+（卡派包税） | F13: 参考时效（开船后） | G13: 理赔时效（开船后）
B14: ONT8，LGB8，SBD1，LAX9 | C14: - | D14: - | E14: - | F14: 13Day | G14: 14Day
B15: POC1，POC3 | C15: - | D15: - | E15: - | F15: 13Day | G15: 15Day
B16: 下单渠道 | C16: Match美西闪送卡派包税 | D16: Match美西闪送卡派包税 | E16: Match美西闪送卡派包税
A17: 时效赔付说明 | C17: 理赔时效计算标准：实际开船日期第二天算起 时效赔偿：RMB1.5/KG/自然日（含税），最高赔偿4.5KG 海派第13天未提取开始理赔，无论国内外任何查验 都计入理赔时效 闪送闪赔 赔偿方案7工作日内到位
A20: 上架延误险 | C20: 上架延误险：+0.1RMB/KG，如签收后72小时无上架信息（check in ）,每工作日赔偿0.1/KG，最多赔偿0.5RMB/KG！
C22: Match美东闪送
C23: 深圳/中山/广州/义乌/汕头/厦门 | E23: 青岛 | G23: 时效
A24: 亚马逊仓库地址（低于50KG 需+2/KG） | C24: 包税50KG+ | D24: 不包税1CBM+ | E24: 包税50KG+ | F24: 不包税1CBM+ | G24: 航程 (开船后) | H24: 参考时效(开船后) | I24: 参考时效(开船后) | J24: 备注
A25: 正常派送区 | B25: TEB6、TEB9、EWR5、EWR4、EWR6、EWR7、EWR9 | C25: - | D25: - | E25: - | F25: - | G25: 19-21 | H25: 25-27 | I25: 28天 | J25: 【含税】渠道： 1、含关税和查验费； 2、体积/6000，不分泡 3、单件最低消费5KG，美东极速快车渠道单票低消21KG,21-49KG单价+2/KG： 【不含税】渠道： 1、不含关税，查验费和查验产生的其他费用； 2、体积/1000000，不分泡，单件最低消费5KG，单票低消1CBM 3.重货按每363KG=1CBM (产品附加费/特殊附加费等详见发货必读) 重货优惠： 包税渠道重货优惠 重货优惠 1 :200 =-0.3/KG 1:240= -0.6/KG 1:280= -0.9/KG 1:320 =-1.2/KG 1:360= -1.5/KG 1:420 = -1.8/KG 1:480=- 2.1/KG 1:500=-2.5/KG （封顶）
B26: ABE8、ACY2、TTN2、LGA9、ACY1、JFK8、JFK2 | C26: - | D26: - | E26: - | F26: - | G26: 19-21 | H26: 25-27 | I26: 28天
B27: TEB3、TEB4、ABE4、ABE3、ABE5、ABE2 | C27: - | D27: - | E27: - | F27: - | G27: 19-21 | H27: 25-27 | I27: 28天
B28: AVP1、AVP9、WBW2、AVP3 | C28: - | D28: - | E28: - | F28: - | G28: 19-21 | H28: 25-27 | I28: 28天
B29: PHL4、PHL5、PHL6、MDT1、RDG1、MDT2 | C29: - | D29: - | E29: - | F29: - | G29: 19-21 | H29: 25-27 | I29: 28天
B30: HIA1、DCA6、DCA1 | C30: - | D30: - | E30: - | F30: - | G30: 19-21 | H30: 27-29 | I30: 30天
B31: SWF2、SWF1、ILG1、PHL3、PHL7、PHL1 | C31: - | D31: - | E31: - | F31: - | G31: 19-21 | H31: 27-29 | I31: 30天
B32: MDT4、ALB1、XLX1、HGR6、HGR2 | C32: - | D32: - | E32: - | F32: - | G32: 19-21 | H32: 28-30 | I32: 31天
B33: IUST、IUSL | C33: - | D33: - | E33: - | F33: - | G33: 19-21 | H33: 27-29 | I33: 30天
B34: BWI2、BDL6、BDL3、BDL2、BWI1、BWI4 | C34: - | D34: - | E34: - | F34: - | G34: 19-21 | H34: 27-29 | I34: 30天
B35: AKR1、CMH6、CMH2、CMH7、RMN3 | C35: - | D35: - | E35: - | F35: - | G35: 19-21 | H35: 28-30 | I35: -
B36: PIT2、LBE1、RIC1、RIC3、XRI3、CHO1、RIC2 | C36: - | D36: - | E36: - | F36: - | G36: 19-21 | H36: 28-30 | I36: -
B37: CMH3、XPH1、ORF2、GSO1 | C37: - | D37: - | E37: - | F37: - | G37: 19-21 | H37: 28-30 | I37: -
... B53: TPA1、TPA2、MCO2、TPA3、TPA6、MCO1 | C53: - | D53: - | E53: - | F53: - | G53: 无 | H53: 无 | I53: 无
A54: 纽约自提 | C54: - | D54: - | E54: - | F54: - | G54: 19-21 | H54: 25-27 | I54: 无
A55: 08邮编海外仓（单票低消500KG或3个方） | C55: - | D55: - | E55: - | F55: - | G55: 19-21 | H55: 25-27 | I55: 无
A56: 08邮编海外仓（1500KG+或6个方+） | C56: - | D56: - | E56: - | F56: - | G56: 19-21 | H56: 25-27 | I56: 无
A57: 沃尔玛仓库 | B57: 沃尔玛 低消费300KG 2CBM+ | C57: 300KG+ | D57: 2CBM+ (不包税) | E57: 300KG+ | F57: 2CBM+ (不包税)
B58: WMT-NJ3 | C58: - | D58: - | G58: - | I58: -
B59: WNT-IND2，WNT-IND1，WNT-BNA1s | C59: - | D59: - | G59: - | I59: -
B60: WMT-ATL1，MWT-ATL2，WMT-ATL3 | C60: - | D60: - | G60: - | I60: -
B61: WMT-MCO1，WMT-KS1 | C61: - | D61: - | G61: - | I61: -
A62: Wayfair | B62: 48 Station Road Cranbury, NJ 08512 | C62: - | D62: - | G62: - | I62: -
B63: 万邑通仓41048（最低消费800KG+ 或 5CBM+） | C63: - | D63: - | E63: - | F63: - | G63: 19-21 | H63: 28-30 | I63: 无
A64: 谷仓 | B64: 2号-08518（此目的地最低消费300KG) | C64: - | D64: - | G64: - | H64: - | I64: -
B65: 5号-08831（此目的地最低消费300KG) | C65: - | D65: - | G65: - | H65: - | I65: -
B66: 8号-07836（此目的地最低消费300KG) | C66: - | D66: - | G66: - | H66: - | I66: -
B67: 11号-08505（此目的地最低消费300KG) | C67: - | D67: - | G67: - | H67: - | I67: -
B68: 15号-08036（此目的地最低消费300KG) | C68: - | D68: - | G68: - | H68: - | I68: -
B69: 16号-08057（此目的地最低消费300KG) | C69: - | D69: - | G69: - | H69: - | I69: -
B70: 18号-08016（此目的地最低消费300KG) | C70: - | D70: - | G70: - | H70: - | I70: -
A71: 其他 | B71: 美国新泽西1仓：1000 High Street，PERTH AMBOY，NJ 08861（此目的地最低消费300KG) | C71: - | D71: - | G71: - | H71: - | I71: -
B72: 易达云美东10仓：480 Elizabeth Ave，Somerset NJ 08873（此目的地最低消费300KG) | C72: - | D72: - | G72: - | H72: - | I72: -
B73: 4PX美东2号仓：4PX Express CO.,LTD 1401 w front st, Florence, NJ 08518（此目的地最低消费300KG) | C73: - | D73: - | G73: - | H73: - | I73: -
B74: 美东11号仓：1175 Florence Columbus Road UNITB（A12-A35), Bordentown,NJ,08505（此目的地最低消费300KG) | C74: - | D74: - | G74: - | H74: - | I74: -
A75: 下单渠道 | C75: 美东闪送-包税 | D75: 美东闪送-不包税 | E75: 美东闪送-包税 | F75: 美东闪送-不包税
A76: 赔付说明 | C76: 从盐田离港后第二天算起，超过承诺时效后1/KG/天，3天封顶 含税渠道:赔偿RMB1/KG/天，最高3RMB/KG； 不含税渠道:赔偿RMB100/CBM/天，最高赔偿300RMB/CBM 船期延误、到港延误、进出口查验、亚马逊问题不赔(删约/不放约/拒收/关仓等)

Sheet Match系列 
B2: 美 琦 国 际 货 运 代 理（深圳）有 限 公 司 地址：深圳市龙岗区坂田街道坂雪岗大道4088号奥博中心6楼A609-611
B3: M A T C H 系 列 王 牌 产 品
D4: Match12-卡派（CLX+MAX-GES服务) | L4: Match15-卡派（ZIM带车架、EXX统配） | T4: Match20-卡派（长荣定提 、合德快提统配）
D5: 深圳/中山/广州/汕头/厦门 | F5: 义乌/苏州 | H5: 青岛 | J5: 时效 | L5: 深圳/中山/广州/汕头/厦门 | N5: 义乌/苏州 | P5: 青岛 | R5: 时效 | T5: 深圳/中山/广州/汕头/厦门 | V5: 义乌/苏州 | X5: 青岛 | Z5: 时效
B6: 亚马逊仓库地址 | D6: 21KG+ （包税） | E6: 1CBM+（不包税） | F6: 21KG+ （包税） | G6: 1CBM+（不包税） | H6: 21KG+ （包税） | I6: 1CBM+（不包税） | J6: 参考时效（开船后） | K6: 理赔时效（开船后） | L6: 21KG+ （包税） | M6: 1CBM+（不包税） | N6: 21KG+ （包税） | O6: 1CBM+（不包税） | P6: 21KG+ （包税） | Q6: 1CBM+（不包税） | R6: 参考时效（开船后） | S6: 理赔时效（开船后） | T6: 21KG+ （包税） | U6: 1CBM+（不包税） | V6: 21KG+ （包税） | W6: 1CBM+（不包税） | X6: 21KG+ （包税） | Y6: 1CBM+（不包税） | Z6: 参考时效（开船后） | AA6: 理赔时效（开船后） | AB6: 返回目录 | AC6: 涨价幅度
B7: 热门仓 | C7: ONT8、LGB8、SBD1、LAX9 | D7: 11.2 | E7: 1580 | F7: 10.7 | G7: 1505 | H7: 11.2 | I7: 1580 | J7: 13-15 | K7: 15天 | L7: 8.8 | M7: 1210 | N7: 8.8 | O7: 1210 | P7: 9.3 | Q7: 1285 | R7: 15-17 | S7: 19天 | T7: 7.5 | U7: 1060 | V7: 7.5 | W7: 1060 | X7: 8 | Y7: 1135 | Z7: 19-21 | AA7: 23天 | AB7: 重货优惠 1 :200 =-0.3/KG 1:240= -0.6/KG 1:280= -0.9/KG 1:320 =-1.2/KG 1:360= -1.5/KG 1:420 = -1.8/KG 1:480=- 2.1/KG 1:500=-2.5/KG （封顶） 1、包税渠道含关税和查验费； 2、体积/6000； 3、不分泡 4、不包税渠道不含关税和查验费；如查验按照68CBM分摊查验费 8、体积/6000； 6、不分泡，最低消费1个方 ，不足1个方按照1个方算 10、1CBM=363KG (产品附加费/特殊附加费等详见发货必读) | AC7: Match12 | AD7: 0.1 | AE7: 15
C8: POC1、POC2、POC3 | D8: 11.2 | E8: 1580 | F8: 10.7 | G8: 1505 | H8: 11.2 | I8: 1580 | J8: 13-15 | K8: 15天 | L8: 8.8 | M8: 1210 | N8: 8.8 | O8: 1210 | P8: 9.3 | Q8: 1285 | R8: 15-17 | S8: 19天 | T8: 7.5 | U8: 1060 | V8: 7.5 | W8: 1060 | X8: 8 | Y8: 1135 | Z8: 19-21 | AA8: 24天 | AC8: Match15 | AD8: 0.5 | AE8: 75
C9: SMF3、SCK4、SCK4、SCK8、HLI2、TCY1、TCY2、PSP3 | D9: 11.8 | E9: 1670 | F9: 11.3 | G9: 1595 | H9: 11.8 | I9: 1670 | J9: 15-17 | K9: 无 | L9: 9.7 | M9: 1345 | N9: 9.7 | O9: 1345 | P9: 10.2 | Q9: 1420 | R9: 17-19 | S9: 无 | T9: 8.4 | U9: 1195 | V9: 8.4 | W9: 1195 | X9: 8.9 | Y9: 1270 | Z9: 20-22 | AA9: 无 | AC9: Match20 | AD9: 0.8 | AE9: 120
C10: LAS1、VGT2、GYR2、GYR3、LAS6、IUTE | D10: 11.8 | E10: 1670 | F10: 11.3 | G10: 1595 | H10: 11.8 | I10: 1670 | J10: 15-17 | K10: 无 | L10: 9.7 | M10: 1345 | N10: 9.7 | O10: 1345 | P10: 10.2 | Q10: 1420 | R10: 17-19 | S10: 无 | T10: 8.4 | U10: 1195 | V10: 8.4 | W10: 1195 | X10: 8.9 | Y10: 1270 | Z10: 20-22 | AA10: 无
C11: GEU2、GEU3、MIT2 | D11: 11.8 | E11: 1670 | F11: 11.3 | G11: 1595 | H11: 11.8 | I11: 1670 | J11: 15-17 | K11: 无 | L11: 9.7 | M11: 1345 | N11: 9.7 | O11: 1345 | P11: 10.2 | Q11: 1420 | R11: 17-19 | S11: 无 | T11: 8.4 | U11: 1195 | V11: 8.4 | W11: 1195 | X11: 8.9 | Y11: 1270 | Z11: 20-22 | AA11: 无
C12: ABQ2 | D12: 12.8 | E12: 1820 | F12: 12.3 | G12: 1745 | H12: 12.8 | I12: 1820 | J12: 15-19 | K12: 无 | L12: 10.9 | M12: 1525 | N12: 10.9 | O12: 1525 | P12: 11.4 | Q12: 1600 | R12: 19-21 | S12: 无 | T12: 9.6 | U12: 1375 | V12: 9.6 | W12: 1375 | X12: 10.1 | Y12: 1450 | Z12: 22-24 | AA12: 无
C13: PSC2 | D13: 13.2 | E13: 1880 | F13: 12.7 | G13: 1805 | H13: 13.2 | I13: 1880 | J13: 15-19 | K13: 无 | L13: 11.3 | M13: 1585 | N13: 11.3 | O13: 1585 | P13: 11.8 | Q13: 1660 | R13: 19-21 | S13: 无 | T13: 10 | U13: 1435 | V13: 10 | W13: 1435 | X13: 10.5 | Y13: 1510 | Z13: 22-24 | AC13: 0.4 | AD13: 60
C14: FTW1、MDW2、IND9、MEM1 | D14: 14 | E14: 2000 | F14: 13.5 | G14: 1925 | H14: 14 | I14: 2000 | J14: 16-20 | K14: 无 | L14: 11.6 | M14: 1630 | N14: 11.6 | O14: 1630 | P14: 12.1 | Q14: 1705 | R14: 20-22 | S14: 无 | T14: 10.3 | U14: 1480 | V14: 10.3 | W14: 1480 | X14: 10.8 | Y14: 1555 | Z14: 22-24 | AA14: 无
C15: IAH3 | D15: 14.1 | E15: 2015 | F15: 13.6 | G15: 2030 | H15: 14.1 | I15: 2015 | J15: 16-20 | K15: 无 | L15: 11.7 | M15: 1645 | N15: 11.7 | O15: 1645 | P15: 12.2 | Q15: 1720 | R15: 20-22 | S15: 无 | T15: 10.4 | U15: 1495 | V15: 10.4 | W15: 1495 | X15: 10.9 | Y15: 1570 | Z15: 22-24 | AA15: 无
C16: LGB4、LGB9、LGB9、ONT6、ONT9、XLX7、LGB6、 SBD2、IUS1、IUSW、IUT1 | D16: 11.5 | E16: 1625 | F16: 11 | G16: 1550 | H16: 11.5 | I16: 1625 | J16: 15-17 | K16: 无 | L16: 8.9 | M16: 1225 | N16: 8.9 | O16: 1225 | P16: 9.4 | Q16: 1300 | R16: 18-20 | S16: 无 | T16: 7.6 | U16: 1075 | V16: 7.6 | W16: 1075 | X16: 8.1 | Y16: 1150 | Z16: 22-24 | AA16: 无
B17: 加州其他仓库 | C17: SCK1、SCK3、OAK3、SJC7、SMF6、QXY5、QZZ7 | D17: 12 | E17: 1700 | F17: 11.5 | G17: 1625 | H17: 12 | I17: 1700 | J17: 15-18 | K17: 无 | L17: 9.7 | M17: 1345 | N17: 9.7 | O17: 1345 | P17: 10.2 | Q17: 1420 | R17: 18-20 | S17: 无 | T17: 8.4 | U17: 1195 | V17: 8.4 | W17: 1195 | X17: 8.9 | Y17: 1270 | Z17: 24-26 | AA17: 无
B18: 海外仓 | C18: 仓库自提（出仓费15USD/板） | D18: 11 | E18: 1550 | F18: 10.5 | G18: 1475 | H18: 11.1 | I18: 1565 | J18: 13-15 | K18: 无 | L18: 8.6 | M18: 1180 | N18: 8.6 | O18: 1180 | P18: 9.1 | Q18: 1255 | R18: 15-17 | S18: 无 | T18: 7.3 | U18: 1030 | V18: 7.3 | W18: 1030 | X18: 7.8 | Y18: 1105 | Z18: 19-21 | AA18: 无
C19: 亚马逊仓库地址（以下地址 不足50KG 需+2） | D19: 50KG+（包税） | E19: 1CBM+（不包税） | F19: 50KG+（包税） | G19: 1CBM+（不包税） | H19: 50KG+（包税） | I19: 1CBM+（不包税） | J19: 参考时效（开船后） | K19: 理赔时效（开船后） | L19: 50KG+（包税） | M19: 1CBM+（不包税） | N19: 50KG+（包税） | O19: 1CBM+（不包税） | P19: 50KG+（包税） | Q19: 1CBM+（不包税） | R19: 参考时效（开船后） | S19: 理赔时效（开船后） | T19: 50KG+（包税） | U19: 1CBM+（不包税） | V19: 50KG+（包税） | W19: 1CBM+（不包税） | X19: 50KG+（包税） | Y19: 1CBM+（不包税） | Z19: 参考时效（开船后） | AA19: 理赔时效（开船后）
B20: 外州 | C20: PHX5、PHX7、RNO4 | D20: 12.1 | E20: 1715 | F20: 11.6 | G20: 1640 | H20: 12.1 | I20: 1715 | J20: 20-22 | K20: 无 | L20: 10 | M20: 1390 | N20: 10 | O20: 1390 | P20: 10.5 | Q20: 1465 | R20: 20-22 | S20: 无 | T20: 8.7 | U20: 1240 | V20: 8.7 | W20: 1240 | X20: 9.2 | Y20: 1315 | Z20: 21-23 | AA20: 无
C21: DEN2、DEN8、SLC2 | D21: 13.6 | E21: 1940 | F21: 13.1 | G21: 1865 | H21: 13.6 | I21: 1940 | J21: 20-23 | K21: 无 | L21: 10.7 | M21: 1495 | N21: 10.7 | O21: 1495 | P21: 11.2 | Q21: 1570 | R21: 21-23 | S21: 无 | T21: 9.4 | U21: 1345 | V21: 9.4 | W21: 1345 | X21: 9.9 | Y21: 1420 | Z21: 22-24 | AA21: 无
C22: GEG2、PDX7 | D22: 13.9 | E22: 1985 | F22: 13.4 | G22: 1910 | H22: 13.9 | I22: 1985 | J22: 20-23 | K22: 无 | L22: 11.5 | M22: 1615 | N22: 11.5 | O22: 1615 | P22: 12 | Q22: 1690 | R22: 21-23 | S22: 无 | T22: 10.2 | U22: 1465 | V22: 10.2 | W22: 1465 | X22: 10.7 | Y22: 1540 | Z22: 22-24 | AA22: 无
C23: CLT2、PBI3 | D23: 15 | E23: 2150 | F23: 14.5 | G23: 2075 | H23: 15 | I23: 2150 | J23: 25-28 | K23: 无 | L23: 11.9 | M23: 1675 | N23: 11.9 | O23: 1675 | P23: 12.4 | Q23: 1750 | R23: 27-29 | S23: 无 | T23: 10.6 | U23: 1525 | V23: 10.6 | W23: 1525 | X23: 11.1 | Y23: 1600 | Z23: 28-30 | AA23: 无
C24: ABE8、AVP1、RMN3、TEB9 | D24: 15.7 | E24: 2255 | F24: 15.2 | G24: 2180 | H24: 15.7 | I24: 2255 | J24: 25-28 | K24: 无 | L24: 13.2 | M24: 1870 | N24: 13.2 | O24: 1870 | P24: 13.7 | Q24: 1955 | R24: 27-29 | S24: 无 | T24: 11.8 | U24: 1660 | V24: 11.8 | W24: 1660 | X24: 12.3 | Y24: 1735 | Z24: 28-30 | AA24: 无 | AC24: 0.9 | AD24: 135
B25: 下单渠道 | D25: Match12-卡派 | E25: Match12-卡派-BB | F25: Match12-卡派 | G25: Match12-卡派-BB | H25: Match12-卡派 | I25: Match12-卡派-BB | L25: Match15-卡派 | M25: Match15-卡派-BB | N25: Match15-卡派 | O25: Match15-卡派-BB | P25: Match15-卡派 | Q25: Match15-卡派-BB | T25: Match20-卡派 | U25: Match20-卡派-BB | V25: Match20-卡派 | W25: Match20-卡派-BB | X25: Match20-卡派 | Y25: Match20-卡派-BB
B26: 时效赔付说明（实际开船日期第二天算起） | D26: RMB 0.5/KG/工作日，最高赔偿1.5RMB/KG，不包税渠道RMB 75/CBM/工作日，最高赔偿150RMB/CBM，无论进出口查验赔偿统一最高赔偿统一最高1/KG | L26: RMB 0.5/KG/工作日，最高赔偿1.5RMB/KG，不包税渠道RMB 75/CBM/工作日，最高赔偿150RMB/CBM进出口查验、船期延误 亚马逊删约改约、拒收不赔 | T26: RMB 0.5/KG/工作日，最高赔偿1RMB/KG，不包税渠道RMB 75/CBM/工作日，最高赔偿75RMB/CBM进出口查验、船期延误 亚马逊删约改约、拒收不赔
B27: 上架延误险 | D27: 上架延误险：+0.1RMB/KG，如签收后72小时无上架信息（check in ）,每工作日赔偿0.1/KG，最多赔偿0.5RMB/KG！ | L27: 上架延误险：+0.1RMB/KG，如签收后72小时无上架信息（check in ）,每工作日赔偿0.1/KG，最多赔偿0.5RMB/KG！ | T27: 上架延误险：+0.1RMB/KG，如签收后72小时无上架信息（check in ）,每工作日赔偿0.1/KG，最多赔偿0.5RMB/KG！

Sheet 美森美东秒送
B2: 美 琦 国 际 货 运 代 理（深圳）有 限 公 司 地址：深圳市龙岗区坂田街道坂雪岗大道4088号奥博中心6楼A609-611
B4: 美森美东秒送 | L4: 返回目录
D5: 深圳/中山/广州/义乌/苏州/汕头/厦门 | F5: 青岛 | H5: 产品说明
B6: 亚马逊仓库地址（低于50KG 需+2/KG） | D6: 包税 50KG+ | E6: 不包税 1CBM+ | F6: 包税 50KG+ | G6: 不包税 1CBM+ | H6: 航程 (开船后) | I6: 参考时效 (开船后) | J6: 时效赔付 | K6: 备注 | L6: 涨价幅度
B7: 正常派送区 | C7: TEB4、TEB3、TEB6、TEB9、XEW5、ABE8、ABE4 | D7: 15 | E7: 2345 | F7: 15.2 | G7: 2375 | H7: 17-18 | I7: 21-22 | J7: 23天 | K7: 【含税】渠道： 1、含关税和查验费； 2、体积/6000，不分泡 3、单件最低消费5KG，渠道单票低消21KG,21-49KG单价+2/KG： 【不含税】渠道： 1、不含关税，查验费和查验产生的其他费用； 2、体积/1000000，不分泡，单件最低消费5KG，单票低消1CBM 3.重货按每363KG=1CBM (产品附加费/特殊附加费等详见发货必读) 包税渠道重货优惠 1:200= -0.3/KG 1:240= -0.6/KG 1:280= -0.9/KG 1:320= -1.2/KG 1:360= -1.5/KG 1:420= -1.8/KG 1:480= -2.1/KG 1:500= -2.5/KG（封顶） | L7: 0.1 | M7: 15
C8: SWF2、AVP1、ILG1、MDT1 | D8: 15.2 | E8: 2375 | F8: 15.4 | G8: 2405 | H8: 17-18 | I8: 21-22 | J8: 23天
C9: ALB1、XLX1、MDT4 | D9: 16.2 | E9: 2575 | F9: 16.4 | G9: 2605 | H9: 17-18 | I9: 23-24 | J9: 25天
C10: RMN3 | D10: 16.8 | E10: 2665 | F10: 17 | G10: 2695 | H10: 17-18 | I10: 23-24 | J10: 25天
C11: ORF2、XLX6 | D11: 16.9 | E11: 2680 | F11: 17.1 | G11: 2710 | H11: 17-18 | I11: 23-24 | J11: 25天
C12: EWR5、EWR4、EWR6、EWR7、EWR9 | D12: 15 | E12: 2345 | F12: 15.2 | G12: 2375 | H12: 17-18 | I12: 21-22 | J12: /
C13: ACY2、TTN2、LGA9、ACY1、JFK8、JFK2 | D13: 15 | E13: 2345 | F13: 15.2 | G13: 2375 | H13: 17-18 | I13: 21-22 | J13: /
C14: ABE3、ABE5、ABE2 | D14: 15.1 | E14: 2360 | F14: 15.3 | G14: 2390 | H14: 17-18 | I14: 21-22 | J14: /
C15: AVP9、AVP3 | D15: 15.2 | E15: 2375 | F15: 15.4 | G15: 2405 | H15: 17-18 | I15: 21-22 | J15: /
C16: PHL4、PHL5、PHL6、RDG1、MDT2 | D16: 15.2 | E16: 2375 | F16: 15.4 | G16: 2405 | H16: 17-18 | I16: 23-24 | J16: /
C17: HIA1、DCA6、DCA1 | D17: 16 | E17: 2545 | F17: 16.2 | G17: 2575 | H17: 17-18 | I17: 23-24 | J17: /
C18: PHL3、PHL7、PHL1、SWF1 | D18: 15.2 | E18: 2375 | F18: 15.4 | G18: 2405 | H18: 17-18 | I18: 23-24 | J18: /
C19: HGR6、HGR2 | D19: 16.2 | E19: 2575 | F19: 16.4 | G19: 2605 | H19: 17-18 | I19: 23-24 | J19: /
... C25: CLT3、CLT4、CLT2、CLT6、DET1、DET2、TOL3 | D25: 16.9 | E25: 2680 | F25: 17.1 | G25: 2710 | H25: 17-18 | I25: 23-24 | J25: /
B26: 其他 | C26: 纽约自提（出仓费15USD/板） | D26: 14.8 | E26: 2315 | F26: 15 | G26: 2345 | H26: 17-18 | I26: 21-22 | J26: /
B27: 下单渠道 | D27: 美森美东秒送 | E27: 美森美东秒送-BB | F27: 美森美东秒送 | G27: 美森美东秒送-BB
D28: CLX-GEX服务
B29: 赔付说明 | D29: 1.5RMB/KG起赔，+0.5RMB/KG递增，赔付上限3.5RMB/KG

Sheet OA-拆送 
B2: 美 琦 国 际 货 运 代 理（深圳）有 限 公 司 地址：深圳市龙岗区坂田街道坂雪岗大道4088号奥博中心6楼A609-611
B4: OA-拆送（OA联盟）
D5: 深圳/中山/广州/义乌/苏州/汕头/厦门 | F5: 青岛 | L5: 返回目录
B6: 亚马逊仓库地址 | D6: 21KG+ （包税） | E6: 1CBM+ （不包税） | F6: 21KG+ （包税） | G6: 1CBM+ （不包税） | H6: 航程 | I6: 派送时效 | J6: 报关条件 | K6: 包税渠道重货优惠 1 :200 =-0.3/KG 1:240= -0.6/KG 1:280= -0.9/KG 1:320 =-1.2/KG 1:360= -1.5/KG 1:420 = -1.8/KG 1:480=- 2.1/KG 1:500=-2.5/KG (封顶) 1、包税渠道含关税和查验费； 2、体积/6000； 3、不分泡 4、不包税渠道不含关税和查验费；如查验按照68CBM分摊查验费 8、体积/6000； 6、不分泡，最低消费1个方 ，不足1个方按照1个方算 10、1CBM=363KG (产品附加费/特殊附加费等详见发货必读) | L6: 涨价幅度
B7: 热门仓 | C7: ONT8、LGB8、SBD1、LAX9 | D7: 6.8 | E7: 980 | F7: 7 | G7: 1010 | H7: 14-16 | I7: 24-26 | J7: 该区域内可合并报关 | L7: 0.8 | M7: 120
C8: POC1、POC2、POC3 | D8: 6.8 | E8: 980 | F8: 7 | G8: 1010 | H8: 14-16 | I8: 24-26
C9: IUSJ、IUSP、IUSQ | D9: 7.4 | E9: 1070 | F9: 7.6 | G9: 1100 | H9: 14-16 | I9: 24-28
C10: SBD2、SNA4、LGB6、LGB9、LGB4、XLX7、IUSI、IUSW、IUTI | D10: 7.4 | E10: 1070 | F10: 7.6 | G10: 1100 | H10: 14-16 | I10: 24-28
C11: LAS1、VGT2、GYR2、GYR3、LAS6、IUTE | D11: 7.5 | E11: 1085 | F11: 7.7 | G11: 1115 | H11: 14-16 | I11: 24-28
C12: SMF3、SCK4、HLI2、PSP3 | D12: 7.9 | E12: 1130 | F12: =D12+0.2 -> 8.1 | G12: =E12+30 -> 1160 | H12: 14-16 | I12: 24-26
C13: GEU2、GEU3、MIT2、TCY1、TCY2 | D13: 7.9 | E13: 1130 | F13: =D13+0.2 -> 8.1 | G13: =E13+30 -> 1160 | H13: 14-16 | I13: 24-28
C14: SCK1、SCK3、SCK8、OAK3、SJC7、SMF6、QZZ7 | D14: 8.1 | E14: 1160 | F14: =D14+0.2 -> 8.3 | G14: =E14+30 -> 1190 | H14: 14-16 | I14: 26-32
C15: FAT2、QXY8、MCC1、MCE1 | D15: 8.1 | E15: 1160 | F15: =D15+0.2 -> 8.3 | G15: =E15+30 -> 1190 | H15: 14-16 | I15: 26-32
C16: ABQ2 | D16: 8.8 | E16: 1280 | F16: =D16+0.2 -> 9 | G16: =E16+30 -> 1310 | H16: 14-16 | I16: 26-32
C17: PSC2 | D17: 9.2 | E17: 1340 | F17: 9.4 | G17: 1370 | H17: 14-16 | I17: 26-32 | L17: 0.4 | M17: 60
C18: MDW2、IND9、MQJ1、MEM1、FWA4 | D18: 9.9 | E18: 1445 | F18: 10.1 | G18: 1475 | H18: 14-16 | I18: 26-32 | J18: 该区域内可合并报关
C19: PBI3、BNA6 | D19: 10.4 | E19: 1520 | F19: 10.6 | G19: 1550 | H19: 14-16 | I19: 26-32
B20: 海外仓 | C20: 仓库自提（出仓费15USD/板） | D20: 6.6 | E20: 950 | F20: 6.8 | G20: 980 | H20: 14-16 | I20: 24-26
C21: 亚马逊仓库地址（以下地址 不足50KG 需+2） | D21: 50KG+ （包税） | E21: 1CBM+ （不包税） | F21: 50KG+ （包税） | G21: 1CBM+ （不包税） | H21: 航程 | I21: 派送时效
B22: 外州 | C22: PHX5、PHX6、PHX7、AZA4、RNO4 | D22: 8.5 | E22: 1235 | F22: 8.7 | G22: 1265 | H22: 14-16 | I22: 26-30 | J22: 该区域内可合并报关
C23: BFI3、PDX7、GEG2 | D23: 10.1 | E23: 1475 | F23: 10.3 | G23: 1505 | H23: 14-16 | I23: 27-33
C24: SLC2、DEN2、DEN8 | D24: 10.1 | E24: 1475 | F24: 10.3 | G24: 1505 | H24: 14-16 | I24: 27-33
C25: HOU8、SAT1、SAT4、OKC2、FTW1、IAH3 | D25: 10.2 | E25: 1490 | F25: 10.4 | G25: 1520 | H25: 14-16 | I25: 27-33
C26: 万邑通（USKY3、USKY5、USTX） | D26: 10.2 | E26: 1490 | F26: 10.4 | G26: 1520 | H26: 14-16 | I26: 27-33
C27: CLT2、CLT3 、RDU2、MGE3、GSO1、JAX3、CHA1、CHA2、TOL3 | D27: 11 | E27: 1610 | F27: =D27+0.2 -> 11.2 | G27: =E27+30 -> 1640 | H27: 14-16 | I27: 30-36 | J27: 该区域内可合并报关 | L27: 新增仓点
C28: ABE8、 ABE4、TEB6、TEB9、TEB4、AVP1、SWF2、PHL4 | D28: 11.1 | E28: 1625 | F28: =D28+0.2 -> 11.3 | G28: =E28+30 -> 1655 | H28: 14-16 | I28: 33-39 | L28: 新增仓点
B29: 沃尔玛 | C29: WM-LAX1、WM-LAX2、WM-LAX2N | D29: 8.1 | E29: 1175 | F29: 8.3 | G29: 1205 | H29: 14-16 | I29: 26-30
B30: 下单渠道 | D30: OA-拆送 | E30: OA-拆送-BB | F30: OA-拆送 | G30: OA-拆送-BB
B31: 预配船公司 | D31: OA联盟
B32: 注意事项 | D32: 可接受单件超22.5KG 单边超63CM 货件。 扣货费200USD/票。 （注：PSC2，BFI3,PDX7,GEG2目的港-西雅图）

Sheet OA-直送
B2: 美 琦 国 际 货 运 代 理（深圳）有 限 公 司 地址：深圳市龙岗区坂田街道坂雪岗大道4088号奥博中心6楼A609-611
B4: OA-直送包税（OA联盟）
D5: 深圳/中山/广州/义乌/苏州/汕头/厦门 | F5: 青岛 | N5: 返回目录
B6: 亚马逊仓库地址 | D6: 21KG+（包税） | E6: 1CBM+（不包税） | F6: 21KG+（包税） | G6: 1CBM+（不包税） | H6: 航程 | I6: 整体时效 | J6: 目的港口 | K6: 备注 | L6: 涨价幅度
C7: ONT8，LGB8，SBD1，LAX9 | D7: 6.6 | E7: 935 | F7: 6.8 | G7: 965 | H7: 14-16 | I7: 24-26 | J7: LA | K7: 包税渠道重货优惠 1 :200 =-0.3/KG 1:240= -0.6/KG 1:280= -0.9/KG 1:320 =-1.2/KG 1:360= -1.5/KG 1:420 = -1.8/KG 1:480=- 2.1/KG 1:500=-2.5/KG （封顶） 1、包税渠道含关税和查验费； 2、体积/6000； 3、不分泡 4、不包税渠道不含关税和查验费；如查验按照68CBM分摊查验费 8、体积/6000； 6、不分泡，最低消费1个方 ，不足1个方按照1个方算 10、1CBM=363KG (产品附加费/特殊附加费等详见发货必读) | L7: 0.8 | M7: 120
C8: POC1，POC2，POC3 | D8: 6.6 | E8: 935 | F8: 6.8 | G8: 965 | H8: 14-16 | I8: 24-26
C9: SMF3、SCK4 | D9: 7.5 | E9: 1070 | F9: 7.7 | G9: 1100 | H9: 16-19 | I9: 28-30
C10: SCK8，TCY1，TCY2 | D10: 7.6 | E10: 1085 | F10: 7.8 | G10: 1115 | H10: 14-16 | I10: 28-30
C11: PSP3 | D11: 7.3 | E11: 1040 | F11: 7.5 | G11: 1070 | H11: 16-19 | I11: 28-30
C12: MIT2 | D12: 7.3 | E12: 1040 | F12: 7.5 | G12: 1070 | H12: 14-16 | I12: 24-26
C13: LAS1,VGT2,GYR2,GYR3 | D13: 7.3 | E13: 1040 | F13: 7.5 | G13: 1070 | H13: 14-16 | I13: 24-26
C14: GEU3 ，GEU2 | D14: 7.3 | E14: 1040 | F14: 7.5 | G14: 1070 | H14: 14-16 | I14: 24-26
C15: ABQ2 | D15: 8.7 | E15: 1250 | F15: =D15+0.2 -> 8.9 | G15: =E15+30 -> 1280 | H15: 14-16 | I15: 28-32
C16: PSC2 | D16: 9.1 | E16: 1310 | F16: =D16+0.2 -> 9.3 | G16: =E16+30 -> 1340 | H16: 14-16 | I16: 28-32 | L16: 0.4 | M16: 60
C17: 下单渠道 | D17: OA-直送 | E17: OA-直送-BB | F17: OA-直送 | G17: OA-直送-BB
B18: 美东直送
C19: ABE8,TEB9 | D19: 7.5 | E19: 1070 | F19: 7.7 | G19: 1100 | H19: 28-35 | I19: 35-45 | J19: 美东
C20: AVP1 | D20: 7.6 | E20: 1085 | F20: 7.8 | G20: 1115 | H20: 28-35 | I20: 35-45
C21: 下单渠道 | D21: OA-美东直送 | E21: OA-美东直送-BB | F21: OA-美东直送 | G21: OA-美东直送-BB
B22: 预配船公司 | D22: OA联盟
B23: 注意事项 | D23: 不接受单件超22.5/KG 最长边超80CM货件 扣货费1200USD/票 请谨慎扣货

Sheet 商业|私人地址
A2: 美 琦 国 际 货 运 代 理（深圳）有 限 公 司 地址：深圳市龙岗区坂田街道坂雪岗大道4088号奥博中心6楼A609-611
B4: 深圳/中山/广州/汕头/厦门 | J4: 义乌/苏州 | P4: 青岛 | W4: 备注
A5: 美西 （90、91、92邮编） | B5: 渠道 | D5: 300KG+ （包税） | E5: 1.5CBM+ （不包税） | F5: 500KG+ （包税） | G5: 2CBM+ （不包税） | H5: 1500KG+ （包税） | I5: 6CBM+ （不包税） | J5: 300KG+ （包税） | K5: 1.5CBM+ （不包税） | L5: 500KG+ （包税） | M5: 2CBM+ （不包税） | N5: 1500KG+ （包税） | O5: 6CBM+ （不包税） | P5: 300KG+ （包税） | Q5: 1.5CBM+ （不包税） | R5: 500KG+ （包税） | S5: 2CBM+ （不包税） | T5: 1500KG+ （包税） | U5: 6CBM+ （不包税） | V5: 参考时效 （开船后） | W5: 重货优惠 1 :200 =-0.3/KG 1:240= -0.6/KG 1:280= -0.9/KG 1:320 =-1.2/KG 1:360= -1.5/KG 1:420 = -1.8/KG 1:480=- 2.1/KG 1:500=-2.5/KG （封顶） 1、包税渠道含关税和查验费； 2、体积/6000； 3、不分泡 4、不包税渠道不含关税和查验费；如查验按照68CBM分摊查验费 5、体积/6000； 6、不分泡，最低消费1个方 ，不足1个方按照1个方算 7、1CBM=363KG (产品附加费/特殊附加费等详见发货必读) | X5: 涨价幅度
B6: Match12 （500KG起） | D6: / | E6: / | F6: 11.5 | G6: 1625 | H6: 11.2 | I6: 1580 | J6: / | K6: / | L6: 11 | M6: 1550 | N6: 10.7 | O6: 1505 | P6: / | Q6: / | R6: 11.7 | S6: 1655 | T6: 11.4 | U6: 1610 | V6: 13-15 | X6: 0.1 | Y6: 15
B7: Match15 （500KG起） | D7: / | E7: / | F7: 9.1 | G7: 1255 | H7: 8.7 | I7: 1195 | J7: / | K7: / | L7: 9.1 | M7: 1255 | N7: 8.7 | O7: 1195 | P7: / | Q7: / | R7: 9.3 | S7: 1285 | T7: 8.9 | U7: 1225 | V7: 15-17 | X7: 0.5 | Y7: 75
B8: Match20 （500KG起） | D8: / | E8: / | F8: 8 | G8: 1160 | H8: 7.8 | I8: 1130 | J8: 8.5 | K8: 1235 | L8: 8 | M8: 1160 | N8: 7.8 | O8: 1130 | P8: 8.7 | Q8: 1265 | R8: 8.2 | S8: 1190 | T8: 8 | U8: 1160 | V8: 19-21 | X8: 0.8 | Y8: 120
B9: OA-拆送 （300KG起） | D9: 7.8 | E9: 1130 | F9: 7.3 | G9: 1055 | H9: 7.1 | I9: 1025 | J9: 7.8 | K9: 1130 | L9: 7.3 | M9: 1055 | N9: 7.1 | O9: 1025 | P9: 8 | Q9: 1160 | R9: 7.5 | S9: 1085 | T9: 7.3 | U9: 1055 | V9: 24-26 | X9: 0.8 | Y9: 120
A11: 美东 （07、08邮编） | B11: 美东普快专线 07邮编（500KG起） | D11: / | E11: / | F11: 9.5 | G11: 1380 | H11: 9.1 | I11: 1320 | J11: / | K11: / | L11: 9.5 | M11: 1380 | N11: 9.1 | O11: 1320 | P11: / | Q11: / | R11: 9.7 | S11: 1410 | T11: 9.3 | U11: 1350 | V11: 40-45 | X11: 0.8 | Y11: 120
B12: 美东普快专线 08邮编（500KG起） | D12: / | E12: / | F12: 8.5 | G12: 1230 | H12: 8.1 | I12: 1170 | J12: / | K12: / | L12: 8.5 | M12: 1230 | N12: 8.1 | O12: 1170 | P12: / | Q12: / | R12: 8.7 | S12: 1260 | T12: 8.3 | U12: 1200 | V12: 40-45 | X12: 0.8 | Y12: 120
B13: 美东极速快车 07邮编（500KG起） | D13: / | E13: / | F13: 15.4 | G13: 1755 | H13: 15 | I13: 1695 | J13: / | K13: / | L13: 15.4 | M13: 1755 | N13: 15 | O13: 1695 | P13: / | Q13: / | R13: 15.6 | S13: 1785 | T13: 15.2 | U13: 1725 | V13: 30-32 | X13: 2.3 | Y13: 345
B14: 美东极速快车 08邮编（500KG起） | D14: / | E14: / | F14: 14.4 | G14: 1605 | H14: 14 | I14: 1545 | J14: / | K14: / | L14: 14.4 | M14: 1605 | N14: 14 | O14: 1545 | P14: / | Q14: / | R14: 14.6 | S14: 1635 | T14: 14.2 | U14: 1575 | V14: 30-32 | X14: 2.3 | Y14: 345
B15: 美森美东秒送 07邮编（500KG起） | D15: / | E15: / | F15: 17.7 | G15: 2800 | H15: 17.3 | I15: 2740 | J15: / | K15: / | L15: 17.2 | M15: 2725 | N15: 16.8 | O15: 2665 | P15: / | Q15: / | R15: 17.9 | S15: 2830 | T15: 17.5 | U15: 2770 | V15: 21-22 | X15: 0.1 | Y15: 15
B16: 美森美东秒送 08邮编（500KG起） | D16: / | E16: / | F16: 16.7 | G16: 2650 | H16: 16.3 | I16: 2540 | J16: / | K16: / | L16: 16.2 | M16: 2575 | N16: 15.8 | O16: 2465 | P16: / | Q16: / | R16: 16.9 | S16: 2680 | T16: 16.5 | U16: 2570 | V16: 21-22 | X16: 0.1 | Y16: 15
A18: 芝加哥 （60邮编） | B18: 芝加哥海铁快车 （500KG起） | D18: / | E18: / | F18: 10.6 | G18: 1535 | H18: 10.2 | I18: 1475 | J18: / | K18: / | L18: 10.6 | M18: 1535 | N18: 10.2 | O18: 1475 | P18: / | Q18: / | R18: 10.8 | S18: 1565 | T18: 10.4 | U18: 1505 | V18: 38-45 | X18: 0.6 | Y18: 90
B19: 芝加哥海铁联运 （500KG起） | D19: / | E19: / | F19: 9.4 | G19: 1355 | H19: 9 | I19: 1295 | J19: / | K19: / | L19: 9.4 | M19: 1355 | N19: 9 | O19: 1295 | P19: / | Q19: / | R19: 9.6 | S19: 1385 | T19: 9.2 | U19: 1325 | V19: 38-45 | X19: 0.8 | Y19: 120
D20: 备注 | E20: ----------------------不满低消，按照低消金额计算！-----------------------
B22: 美西参考地址 （不在范围内请单询） | E22: 城市 | G22: 邮编 | K22: 城市 | M22: 邮编 | Q22: 城市 | S22: 邮编
E23: Los Angeles | G23: 9002X | K23: LA PUENTE | M23: 9174X | Q23: WEST COVINA | S23: 9179X
E24: WHITTIER | G24: 9060X | K24: ROWLAND HEIGHTS | M24: 9174X | Q24: ALHAMNRA | S24: 9180X
E25: MONTEBELLO | G25: 9064X | K25: HACIENDA HEIGHTS | M25: 9174X | Q25: COLTON | S25: 9232X
E26: NORWALK | G26: 9065X | K26: CITY OF INDUSTRY | M26: 9174X | Q26: FONTANA | S26: 9233X
E27: SANTA FE SPRINGS | G27: 9067X | K27: MONTEREY PARK | M27: 9175X | Q27: RIALTO | S27: 9237X
E28: CERRITOS | G28: 9070X | K28: ONTARIO | M28: 9176X | Q28: SAN BERNARDINO | S28: 9240X
E29: ARCADIA | G29: 9100X | K29: DIAMOND BAR | M29: 9176X | Q29: RIVERSIDE | S29: 9250X
E30: PASADENA | G30: 9110X | K30: POMONA | M30: 9176X | Q30: ANAHEIM | S30: 9280X
E31: AZUSA | G31: 9170X | K31: ROSEMEAD | M31: 9177X | Q31: BREA | S31: 9282X
E32: CHINO | G32: 9171X | K32: SAN DIMAS | M32: 9177X | Q32: FULLERTON | S32: 9283X
E33: RANCHO CUCAMONGA | G33: 9173X | K33: WALNUT | M33: 9178X | Q33: CORONA | S33: 9288X
E34: EL MONTE | G34: 9173X | K34: TEMPLE CITY | M34: 9178X | Q34: YORBA LINDA | S34: 9288X
B36: 美东参考地址 （不在范围内请单询） | E36: 城市 | G36: 邮编 | K36: 城市 | M36: 邮编 | Q36: 城市 | S36: 邮编
E37: CARTERET | G37: 0700X | K37: PERTH AMBOY | M37: 0886X | Q37: South Amboy | S37: 0887X
E38: NEWARK | G38: 0710X | K38: NEW BRUNSWICK | M38: 0890X | Q38: Union | S38: 0708X
E39: ATLANTIC HIGHLANDS | G39: 0771X | K39: HILLSBOROUGH | M39: 0884X | Q39: Parlin | S39: 0885X
E40: Woodbridge Township | G40: 0709X | K40: MONROE TOWNSHIP | M40: 0883X | Q40: New Providence | S40: 0797X
E41: Roselle | G41: 0720X | K41: BURLINGTON | M41: 0801X | Q41: Millburn | S41: 0704X
E42: PORT READING | G42: 0706X | K42: BORDENTOWN | M42: 0850X | Q42: Bound Brook | S42: 0880X
E43: LINDEN | G43: 0703X | K43: EDISON | M43: 0881X | Q43: Rutherford | S43: 0707X
E44: Cranford | G44: 0701X | K44: LAKEWOOD | M44: 0870X | Q44: Wallington | S44: 0705X
B46: 芝加哥参考地址 （不在范围内请单询） | E46: 城市 | G46: 邮编 | K46: 城市 | M46: 邮编
E47: Joliet | G47: 6043X | K47: Westmont | M47: 6055X
E48: Mokena | G48: 6044X | K48: Morgan Park | M48: 6064X
E49: Frankfort | G49: 6042X | K49: Lisle | M49: 6053X
E50: Channahon | G50: 6041X | K50: Downers Grove | M50: 6051X
E51: Orland Park | G51: 6046X | K51: Hinsdale | M51: 6052X
E52: Woodridge | G52: 6051X | K52: Oak Lawn | M52: 6045X
E53: Darien | G53: 6056X | K53: Glen Ellyn | M53: 6013X
E54: Naperville | G54: 6054X
B56: 说明 | D56: 额外费用（如产生） | F56: 金额 | H56: 单位 | J56: 备注
D57: 卸货等候费 | F57: 85 | H57: 每小时 | J57: 免费等待一小时
D58: 跑空费 | F58: 派送费100% | H58: 每次 | J58: 客户自行承担
D59: 更改地址派送 | F59: 50 | H59: 每次 | J59: 更改一次$50,不含改派后派送费
D60: 更改自提（出库费） | F60: 10 | H60: 每板 | J60: 原运费不退
D61: 尾板费 | F61: 65 | H61: 每次 | J61: 无卸货平台需收取

Sheet MT-专线
B2: 美 琦 国 际 货 运 代 理（深圳）有 限 公 司 地址：深圳市龙岗区坂田街道坂雪岗大道4088号奥博中心6楼A609-611
B4: MT-专线
D5: 深圳/中山/广州/义乌/苏州/汕头/厦门 | F5: 青岛 | H5: 产品说明 | M5: 返回目录
B6: 亚马逊仓库地址 | D6: 21KG+ （包税） | E6: 1CBM+ （不包税） | F6: 21KG+ （包税） | G6: 1CBM+ （不包税） | H6: 航程 | I6: 派送时效 | J6: 报关条件 | K6: 下单渠道 | L6: 包税渠道重货优惠 1 :200 =-0.3/KG 1:240= -0.6/KG 1:280= -0.9/KG 1:320 =-1.2/KG 1:360= -1.5/KG 1:420 = -1.8/KG 1:480=- 2.1/KG 1:500=-2.5/KG (封顶) 1、包税渠道含关税和查验费； 2、体积/6000； 3、不分泡 4、不包税渠道不含关税和查验费；如查验按照68CBM分摊查验费 8、体积/6000； 6、不分泡，最低消费1个方 ，不足1个方按照1个方算 10、1CBM=363KG (产品附加费/特殊附加费等详见发货必读) | M6: 涨价幅度
B7: 热门仓 | C7: ONT8、LAX9、LGB8、SBD1、POC1、POC3、POC2 | D7: 6.5 | E7: 920 | F7: 6.7 | G7: 950 | H7: 18-20 | I7: 30-35 | J7: 该区域内可合并报关 | K7: MT-专线-美西 | M7: 0.8 | N7: 120
C8: GEU3 、GEU2 、MIT2、GYR2、GYR3、LAS1、VGT2 | D8: 7.2 | E8: 1025 | F8: 7.4 | G8: 1055 | H8: 18-20 | I8: 32-37 | J8: 可合并报关
C9: SCK8 | D9: 7.4 | E9: 1055 | F9: 7.6 | G9: 1085 | H9: 18-20 | I9: 32-37
C10: SMF3、SCK4、TCY1 、TCY2、MCC1 、HLI2 、QXY8 | D10: 7.4 | E10: 1055 | F10: 7.6 | G10: 1085 | H10: 18-20 | I10: 32-37 | J10: 该区域内可合并报关
C11: ABE8、TEB4、TEB6、TEB9、XEW5 | D11: 7.4 | E11: 1055 | F11: 7.6 | G11: 1085 | H11: 35-43 | I11: 52-58 | J11: 该区域内可合并报关 | K11: MT-专线-纽约
C12: AVP1 | D12: 7.5 | E12: 1070 | F12: 7.7 | G12: 1100 | H12: 35-43 | I12: 52-58
C13: ABE4、HEA2、SWF1、SWF2 | D13: 7.6 | E13: 1085 | F13: 7.8 | G13: 1115 | H13: 35-43 | I13: 52-58
C14: MDT4、PHL4、PHL6 | D14: 7.6 | E14: 1085 | F14: 7.8 | G14: 1115 | H14: 35-43 | I14: 52-58
C15: RMN3、ORF2、MQJ1 | D15: 7.6 | E15: 1085 | F15: 7.8 | G15: 1115 | H15: 35-43 | I15: 52-58 | J15: 该区域内可合并报关 | M15: 新增
C16: SAV3、JAX3、GSP1、MGE3、XLX6、CLT2、CLT3 | D16: 8.2 | E16: 1170 | F16: 8.4 | G16: 1200 | H16: 35-43 | I16: 52-58 | J16: 该区域内可合并报关 | K16: MT-专线-萨凡纳
C17: GSO1、MGE1、IUSR | D17: 8.4 | E17: 1200 | F17: 8.6 | G17: 1230 | H17: 35-43 | I17: 52-58
C18: BNA6、XCH2、IND9、MEM1、RDU2 | D18: 8.4 | E18: 1200 | F18: 8.6 | G18: 1230 | H18: 35-43 | I18: 52-58 | J18: 该区域内可合并报关 | M18: 新增
B19: 预配船公司 | D19: 2M/THE联盟
B20: 注意事项 | D20: 可接受单件超22.5KG 单边超80CM 货件。 不接受扣货。

Sheet OA-奥克兰
B2: 美 琦 国 际 货 运 代 理（深圳）有 限 公 司 地址：深圳市龙岗区坂田街道坂雪岗大道4088号奥博中心6楼A609-611
B4: OA-奥克兰
D5: 深圳/中山/广州/义乌/苏州/汕头/厦门 | F5: 青岛 | K5: 返回目录
B6: 亚马逊仓库地址 | D6: 21KG+ （包税） | E6: 1CBM+ （不包税） | F6: 21KG+ （包税） | G6: 1CBM+ （不包税） | H6: 航程 | I6: 派送时效 | J6: 包税渠道重货优惠 1 :200 =-0.3/KG 1:240= -0.6/KG 1:280= -0.9/KG 1:320 =-1.2/KG 1:360= -1.5/KG 1:420 = -1.8/KG 1:480=- 2.1/KG 1:500=-2.5/KG （封顶） 1、包税渠道含关税和查验费； 2、体积/6000； 3、不分泡 4、不包税渠道不含关税和查验费；如查验按照68CBM分摊查验费 8、体积/6000； 6、不分泡，最低消费1个方 ，不足1个方按照1个方算 10、1CBM=363KG (产品附加费/特殊附加费等详见发货必读) | K6: 涨价幅度
B7: 热门仓 | C7: SMF3、SCK4、QXY5、TCY1、TCY2 | D7: 5.2 | E7: 725 | F7: 5.6 | G7: 785 | H7: 16-19 | I7: 28-30
C8: SCK1、SCK3、SJC7、OAK3、SCK8 | D8: 5.2 | E8: 725 | F8: 5.5 | G8: 770 | H8: 16-19 | I8: 28-30
C9: MCE1、MCC1、FAT2、SMF6、SMF7、HLI2、QXY8 | D9: 5.4 | E9: 755 | F9: 5.8 | G9: 815 | H9: 16-19 | I9: 28-30
C10: RNO4 | D10: 5.8 | E10: 830 | F10: 6 | G10: 860 | H10: 16-19 | I10: 28-30
B11: 仓库自提（出仓费15USD/板） | D11: 5.2 | E11: 725 | F11: 5.6 | G11: 785 | H11: 16-19 | I11: 28-30
B12: 93 邮编海外仓（ 最低消费500KG 或 2个CBM） | D12: 7 | E12: 995 | F12: 7.2 | G12: 1025 | H12: 16-19 | I12: 28-30
B13: 93 邮编海外仓（ 1500KG+ 或 6个CBM+） | D13: 6.6 | E13: 935 | F13: 6.8 | G13: 965 | H13: 16-19 | I13: 28-30
B14: 94-95邮编海外仓（ 最低消费500KG 或 2个CBM） | D14: 6.6 | E14: 935 | F14: 6.8 | G14: 965 | H14: 16-19 | I14: 28-30
B15: 94-95邮编海外仓（ 1500KG+ 或 6个CBM+） | D15: 6.2 | E15: 875 | F15: 6.4 | G15: 905 | H15: 16-19 | I15: 28-30
B16: 下单渠道 | D16: OA-奥克兰卡派 | E16: OA-奥克兰卡派-BB | F16: OA-奥克兰卡派 | G16: OA-奥克兰卡派-BB
B17: 预配船公司 | D17: OA联盟
B18: 注意事项 | D18: 卸货港：洛杉矶 扣货费200USD/票。

Sheet TH特惠
B1: 美琦国际货运代理（深圳）有限公司
B2: 地址：深圳市龙岗区象角塘村二路2-4号锦绣华城A区4栋309号-310号
B3: T H (特惠）专线-暂停 | J3: 返回目录
B4: 亚马逊仓库地址 | C4: 21KG+（特惠） | D4: 1CBM+（特惠） | E4: 卸货港 | F4: 备注 | G4: 航程（不保仓保柜） | H4: 参考时效（开船后） | I4: 重货优惠
B5: ONT8、LGB8、SBD1 | C5: 3.58 | D5: 530 | E5: 洛杉矶 | F5: 1、包税渠道含关税和查验费；不包税渠道不含关税和查验费；如查验按照68CBM分摊查验费 2、体积/6000； 3、不分泡，不包税渠道最低消费1个方 ，不足1个方按照1个方算 4、单件最长边尺寸不超63CM,重不超22.5KG | G5: 16-20Day | H5: 30-38Day | I5: 包税渠道重货优惠 1 :200 =-0.3/KG 1:240= -0.5/KG 1:280= -0.8/KG 1:320 =-1.1/KG 1:360= -1.4/KG 1:420 = -1.7/KG 1:480=- 2/KG 1:500=-2.5/KG （封顶）
B6: LAS1、GRY2、GYR3、MIT2 | C6: 4.28 | D6: 700 | E6: 洛杉矶 | G6: 16-20Day | H6: 30-38Day
B7: GEU3 | C7: 4.28 | D7: 700 | E7: 洛杉矶 | G7: 16-20Day | H7: 30-38Day
B8: LGB4、LGB6、LGB9、LGB7 | C8: 4.38 | D8: 720 | E8: 洛杉矶 | G8: 16-20Day | H8: 30-38Day
B9: ONT6、ONT9、KRB1、SBD2、XLX7 | C9: 4.38 | D9: 720 | E9: 洛杉矶 | G9: 16-20Day | H9: 30-38Day
B10: 下单渠道： | C10: TH(特惠)专线-包税 | D10: TH(特惠)专线-不包税 | E10: 预配船司 | F10: OA联盟,THE联盟,2M联盟,SML,WHL 统配

Sheet 海派渠道
B2: 美 琦 国 际 货 运 代 理（深圳）有 限 公 司 地址：深圳市龙岗区坂田街道坂雪岗大道4088号奥博中心6楼A609-611
D4: Match12-海派（CLX、MAX-GES服务) | M4: Match15-海派(ZIM带车架、EXX统配） | V4: 返回目录
B5: 分区 | D5: 深圳/中山/广州/汕头/厦门 | F5: 义乌/苏州 | H5: 青岛 | M5: 深圳/中山/广州/汕头/厦门 | O5: 义乌/苏州 | Q5: 青岛
B6: 亚马逊仓库地址 | D6: 12KG+（包税） | E6: 100KG+（包税） | F6: 12KG+（包税） | G6: 100KG+（包税） | H6: 12KG+（包税） | I6: 100KG+（包税） | J6: 参考提取时效（开船后） | K6: 理赔提取时效（开船后） | L6: 重货优惠 1 :200 =-0.3/KG 1:240= -0.6/KG 1:280= -0.9/KG 1:320 =-1.2/KG 1:360= -1.5/KG 1:420 = -1.8/KG 1:480=- 2.1/KG 1:500=-2.5/KG （封顶） | M6: 12KG+（包税） | N6: 100KG+（包税） | O6: 12KG+（包税） | P6: 100KG+（包税） | Q6: 12KG+（包税） | R6: 100KG+（包税） | S6: 参考提取时效（开船后） | T6: 理赔提取时效（开船后） | U6: 重货优惠 1 :200 =-0.3/KG 1:240= -0.6/KG 1:280= -0.9/KG 1:320 =-1.2/KG 1:360= -1.5/KG 1:420 = -1.8/KG 1:480=- 2.1/KG 1:500=-2.5/KG （封顶） | V6: Match12 | W6: 0.1
B7: 美西（邮编 8 9） | D7: 16.2 | E7: 13.2 | F7: 15.7 | G7: 12.7 | H7: 16.2 | I7: 13.2 | J7: 14-15 | K7: 16天 | M7: 14.6 | N7: 11.6 | O7: 14.1 | P7: 11.1 | Q7: 14.6 | R7: 11.6 | S7: 16-17 | T7: 18天 | V7: Match15 | W7: 0.5
B8: 美西二区（邮编 （97 98 99）） | D8: 16.7 | E8: 13.7 | F8: 16.2 | G8: 13.2 | H8: 16.7 | I8: 13.7 | J8: 14-15 | K8: 16天 | M8: 15.1 | N8: 12.1 | O8: 14.6 | P8: 11.6 | Q8: 15.1 | R8: 12.1 | S8: 16-17 | T8: 18天
B9: 美中（邮编 5 6 7） | D9: 17.7 | E9: 14.7 | F9: 17.2 | G9: 14.2 | H9: 17.7 | I9: 14.7 | J9: 14-15 | K9: 16天 | M9: 16.1 | N9: 13.1 | O9: 15.6 | P9: 12.6 | Q9: 16.1 | R9: 13.1 | S9: 16-17 | T9: 18天
B10: 美东（邮编 0 1 2 3 4） | D10: 19.1 | E10: 16.1 | F10: 18.6 | G10: 15.6 | H10: 19.1 | I10: 16.1 | J10: 14-15 | K10: 16天 | M10: 17.5 | N10: 14.5 | O10: 17 | P10: 14 | Q10: 17.5 | R10: 14.5 | S10: 16-17 | T10: 18天
B11: 下单渠道 | D11: Match12-海派 | F11: Match12-海派 | H11: Match12-海派 | M11: Match15-海派 | O11: Match15-海派 | Q11: Match15-海派
B12: 预配船公司 | D12: MATSON | M12: MATSON /ZIM/EXX
B13: 理赔说明 | D13: RMB 0.5/KG/工作日，最高赔偿1.5RMB/KG， 无论进出口查验赔偿统一最高赔偿统一最高1/KG | M13: RMB 0.5/KG/工作日，最高赔偿1.5RMB/KG，(除周末以外的公众假期，以及海关查验、船期延误 码头罢工、亚马逊关仓等不可抗力因素除外)
D14: Match20-海派 (长荣定提 合德快提） | M14: OA专线-海派（OA联盟） | V14: 涨价幅度
B15: 分区 | D15: 深圳/中山/广州/汕头/厦门 | F15: 义乌/苏州 | H15: 青岛 | M15: 深圳/中山/广州/汕头/厦门 | O15: 义乌/苏州 | Q15: 青岛 | V15: Match20 | W15: 0.8
B16: 亚马逊仓库地址 | D16: 12KG+（包税） | E16: 100KG+（包税） | F16: 12KG+（包税） | G16: 100KG+（包税） | H16: 12KG+（包税） | I16: 100KG+（包税） | J16: 参考提取时效（开船后） | K16: 理赔提取时效（开船后） | L16: 重货优惠 1 :200 =-0.3/KG 1:240= -0.6/KG 1:280= -0.9/KG 1:320 =-1.2/KG 1:360= -1.5/KG 1:420 = -1.8/KG 1:480=- 2.1/KG 1:500=-2.5/KG （封顶） | M16: 12KG+（包税） | N16: 100KG+（包税） | O16: 12KG+（包税） | P16: 100KG+（包税） | Q16: 12KG+（包税） | R16: 100KG+（包税） | S16: 参考提取时效（开船后） | T16: 理赔提取时效（开船后） | U16: 重货优惠 1 :200 =-0.3/KG 1:240= -0.6/KG 1:280= -0.9/KG 1:320 =-1.2/KG 1:360= -1.5/KG 1:420 = -1.8/KG 1:480=- 2.1/KG 1:500=-2.5/KG （封顶） | V16: OA专线-海派 | W16: 0.8
B17: 美西（邮编 8 9） | D17: 12.7 | E17: 9.7 | F17: 12.7 | G17: 9.7 | H17: 13.2 | I17: 10.2 | J17: 21-22 | K17: 23天 | M17: 12.5 | N17: 9.5 | O17: 12.5 | P17: 9.5 | Q17: 12.7 | R17: 9.7 | S17: 26-28天 | T17: 无
B18: 美西二区（邮编 （97 98 99）） | D18: 13.2 | E18: 10.2 | F18: 13.2 | G18: 10.2 | H18: 13.7 | I18: 10.7 | J18: 21-22 | K18: 23天 | M18: 13 | N18: 10 | O18: 13 | P18: 10 | Q18: 13.2 | R18: 10.2 | S18: 26-28天 | T18: 无
B19: 美中（邮编 5 6 7） | D19: 14.2 | E19: 11.2 | F19: 14.2 | G19: 11.2 | H19: 14.7 | I19: 11.7 | J19: 21-22 | K19: 23天 | M19: 14 | N19: 11 | O19: 14 | P19: 11 | Q19: 14.2 | R19: 11.2 | S19: 26-28天 | T19: 无
B20: 美东（邮编 0 1 2 3 4） | D20: 15.6 | E20: 12.6 | F20: 15.6 | G20: 12.6 | H20: 16.1 | I20: 13.1 | J20: 21-22 | K20: 23天 | M20: 15.4 | N20: 12.4 | O20: 15.4 | P20: 12.4 | Q20: 15.6 | R20: 12.6 | S20: 26-28天 | T20: 无
B21: 下单渠道 | D21: Match20-海派 | F21: Match20-海派 | H21: Match20-海派 | M21: OA-拆送海派 | O21: OA-拆送海派 | Q21: OA-拆送海派
B22: 预配船公司 | D22: 长荣定提 合德快提 | M22: OA联盟
B23: 理赔说明 | D23: RMB 0.5/KG/工作日，最高赔偿1RMB/KG，(除周末以外的公众假期，以及海关查验、船期延误 码头罢工、亚马逊关仓等不可抗力因素除外) | M23: 无

Sheet 纽约
B2: 美 琦 国 际 货 运 代 理（深圳）有 限 公 司 地址：深圳市龙岗区坂田街道坂雪岗大道4088号奥博中心6楼A609-611
D4: 美东极速快车(ZIM带车架） | K4: 美东普快专线（OA) | R4: 返回目录
D5: 深圳/中山/广州/义乌/苏州/汕头/厦门 | F5: 青岛 | H5: 产品说明 | K5: 深圳/中山/广州/义乌/苏州/汕头/厦门 | M5: 青岛 | O5: 产品说明
B6: 亚马逊仓库地址（低于50KG 需+2/KG） | D6: 包税50KG+ | E6: 不包税1CBM+ | F6: 包税50KG+ | G6: 不包税1CBM+ | H6: 航程 (开船后) | I6: 参考时效 (开船后) | J6: 时效赔付 | K6: 包税50KG+ | L6: 不包税1CBM+ | M6: 包税50KG+ | N6: 不包税1CBM+ | O6: 航程 (开船后) | P6: 参考时效 (开船后) | Q6: 备注 | R6: 涨价幅度
B7: 正常派送区 | C7: TEB4、TEB3、TEB6、TEB9、XEW5、ABE8、ABE4 | D7: 13.6 | E7: 1980 | F7: 13.8 | G7: 2010 | H7: 21-22 | I7: 26-28 | J7: 35天 | K7: 7.7 | L7: 1095 | M7: 7.9 | N7: 1125 | O7: 30-38 | P7: 40-45 | Q7: 【含税】渠道： 1、含关税和查验费； 2、体积/6000，不分泡 3、单票低于50KG 默认+2/KG 【不含税】渠道： 1、不含关税，查验费和查验产生的其他费用； 2、体积/1000000，不分泡，单件最低消费5KG，单票低消1CBM 3.重货按每363KG=1CBM (产品附加费/特殊附加费等详见发货必读) 包税渠道重货优惠 1:200= -0.3/KG 1:240= -0.6/KG 1:280= -0.9/KG 1:320= -1.2/KG 1:360= -1.5/KG 1:420= -1.8/KG 1:480=- 2.1/KG 1:500=-2.5/KG（封顶） | R7: 美东极速快车 | S7: 2.3 | T7: 345
C8: SWF2、AVP1、ILG1、MDT1 | D8: 13.9 | E8: 2025 | F8: 14.1 | G8: 2055 | H8: 21-22 | I8: 29-30 | J8: 37天 | K8: 8.2 | L8: 1170 | M8: 8.4 | N8: 1200 | O8: 30-38 | P8: 40-45 | R8: 美东普快专线 | S8: 0.8 | T8: 120
C9: ALB1、XLX1、MDT4 | D9: 14.1 | E9: 2055 | F9: 14.3 | G9: 2085 | H9: 21-22 | I9: 30-32 | J9: 37天 | K9: 8.7 | L9: 1245 | M9: 8.9 | N9: 1275 | O9: 30-38 | P9: 40-45
C10: RMN3 | D10: 14.1 | E10: 2055 | F10: 14.3 | G10: 2085 | H10: 21-22 | I10: 30-32 | J10: 38天 | K10: 8.4 | L10: 1200 | M10: 8.6 | N10: 1230 | O10: 30-38 | P10: 40-45
C11: ORF2、XLX6 | D11: 14.5 | E11: 2115 | F11: 14.7 | G11: 2145 | H11: 21-22 | I11: 32-36 | J11: 40天 | K11: 9.1 | L11: 1305 | M11: 9.3 | N11: 1335 | O11: 30-38 | P11: 43-48
C12: EWR5、EWR4、EWR6、EWR7、EWR9 | D12: 13.6 | E12: 1980 | F12: 13.8 | G12: 2010 | H12: 21-22 | I12: 26-28 | J12: 无 | K12: 7.7 | L12: 1095 | M12: 7.9 | N12: 1125 | O12: 30-38 | P12: 40-45
C13: ACY2、TTN2、LGA9、ACY1、JFK8、JFK2 | D13: 13.6 | E13: 1980 | F13: 13.8 | G13: 2010 | H13: 21-22 | I13: 26-28 | J13: 无 | K13: 7.7 | L13: 1095 | M13: 7.9 | N13: 1125 | O13: 30-38 | P13: 40-45
C14: ABE3、ABE5、ABE2 | D14: 13.6 | E14: 1980 | F14: 13.8 | G14: 2010 | H14: 21-22 | I14: 26-28 | J14: 无 | K14: 7.7 | L14: 1095 | M14: 7.9 | N14: 1125 | O14: 30-38 | P14: 40-45
C15: AVP9、AVP3 | D15: 13.6 | E15: 1980 | F15: 13.8 | G15: 2010 | H15: 21-22 | I15: 26-28 | J15: 无 | K15: 7.7 | L15: 1095 | M15: 7.9 | N15: 1125 | O15: 30-38 | P15: 40-45
C16: PHL4、PHL5、PHL6、RDG1、MDT2 | D16: 13.6 | E16: 1980 | F16: 13.8 | G16: 2010 | H16: 21-22 | I16: 29-30 | J16: 无 | K16: 7.7 | L16: 1095 | M16: 7.9 | N16: 1125 | O16: 30-38 | P16: 40-45
C17: HIA1、DCA6、DCA1 | D17: 13.9 | E17: 2025 | F17: 14.1 | G17: 2055 | H17: 21-22 | I17: 29-30 | J17: 无 | K17: 8.2 | L17: 1170 | M17: 8.4 | N17: 1200 | O17: 30-38 | P17: 40-45
C18: SWF1、PHL3、PHL7、PHL1、HEA2 | D18: 13.9 | E18: 2025 | F18: 14.1 | G18: 2055 | H18: 21-22 | I18: 29-30 | J18: 无 | K18: 8.2 | L18: 1170 | M18: 8.4 | N18: 1200 | O18: 30-38 | P18: 40-45
C19: HGR6、HGR2 | D19: 14.1 | E19: 2055 | F19: 14.3 | G19: 2085 | H19: 21-22 | I19: 30-32 | J19: 无 | K19: 8.7 | L19: 1245 | M19: 8.9 | N19: 1275 | O19: 30-38 | P19: 40-45
C20: IUST、IUSL | D20: 14.1 | E20: 2055 | F20: 14.3 | G20: 2085 | H20: 21-22 | I20: 30-32 | J20: 无 | K20: 8.7 | L20: 1245 | M20: 8.9 | N20: 1275 | O20: 30-38 | P20: 40-45
... C33: TPA1、TPA2、MCO2、TPA3、TPA6、MCO1 | D33: 16.5 | E33: 2400 | F33: 16.7 | G33: 2430 | H33: 21-22 | I33: 32-36 | J33: 无 | K33: 11.1 | L33: 1605 | M33: 11.3 | N33: 1635 | O33: 30-38 | P33: 45-52
B34: 其他 | C34: 纽约自提（出仓费15USD/板） | D34: 13.4 | E34: 1950 | F34: 13.6 | G34: 1980 | H34: 21-22 | I34: 26-28 | J34: 无 | K34: 7.5 | L34: 1080 | M34: 7.7 | N34: 1110 | O34: 30-38 | P34: 40-45
B35: 沃尔玛 低消费300KG 2CBM+ | D35: 300KG+ | E35: 2CBM+ (不包税) | F35: 300KG+ | G35: 2CBM+ (不包税) | H35: 航程 (开船后) | I35: 参考时效 (开船后) | J35: 时效赔付 | K35: 300KG+ | L35: 2CBM+ (不包税) | M35: 300KG+ | N35: 2CBM+ (不包税) | O35: 航程 (开船后) | P35: 参考时效 (开船后)
B36: 沃尔玛仓库 | C36: WMT-NJ3，WM-PHL5S | D36: 14.1 | E36: 2055 | F36: 14.3 | G36: 2085 | H36: 21-22 | I36: 32-36 | J36: 无 | K36: 8.4 | L36: 1215 | M36: 8.6 | N36: 1245 | O36: 30-38 | P36: 45-52
C37: WNT-IND2，WNT-IND1，WNT-BNA1s | D37: 15.9 | E37: 2310 | F37: 16.1 | G37: 2340 | H37: 21-22 | I37: 32-36 | J37: 无 | K37: 10.1 | L37: 1470 | M37: 10.3 | N37: 1500 | O37: 30-38 | P37: 45-52
C38: WMT-ATL1，MWT-ATL2，WMT-ATL3 | D38: 16 | E38: 2325 | F38: 16.2 | G38: 2355 | H38: 21-22 | I38: 32-36 | J38: 无 | K38: 10.4 | L38: 1515 | M38: 10.6 | N38: 1545 | O38: 30-38 | P38: 45-52
C39: WMT-MCO1，WMT-KS1 | D39: 17.2 | E39: 2505 | F39: 17.4 | G39: 2535 | H39: 21-22 | I39: 32-36 | J39: 无 | K39: 11.7 | L39: 1710 | M39: 11.9 | N39: 1740 | O39: 30-38 | P39: 45-52
B40: Wayfair | C40: 48 Station Road Cranbury, NJ 08512 | D40: 14.3 | E40: 2085 | F40: 14.5 | G40: 2115 | H40: 21-22 | I40: 32-36 | J40: 无 | K40: 8.9 | L40: 1290 | M40: 9.1 | N40: 1320 | O40: 30-38 | P40: 45-52
C41: 万邑通仓41048（最低消费800KG+ 或 5CBM+） | D41: 17 | E41: 2475 | F41: 17.2 | G41: 2505 | H41: 21-22 | I41: 32-36 | J41: 无 | K41: 11.4 | L41: 1665 | M41: 11.6 | N41: 1695 | O41: 30-38 | P41: 45-52
B42: 谷仓 | C42: 2号-08518（此目的地最低消费300KG) | D42: 13.7 | E42: 1995 | F42: 13.9 | G42: 2025 | H42: 21-22 | I42: 32-36 | J42: 无 | K42: 8 | L42: 1155 | M42: 8.2 | N42: 1185 | O42: 30-38 | P42: 45-52
C43: 5号-08831（此目的地最低消费300KG) | D43: 13.7 | E43: 1995 | F43: 13.9 | G43: 2025 | H43: 21-22 | I43: 32-36 | J43: 无 | K43: 8 | L43: 1155 | M43: 8.2 | N43: 1185 | O43: 30-38 | P43: 45-52
C44: 8号-07836（此目的地最低消费300KG) | D44: 13.7 | E44: 1995 | F44: 13.9 | G44: 2025 | H44: 21-22 | I44: 32-36 | J44: 无 | K44: 8 | L44: 1155 | M44: 8.2 | N44: 1185 | O44: 30-38 | P44: 45-52
C45: 11号-08505（此目的地最低消费300KG) | D45: 13.7 | E45: 1995 | F45: 13.9 | G45: 2025 | H45: 21-22 | I45: 32-36 | J45: 无 | K45: 8 | L45: 1155 | M45: 8.2 | N45: 1185 | O45: 30-38 | P45: 45-52
C46: 15号-08036（此目的地最低消费300KG) | D46: 13.7 | E46: 1995 | F46: 13.9 | G46: 2025 | H46: 21-22 | I46: 32-36 | J46: 无 | K46: 8 | L46: 1155 | M46: 8.2 | N46: 1185 | O46: 30-38 | P46: 45-52
C47: 16号-08057（此目的地最低消费300KG) | D47: 13.7 | E47: 1995 | F47: 13.9 | G47: 2025 | H47: 21-22 | I47: 32-36 | J47: 无 | K47: 8 | L47: 1155 | M47: 8.2 | N47: 1185 | O47: 30-38 | P47: 45-52
C48: 18号-08016（此目的地最低消费300KG) | D48: 13.7 | E48: 1995 | F48: 13.9 | G48: 2025 | H48: 21-22 | I48: 32-36 | J48: 无 | K48: 8 | L48: 1155 | M48: 8.2 | N48: 1185 | O48: 30-38 | P48: 45-52
B49: 其他 | C49: 美国新泽西1仓：1000 High Street，PERTH AMBOY，NJ 08861 （此目的地最低消费300KG) | D49: 13.7 | E49: 1995 | F49: 13.9 | G49: 2025 | H49: 21-22 | I49: 32-36 | J49: 无 | K49: 8 | L49: 1155 | M49: 8.2 | N49: 1185 | O49: 30-38 | P49: 45-52
C50: 易达云美东10仓：480 Elizabeth Ave，Somerset NJ 08873 （此目的地最低消费300KG) | D50: 13.7 | E50: 1995 | F50: 13.9 | G50: 2025 | H50: 21-22 | I50: 32-36 | J50: 无 | K50: 8 | L50: 1155 | M50: 8.2 | N50: 1185 | O50: 30-38 | P50: 45-52
C51: 4PX美东2号仓：4PX Express CO.,LTD 1401 w front st, Florence, NJ 08518（此目的地最低消费300KG) | D51: 13.8 | E51: 2010 | F51: 14 | G51: 2040 | H51: 21-22 | I51: 32-36 | J51: 无 | K51: 8.1 | L51: 1170 | M51: 8.3 | N51: 1200 | O51: 30-38 | P51: 45-52
C52: 美东11号仓：1175 Florence Columbus Road UNITB（A12-A35), Bordentown,NJ,08505（此目的地最低消费300KG) | D52: 13.8 | E52: 2010 | F52: 14 | G52: 2040 | H52: 21-22 | I52: 32-36 | J52: 无 | K52: 8.1 | L52: 1170 | M52: 8.3 | N52: 1200 | O52: 30-38 | P52: 45-52
B53: 下单渠道 | D53: 美东极速快车 | E53: 美东极速快车-BB | F53: 美东极速快车 | G53: 美东极速快车-BB | K53: 美东普快专线 | L53: 美东普快专线-BB | M53: 美东普快专线 | N53: 美东普快专线-BB
B54: 赔付说明 | D54: 离港后第二天算起，超过承诺时效后 含税渠道:赔偿RMB0.5/KG/工作日，最高1.5RMB/KG； 不含税渠道:赔偿RMB100/CBM/工作日，最高赔偿300RMB/CBM 船期延误、到港延误、进出口查验、码头/火车站延误、亚马逊问题不赔(删约/不放约/拒收/关仓等) | K54: 无时效赔付

Sheet 芝加哥
B2: 美 琦 国 际 货 运 代 理（深圳）有 限 公 司 地址：深圳市龙岗区坂田街道坂雪岗大道4088号奥博中心6楼A609-611
C4: 芝加哥海铁快车 | J4: 芝加哥海铁联运
C5: 深圳/中山/广州/义乌/苏州/汕头/厦门 | E5: 青岛 | J5: 深圳/中山/广州/义乌/苏州/汕头/厦门 | L5: 青岛 | R5: 返回目录
B6: 亚马逊仓库地址 | C6: 50KG+ （包税） | D6: 1CBM+ (不包税) | E6: 50KG+ （包税） | F6: 1CBM+ (不包税) | G6: 航程 (开船后) | H6: 参考时效(开船后) | I6: 理赔时效 | J6: 50KG+ （包税） | K6: 1CBM+ (不包税) | L6: 50KG+ （包税） | M6: 1CBM+ (不包税) | N6: 航程 (开船后) | O6: 参考时效(开船后) | P6: 理赔时效 | Q6: 重货优惠 | R6: 涨价幅度
B7: MDW4，MDW8、MDW2、MDW6、MDW9、ORD2、IGQ2 | C7: 10.3 | D7: 1490 | E7: 10.5 | F7: 1520 | G7: 21-24 | H7: 28-32 | I7: 33天 | J7: 9.1 | K7: 1310 | L7: 9.3 | M7: 1340 | N7: 32-35 | O7: 38-45 | P7: 无 | Q7: 包税渠道重货优惠 重货优惠 1 :200 =-0.3/KG 1:240= -0.6/KG 1:280= -0.9/KG 1:320 =-1.2/KG 1:360= -1.5/KG 1:420 = -1.8/KG 1:480=- 2.1/KG 1:500=-2.5/KG （封顶） | R7: 芝加哥海铁快车 | S7: 0.6 | T7: 90
B8: RFD4，RFD2，RFD3 | C8: 10.7 | D8: 1550 | E8: 10.9 | F8: 1580 | G8: 21-24 | H8: 30-34 | I8: 35天 | J8: 9.5 | K8: 1370 | L8: 9.7 | M8: 1400 | N8: 32-35 | O8: 38-45 | P8: 无 | R8: 芝加哥海铁联运 | S8: 0.8 | T8: 120
B9: IND4、IND5、IND9、MQJ1、STL4、FWA4、JVL1、STL6、MQJ2、MKE1 | C9: 11.1 | D9: 1610 | E9: 11.3 | F9: 1640 | G9: 21-24 | H9: 28-32 | I9: 无 | J9: 9.9 | K9: 1430 | L9: 10.1 | M9: 1460 | N9: 32-35 | O9: 38-45 | P9: 无
B10: CMH1，CMH2，CMH3，CVG1 | C10: 11.4 | D10: 1655 | E10: 11.6 | F10: 1685 | G10: 21-24 | H10: 30-34 | I10: 无 | J10: 10.2 | K10: 1475 | L10: 10.4 | M10: 1505 | N10: 32-35 | O10: 38-45 | P10: 无
B11: DET1，DET2，TOL3 | C11: 11.4 | D11: 1655 | E11: 11.6 | F11: 1685 | G11: 21-24 | H11: 30-34 | I11: 无 | J11: 10.2 | K11: 1475 | L11: 10.4 | M11: 1505 | N11: 32-35 | O11: 38-45 | P11: 无
B12: SDF4 | C12: 11.9 | D12: 1730 | E12: 12.1 | F12: 1760 | G12: 21-24 | H12: 30-34 | I12: 无 | J12: 10.7 | K12: 1550 | L12: 10.9 | M12: 1580 | N12: 32-35 | O12: 38-45 | P12: 无
B13: FOE1、MKC4、STL3、ICT2、MEM1、MEM6 | C13: 12.4 | D13: 1805 | E13: 12.6 | F13: 1835 | G13: 21-24 | H13: 30-34 | I13: 无 | J13: 11.2 | K13: 1625 | L13: 11.4 | M13: 1655 | N13: 32-35 | O13: 38-45 | P13: 无
B14: WM-IND1、WM-IND2、WM-IND3、WM-IND2T | C14: 11.1 | D14: 1610 | E14: 11.3 | F14: 1640 | G14: 21-24 | H14: 28-32 | I14: 无 | J14: 9.9 | K14: 1430 | L14: 10.1 | M14: 1460 | N14: 32-35 | O14: 38-45 | P14: 无
B15: WM-CVG1n、WM-MCI1n、WM-KY1、WM-KS1 | C15: 12.4 | D15: 1805 | E15: 12.6 | F15: 1835 | G15: 21-24 | H15: 30-34 | I15: 无 | J15: 11.2 | K15: 1625 | L15: 11.4 | M15: 1655 | N15: 32-35 | O15: 38-45 | P15: 无
B16: 芝加哥自提（出仓费15USD/板） | C16: 9.8 | D16: 1415 | E16: 10 | F16: 1445 | G16: 21-24 | H16: 28-32 | I16: 无 | J16: 8.6 | K16: 1235 | L16: 8.8 | M16: 1265 | N16: 32-35 | O16: 38-45 | P16: 无
B17: 万邑通仓41048（最低消费800KG+ 或 5CBM+） | C17: 11.1 | D17: 1610 | E17: 11.3 | F17: 1640 | G17: 21-24 | H17: 30-34 | I17: 35天 | J17: 9.9 | K17: 1430 | L17: 10.1 | M17: 1460 | N17: 32-35 | O17: 38-45 | P17: 无
B18: 下单渠道 | C18: 芝加哥海铁快车-卡派 | D18: 芝加哥海铁快车-卡派-BB | E18: 芝加哥海铁快车-卡派 | F18: 芝加哥海铁快车-卡派-BB | J18: 芝加哥海铁联运-卡派 | K18: 芝加哥海铁联运-卡派-BB | L18: 芝加哥海铁联运-卡派 | M18: 芝加哥海铁联运-卡派-BB
B19: 预配船公司：COSCO/EMC/OOCL | C19: 预计航程： | D19: 23天 | E19: 理赔说明：从离港后第二天算起，超过承诺时效，含税渠道:赔偿RMB0.5/KG/工作日，最高1RMB/KG；不含税渠道:赔偿RMB80/CBM/工作日，最高赔偿180RMB/CBM。船期延误、进出口查验、亚马逊问题不赔(删约/不放约/拒收/关仓等) | J19: 无

Sheet 休斯敦
B2: 美 琦 国 际 货 运 代 理（深圳）有 限 公 司 地址：深圳市龙岗区坂田街道坂雪岗大道4088号奥博中心6楼A609-611
B4: 休斯顿专线
C5: 深圳/中山/广州/义乌/苏州/汕头/厦门 | E5: 青岛 | K5: 返回目录
B6: 亚马逊仓库地址 | C6: 50KG+ （包税） | D6: 1CBM+ （不包税） | E6: 50KG+ （包税） | F6: 1CBM+ （不包税） | G6: 航程 （开船后） | H6: 参考时效（开船后） | I6: 理赔时效 | J6: 重货优惠 | K6: 涨价幅度
B7: HOU8、HOU1、HOU3、HOU7 | C7: 8.3 | D7: 1190 | E7: 8.5 | F7: 1220 | G7: 32-35 | H7: 38-45 | I7: 无 | J7: 包税渠道重货优惠 重货优惠 1 :200 =-0.3/KG 1:240= -0.6/KG 1:280= -0.9/KG 1:320 =-1.2/KG 1:360= -1.5/KG 1:420 = -1.8/KG 1:480=- 2.1/KG 1:500=-2.5/KG （封顶） | K7: 0.8 | L7: 120
B8: FTW1、FTW5、FTW2、FTW9 | C8: 8.4 | D8: 1205 | E8: 8.6 | F8: 1235 | G8: 32-35 | H8: 38-45 | I8: 无
B9: DFW5、DFW6、DFW7、DFW9 | C9: 8.5 | D9: 1220 | E9: 8.7 | F9: 1250 | G9: 32-35 | H9: 38-45 | I9: 无
B10: IAH3、SAT1、SAT4 | C10: 8.6 | D10: 1235 | E10: 8.8 | F10: 1265 | G10: 32-35 | H10: 38-45 | I10: 无
B11: LFT1、LIT2、OKC2、FOE1 | C11: 9.1 | D11: 1310 | E11: 9.3 | F11: 1340 | G11: 32-35 | H11: 38-45 | I11: 无
B12: MEM6 | C12: 9.4 | D12: 1355 | E12: 9.6 | F12: 1385 | G12: 32-35 | H12: 38-45 | I12: 无
B13: AMA1、ICT2 | C13: 9.8 | D13: 1415 | E13: 10 | F13: 1445 | G13: 32-35 | H13: 38-45 | I13: 无
B14: Walmart DFW5s（800KG或5CBM起） | C14: 单询 | D14: 单询 | E14: 单询 | F14: 单询 | G14: 32-35 | H14: 38-45 | I14: 无
B15: Walmart DFW2n（800KG或5CBM起） | C15: 单询 | D15: 单询 | E15: 单询 | F15: 单询 | G15: 32-35 | H15: 38-45 | I15: 无
B16: 休斯敦自提（出仓费15USD/板） | C16: 7.8 | D16: 1115 | E16: 8 | F16: 1145 | G16: 32-35 | H16: 38-45 | I16: 无
B17: 77邮编海外仓（最低消费500KG+ 或 3CBM+） | C17: 9.8 | D17: 1415 | E17: 10 | F17: 1445 | G17: 32-35 | H17: 38-45 | I17: 无
B18: 77邮编海外仓（1500KG+ 或6个CBM+） | C18: 9.4 | D18: 1355 | E18: 9.6 | F18: 1385 | G18: 32-35 | H18: 38-45 | I18: 无
B19: 下单渠道 | C19: 休斯顿专线-卡派 | D19: 休斯顿专线-卡派-BB | E19: 休斯顿专线-卡派 | F19: 休斯顿专线-卡派-BB
B20: 预配船公司：COSCO/EMC/OOCL

Sheet 萨瓦纳
B2: 美 琦 国 际 货 运 代 理（深圳）有 限 公 司 地址：深圳市龙岗区坂田街道坂雪岗大道4088号奥博中心6楼A609-611
B4: 萨瓦纳专线（普船卡派）
C5: 深圳/中山/广州/义乌/苏州/汕头/厦门 | E5: 青岛 | L5: 返回目录
B6: 亚马逊仓库地址 | C6: 50KG+ （包税） | D6: 1CBM+ （不包税） | E6: 50KG+ （包税） | F6: 1CBM+ （不包税） | G6: 航程（开船后） | H6: 参考时效（开船后） | I6: 理赔时效 | J6: 备注 | K6: 重货优惠 | L6: 涨价幅度
B7: ATL8、 JAX3、XLX6 | C7: 8.3 | D7: 1190 | E7: 8.5 | F7: 1220 | G7: 30-36 | H7: 40-45 | I7: 无 | J7: 采用OA联盟 海铁萨瓦纳 航程时效20-24天 七截二开 1、含关税和查验费； 2、体积/6000；单票低于50KG 默认+2/KG 3、不分泡，单件最低消费5KG 不含税注意事项： 1、不含关税，查验费和查验产生的其他费用；如因客户资料、产品问题，需承担因此产生的所有仓租、柜租、罚金、销毁费等，恶意瞒报的还需承担进口商损失费1500美金； 2、不分泡， | K7: 包税渠道重货优惠 重货优惠 1 :200 =-0.3/KG 1:240= -0.6/KG 1:280= -0.9/KG 1:320 =-1.2/KG 1:360= -1.5/KG 1:420 = -1.8/KG 1:480=- 2.1/KG 1:500=-2.5/KG （封顶） | L7: 0.8 | M7: 120
B8: CLT2、CLT3、MGE3、MGE1、GSP1、GSO1、ATL2 | C8: 8.5 | D8: 1220 | E8: 8.7 | F8: 1250 | G8: 30-36 | H8: 40-45 | I8: 无
B9: RDU2、CLT4、CLT6、RYY2 | C9: 8.5 | D9: 1220 | E9: 8.7 | F9: 1250 | G9: 30-36 | H9: 40-45 | I9: 无
B10: TPA2、 TPA3、TPA6、PBI2、PBI3、MCO2、XPB2 | C10: 8.5 | D10: 1220 | E10: 8.7 | F10: 1250 | G10: 30-36 | H10: 40-45 | I10: 无
B11: BNA2、BNA6、MEM8、MEM1、HSV1、HSV2 | C11: 9.9 | D11: 1430 | E11: 10.1 | F11: 1460 | G11: 30-36 | H11: 40-45 | I11: 无
B12: WM-ATL1、WM-ATL2n、WM-ATL3 | C12: 9.4 | D12: 1355 | E12: 9.6 | F12: 1385 | G12: 30-36 | H12: 40-45 | I12: 无
B13: WM-MCO1、WM-BNA1S | C13: 9.9 | D13: 1430 | E13: 10.1 | F13: 1460 | G13: 30-36 | H13: 40-45 | I13: 无
B14: 谷仓美南1号(GA30168)/低消300KG起 | C14: 10.1 | D14: 1460 | E14: 10.3 | F14: 1490 | G14: 30-36 | H14: 40-45 | I14: 无
B15: 谷仓美南2号(GA 30122)/低消300KG起 | C15: 10.1 | D15: 1460 | E15: 10.3 | F15: 1490 | G15: 30-36 | H15: 40-45 | I15: 无
B16: TIKTOK GA仓(GA30518)/低消300KG起 | C16: 10.1 | D16: 1460 | E16: 10.3 | F16: 1490 | G16: 30-36 | H16: 40-45 | I16: 无
B17: 西邮WPGA1(GA 30046)/低消300KG起 | C17: 10.1 | D17: 1460 | E17: 10.3 | F17: 1490 | G17: 30-36 | H17: 40-45 | I17: 无
B18: 西邮WPGA4(GA31405)/低消300KG起 | C18: 10.1 | D18: 1460 | E18: 10.3 | F18: 1490 | G18: 30-36 | H18: 40-45 | I18: 无
B19: 易达云仓GA（30071 ）/低消300KG起 | C19: 10.1 | D19: 1460 | E19: 10.3 | F19: 1490 | G19: 30-36 | H19: 40-45 | I19: 无
B20: 萨瓦纳自提（出仓费15USD/板） | C20: 8.3 | D20: 1190 | E20: 8.5 | F20: 1220 | G20: 30-36 | H20: 40-45 | I20: 无
B21: 下单渠道 | C21: 萨瓦纳专线-卡派 | D21: 萨瓦纳专线-卡派-BB | E21: 萨瓦纳专线-卡派 | F21: 萨瓦纳专线-卡派-BB
B22: 预配船公司：COSCO/EMC/OOCL | C22: 预计航程： | D22: 30-36Day

Sheet 加拿大
B2: 美 琦 国 际 货 运 代 理（深圳）有 限 公 司 地址：深圳市龙岗区坂田街道坂雪岗大道4088号奥博中心6楼A609-611
B4: 加 拿 大 直 航
D5: 深圳/中山/广州 | F5: 义乌/苏州 | H5: 汕头/厦门 | J5: 青岛 | O5: 返回目录
B6: 亚马逊仓库地址 | D6: 包税100KG+ | E6: 不包税1CBM+ | F6: 包税100KG+ | G6: 不包税1CBM+ | H6: 包税100KG+ | I6: 不包税1CBM+ | J6: 包税100KG+ | K6: 不包税1CBM+ | L6: 参考时效 | M6: 下单渠道（义乌渠道开开头+Y） | N6: 包税渠道重货优惠 重货优惠 1 :200 =-0.3/KG 1:240= -0.6/KG 1:280= -0.9/KG 1:320 =-1.2/KG 1:360= -1.5/KG 1:420 = -1.8/KG 1:480=- 2.1/KG 1:500=-2.5/KG （封顶） | O6: 涨价幅度
B7: 温哥华 | C7: YVR1、YVR2、YVR3、YVR4、YXX2 | D7: 9.7 | E7: 1355 | F7: 10.2 | G7: 1430 | H7: 10 | I7: 1400 | J7: 10.7 | K7: 1505 | L7: 35-40 | M7: 加拿大直航-温哥华/加拿大直航-温哥华-BB | O7: 0.8 | P7: 120
B8: 卡尔加里 | C8: YYC1、YYC4、YYC6、YEG1、YEG2 | D8: 7.9 | E8: 1085 | F8: 8.4 | G8: 1160 | H8: 8.2 | I8: 1130 | J8: 8.9 | K8: 1235 | L8: 35-40 | M8: 加拿大直航-卡尔加里/加拿大直航-卡尔加里-BB
B9: 多伦多 | C9: YYZ1、YYZ3、YYZ4、YYZ6 | D9: 8 | E9: 1100 | F9: 8.5 | G9: 1175 | H9: 8.3 | I9: 1145 | J9: 9 | K9: 1250 | L9: 33-38 | M9: 加拿大直航-多伦多/加拿大直航-多伦多-BB
C10: YYZ7、YYZ9、YXU1、YHM1、YOO1、XYY1、XYY4 | D10: 8 | E10: 1100 | F10: 8.5 | G10: 1175 | H10: 8.3 | I10: 1145 | J10: 9 | K10: 1250 | L10: 33-38
C11: YOW1、YOW2、YOW3、YGK1、YUL2 | D11: 8.5 | E11: 1175 | F11: 9 | G11: 1250 | H11: 8.8 | I11: 1220 | J11: 9.5 | K11: 1325 | L11: 33-38
C12: 商业地址 | D12: 8.9 | E12: 1235 | F12: 9.4 | G12: 1310 | H12: 9.2 | I12: 1280 | J12: 9.9 | K12: 1385 | L12: 33-38
C13: 商业地址：Agincourt、Newmarket、Aurora、North York、Bolton、Oak Ridges、Brampton、Oakville、Concord、Richmond Hill、Downsview、Scarborough、Don Mills、Schomberg、East York、Whitchurch Stouffville、Etobicoke、Thornhill、Gormley、Toronto、King、Unionville、Maple、Weston、Markham、Willowdale、Mississauga、Woodbridge、Halton Hills、Caledon、Vaughan （无卸货平台+150USD/票），所有商业/私人地址8CBM/1000KG起收
B14: 预配船司 | C14: OA联盟
B15: 含税渠道 | C15: 1、含关税和查验费； 2、加拿大直航包税低于100KG按照21-49单价+1/KG 50-99KG单价+0.5/KG 不足1CBM按1CBM收费，单件不足5KG按5KG计费，财务默认出账单； 3、计费重：体积重和实重取大者，体积重=长cm*宽cm*高cm/6000； 4、超长/超重附加：120cm＜外箱单边长度≤150cm，包税+RMB1.2/KG,不包税+228/CBM；150cm＜外箱单边长度≤200cm、包税+RMB1.8/KG,不包税+285/CBM；外箱单边长度＞2m单询； 30KG＜单件实重＜70KG，包税+RMB10/件。（适用于商业/私人/亚马逊可接收地址，另亚马逊收货尺寸/重量限制请客户出货前自行确认/咨询我司客服同事）
B16: 附加费 | C16: 以下产品+1/KG：空气净化器、汽车配件、耳机、电动剃须刀、地垫\地毯、玩具（包含儿童玩具，但不包括婴幼儿玩具)、纺/竹/木制品
C17: 以下产品+2/KG： 眼镜类（潜水眼镜、滑雪眼镜、游泳镜、3D眼镜），纺织品（衣服、鞋、袜子、包包等穿着类） 高价值产品（摄像头、扫地机/扫地机器人、吸尘器、安防/监控设备、车载显示器DVD、导航仪/行车记录仪、相机及相机配件、显微镜、投影仪、音箱、手机屏、对讲机、机顶、云台、路由器、显示屏雕刻机、打印机、手表）皮革产品、橡胶衣服、蜡烛......
B18: 不含税渠道 | C18: 1、不含关税、如遇查验费实销； 2、计费重=长cm*宽cm*高cm/1000000，不分泡； 3、如因客户资料\产品问题，需承担因此产生的所有仓租、柜租、罚金、销毁费等，恶意瞒报的还需承担进口商损失费2000美金；
B19: 拒收产品 | C19: 1、手机、智能手环、假发、汽车诊断仪、望远镜、硒鼓、化妆品（面膜等），3岁以下儿童产品、婴儿玩具、母婴用品，二类医疗产品（牙刷、牙线、冲牙器、吸奶器等）、禁塑令产品（一次性纸杯等）、成人用品； 2、液体、纯电池、食品、粉末、移动电源、电子烟、制毒用品、医疗用品、仿牌商品、化工产品、美国/加拿大反倾销产品等。如发现冲货罚款RMB2000/票。 3、纯太阳能板、筋膜枪等按摩类产品 4、反倾销产品：查看网站： https://www.cbsa-asfc.gc.ca/sima-lmsi/mif-mev/menu-eng.html

Sheet 美转加
C2: 美 琦 国 际 货 运 代 理（深圳）有 限 公 司 地址：深圳市龙岗区坂田街道坂雪岗大道4088号奥博中心6楼A609-611
C4: 美 转 加----暂停
C5: 渠道: | E5: 美转加 闪送线（包税） | M5: 美转加 速快线（包税） | T5: 美转加 普快线（包税） | AD5: 返回目录
E6: 深圳/中山/义乌/苏州/广州 | G6: 汕头/厦门 | I6: 青岛 | M6: 深圳/中山/义乌/苏州/广州 | O6: 汕头/厦门 | Q6: 青岛 | T6: 深圳/中山/义乌/苏州/广州 | V6: 汕头/厦门 | X6: 青岛
C7: 亚马逊仓库地址 | E7: 50KG+ | F7: 100KG+ | G7: 50KG+ | H7: 100KG+ | I7: 50KG+ | J7: 100KG+ | K7: 参考时效（自然日） | L7: 理赔时效（自然日） | M7: 50KG+ | N7: 100KG+ | O7: 50KG+ | P7: 100KG+ | Q7: 50KG+ | R7: 100KG+ | S7: 参考时效 | T7: 50KG+ | U7: 100KG+ | V7: 50KG+ | W7: 100KG+ | X7: 50KG+ | Y7: 100KG+ | Z7: 参考时效 | AA7: 备注
C8: 温哥华 | D8: YVR1、YVR2、YVR3、YVR4、YXX2 | E8: - | F8: - | G8: - | H8: - | I8: - | J8: - | K8: 22-25 | L8: 29天 | M8: - | N8: - | O8: - | P8: - | Q8: - | R8: - | S8: 30-35 | T8: - | U8: - | V8: - | W8: - | X8: - | Y8: - | Z8: 35-40 | AA8: 包税渠道重货优惠 重货优惠 1 :200 =-0.3/KG 1:240= -0.6/KG 1:280= -0.9/KG 1:320 =-1.2/KG 1:360= -1.5/KG 1:420 = -1.8/KG 1:480=- 2.1/KG 1:500=-2.5/KG （封顶）
C9: 卡尔加里 | D9: YYC1、YYC4、YYC6、YEG1、YEG2 | E9: - | F9: - | G9: - | H9: - | I9: - | J9: - | K9: 22-25 | L9: 29天 | M9: - | N9: - | O9: - | P9: - | Q9: - | R9: - | S9: 30-35 | T9: - | U9: - | V9: - | W9: - | X9: - | Y9: - | Z9: 35-40
D10: YYZ1、YYZ3、YYZ4、YYZ6 | E10: - | F10: - | G10: - | H10: - | I10: - | J10: - | K10: 22-25 | L10: 29天 | M10: - | N10: - | O10: - | P10: - | Q10: - | R10: - | S10: 30-35 | T10: - | U10: - | V10: - | W10: - | X10: - | Y10: - | Z10: 35-40
C11: 多伦多 | D11: YYZ7、YYZ9、YXU1、YHM1、YOO1、XYY1 | E11: - | F11: - | G11: - | H11: - | I11: - | J11: - | K11: 22-25 | L11: 29天 | M11: - | N11: - | O11: - | P11: - | Q11: - | R11: - | S11: 30-35 | T11: - | U11: - | V11: - | W11: - | X11: - | Y11: - | Z11: 35-40
D12: YOW1、YOW2、YOW3、YGK1、YUL2 | E12: - | F12: - | G12: - | H12: - | I12: - | J12: - | K12: 22-25 | L12: 29天 | M12: - | N12: - | O12: - | P12: - | Q12: - | R12: - | S12: 30-35 | T12: - | U12: - | V12: - | W12: - | X12: - | Y12: - | Z12: 35-40
D13: 商业地址 | E13: - | F13: - | G13: - | H13: - | I13: - | J13: - | K13: - | L13: - | M13: - | N13: - | O13: - | P13: - | Q13: - | R13: - | S13: - | T13: - | U13: - | V13: - | W13: - | Z13: -
C14: 下单渠道 | E14: 美转加 闪送线（包税） | F14: 美转加 闪送线（包税） | G14: 美转加 闪送线（包税） | H14: 美转加 闪送线（包税） | I14: 美转加 闪送线（包税） | J14: 美转加 闪送线（包税） | K14: - | M14: 美转加 速快线 | N14: 美转加 速快线 | O14: 美转加 速快线 | P14: 美转加 速快线 | Q14: 美转加 速快线 | R14: 美转加 速快线 | T14: 美转加 普快线 | U14: 美转加 普快线 | V14: 美转加 普快线 | W14: 美转加 普快线 | X14: 美转加 普快线 | Y14: 美转加 普快线
C15: 预配船司 | E15: MATSON-CLX | M15: ZIM | T15: OA 为主
C16: 赔付标准 | D16: 开船后拆过理赔时效（POD签收时间为准，亚马逊爆仓除外） 按照每天赔偿0.5元/KG，直到最高赔偿RMB3/KG （国内查验，目的国节日延误、海关查验、天灾等不可抗力除外） | M16: 无 | T16: 无
C18: 含税渠道 | D18: 1、含关税和查验费； 2、美转加包税低于50KG的按照按50KG单价+2RMB/KG,单件不足5KG按5KG计费，财务默认出账单； 3、计费重：体积重和实重取大者，体积重=长cm*宽cm*高cm/6000； 4、超长/超重附加：120cm＜外箱单边长度≤150cm，包税+RMB1.2/KG,不包税+228/CBM；150cm＜外箱单边长度≤200cm、包税+RMB1.8/KG,不包税+285/CBM；外箱单边长度＞2m单询； 30KG＜单件实重＜70KG，包税+RMB10/件。（适用于商业/私人/亚马逊可接收地址，另亚马逊收货尺寸/重量限制请客户出货前自行确认/咨询我司客服同事）
C19: 附加费 | D19: 以下产品+1/KG：空气净化器、汽车配件、耳机、电动剃须刀、地垫\地毯、玩具（包含儿童玩具，但不包括婴幼儿玩具)、纺/竹/木制品
D20: 以下产品+2/KG： 眼镜类（潜水眼镜、滑雪眼镜、游泳镜、3D眼镜），纺织品（衣服、鞋、袜子、包包等穿着类） 高价值产品（摄像头、扫地机/扫地机器人、吸尘器、安防/监控设备、车载显示器DVD、导航仪/行车记录仪、相机及相机配件、显微镜、投影仪、音箱、手机屏、对讲机、机顶、云台、路由器、显示屏雕刻机、打印机、手表）皮革产品、橡胶衣服、蜡烛......
C21: 不含税渠道 | D21: 1、不含关税、如遇查验费实销； 2、计费重=长cm*宽cm*高cm/1000000，不分泡； 3、如因客户资料\产品问题，需承担因此产生的所有仓租、柜租、罚金、销毁费等，恶意瞒报的还需承担进口商损失费2000美金；
C22: 拒收产品 | D22: 1、手机、智能手环、假发、汽车诊断仪、望远镜、硒鼓、化妆品（面膜等），3岁以下儿童产品、婴儿玩具、母婴用品，二类医疗产品（牙刷、牙线、冲牙器、吸奶器等）、禁塑令产品（一次性纸杯等）、成人用品； 2、液体、纯电池、食品、粉末、移动电源、电子烟、制毒用品、医疗用品、仿牌商品、化工产品、美国/加拿大反倾销产品等。如发现冲货罚款RMB2000/票。 3、纯太阳能板、筋膜枪等按摩类产品 4、反倾销产品：查看网站： https://www.cbsa-asfc.gc.ca/sima-lmsi/mif-mev/menu-eng.html

Sheet 暂存渠道
B2: 美 琦 国 际 货 运 代 理（深圳）有 限 公 司 地址：深圳市龙岗区坂田街道坂雪岗大道4088号奥博中心6楼A609-611
B4: 产品 | C4: 服务项目 | D4: 单价 | E4: 币制 | F4: 单位 | G4: 备注说明 | H4: 返回目录 | I4: 涨价幅度
B5: 头程到美琦美西海外仓 | C5: OA-拆送暂存 | D5: 6.6 | E5: RMB | F5: 每KG | G5: 最低消费150KG，船期附加费参考TK拆送 | I5: 0.8 | J5: 120
C6: OA-拆送暂存-BB | D6: 950 | E6: RMB | F6: 每CBM | G6: 最低消费1CBM，船期附加费参考TK拆送
C7: Match20暂存 | D7: 7.3 | E7: RMB | F7: 每KG | G7: 最低消费150KG，船期附加费参考Match20
C8: Match20暂存-BB | D8: 1030 | E8: RMB | F8: 每CBM | G8: 最低消费1CBM，船期附加费参考Match20
B9: 产品 | C9: 服务项目 | D9: 单价 | E9: 币制 | F9: 单位 | G9: 备注说明
B10: 库内操作 | C10: 贴标费 | D10: 0.5 | E10: USD | F10: 每张 | G10: 包含SKU/FBA/快递等标签；托盘标则是1美金/张
C11: 拆、封箱费 | D11: 1.5 | E11: USD | F11: 每箱 | G11: 贴SKU标时产生，包括破损箱封胶带
C12: 按箱号贴FBA标签 | D12: 0.5 | E12: USD | F12: 每张 | G12: 额外加收，与贴标费叠加收取，例如1号箱贴FBAXXX001
C13: 覆盖标签 | D13: 0.5 | E13: USD | F13: 每张 | G13: 额外加收，与贴标费叠加收取，需要覆盖原标签
C14: 分票费 | D14: 0.5 | E14: USD | F14: 每箱 | G14: 如有需要，例如1票货中分出几件发走，最低消费20美金，最高消费50美金
C15: 理货费 | D15: 1 | E15: USD | F15: 每箱 | G15: 从1票货中分出指定唛头的几件发走，例如一票20件，需要挑5件出来，理货费：20*1
C16: 自提费 | D16: 15 | E16: USD | F16: 每托 | G16: 客户自打单提供快递面单；亚马逊卡派自提
C17: 出仓费 | D17: 20 | E17: USD | F17: 每托 | G17: 固定收取
C18: 仓储费（免仓30天，从到仓当天开始算） | D18: 0 | E18: USD | F18: CBM/每天 | G18: 1-30天
D19: 2 | E19: USD | F19: CBM/每天 | G19: 31-90天
D20: 3 | E20: USD | F20: CBM/每天 | G20: 90天-180天（180天以上默认销毁，销毁费20美金/箱）
B21: KD-快递派送 | C21: 派送费(邮编8.9开头) | D21: 4 | E21: RMB | F21: 每KG | G21: 单件最低消费12KG，单票最低消费780RMB；
C22: 派送费(邮编7开头) | D22: 5 | E22: RMB | F22: 每KG
C23: 派送费(邮编4.5.6.开头) | D23: 6 | E23: RMB | F23: 每KG
C24: 派送费(邮编0.1.2.3开头) | D24: 7 | E24: RMB | F24: 每KG
B25: KC-卡车派送 | C25: ONT8，LGB8，LAX9，SBD1 | D25: 268 | E25: RMB | F25: 每板 | G25: 1.7CBM/板，尾板进位制，时效：出仓后当天递送
C26: SMF3、LAS1，GYR3、GYR2、SCK4、LAS6 | D26: 568 | E26: RMB | F26: 每板 | G26: 1.7CBM/板，尾板进位制，时效：出仓后1-2天递送
C27: OAK3、SJC7、SCK1、VGT2 | D27: 580 | E27: RMB | F27: 每板 | G27: 1.7CBM/板，尾板进位制，时效：出仓后3-4天递送
C28: PHX3、PHX5、PHX6、PHX7 | D28: 600 | E28: RMB | F28: 每板 | G28: 1.7CBM/板，尾板进位制，时效：出仓后3-5天递送
C29: FTW1 | D29: 1158 | E29: RMB | F29: 每板 | G29: 1.7CBM/板，尾板进位制，时效：出仓后3-6天递送
C30: MDW2、IND9，MEM1 | D30: 1400 | E30: RMB | F30: 每板 | G30: 1.7CBM/板，尾板进位制，时效：出仓后3-7天递送
C31: ABQ2 | D31: 1120 | E31: RMB | F31: 每板 | G31: 1.7CBM/板，尾板进位制，时效：出仓后3-7天递送
C32: PSC2、IAH3、FWA4 | D32: 1360 | E32: RMB | F32: 每板 | G32: 1.7CBM/板，尾板进位制，时效：出仓后3-7天递送
C33: GEU2、GEU3、MIT2 | D33: 650 | E33: RMB | F33: 每板 | G33: 1.7CBM/板，尾板进位制，时效：出仓后3-7天递送
C34: WMT-LAX2、WMT-SMF1、WMT-PHX1 | D34: 单询 | E34: RMB | F34: 每板 | G34: 1.7CBM/板，尾板进位制，时效：出仓后3-7天递送
C35: WMT-KS1、WMT-KY1、WMT-PHL2 | D35: 单询 | E35: RMB | F35: 每板 | G35: 1.7CBM/板，尾板进位制，时效：出仓后3-7天递送

Sheet 超大件海派
A1: 美琦国际货运代理（深圳）有限公司
A2: 地址：深圳市龙岗区坂田街道布龙路369号东海王B座503-509
A4: 超大件海派（包税+FEDEX派送） | G4: 返回目录
A5: 邮编分区 | B5: 150KG+ | C5: 备注 | D5: 提取时效（开船后） | E5: 理赔时效 | F5: 理赔标准
A6: 美国西岸1（邮编9.8开头除96 97 98 邮编） | B6: 10.18 | C6: 船公司：EMC/OOCL/COSCO 1、含关税和查验费； 2、体积/6000； 3、义乌宁波交货+0.5/KG | D6: 26天左右 | E6: 无 | F6: 无
A7: 美国中部(邮编5.6.7、96 97 98开头) | B7: 11.18 | D7: 26天左右 | E7: 无
A8: 美国东岸(邮编0.1.2.3.4开头) | B8: 12.18 | D8: 26天左右 | E8: 无
A9: 一：末端采用正规联邦超大件账号派送，正规账号十年历程。
A10: 二：可收单件实重22.5-68KG货物，最长边不超240cm 一长+2宽+2高不超330CM，无超大件附加费
A11: 三：私人地址附加费 5.5USD/件、
A12: 四：偏远地址附加费 RMB4/KG

Sheet 海外仓地址
B2: 美 琦 国 际 货 运 代 理（深圳）有 限 公 司 地址：深圳市龙岗区坂田街道坂雪岗大道4088号奥博中心6楼A609-611
B4: 美西商业地址递送表
B5: 城市 | C5: 邮编 | D5: 城市 | E5: 邮编 | F5: 返回目录
B6: Los Angeles（海外仓+1RMB/KG) | C6: 9002X | D6: DIAMOND BAR | E6: 9176X
B7: WHITTIER | C7: 9060X | D7: POMONA | E7: 9176X
B8: MONTEBELLO | C8: 9064X | D8: ROSEMEAD | E8: 9177X
B9: NORWALK | C9: 9065X | D9: SAN DIMAS | E9: 9177X
B10: SANTA FE SPRINGS | C10: 9067X | D10: WALNUT | E10: 9178X
B11: CERRITOS | C11: 9070X | D11: TEMPLE CITY | E11: 9178X
B12: ARCADIA | C12: 9100X | D12: WEST COVINA | E12: 9179X
B13: PASADENA | C13: 9110X | D13: ALHAMNRA | E13: 9180X
B14: AZUSA | C14: 9170X | D14: COLTON | E14: 9232X
B15: CHINO | C15: 9171X | D15: FONTANA | E15: 9233X
B16: RANCHO CUCAMONGA | C16: 9173X | D16: RIALTO | E16: 9237X
B17: EL MONTE | C17: 9173X | D17: SAN BERNARDINO | E17: 9240X
... B23: ONTARIO | C23: 9176X | D23: YORBA LINDA | E23: 9288X
B24: 说明：尾数的X可为1-9的数字
B25: 美东商业地址递送表
B26: 城市 | C26: 邮编 | D26: 城市 | E26: 邮编
B27: CARTERET(海外仓+0.5RMB/KG) | C27: 0700X | D27: PERTH AMBOY | E27: 0886X
B28: NEWARK(海外仓+0.5RMB/KG) | C28: 0710X | D28: NEW BRUNSWICK | E28: 0890X
B29: ATLANTIC HIGHLANDS | C29: 0771X | D29: STATEN ISLAND(海外仓+1RMB/KG) | E29: 1031X
B30: LAKEWOOD | C30: 0870X | D30: OCEANSIDE(海外仓+1RMB/KG) | E30: 1157X
B31: EDISON | C31: 0881X | D31: HILLSBOROUGH | E31: 0884X
B32: PORT READING | C32: 0706X | D32: MONROE TOWNSHIP | E32: 0883X
B33: LINDEN | C33: 0703X | D33: BURLINGTON | E33: 0801X
B34: BORDENTOWN | C34: 0850X | D34: PARSIPPANY | E34: 0705X
B35: 说明：尾数的X可为1-9的数字
B36: 额外产生的费用 | C36: 金额 | D36: 单位 | E36: 备注
B37: 卸货等候费 | C37: 85 | D37: Per Hour 每小时 | E37: 免费等候一小时
B38: 跑空 | C38: 报价的50% | D38: Per Entry 每次 | E38: 如果产生
B39: 地址更改 | C39: 报价的50% | D39: Per Entry 每次 | E39: 需在我司可派送范围内
B40: 更改自提 | C40: 10 | D40: 每板 | E40: 原运费不退
B41: 尾板费 | C41: 65 | D41: Per Entry 每次 | E41: 无卸货平台需收取

Sheet 美国亚马逊仓库
A1: 美国FBA仓库
A2: FBA Code | B2: 地址 | C2: City | D2: State | E2: Zip | F2: 返回目录
A3: ABE2 | B3: 705 Boulder Drive | C3: Breinigsville | D3: PA | E3: 18031
A4: ABE3 | B4: 650 Boulder Drive | C4: Breinigsville | D4: PA | E4: 18031
A5: ABE4 | B5: 1610 Van Buren Road, Easton, PA, United States, 18 | C5: Easton | D5: PA | E5: 18045
A6: ABE5 | B6: 6455 Allentown Boulevard | C6: Harrisburg | D6: PA | E6: 17112
A7: ABE8-309 | B7: 309 Cedar Lane | C7: Florence | D7: NJ | E7: 08518-2802
A8: ABE8-401 | B8: 401 Independence Road | C8: Florence | D8: NJ | E8: 8518
A9: ATL6 | B9: 4200 North Commerce | C9: East Point | D9: GA | E9: 30344
A10: ATL8 | B10: 2201 Thornton Road Lithia Springs GA 30122-3895 Un | C10: Lithia Springs | D10: GA | E10: 30122
A11: AVP1 | B11: 550 Oak Ridge Road | C11: Hazle Township | D11: PA | E11: 18202-9361
A12: AVP3 | B12: 298 1ST AVE | C12: GOULDSBORO | D12: PA | E12: 18424-9492
A13: BDL1 | B13: 801 Day Hill Rd. | C13: Windsor | D13: CT | E13: 6095
A14: BDL2 | B14: 200 Old Iron Ore Rd | C14: Windsor | D14: CT | E14: 06095-2144
A15: BFI1 | B15: 1800 140th Avenue E. | C15: Sumner | D15: WA | E15: 98390
A16: BFI3 | B16: 2700 Center Drive | C16: Dupont | D16: WA | E16: 98327-9607
A17: BFI4 | B17: 20529 59th Place South,Kent,WA 98032 United States | C17: Kent | D17: WA | E17: 98032
A18: BFI5 | B18: 20526 59th Place South,Kent | C18: King County | D18: WA | E18: 98032
A19: BFI7 | B19: 1901 140th Ave E | C19: Sumner | D19: WA | E19: 98390
A20: BNA1 | B20: 14840 Central Pike Suite 190 | C20: Lebanon | D20: TN | E20: 37090
A21: BNA2 | B21: 500 Duke DR | C21: Franklin | D21: TN | E21: 37067
A22: BNA3 | B22: Joe B Jackson Pkwy | C22: Murfreesboro | D22: TN | E22: 37127
A23: BNA4 | B23: 50 airways Blvd | C23: Nashville | D23: TN | E23: 37217
A24: BOS1 | B24: 10 State St. | C24: Nashua | D24: NH | E24: 3063
A25: BOS2 | B25: 1000 Tech Centre | C25: Drive Stoughton | D25: MA | E25: 2072
A26: BOS7 | B26: 1180 Innovation Way | C26: Fall River | D26: MA | E26: 2720
A27: BWI1 | B27: 2010 Broening Highway | C27: Baltimore | D27: MD | E27: 21224
A28: BWI2 | B28: 5001 Holbird Ave. | C28: Baltimore | D28: MD | E28: 21224
... A32: CHA2 | B32: 225 Infinity Dr NW | C32: Charleston | D32: TN | E32: 37310
A33: CLT2 | B33: Am azon.com .dedc LLC 10240 O ld D owd Rd Charlotte, N C 28214-8082 U nited States | C33: Charlotte | D33: NC | E33: 28214-8082
A34: CLT3 | B34: 6500 Davidson Hwy Concord NC 28027-7995 United States | C34: Concord | D34: NC | E34: 28027
A35: CMH1 | B35: 11903 National Road SW | C35: Etna | D35: OH | E35: 43062-7793
A36: CMH1-11999 | B36: 11999 National Road SW Etna, OH 43062-7793 United States | C36: Etna | D36: OH | E36: 43062
A37: CMH2 | B37: 6050 Gateway Court Groveport | C37: COLUMBUS | D37: OH | E37: 43125-9016
A38: CVG1 | B38: 1155 Worldwide Blvd | C38: Hebron | D38: KY | E38: 41048
A39: CVG2 | B39: 1600 Worldwide Blvd | C39: Hebron | D39: KY | E39: 41048
A40: CVG3 | B40: 3680 Langley Dr. | C40: Hebron | D40: KY | E40: 41048
A41: CVG5 | B41: 2285 Litton Lane | C41: Hebron | D41: KY | E41: 41048
A42: DEN2 | B42: 22205 East 19th Ave Aurora CO 80019 United States | C42: Aurora | D42: CO | E42: 80019
A43: DET1 | B43: 39000 Amrhein Road | C43: Livonia | D43: MI | E43: 48150
A44: DFW6 | B44: 940 W Bethel Road | C44: Coppell | D44: TX | E44: 75019
A45: DFW7 | B45: 700 Westport Parkway | C45: Haslet | D45: TX | E45: 76177
A46: DFW8 | B46: 2700 Regent Blvd | C46: DFW Airport | D46: TX | E46: 75261
A47: DTW1 | B47: 32801 Ecorse Road,Romulus,48174 MI,United States | C47: Romulus | D47: MI | E47: 48174
A48: EWR4 | B48: 50 New Canton Way | C48: Robbinsville | D48: NJ | E48: 8691
A49: EWR5 | B49: 301 Blair Rd. | C49: Avenel | D49: NJ | E49: 7001
... A57: HOU1 | B57: 8120 Humble Westfield Rd | C57: Humble | D57: TX | E57: 77338
A58: HOU2 | B58: 10550 Ella Blvd. | C58: Houston | D58: TX | E58: 77038-2324
A59: HOU3 | B59: 31555 Highway 90 E | C59: Brookshire | D59: TX | E59: 77423
A60: IND1 | B60: 4255 Anson Blvd | C60: Whitestown | D60: IN | E60: 46075
A61: IND2 | B61: 715 Airtech Pkwy | C61: Plainfield | D61: IN | E61: 46168
A62: IND3 | B62: 715 Airtech Pkwy Suite 195 | C62: Plainfield | D62: IN | E62: 46168
A63: IND4 | B63: 710 S. Girls School Rd | C63: Indianapolis | D63: IN | E63: 46231
A64: IND5 | B64: 800 Perry Road | C64: Plainfield | D64: IN | E64: 46168
A65: IND6 | B65: 1453 E 10th St | C65: Jeffersonville | D65: IN | E65: 47130
A66: ITX1 | B66: 9851 Fallbrook Pines Drive Suite 100 Houston, TX 77064-3329 | C66: Houston | D66: TX | E66: 77064
A67: ITX2 | B67: 6911 FAIRBANKS N HOUSTON RD SUITE 160 Houston, TX 77040-1437 United States | C67: Houston | D67: TX | E67: 77040
A68: IVSA | B68: 4620 Olympic Blvd | C68: Erlanger | D68: KY | E68: 41018
A69: IVSB | B69: 3521 POINT PLEASANT RD | C69: HEBRON | D69: KY | E69: 41048
A70: IVSC | B70: Uno - West Deptford 1225 Forest Parkway West Deptf | C70: West Deptford | D70: NJ | E70: 8066
... A73: JAX2 | B73: 12900 Pecan Park Road Jacksonville, FL 32218 Unite | C73: Jacksonville | D73: FL | E73: 32218
A74: JAX3 | B74: 13333 103rd Street | C74: Jacksonville | D74: FL | E74: 32210-8686
A75: LAL1 | B75: 1760 County Line Rd.Lakeland, Florida 33811， Unite | C75: Lakeland | D75: FL | E75: 33811
A76: LAS1 | B76: 4550 Nexus Way | C76: Las Vegas | D76: NV | E76: 89115
A77: LAS2 | B77: 3837 Bay Lake Trail, Suite 111 North | C77: Las Vegas | D77: NV | E77: 89030
A78: LAS6 | B78: 4550 Nexus Way Las Vegas NV 89115,United States | C78: Las Vegas | D78: NV | E78: 89115
A79: LEX1 | B79: 1850 Mercer RD | C79: Lexington | D79: KY | E79: 40511
A80: LEX2 | B80: 172 Trade St. | C80: Lexington | D80: KY | E80: 40511
A81: LGB3 | B81: 4950 Goodman Way | C81: Eastvale | D81: CA | E81: 91752
A82: LGB4 | B82: 27517 Pioneer Avenue | C82: Redlands | D82: CA | E82: 92374
A83: LGB6 | B83: 20901 Krameria Ave | C83: Riverside | D83: CA | E83: 92518-1513
A84: LGB8 | B84: 1568 N Linden Ave | C84: Rialto | D84: CA | E84: 92376
A85: MCI1 | B85: 113th St & Renner Blvd. | C85: Lenexa | D85: KS | E85: 66219
A86: MDT1 | B86: 2 Ames Drive | C86: Carlisle | D86: PA | E86: 17015
A87: MDT1 | B87: 2Ames Drive,Building#2 | C87: Carlisle | D87: PA | E87: 17015
A88: MDT2 | B88: 600 Principio Parkway West North East, MD 21901-29 | C88: West North East | D88: MD | E88: 21901
A89: MDW2 | B89: 250 Emerald | C89: Joliet | D89: IL | E89: 60433-3280
A90: MDW2-250 | B90: 250 Emerald Drive Joliet,IL 60433-3280 United Stat | C90: Joliet | D90: IL | E90: 60433
A91: MDW2-402 | B91: 402 Emerald Drive Joliet,IL 60433-3279 United Stat | C91: Joliet | D91: IL | E91: 60433
A92: MDW4 | B92: 250 Emetald Drive Joliet, IL 60433-9642 United Sta | C92: Joliet | D92: IL | E92: 60433
A93: MDW6 | B93: 1125 W REMINGTON BLVD ROMEOVILLE | C93: ROMEOVILLE | D93: IL | E93: 60446-6529
A94: MDW7 | B94: 6605 Monee Manhattan Road | C94: Monee | D94: IL | E94: 60449
A95: MDW8 | B95: 1750 Bridge Drive | C95: Waukegan | D95: IL | E95: 60085
A96: MDW9 | B96: 2865 Duke Parkway | C96: Aurora | D96: IL | E96: 60502
A97: MGE3 | B97: 808 Hog Mountain Road | C97: Jefferson | D97: GA | E97: 30549
A98: MIA1 | B98: 1900 NW 132nd Place Doral | C98: Miami | D98: FL | E98: 33182
A99: MKC4 | B99: 19645 Waverly Rd | C99: Edgerton | D99: KS | E99: 66021-9588
A100: MKC6 | B100: 6925 Riverview Avenue | C100: Kansas City | D100: KX | E100: 66102
A101: MKE1 | B101: 3501 120th Ave,Kenosha,WI 53144 | C101: Kenosha | D101: WI | E101: 53144
A102: MSP1 | B102: 2601 4th Avenue East | C102: Shakopee | D102: MN | E102: 55379
A103: OAK3 | B103: 255 Park Center Drive | C103: Patterson | D103: CA | E103: 95363
A104: OAK4 | B104: 1555 N. Chrisman Rd | C104: Tracy | D104: CA | E104: 95376
A105: ONT2 | B105: 1910 E Central Ave | C105: San Bernardino | D105: CA | E105: 92408
A106: ONT6 | B106: 24208 San Michele Rd | C106: Moreno Valley | D106: CA | E106: 92551
A107: ONT7 | B107: 2125 W. San Bernandino Ave.Redlands, CA 92374， Uni | C107: Redlands | D107: CA | E107: 92374
A108: ONT8 | B108: 24300 Nandina Ave Moreno | C108: Valley | D108: CA | E108: 92551
A109: ONT9 | B109: 2125 W. San Bernandino Ave | C109: Redlands | D109: CA | E109: 92374
A110: ORD6 | B110: 1250 N Mittel Blvd | C110: Wood Dale | D110: IL | E110: 60191
A111: PDX9 | B111: 1250 NW Swigert Way Troutdale, OR 97060 United States | C111: Troutdale | D111: OR | E111: 97060
... A129: RNO4 | B129: Amazon.com.NVDC Inc. 8000 North Virginia Street | C129: Reno | D129: NV | E129: 89506
...

Sheet 美转墨限时达
A1: 美转墨限时达
A2: 产品类目(无品牌无仿外形无卡通等无侵权产品) | B2: 渠道代码 | C2: 1CBM+ | D2: 5CBM+ | E2: 10CBM+ | F2: 30CBM+（或整柜） | G2: 特殊说明 | H2: 涨价幅度
A3: 一类：塑料制品(塑料杯,塑料瓶,塑料盘等),行李箱,手提箱,公文包,箱包,普通拉杆箱,日用百货产品（材质为塑料的,铁的,不锈钢的,橡胶等),厨房用去油布(非纺织品材质),手机壳,保护膜,数据线,配件(镜架)(眼镜镜片是玻璃制品需要跌落证明),手表配件(壳.盖子.表带)(带蓝牙LOGO字样需要注册并授权),人造PU卷材,人造皮革(PU),复合皮革,硅胶制品,塑料制工艺品,PVC,汽车配件及其它配件类(不含纺织品),硅胶垫,不锈钢套锅,收纳架,筛网,橡胶制品,化纤假发等 未列明产品请单询 | B3: 美转墨-限时达 | C3: 4700 | D3: 4700 | E3: 4700 | F3: 可单询申请 | G3: 墨西哥城内的美客多,亚马逊,虾皮以及距离我司海外仓40公里内私人和商业地址:免派送费 墨城以外地址派送费:单询.美森/ZIM统配 开船次日起算20-22个自然日左右到我 司墨西哥城仓库，24天未到海外仓，从 第25天开始赔偿100/天/方(不含清关 查验或其它不可控因素)
A4: 二类：家用和商用的电器,电子类产品，灯具,LED灯,行车记录仪,骑行灯,耳机,音响,加湿器,监控摄像头,小型风扇,除螨仪,推发剪,电饼铛,除毛仪,吹风机，厨房用品,果汁机,普货需要认证电子产品(需要NOM.蓝牙、HDMI、FDA、FCC、Lacey Act、DOT等认证的产品),玩具,充电器,收音机,行车记录仪,音响(带蓝牙LOGO需要授权),包装机,食品机,压榨机,电砖,摄影或电影摄像机,车灯,LED显示屏,工业冷水机,车载MP5播放器,LED工矿灯,饲料颗粒机,温度计(无水银),脸部喷雾器,捆扎机,自行车灯,氛围灯,交换机,口罩(非医用),一次性头帽(非医用),普通木制小工艺品,五金类（石墨制品,螺丝）,材质为塑料及小部分加工木制品桌椅,婴儿车等未列明产品请单询 | C4: 4800 | D4: 4800 | E4: 4800
A5: 三类：纺织品类(原材料以及成品衣物或其他纺织品),手套,皮革（PU）,鞋子，服装辅料,台布,纺织手套,纺织帽子,布匹,服装,牛仔裤,窗帘,帷幔和踢脚板,记忆棉枕头等 未列明产品请单询 | C5: 4900 | D5: 4900 | E5: 4900
A6: 海派渠道海外仓收费参考（具体请单询）
A7: 体积：长*宽*高（CM）/5000后大于69KG或单件实重超69KG派送费及超大件费用需单询！
A8: 备注： 交货必须告知我司交货渠道代码，否则按最高计算！
A9: 一、计费方式：长CM*宽CM*高CM/1000000=方数（CBM）实重：1CBM：300KG，计费重R/T，取最大值计费，最低1CBM起收，不足1CBM按1CBM计费，1CBM以上按实际收费；
A10: 墨西哥品牌查询网站：https://acervomarcas.impi.gob.mx:8181/marcanet
A11: 中国品牌查询网站：http://202.127.48.145:8888/zscq/search/jsp/vBrandSearchIndex.jsp
A12: 统配美森 ，每周六截，每周六装柜，具体以实际SO为准，满柜即装下一柜. 以实际开船为准，系统可自行查询船名航次跟踪。航程10-12天左右，清关3-5天左右(通关正常情况下)， 清关后再预约拖车(1-2天)到海外仓，海外仓2天左右清理货物，海外仓分拣安排派送(根据不同的地址/货型等因素安排,无固定某种派送方式).派送时效根据中、墨节假日顺延.
A13: 二、美客多/亚马逊电商平台货物要求（以平台要求为准）：
A14: ①重量要求：
A15: 单件10KG起收，单件实重或者体积不能超30KG
A16: ②尺寸要求：
A17: 单箱边长不能超60CM，单个产品单边长不能超48CM;
... A49: 特别注意：出货前请仔细阅读我司理赔标准及各服务说明条款，交货后我司默认交货公司已阅读并已同意此赔偿方案,不另做争议!

Sheet 美转墨快线
A1: 美转墨快线
A2: 产品类目(无品牌无仿外形无卡通等无侵权产品) | B2: 渠道代码 | C2: 1CBM+ | D2: 5CBM+ | E2: 10CBM+ | F2: 30CBM+（或整柜） | G2: 特殊说明 | H2: 涨价幅度
A3: 一类：塑料制品(塑料杯,塑料瓶,塑料盘等),行李箱,手提箱,公文包,箱包,普通拉杆箱,日用百货产品（材质为塑料的,铁的,不锈钢的,橡胶等),厨房用去油布(非纺织品材质),手机壳,保护膜,数据线,配件(镜架)(眼镜镜片是玻璃制品需要跌落证明),手表配件(壳.盖子.表带)(带蓝牙LOGO字样需要注册并授权),人造PU卷材,人造皮革(PU),复合皮革,硅胶制品,塑料制工艺品,PVC,汽车配件及其它配件类(不含纺织品),硅胶垫,不锈钢套锅,收纳架,筛网,橡胶制品,化纤假发等 未列明产品请单询 | B3: 美转墨-快线 | C3: 3250 | D3: 3250 | E3: 3250 | F3: 可单询申请 | G3: 墨西哥城内的美客多,亚马逊,虾皮以及距离我司海外仓40公里内私人和商业地址:免派送费 墨城以外地址派送费:单询.开船后35-38个自然日左右到我司墨西哥城仓库（不含清关查验或其它不可控因素） | H3: 100
A4: 二类：家用和商用的电器,电子类产品，灯具,LED灯,行车记录仪,骑行灯,耳机,音响,加湿器,监控摄像头,小型风扇,除螨仪,推发剪,电饼铛,除毛仪,吹风机，厨房用品,果汁机,普货需要认证电子产品(需要NOM.蓝牙、HDMI、FDA、FCC、Lacey Act、DOT等认证的产品),玩具,充电器,收音机,行车记录仪,音响(带蓝牙LOGO需要授权),包装机,食品机,压榨机,电砖,摄影或电影摄像机,车灯,LED显示屏,工业冷水机,车载MP5播放器,LED工矿灯,饲料颗粒机,温度计(无水银),脸部喷雾器,捆扎机,自行车灯,氛围灯,交换机,口罩(非医用),一次性头帽(非医用),普通木制小工艺品,五金类（石墨制品,螺丝）,材质为塑料及小部分加工木制品桌椅,婴儿车等未列明产品请单询 | C4: 3350 | D4: 3350 | E4: 3350
A5: 三类：纺织品类(原材料以及成品衣物或其他纺织品),手套,皮革（PU）,鞋子，服装辅料,台布,纺织手套,纺织帽子,布匹,服装,牛仔裤,窗帘,帷幔和踢脚板,记忆棉枕头等 未列明产品请单询 | C5: 3450 | D5: 3450 | E5: 3450
A6: 海派渠道海外仓收费参考（具体请单询）
A7: 体积：长*宽*高（CM）/5000后大于69KG或单件实重超69KG派送费及超大件费用需单询！
A8: 备注： 交货必须告知我司交货渠道代码，否则按最高计算！
A9: 一、计费方式：长CM*宽CM*高CM/1000000=方数（CBM）实重：1CBM：300KG，计费重R/T，取最大值计费，最低1CBM起收，不足1CBM按1CBM计费，1CBM以上按实际收费；
A10: 墨西哥品牌查询网站：https://acervomarcas.impi.gob.mx:8181/marcanet
A11: 中国品牌查询网站：http://202.127.48.145:8888/zscq/search/jsp/vBrandSearchIndex.jsp
A12: 统配WHL,COSCO,YM ，每周三/六截，每周五/六左右装柜，具体以实际SO为准，满柜即装下一柜. 以实际开船为准，系统可自行查询船名航次跟踪。航程22-24天左右，清关3-5天左右(通关正常情况下)， 清关后再预约拖车(1-2天)到海外仓，海外仓2天左右清理货物，海外仓分拣安排派送(根据不同的地址/货型等因素安排,无固定某种派送方式).派送时效根据中、墨节假日顺延.
A13: 二、美客多/亚马逊电商平台货物要求（以平台要求为准）：
A14: ①重量要求：
A15: 单件10KG起收，单件实重或者体积不能超30KG
A16: ②尺寸要求：
A17: 单箱边长不能超60CM，单个产品单边长不能超48CM;
... A49: 特别注意：出货前请仔细阅读我司理赔标准及各服务说明条款，交货后我司默认交货公司已阅读并已同意此赔偿方案,不另做争议!

Sheet 美转墨普线
B1: 美转墨普线
B2: 产品类目(无品牌无仿外形无卡通等无侵权产品) | C2: 渠道代码 | D2: 1CBM+ | E2: 5CBM+ | F2: 10CBM+ | G2: 30CBM+（或整柜） | H2: 特殊说明 | I2: 涨价幅度
B3: 一类：塑料制品(塑料杯,塑料瓶,塑料盘等),行李箱,手提箱,公文包,箱包,普通拉杆箱,日用百货产品（材质为塑料的,铁的,不锈钢的,橡胶等),厨房用去油布(非纺织品材质),手机壳,保护膜,数据线,配件(镜架)(眼镜镜片是玻璃制品需要跌落证明),手表配件(壳.盖子.表带)(带蓝牙LOGO字样需要注册并授权),人造PU卷材,人造皮革(PU),复合皮革,硅胶制品,塑料制工艺品,PVC,汽车配件及其它配件类(不含纺织品),硅胶垫,不锈钢套锅,收纳架,筛网,橡胶制品,化纤假发等 未列明产品请单询 | C3: 美转墨-普线 | D3: 3100 | E3: 3100 | F3: 3100 | G3: 可单询申请 | H3: 墨西哥城内的美客多,亚马逊,虾皮以及距离我司海外仓40公里内私人和商业地址:免派送费 墨城以外地址派送费:单询.开船后40-50个自然日左右到我司墨西哥城仓库 （不含清关查验或其它不可控因素） | I3: 100
B4: 二类：家用和商用的电器,电子类产品，灯具,LED灯,行车记录仪,骑行灯,耳机,音响,加湿器,监控摄像头,小型风扇,除螨仪,推发剪,电饼铛,除毛仪,吹风机，厨房用品,果汁机,普货需要认证电子产品(需要NOM.蓝牙、HDMI、FDA、FCC、Lacey Act、DOT等认证的产品),玩具,充电器,收音机,行车记录仪,音响(带蓝牙LOGO需要授权),包装机,食品机,压榨机,电砖,摄影或电影摄像机,车灯,LED显示屏,工业冷水机,车载MP5播放器,LED工矿灯,饲料颗粒机,温度计(无水银),脸部喷雾器,捆扎机,自行车灯,氛围灯,交换机,口罩(非医用),一次性头帽(非医用),普通木制小工艺品,五金类（石墨制品,螺丝）,材质为塑料及小部分加工木制品桌椅,婴儿车等未列明产品请单询 | D4: 3200 | E4: 3200 | F4: 3200
B5: 三类：纺织品类(原材料以及成品衣物或其他纺织品),手套,皮革（PU）,鞋子，服装辅料,台布,纺织手套,纺织帽子,布匹,服装,牛仔裤,窗帘,帷幔和踢脚板,记忆棉枕头等 未列明产品请单询 | D5: 3300 | E5: 3300 | F5: 3300
B6: 海派渠道海外仓收费参考（具体请单询）
B7: 体积：长*宽*高（CM）/5000后大于69KG或单件实重超69KG派送费及超大件费用需单询！
B8: 备注： 交货必须告知我司交货渠道代码，否则按最高计算！
B9: 一、计费方式：长CM*宽CM*高CM/1000000=方数（CBM）实重：1CBM：300KG，计费重R/T，取最大值计费，最低1CBM起收，不足1CBM按1CBM计费，1CBM以上按实际收费；
B10: 墨西哥品牌查询网站：https://acervomarcas.impi.gob.mx:8181/marcanet
B11: 中国品牌查询网站：http://202.127.48.145:8888/zscq/search/jsp/vBrandSearchIndex.jsp
B12: 统配WHL,COSCO,YM ，每周三/六截，每周五/六左右装柜，具体以实际SO为准，满柜即装下一柜. 以实际开船为准，系统可自行查询船名航次跟踪。航程22-24天左右，清关3-5天左右(通关正常情况下)， 清关后再预约拖车(1-2天)到海外仓，海外仓2天左右清理货物，海外仓分拣安排派送(根据不同的地址/货型等因素安排,无固定某种派送方式).派送时效根据中、墨节假日顺延.
B13: 二、美客多/亚马逊电商平台货物要求（以平台要求为准）：
B14: ①重量要求：
B15: 单件10KG起收，单件实重或者体积不能超30KG
B16: ②尺寸要求：
B17: 单箱边长不能超60CM，单个产品单边长不能超48CM;
... B49: 特别注意：出货前请仔细阅读我司理赔标准及各服务说明条款，交货后我司默认交货公司已阅读并已同意此赔偿方案,不另做争议!

Sheet 美转墨铭感货
B1: 美转墨敏感货
B2: 产品类目 | C2: 渠道代码 | D2: 1CBM+ | E2: 5CBM+ | F2: 10CBM+ | G2: 30CBM+（或整柜） | H2: 特殊说明 | I2: 涨价幅度
B3: 敏感货、防疫物资、 电池、液体 等 | C3: 美转墨-慢线-MG | D3: 3950 | E3: 3950 | F3: 3950 | G3: 单询 | H3: 墨西哥城内的美客多,亚马逊,虾皮以及距离我司海外仓40公里内私人和商业地址:免派送费 墨城以外地址派送费:单询.开船后40-50个自然日左右到我司墨西哥城仓库 （不含清关查验或其它不可控因素）
B4: 医疗器械类 | D4: 4400 | E4: 4400 | F4: 4400
B5: 敏感货、防疫物资、 电池、液体 等 | C5: 美转墨-快线-MG | D5: 4100 | E5: 4100 | F5: 4100 | G5: 单询 | H5: 墨西哥城内的美客多,亚马逊,虾皮以及距离我司海外仓40公里内私人和商业地址:免派送费 墨城以外地址派送费:单询.开船后30个自然日左右到我司墨西哥城仓库 （不含清关查验或其它不可控因素）
B6: 医疗器械类 | D6: 4550 | E6: 4550 | F6: 4550
B7: 海派渠道海外仓收费参考（具体请单询）
B8: 体积：长*宽*高（CM）/5000后大于69KG或单件实重超69KG派送费及超大件费用需单询！
B9: 备注： 交货必须告知我司交货渠道代码，否则按最高计算！
B10: 一、计费方式：长CM*宽CM*高CM/6000=方数（CBM）实重：1CBM：300KG，计费重R/T，取最大值计费，最低1CBM起收，不足1CBM按1CBM计费，1CBM以上按实际收费；
B11: 墨西哥品牌查询网站：https://acervomarcas.impi.gob.mx:8181/marcanet
B12: 中国品牌查询网站：http://202.127.48.145:8888/zscq/search/jsp/vBrandSearchIndex.jsp
B13: 统配WHL,COSCO,YM ，每周三/六截，每周五/六左右装柜，具体以实际SO为准，满柜即装下一柜. 以实际开船为准，系统可自行查询船名航次跟踪。航程22-24天左右，清关3-5天左右(通关正常情况下)， 清关后再预约拖车(1-2天)到海外仓，海外仓2天左右清理货物，海外仓分拣安排派送(根据不同的地址/货型等因素安排,无固定某种派送方式).派送时效根据中、墨节假日顺延.
B14: 二、含有内置电池产品另加收100RMB/CBM且需要提供MSDS/UN38.3/海运鉴定书(功率不能超100W且带产品电池必须做好独立包装及绝缘完好,如因电池本身质量问题导致事故,交货公司将承担所有的损失后果)； 带磁产品需单询，如隐瞒申报，我司将视为冲货，冲货罚款5000/票以上不等，如因瞒报发生目的港清关产生一切费用由交货公司承担所有，不另做争议；锂离子电池上需要有的伏数V和毫安mAh，功率WH值. 电池计算功率方式：（毫安*伏数/1000时功率要小于100WH）
B15: 三、为便于清关，请于外箱贴唛头顺序编号和产品上贴上“made in china"的字样. 自提货物:货物到仓后,需要提前告知我司提货时间(仓库需要提前找出货物后约好时间自提)/单号/件数/姓名/提货人身份证/车牌.
B16: 四、单票货物超过5个品名以上多出部分需加收50RMB/个（具体请单询业务）；
B17: 五、关于超大件单件100KG起或单边120CM起请单询，其它注意事项：所有货物出货前发货方必须与收货人核实是否有卸货工具及卸货平台,避免无法派送，否则后端产生其它派送杂费另加收取。 需要木箱或标准木架包装带卡板脚（9CM高以上避免叉车无法使用，如无合格叉车高脚不出货）且必须打合页以便开箱查货，如果无活页可直接开箱查货的我司会直接加收交货方操作费30RMB/件处理活页费用不得争议，所以请各客户出货前必须处理好包装问题避免不必要的延误及费用；如木箱或木架包装不合格，必须重新处理包装费用则实报实销；如需要我司代打卡板出货，操作费150RMB/板（具体视实际情况实报实销）；
B18: 六、私人或商业件出货前必须提供准确有效的收货人地址和联系方式，如因收货方联系资料问题或收货方其它原因导致延误滞留仓库，从货物到达墨西哥仓库当天起，免仓15天，从第16天起收取RMB0.2/KG/天仓租，不得争议；展会需要提供展位/展馆名称/参展时间/参展单位；送学校/实验室/大使馆等需提前确认派送是否有特殊要求；所有的商业或私人地址是否较偏远我司无法查询，必须交货前自主与收货方确认核实；如因收货客户或发货公司原因导致派送不成功，再次派送需另行支付派送费用，不得争议；
... B33: 特别注意：出货前请仔细阅读我司理赔标准及各服务说明条款，交货后我司默认交货公司已阅读并已同意此赔偿方案,不另做争议!

Sheet 墨西哥海外仓
A1: 免费派送邮编墨西哥城邮编 Código Postal | B1: 城镇 Ciudad/Municipio | C1: 城市 Ciudad | F1: 免费派送邮编墨西哥州邮编 Código Postal | G1: 城镇 Ciudad/Municipio | H1: 城市 Ciudad | J1: 请注意：免派邮编最低1方起，不足1方按照200/票计费
A2: 01000 | B2: Álvaro Obregón | C2: CDMX | F2: 54000 | G2: Tlalnepantla de Baz | H2: EDOMEX墨西哥州
A3: 01010 | B3: Álvaro Obregón | C3: CDMX | F3: 54009 | G3: Tlalnepantla de Baz | H3: EDOMEX墨西哥州
A4: 01020 | B4: Álvaro Obregón | C4: CDMX | F4: 54010 | G4: Tlalnepantla de Baz | H4: EDOMEX墨西哥州
A5: 01028 | B5: Álvaro Obregón | C5: CDMX | F5: 54015 | G5: Tlalnepantla de Baz | H5: EDOMEX墨西哥州
A6: 01029 | B6: Álvaro Obregón | C6: CDMX | F6: 54016 | G6: Tlalnepantla de Baz | H6: EDOMEX墨西哥州
A7: 01030 | B7: Álvaro Obregón | C7: CDMX | F7: 54017 | G7: Tlalnepantla de Baz | H7: EDOMEX墨西哥州
A8: 01040 | B8: Álvaro Obregón | C8: CDMX | F8: 54020 | G8: Tlalnepantla de Baz | H8: EDOMEX墨西哥州
A9: 01048 | B9: Álvaro Obregón | C9: CDMX | F9: 54021 | G9: Tlalnepantla de Baz | H9: EDOMEX墨西哥州
A10: 01049 | B10: Álvaro Obregón | C10: CDMX | F10: 54022 | G10: Tlalnepantla de Baz | H10: EDOMEX墨西哥州
A11: 01050 | B11: Álvaro Obregón | C11: CDMX | F11: 54023 | G11: Tlalnepantla de Baz | H11: EDOMEX墨西哥州
A12: 01060 | B12: Álvaro Obregón | C12: CDMX | F12: 54025 | G12: Tlalnepantla de Baz | H12: EDOMEX墨西哥州
A13: 01070 | B13: Álvaro Obregón | C13: CDMX | F13: 54026 | G13: Tlalnepantla de Baz | H13: EDOMEX墨西哥州
... A227: 02860 | B227: Azcapotzalco | C227: CDMX | F227: 55739 | G227: Coacalco de Berriozábal | H227: EDOMEX墨西哥州
A228: 02870 | B228: Azcapotzalco | C228: CDMX
A229: 02900 | B229: Azcapotzalco | C229: CDMX
A230: 02910 | B230: Azcapotzalco | C230: CDMX
A231: 02920 | B231: Azcapotzalco | C231: CDMX
A232: 02930 | B232: Azcapotzalco | C232: CDMX
A233: 02940 | B233: Azcapotzalco | C233: CDMX
A234: 02950 | B234: Azcapotzalco | C234: CDMX
A235: 02960 | B235: Azcapotzalco | C235: CDMX
A236: 02970 | B236: Azcapotzalco | C236: CDMX
A237: 02980 | B237: Azcapotzalco | C237: CDMX
A238: 02990 | B238: Azcapotzalco | C238: CDMX
A239: 03000 | B239: Benito Juárez | C239: CDMX
... A1408: 11570 | B1408: Miguel Hidalgo | C1408: CDMX

Sheet 墨西哥仓库
A1: 墨西哥仓库地址
A2: 电商平台 | B2: 编号 | C2: 仓库代码/编号 | D2: 仓库详细地址 | E2: 所属区域 | F2: 配送收费标准
A3: 美客多 | B3: 1 | C3: MXRC03 | D3: Vialidad Cola de Caballo S/N, Rancho Nuevo la Virgen, Cuautitlan, Estado De México. ZIP CODE: 54800 | E3: 墨西哥城内 | F3: 已含派送费
B4: 2 | C4: MXCD05 | D4: CPA Logistics Center-V Av. Lic. Arturo Montiel Rojas, entre esquina el terremoto y hacienda las arboledas , San Juan, Cuautitlan, Estado De México. ZIP CODE: 54800 | E4: 墨西哥城内 | F4: 已含派送费
B5: 3 | C5: MXCD06 | D5: Carretera Cuautitlan -Tultepec lote B no. 2 y lote C 1, Colonia Terremoto, Cuautitlan, Estado De México.ZIP CODE: 54803 | E5: 墨西哥城内 | F5: 已含派送费
B6: 4 | C6: MXCD08 | D6: Autopista Arco norte 057, Jilotepec de Molina Enriquez, Jilotepec, Estado De México. ZIP CODE: 54250 | E6: 墨西哥城内（偏远） | F6: 单询
B7: 5 | C7: MXCD12 | D7: Parque Industrial Plataforma Logistica del Estado de Hidalgo (PLATAH) - Lote 7 en Calle 5 S/N, Municipio de Villa de Tezontepec, Villa De Tezontepec, Hidalgo. ZIP CODE: 43894 | E7: 墨西哥城外 | F7: 单询
B8: 6 | C8: 瓜仓 | D8: Vesta Park Guadalajara I Mercado Libre Carretera Guadalajara - El Salto vía El Verde 1900, Colonia Potrero El Salitre, El Salto, Jalisco. ZIP CODE: 45694. | E8: 瓜城内 | F8: 单询
B9: 7 | C9: 蒙特雷仓 | D9: Mercado Libre Nexxus MTY Parque Nexxus autopista al aeropuerto KM 3+800, Apodaca, Nuevo León. ZIP CODE: 66648. | E9: 蒙特雷城内 | F9: 单询
A10: 亚马逊 | B10: 8 | C10: MEX1 | D10: Cuautitlán Izcalli,Estado de México,MX（ZIP）：54715 | E10: 墨西哥城内 | F10: 已含派送费
B11: 9 | C11: MEX2 | D11: Cuautitlán Izcalli,MX,（ZIP）：54769 | E11: 墨西哥城内 | F11: 已含派送费
B12: 10 | C12: MEX3 | D12: Tepotzotlán,MX,（ZIP）：54607 | E12: 墨西哥城内 | F12: 已含派送费
B13: 11 | C13: MEX6 | D13: Camino a XOYOACAC，Fracc B Nav Jerusalem， TEPOTZOTLAN, MEXICO 54607 | E13: 墨西哥城内 | F13: 已含派送费
B14: 12 | C14: GDL1 | D14: Guadalajara-Chapala Highway #9999 Building 5 Zapote del Valle, JALISCO 45672 | E14: 墨西哥城外 | F14: 单询
B15: 13 | C15: MTY1 | D15: BLVD GUADALUPE No.403 Interior B012 APODACA, NUEVO LEON 66627 | E15: 墨西哥城外 | F15: 单询
B16: 14 | C16: MTY2 | D16: Servicios Comerciales Amazon México, S. DE R.L Procurement Non Inventory Kronos Industrial Park Av Industrias 500 Apodocada, 66603 | E16: 墨西哥城外 | F16: 单询
B17: 15 | C17: TIJ1 | D17: Camino Vecinal #20652, Nave 4 Colonia Murua Oriente 22465 - Tijuana, BAJA CALIFORNIA - Mexico | E17: 墨西哥城外 | F17: 单询
B18: 16 | C18: HMO3 | D18: Av. Mercury, Polígono B1-2, II Etapa, al Sur de la Carretera a la Colorada Parque Industrial Dynatech Sur Segunda Etapa 83297 - Hermosillo, Sonora - Mexico | E18: 墨西哥城外 | F18: 单询
B19: 17 | C19: BJX1 | D19: Calle Oliver Evans number 107 Carretera a Santa Ana del Conde, Km 4.5 Parque Industrial Bajío (PILBA) León, Guanajuato 37680 MX (BJX1) | E19: 墨西哥城外 | F19: 单询

Sheet 反倾销列表
A1: 美国反倾销表
A2: CASE# | B2: 产品 | C2: 英文
A3: A-570-010 | B3: 晶体硅光伏产品(太阳能板晶体硅光伏电池) | C3: Crystalline Silicon Photovoltaic Products
A4: A-570-016 | B4: 乘用车和轻型卡车轮胎 | C4: Passenger Vehicle And Light Truck Tires
A5: A-570-018 | B5: 无螺栓钢制货架 | C5: Boltless Steel Shelving Units Prepackaged For Sale
A6: A-570-026 | B6: 耐腐蚀钢板 | C6: Corrosion Resistant Steel
A7: A-570-028 | B7: 氢氟烃制冷剂 | C7: Hydrofluorocarbon Blends And ComponentsThereof
A8: A-570-033 | B8: 大型家用洗衣机 | C8: Large Residential Washers
A9: A-570-040 | B9: 卡车和客车轮胎 | C9: Truck And Bus Tires
A10: A-570-051 | B10: 硬木胶合板 | C10: Hardwood Plywood Products
A11: A-570-053 | B11: 铝箔 | C11: Aluminum Foil
A12: A-570-055 | B12: 封箱钉 | C12: Carton Closing Staples
A13: A-570-056 | B13: 工具箱和工具柜 | C13: Tool Chests And Cabinets
... A74: A-570-930 | B74: circular welded a ustenitic stainless pressure pipe | C74: 圆形焊接奥氏体不锈高压套管

Sheet 合作流程
A1: 流程说明 | C1: 返回目录
A2: 一、 | B2: 先建档开户
A3: 二、 | B3: 出货前请先预报仓位，以确保货物正常装柜（企业微信群对接）
A4: 三、 | B4: 发货前请在客户端下单，货到仓前务必在系统下好预报单，若因未及时下单导致延误出货后果负责！下单方式：手动或发票导入一次到位（详细操作步骤请查看附件）
A5: 四、 | B5: 如果是报关件，报关资料请在交货后上传运单附件-报关资料，未及时提供报关资料导致赶不上报关将默认买单出货。 报关件文件命名统一为：客户名+单号+渠道+件数+（单独/合并）报关+报关方式（9710/9810指定或订单备注好）（若部分报关需要备注报关件数） 举例：美琦+FBA19GR17NVO+OA拆送+100件+9810报关+订单号EV45625685
A6: 五、 | B6: 系统下单后可导出《交仓单》，用于司机与仓库交接
A7: 六、 | B7: 快递派送后有异常可以向我司索要UPS开查表开查
A8: 七、 | B8: 关于赔偿标准（详见《发货须知》）
A9: 八、 | B9: 合作合同签署
A10: 九、 | B10: 仓库及负责人联系方式

Sheet 分区
A1: 仓点 | B1: 邮编 | C1: 邮编-1 | D1: 分区
A2: JFK8 | B2: 10314 | C2: 1 | D2: 美东
A3: HIA1 | B3: 17057 | C3: 1 | D3: 美东
A4: IUST | B4: 17225 | C4: 1 | D4: 美东
A5: MDT4 | B5: 17408 | C5: 1 | D5: 美东
A6: WBW2 | B6: 18447 | C6: 1 | D6: 美东
A7: RMN3 | B7: 22406 | C7: 2 | D7: 美东
A8: CHO1 | B8: 22939 | C8: 2 | D8: 美东
A9: XRI3 | B9: 23234 | C9: 2 | D9: 美东
A10: RDU2 | B10: 27577 | C10: 2 | D10: 美东
A11: XLX6 | B11: 28134 | C11: 2 | D11: 美东
A12: RDU4 | B12: 28303 | C12: 2 | D12: 美东
A13: IUSR | B13: 29330 | C13: 2 | D13: 美东
... A59: PSC2 | B59: 99301 | C59: 9 | D59: 美西二区
A60: CMH7 | B60: 43054-7762 | C60: 4 | D60: 美东
A61: BOS7 | B61: 02720-4766 | C61: 0 | D61: 美东
A62: BDL2 | B62: 06095-2144 | C62: 0 | D62: 美东
A63: BDL6 | B63: 06416-1186 | C63: 0 | D63: 美东
A64: BDL3 | B64: 06473-1307 | C64: 0 | D64: 美东
A65: EWR9 | B65: 07008-3529 | C65: 0 | D65: 美东
A66: ACY2 | B66: 08016-1934 | C66: 0 | D66: 美东
A67: TEB4 | B67: 08069-2957 | C67: 0 | D67: 美东
A68: XEW5 | B68: 08077-2015 | C68: 0 | D68: 美东
A69: TEB3 | B69: 08085-4503 | C69: 0 | D69: 美东
A70: TEB6 | B70: 08512-5007 | C70: 0 | D70: 美东
A71: ABE8 | B71: 08518-2200 | C71: 0 | D71: 美东
... A114: MCO2 | B114: 32725-2610 | C114: 3 | D114: 美东
A115: MCO1 | B115: 32824 | C115: 3 | D115: 美东
A116: TMB8 | B116: 33032-8597 | C116: 3 | D116: 美东
A117: A1MI | B117: 33054 | C117: 3 | D117: 美东
A118: PBI2 | B118: 33478-6456 | C118: 3 | D118: 美东
A119: TPA1 | B119: 33570-5526 | C119: 3 | D119: 美东
A120: TPA2 | B120: 33811-1808 | C120: 3 | D120: 美东
A121: TPA3 | B121: 33823-9429 | C121: 3 | D121: 美东
A122: TPA6 | B122: 34475-4625 | C122: 3 | D122: 美东
A123: HSV1 | B123: 35756-4403 | C123: 3 | D123: 美东
A124: BNA6 | B124: 37040-5502 | C124: 3 | D124: 美东
A125: BNA2 | B125: 37090-8123 | C125: 3 | D125: 美东
A126: BNA3 | B126: 37127 | C126: 3 | D126: 美东
A127: CHA2 | B127: 37310-1400 | C127: 3 | D127: 美东
A128: MEM1 | B128: 38118-8102 | C128: 3 | D128: 美东
A129: MEM2 | B129: 38611-2306 | C129: 3 | D129: 美东
A130: MEM6 | B130: 38654-2510 | C130: 3 | D130: 美东
A131: IVSA | B131: 41018 | C131: 4 | D131: 美东
A132: CVG1 | B132: 41048-8648 | C132: 4 | D132: 美东
A133: CVG3 | B133: 41048-9135 | C133: 4 | D133: 美东
A134: SDF1 | B134: 42718-2454 | C134: 4 | D134: 美东
A135: CMH1 | B135: 43062-7793 | C135: 4 | D135: 美东
A136: CMH2 | B136: 43125-9016 | C136: 4 | D136: 美东
A137: CMH6 | B137: 43137-9670 | C137: 4 | D137: 美东
A138: TOL3 | B138: 43551-4210 | C138: 4 | D138: 美东
A139: CMH3 | B139: 45050-1848 | C139: 4 | D139: 美东
A140: MQJ1 | B140: 46140-7099 | C140: 4 | D140: 美东
A141: IND9 | B141: 46143-7830 | C141: 4 | D141: 美东
A142: IND2 | B142: 46168-7442 | C142: 4 | D142: 美东
A143: IND5 | B143: 46168-7637 | C143: 4 | D143: 美东
... A148: DET1 | B148: 48150-1043 | C148: 4 | D148: 美东
A149: DTW1 | B149: 48174 | C149: 4 | D149: 美东
A150: DET2 | B150: 48317-1318 | C150: 4 | D150: 美东
A151: MKE1 | B151: 53144-7502 | C151: 5 | D151: 美中
A152: JVL1 | B152: 53511-9709 | C152: 5 | D152: 美中
A153: MSP1 | B153: 55379-1726 | C153: 5 | D153: 美中
A154: ORD2 | B154: 60410-8758 | C154: 6 | D154: 美中
A155: MDW2 | B155: 60433-3280 | C155: 6 | D155: 美中
A156: MDW7 | B156: 60449-8316 | C156: 6 | D156: 美中
A157: IGQ2 | B157: 60484-3271 | C157: 6 | D157: 美中
A158: MDW9 | B158: 60502-8200 | C158: 6 | D158: 美中
A159: STL6 | B159: 62025-2801 | C159: 6 | D159: 美中
A160: STL4 | B160: 62025-2815 | C160: 6 | D160: 美中
A161: STL3 | B161: 65738-2779 | C161: 6 | D161: 美中
... A171: FTW1 | B171: 75241-7203 | C171: 7 | D171: 美中
A172: FTW2 | B172: 75261 | C172: 7 | D172: 美中
A173: FTW6 | B173: 75261-4034 | C173: 7 | D173: 美中
A174: FTW3 | B174: 76177-2517 | C174: 7 | D174: 美中
A175: DFW7 | B175: 76177-4513 | C175: 7 | D175: 美中
A176: HOU2 | B176: 77038-2324 | C176: 7 | D176: 美中
A177: ITX2 | B177: 77040-1437 | C177: 7 | D177: 美中
A178: HOU3 | B178: 77423-2769 | C178: 7 | D178: 美中
A179: HOU8 | B179: 77545-1129 | C179: 7 | D179: 美中
A180: SAT1 | B180: 78154-1461 | C180: 7 | D180: 美中
A181: SAT4 | B181: 78245-9512 | C181: 7 | D181: 美中
A182: AMA1 | B182: 79108-7749 | C182: 7 | D182: 美中
A183: DEN2 | B183: 80019-3710 | C183: 8 | D183: 美西
A184: SLC2 | B184: 84081 | C184: 8 | D184: 美西
A185: SLC3 | B185: 84116-4413 | C185: 8 | D185: 美西
A186: PHX7 | B186: 85043-2101 | C186: 8 | D186: 美西
A187: GYR3 | B187: 85043-2356 | C187: 8 | D187: 美西
A188: PHX3 | B188: 85043-4428 | C188: 8 | D188: 美西
A189: PHX6 | B189: 85043-8305 | C189: 8 | D189: 美西
A190: QZZ7 | B190: 85212-9608 | C190: 8 | D190: 美西
A191: PHX5 | B191: 85338-3620 | C191: 8 | D191: 美西
A192: GYR2 | B192: 85395-7672 | C192: 8 | D192: 美西
A193: LAS1 | B193: 89044-8746 | C193: 8 | D193: 美西
A194: LAS6 | B194: 89115-1826 | C194: 8 | D194: 美西
A195: LAS7 | B195: 89115-1935 | C195: 8 | D195: 美西
A196: VGT2 | B196: 89115-2013 | C196: 8 | D196: 美西
... A207: LGB8 | B207: 92376-8624 | C207: 9 | D207: 美西
A208: KRB1 | B208: 92408 | C208: 9 | D208: 美西
A209: ONT2 | B209: 92408-0123 | C209: 9 | D209: 美西
A210: SBD2 | B210: 92408-2805 | C210: 9 | D210: 美西
...
